Workbook

Sheet Item codes
A1: S.NO | B1: ITEM CODE | C1: ITEM DESC
A2: 1 | B2: RTHTMTBNET72X33X06 | C2: Peps Restonic Hotel Motel Bonnell Euro Top 72X33X06 | Q2: RTHTMTPKET72X30X06 | R2: Peps Restonic Hotel Motel Pocketed Euro Top 72X30X06 | S2: RTHTMTPKET72X30X08 | T2: Peps Restonic Hotel Motel Pocketed Euro Top 72X30X08 | U2: RTHTMTPKET72X30X10 | V2: Peps Restonic Hotel Motel Pocketed Euro Top 72X30X10 | W2: RTHTMTPKMFET72X30X06 | X2: Peps Restonic Hotel Motel Pocketed Memory Foam Euro Top 72X30X06 | Y2: RTHTMTPKMFET72X30X08 | Z2: Peps Restonic Hotel Motel Pocketed Memory Foam Euro Top 72X30X08 | AA2: RTHTMTPKMFET72X30X10 | AB2: Peps Restonic Hotel Motel Pocketed Memory Foam Euro Top 72X30X10 | AC2: RTHTMTPKMFRG72X30X06 | AD2: Peps Restonic Hotel Motel Pocketed Memory Foam Regular 72X30X06 | AE2: RTHTMTPKMFRG72X30X08 | AF2: Peps Restonic Hotel Motel Pocketed Memory Foam Regular 72X30X08 | AG2: RTHTMTPKMFRG72X30X10 | AH2: Peps Restonic Hotel Motel Pocketed Memory Foam Regular 72X30X10 | AI2: RTHTMTPKMFRG72X30X12 | AJ2: Peps Restonic Hotel Motel Pocketed Memory Foam Regular 72X30X12 | AK2: RTHTMTPKPT72X30X06 | AL2: Peps Restonic Hotel Motel Pocketed Pillow Top 72X30X06 | AM2: RTHTMTPKPT72X30X08 | AN2: Peps Restonic Hotel Motel Pocketed Pillow Top 72X30X08 | AO2: RTHTMTPKPT72X30X10 | AP2: Peps Restonic Hotel Motel Pocketed Pillow Top 72X30X10 | AQ2: RTHTMTPKRG72X30X06 | AR2: Peps Restonic Hotel Motel Pocketed Regular 72X30X06 | AS2: RTHTMTPKRG72X30X08 | AT2: Peps Restonic Hotel Motel Pocketed Regular 72X30X08 | AU2: RTHTMTPKRG72X30X10 | AV2: Peps Restonic Hotel Motel Pocketed Regular 72X30X10 | AW2: RTHTMTPKRG72X30X12 | AX2: Peps Restonic Hotel Motel Pocketed Regular 72X30X12
A3: 2 | B3: RTHTMTBNET72X39X06 | C3: Peps Restonic Hotel Motel Bonnell Euro Top 72X39X06
A4: 3 | B4: RTHTMTBNET72X45X06 | C4: Peps Restonic Hotel Motel Bonnell Euro Top 72X45X06
A5: 4 | B5: RTHTMTBNET72X51X06 | C5: Peps Restonic Hotel Motel Bonnell Euro Top 72X51X06
A6: 5 | B6: RTHTMTBNET72X54X06 | C6: Peps Restonic Hotel Motel Bonnell Euro Top 72X54X06
A7: 6 | B7: RTHTMTBNET72X57X06 | C7: Peps Restonic Hotel Motel Bonnell Euro Top 72X57X06
A8: 7 | B8: RTHTMTBNET72X63X06 | C8: Peps Restonic Hotel Motel Bonnell Euro Top 72X63X06
A9: 8 | B9: RTHTMTBNET72X69X06 | C9: Peps Restonic Hotel Motel Bonnell Euro Top 72X69X06
A10: 9 | B10: RTHTMTBNET75X33X06 | C10: Peps Restonic Hotel Motel Bonnell Euro Top 75X33X06
A11: 10 | B11: RTHTMTBNET75X39X06 | C11: Peps Restonic Hotel Motel Bonnell Euro Top 75X39X06
A12: 11 | B12: RTHTMTBNET75X45X06 | C12: Peps Restonic Hotel Motel Bonnell Euro Top 75X45X06
A13: 12 | B13: RTHTMTBNET75X51X06 | C13: Peps Restonic Hotel Motel Bonnell Euro Top 75X51X06
A14: 13 | B14: RTHTMTBNET75X54X06 | C14: Peps Restonic Hotel Motel Bonnell Euro Top 75X54X06
... A1361: 1360 | B1361: RTHTMTPKRG84X69X12 | C1361: Peps Restonic Hotel Motel Pocketed Regular 84X69X12

Sheet Workings
A1: DOIGH | B1: S.no | C1: R.no | D1: Date | E1: Bom Code/PS.No | F1: PS Desc. | G1: Item | H1: PS Desc. | I1: PS Usage | J1: PS Category | K1: Process Plan | L1: Uom | M1: Qty | N1: Default For | O1: Wh Code | P1: PS Seq | Q1: I/O Flag | R1: Issue Item | S1: Item Desc | T1: Uom | U1: Qty | V1: Std Wh Code | W1: Backflush | X1: Status | Y1: CC | Z1: LENGTH | AA1: WIDTH | AB1: HE | AC1: Length | AD1: width | AE1: condition | AG1: Conv | AH1: rate | AI1: sub.tot | AJ1: tot | AK1: round | AL1: rm-rate | AM1: PRO-RATE | AN1: Wastage | AO1: DL | AP1: MOH | AQ1: Dep | AR1: Standard Cost | AS1: R-UP | AT1: RM-COST | AU1: PRO-RATE
A2: 1 | B2: 1 | C2: 1 | D2: 28.03.2024 | E2: SFG-FRBNET-MEM-BOR-72X33X08 | F2: Restonic Hotel Motel Bonnell Euro Top Memory Border 72X33X08 | G2: =E2 -> SFG-FRBNET-MEM-BOR-72X33X08 | H2: =F2 -> Restonic Hotel Motel Bonnell Euro Top Memory Border 72X33X08 | I2: Standard | J2: Production | K2: TAIL-BORDER | L2: NOS | M2: 1 | N2: MRP&Rollup | O2: CBESFG | P2: 10 | Q2: I | R2: RM-THRD-QS-TKT40 | S2: THREAD TKT40 210D/3 PLY 10000MTS | T2: MTR | U2: 5.6 | V2: CBEWIP | W2: Backflush | X2: Active | Y2: =RIGHT(E2,8) -> 72X33X08 | Z2: =LEFT(Y2,2) -> 72 | AA2: =MID(Y2,4,2) -> 33 | AB2: =RIGHT(Y2,2) -> 08 | AC2: =Z2 -> 72 | AD2: =AA2 -> 33 | AG2: =U2/10000 -> 0.00056 | AH2: =VLOOKUP(R2,'Rm-feb-24'!B:P,15,0) -> 231.1423 | AI2: =AG2*AH2 -> 0.12943969 | AJ2: =SUM(AI2:AI9) -> 144.14764 | AK2: =ROUND(AJ2,3) -> 144.148 | AL2: =AK2 -> 144.148 | AM2: =+AL2+AR2 -> 161.98617 | AN2: =+SUM(((AL2*3%*18%))) -> 0.7783992 | AO2: =+SUM(((AL2*14.33%*53%))) -> 10.947896 | AP2: =+SUM(((AL2*5.92%*53%))) -> 4.5227876 | AQ2: =+SUM(((AL2*2.08%*53%))) -> 1.5890876 | AR2: =SUM(AN2:AQ2) -> 17.838171 | AS2: =ROUNDUP(AM2,0) -> 162 | AT2: =AL2 -> 144.148 | AU2: =AS2 -> 162
A3: 2 | B3: 2 | C3: =C2 -> 1 | D3: =D2 -> 28.03.2024 | E3: =E2 -> SFG-FRBNET-MEM-BOR-72X33X08 | F3: =F2 -> Restonic Hotel Motel Bonnell Euro Top Memory Border 72X33X08 | G3: =G2 -> SFG-FRBNET-MEM-BOR-72X33X08 | H3: =H2 -> Restonic Hotel Motel Bonnell Euro Top Memory Border 72X33X08 | I3: Standard | J3: Production | K3: TAIL-BORDER | L3: NOS | M3: 1 | N3: MRP&Rollup | O3: CBESFG | P3: 20 | Q3: I | R3: HW-CTON-THREAD | S3: COTTON THREAD WHITE 3PLY | T3: MTR | U3: 5 | V3: CBEWIP | W3: Backflush | X3: Active | Y3: =RIGHT(E3,8) -> 72X33X08 | Z3: =LEFT(Y3,2) -> 72 | AA3: =MID(Y3,4,2) -> 33 | AB3: =RIGHT(Y3,2) -> 08 | AC3: =AC2 -> 72 | AD3: =AD2 -> 33 | AG3: =U3/5000 -> 0.001 | AH3: =VLOOKUP(R3,'Rm-feb-24'!B:P,15,0) -> 58 | AI3: =AG3*AH3 -> 0.058 | AT3: =AT2 -> 144.148 | AU3: =AU2 -> 162
A4: 3 | B4: 3 | C4: =C3 -> 1 | D4: =D3 -> 28.03.2024 | E4: =E3 -> SFG-FRBNET-MEM-BOR-72X33X08 | F4: =F3 -> Restonic Hotel Motel Bonnell Euro Top Memory Border 72X33X08 | G4: =G3 -> SFG-FRBNET-MEM-BOR-72X33X08 | H4: =H3 -> Restonic Hotel Motel Bonnell Euro Top Memory Border 72X33X08 | I4: Standard | J4: Production | K4: TAIL-BORDER | L4: NOS | M4: 1 | N4: MRP&Rollup | O4: CBESFG | P4: 30 | Q4: I | R4: SFG-RTHTMT-BNPK-MEM-BOR-21CM | S4: Hotel Motel Poc ET-8 8MM/16D Pre Foam Memory Border 21 CM Height | T4: MTR | U4: =AE4 -> 5.411 | V4: CBESFG | W4: Backflush | X4: Active | Y4: =RIGHT(E4,8) -> 72X33X08 | Z4: =LEFT(Y4,2) -> 72 | AA4: =MID(Y4,4,2) -> 33 | AB4: =RIGHT(Y4,2) -> 08 | AC4: =AC3 -> 72 | AD4: =AD3 -> 33 | AE4: =ROUNDUP(((((AC4+AD4)*2)+3)*0.0254),3) -> 5.411 | AG4: =U4 -> 5.411 | AH4: =VLOOKUP(R4,'SFG-RM'!A:B,2,0) -> 21.475377 | AI4: =AG4*AH4 -> 116.20327 | AT4: =AT3 -> 144.148 | AU4: =AU3 -> 162
A5: 4 | B5: 4 | C5: =C4 -> 1 | D5: =D4 -> 28.03.2024 | E5: =E4 -> SFG-FRBNET-MEM-BOR-72X33X08 | F5: =F4 -> Restonic Hotel Motel Bonnell Euro Top Memory Border 72X33X08 | G5: =G4 -> SFG-FRBNET-MEM-BOR-72X33X08 | H5: =H4 -> Restonic Hotel Motel Bonnell Euro Top Memory Border 72X33X08 | I5: Standard | J5: Production | K5: TAIL-BORDER | L5: NOS | M5: 1 | N5: MRP&Rollup | O5: CBESFG | P5: 40 | Q5: I | R5: RMI-HCC-SDE-LBL | S5: HOTEL COMFORT CARE SIDE LABEL (IMPORT) | T5: NOS | U5: 1 | V5: CBEWIP | W5: Backflush | X5: Active | Y5: =RIGHT(E5,8) -> 72X33X08 | Z5: =LEFT(Y5,2) -> 72 | AA5: =MID(Y5,4,2) -> 33 | AB5: =RIGHT(Y5,2) -> 08 | AC5: =AC4 -> 72 | AD5: =AD4 -> 33 | AE5: =ROUNDUP(((((72+30)*2)+3)*0.0254),3) -> 5.258 | AG5: =U5 -> 1 | AH5: =VLOOKUP(R5,'Rm-feb-24'!B:P,15,0) -> 5.9957 | AI5: =AG5*AH5 -> 5.9957 | AT5: =AT4 -> 144.148 | AU5: =AU4 -> 162
A6: 5 | B6: 5 | C6: =C5 -> 1 | D6: =D5 -> 28.03.2024 | E6: =E5 -> SFG-FRBNET-MEM-BOR-72X33X08 | F6: =F5 -> Restonic Hotel Motel Bonnell Euro Top Memory Border 72X33X08 | G6: =G5 -> SFG-FRBNET-MEM-BOR-72X33X08 | H6: =H5 -> Restonic Hotel Motel Bonnell Euro Top Memory Border 72X33X08 | I6: Standard | J6: Production | K6: TAIL-BORDER | L6: NOS | M6: 1 | N6: MRP&Rollup | O6: CBESFG | P6: 50 | Q6: I | R6: RML-MRP-BACK-LBL | S6: MRP BACK LABEL(PLAIN) | T6: NOS | U6: 1 | V6: CBEWIP | W6: Backflush | X6: Active | Y6: =RIGHT(E6,8) -> 72X33X08 | Z6: =LEFT(Y6,2) -> 72 | AA6: =MID(Y6,4,2) -> 33 | AB6: =RIGHT(Y6,2) -> 08 | AC6: =AC5 -> 72 | AD6: =AD5 -> 33 | AG6: =U6 -> 1 | AH6: =VLOOKUP(R6,'Rm-feb-24'!B:P,15,0) -> 1.3275 | AI6: =AG6*AH6 -> 1.3275 | AT6: =AT5 -> 144.148 | AU6: =AU5 -> 162
A7: 6 | B7: 6 | C7: =C6 -> 1 | D7: =D6 -> 28.03.2024 | E7: =E6 -> SFG-FRBNET-MEM-BOR-72X33X08 | F7: =F6 -> Restonic Hotel Motel Bonnell Euro Top Memory Border 72X33X08 | G7: =G6 -> SFG-FRBNET-MEM-BOR-72X33X08 | H7: =H6 -> Restonic Hotel Motel Bonnell Euro Top Memory Border 72X33X08 | I7: Standard | J7: Production | K7: TAIL-BORDER | L7: NOS | M7: 1 | N7: MRP&Rollup | O7: CBESFG | P7: 60 | Q7: I | R7: RML-DRN-LBL | S7: DIRECTION LABEL | T7: NOS | U7: 1 | V7: CBEWIP | W7: Backflush | X7: Active | Y7: =RIGHT(E7,8) -> 72X33X08 | Z7: =LEFT(Y7,2) -> 72 | AA7: =MID(Y7,4,2) -> 33 | AB7: =RIGHT(Y7,2) -> 08 | AC7: =AC6 -> 72 | AD7: =AD6 -> 33 | AG7: =U7 -> 1 | AH7: =VLOOKUP(R7,'Rm-feb-24'!B:P,15,0) -> 1.7318 | AI7: =AG7*AH7 -> 1.7318 | AT7: =AT6 -> 144.148 | AU7: =AU6 -> 162
A8: 7 | B8: 7 | C8: =C7 -> 1 | D8: =D7 -> 28.03.2024 | E8: =E7 -> SFG-FRBNET-MEM-BOR-72X33X08 | F8: =F7 -> Restonic Hotel Motel Bonnell Euro Top Memory Border 72X33X08 | G8: =G7 -> SFG-FRBNET-MEM-BOR-72X33X08 | H8: =H7 -> Restonic Hotel Motel Bonnell Euro Top Memory Border 72X33X08 | I8: Standard | J8: Production | K8: TAIL-BORDER | L8: NOS | M8: 1 | N8: MRP&Rollup | O8: CBESFG | P8: 70 | Q8: I | R8: SFG-RTHTMT-MEM-HANDLE | S8: Restonic Hotel Motel Memory Handle | T8: MTR | U8: 0.64 | V8: CBESFG | W8: Backflush | X8: Active | Y8: =RIGHT(E8,8) -> 72X33X08 | Z8: =LEFT(Y8,2) -> 72 | AA8: =MID(Y8,4,2) -> 33 | AB8: =RIGHT(Y8,2) -> 08 | AC8: =AC7 -> 72 | AD8: =AD7 -> 33 | AG8: =U8 -> 0.64 | AH8: =VLOOKUP(R8,'SFG-RM'!A:B,2,0) -> 14.621455 | AI8: =AG8*AH8 -> 9.3577314 | AT8: =AT7 -> 144.148 | AU8: =AU7 -> 162
A9: 8 | B9: 8 | C9: =C8 -> 1 | D9: =D8 -> 28.03.2024 | E9: =E8 -> SFG-FRBNET-MEM-BOR-72X33X08 | F9: =F8 -> Restonic Hotel Motel Bonnell Euro Top Memory Border 72X33X08 | G9: =G8 -> SFG-FRBNET-MEM-BOR-72X33X08 | H9: =H8 -> Restonic Hotel Motel Bonnell Euro Top Memory Border 72X33X08 | I9: Standard | J9: Production | K9: TAIL-BORDER | L9: NOS | M9: 1 | N9: MRP&Rollup | O9: CBESFG | P9: 80 | Q9: I | R9: RMI-BREATHER-GOLD | S9: BREATHER SET GOLD ROUND | T9: SET | U9: 2 | V9: CBEWIP | W9: Backflush | X9: Active | Y9: =RIGHT(E9,8) -> 72X33X08 | Z9: =LEFT(Y9,2) -> 72 | AA9: =MID(Y9,4,2) -> 33 | AB9: =RIGHT(Y9,2) -> 08 | AC9: =AC8 -> 72 | AD9: =AD8 -> 33 | AG9: =U9 -> 2 | AH9: =VLOOKUP(R9,'Rm-feb-24'!B:P,15,0) -> 4.6721 | AI9: =AG9*AH9 -> 9.3442 | AT9: =AT8 -> 144.148 | AU9: =AU8 -> 162
A10: 9
A11: 10 | B11: 1 | C11: 2 | D11: 28.03.2024 | E11: SFG-FRBNET-MEM-BOR-72X39X08 | F11: Restonic Hotel Motel Bonnell Euro Top Memory Border 72X39X08 | G11: =E11 -> SFG-FRBNET-MEM-BOR-72X39X08 | H11: =F11 -> Restonic Hotel Motel Bonnell Euro Top Memory Border 72X39X08 | I11: Standard | J11: Production | K11: TAIL-BORDER | L11: NOS | M11: 1 | N11: MRP&Rollup | O11: CBESFG | P11: 10 | Q11: I | R11: RM-THRD-QS-TKT40 | S11: THREAD TKT40 210D/3 PLY 10000MTS | T11: MTR | U11: 5.6 | V11: CBEWIP | W11: Backflush | X11: Active | Y11: =RIGHT(E11,8) -> 72X39X08 | Z11: =LEFT(Y11,2) -> 72 | AA11: =MID(Y11,4,2) -> 39 | AB11: =RIGHT(Y11,2) -> 08 | AC11: =Z11 -> 72 | AD11: =AA11 -> 39 | AG11: =U11/10000 -> 0.00056 | AH11: =VLOOKUP(R11,'Rm-feb-24'!B:P,15,0) -> 231.1423 | AI11: =AG11*AH11 -> 0.12943969 | AJ11: =SUM(AI11:AI18) -> 150.67615 | AK11: =ROUND(AJ11,3) -> 150.676 | AL11: =AK11 -> 150.676 | AM11: =+AL11+AR11 -> 169.322 | AN11: =+SUM(((AL11*3%*18%))) -> 0.8136504 | AO11: =+SUM(((AL11*14.33%*53%))) -> 11.443692 | AP11: =+SUM(((AL11*5.92%*53%))) -> 4.7276102 | AQ11: =+SUM(((AL11*2.08%*53%))) -> 1.6610522 | AR11: =SUM(AN11:AQ11) -> 18.646004 | AS11: =ROUNDUP(AM11,0) -> 170 | AT11: =AL11 -> 150.676 | AU11: =AS11 -> 170
A12: 11 | B12: 2 | C12: =C11 -> 2 | D12: =D11 -> 28.03.2024 | E12: =E11 -> SFG-FRBNET-MEM-BOR-72X39X08 | F12: =F11 -> Restonic Hotel Motel Bonnell Euro Top Memory Border 72X39X08 | G12: =G11 -> SFG-FRBNET-MEM-BOR-72X39X08 | H12: =H11 -> Restonic Hotel Motel Bonnell Euro Top Memory Border 72X39X08 | I12: Standard | J12: Production | K12: TAIL-BORDER | L12: NOS | M12: 1 | N12: MRP&Rollup | O12: CBESFG | P12: 20 | Q12: I | R12: HW-CTON-THREAD | S12: COTTON THREAD WHITE 3PLY | T12: MTR | U12: 5 | V12: CBEWIP | W12: Backflush | X12: Active | Y12: =RIGHT(E12,8) -> 72X39X08 | Z12: =LEFT(Y12,2) -> 72 | AA12: =MID(Y12,4,2) -> 39 | AB12: =RIGHT(Y12,2) -> 08 | AC12: =AC11 -> 72 | AD12: =AD11 -> 39 | AG12: =U12/5000 -> 0.001 | AH12: =VLOOKUP(R12,'Rm-feb-24'!B:P,15,0) -> 58 | AI12: =AG12*AH12 -> 0.058 | AT12: =AT11 -> 150.676 | AU12: =AU11 -> 170
A13: 12 | B13: 3 | C13: =C12 -> 2 | D13: =D12 -> 28.03.2024 | E13: =E12 -> SFG-FRBNET-MEM-BOR-72X39X08 | F13: =F12 -> Restonic Hotel Motel Bonnell Euro Top Memory Border 72X39X08 | G13: =G12 -> SFG-FRBNET-MEM-BOR-72X39X08 | H13: =H12 -> Restonic Hotel Motel Bonnell Euro Top Memory Border 72X39X08 | I13: Standard | J13: Production | K13: TAIL-BORDER | L13: NOS | M13: 1 | N13: MRP&Rollup | O13: CBESFG | P13: 30 | Q13: I | R13: SFG-RTHTMT-BNPK-MEM-BOR-21CM | S13: Hotel Motel Poc ET-8 8MM/16D Pre Foam Memory Border 21 CM Height | T13: MTR | U13: =AE13 -> 5.715 | V13: CBESFG | W13: Backflush | X13: Active | Y13: =RIGHT(E13,8) -> 72X39X08 | Z13: =LEFT(Y13,2) -> 72 | AA13: =MID(Y13,4,2) -> 39 | AB13: =RIGHT(Y13,2) -> 08 | AC13: =AC12 -> 72 | AD13: =AD12 -> 39 | AE13: =ROUNDUP(((((AC13+AD13)*2)+3)*0.0254),3) -> 5.715 | AG13: =U13 -> 5.715 | AH13: =VLOOKUP(R13,'SFG-RM'!A:B,2,0) -> 21.475377 | AI13: =AG13*AH13 -> 122.73178 | AT13: =AT12 -> 150.676 | AU13: =AU12 -> 170
A14: 13 | B14: 4 | C14: =C13 -> 2 | D14: =D13 -> 28.03.2024 | E14: =E13 -> SFG-FRBNET-MEM-BOR-72X39X08 | F14: =F13 -> Restonic Hotel Motel Bonnell Euro Top Memory Border 72X39X08 | G14: =G13 -> SFG-FRBNET-MEM-BOR-72X39X08 | H14: =H13 -> Restonic Hotel Motel Bonnell Euro Top Memory Border 72X39X08 | I14: Standard | J14: Production | K14: TAIL-BORDER | L14: NOS | M14: 1 | N14: MRP&Rollup | O14: CBESFG | P14: 40 | Q14: I | R14: RMI-HCC-SDE-LBL | S14: HOTEL COMFORT CARE SIDE LABEL (IMPORT) | T14: NOS | U14: 1 | V14: CBEWIP | W14: Backflush | X14: Active | Y14: =RIGHT(E14,8) -> 72X39X08 | Z14: =LEFT(Y14,2) -> 72 | AA14: =MID(Y14,4,2) -> 39 | AB14: =RIGHT(Y14,2) -> 08 | AC14: =AC13 -> 72 | AD14: =AD13 -> 39 | AE14: =ROUNDUP(((((72+30)*2)+3)*0.0254),3) -> 5.258 | AG14: =U14 -> 1 | AH14: =VLOOKUP(R14,'Rm-feb-24'!B:P,15,0) -> 5.9957 | AI14: =AG14*AH14 -> 5.9957 | AT14: =AT13 -> 150.676 | AU14: =AU13 -> 170
A15: 14 | B15: 5 | C15: =C14 -> 2 | D15: =D14 -> 28.03.2024 | E15: =E14 -> SFG-FRBNET-MEM-BOR-72X39X08 | F15: =F14 -> Restonic Hotel Motel Bonnell Euro Top Memory Border 72X39X08 | G15: =G14 -> SFG-FRBNET-MEM-BOR-72X39X08 | H15: =H14 -> Restonic Hotel Motel Bonnell Euro Top Memory Border 72X39X08 | I15: Standard | J15: Production | K15: TAIL-BORDER | L15: NOS | M15: 1 | N15: MRP&Rollup | O15: CBESFG | P15: 50 | Q15: I | R15: RML-MRP-BACK-LBL | S15: MRP BACK LABEL(PLAIN) | T15: NOS | U15: 1 | V15: CBEWIP | W15: Backflush | X15: Active | Y15: =RIGHT(E15,8) -> 72X39X08 | Z15: =LEFT(Y15,2) -> 72 | AA15: =MID(Y15,4,2) -> 39 | AB15: =RIGHT(Y15,2) -> 08 | AC15: =AC14 -> 72 | AD15: =AD14 -> 39 | AG15: =U15 -> 1 | AH15: =VLOOKUP(R15,'Rm-feb-24'!B:P,15,0) -> 1.3275 | AI15: =AG15*AH15 -> 1.3275 | AT15: =AT14 -> 150.676 | AU15: =AU14 -> 170
A16: 15 | B16: 6 | C16: =C15 -> 2 | D16: =D15 -> 28.03.2024 | E16: =E15 -> SFG-FRBNET-MEM-BOR-72X39X08 | F16: =F15 -> Restonic Hotel Motel Bonnell Euro Top Memory Border 72X39X08 | G16: =G15 -> SFG-FRBNET-MEM-BOR-72X39X08 | H16: =H15 -> Restonic Hotel Motel Bonnell Euro Top Memory Border 72X39X08 | I16: Standard | J16: Production | K16: TAIL-BORDER | L16: NOS | M16: 1 | N16: MRP&Rollup | O16: CBESFG | P16: 60 | Q16: I | R16: RML-DRN-LBL | S16: DIRECTION LABEL | T16: NOS | U16: 1 | V16: CBEWIP | W16: Backflush | X16: Active | Y16: =RIGHT(E16,8) -> 72X39X08 | Z16: =LEFT(Y16,2) -> 72 | AA16: =MID(Y16,4,2) -> 39 | AB16: =RIGHT(Y16,2) -> 08 | AC16: =AC15 -> 72 | AD16: =AD15 -> 39 | AG16: =U16 -> 1 | AH16: =VLOOKUP(R16,'Rm-feb-24'!B:P,15,0) -> 1.7318 | AI16: =AG16*AH16 -> 1.7318 | AT16: =AT15 -> 150.676 | AU16: =AU15 -> 170
A17: 16 | B17: 7 | C17: =C16 -> 2 | D17: =D16 -> 28.03.2024 | E17: =E16 -> SFG-FRBNET-MEM-BOR-72X39X08 | F17: =F16 -> Restonic Hotel Motel Bonnell Euro Top Memory Border 72X39X08 | G17: =G16 -> SFG-FRBNET-MEM-BOR-72X39X08 | H17: =H16 -> Restonic Hotel Motel Bonnell Euro Top Memory Border 72X39X08 | I17: Standard | J17: Production | K17: TAIL-BORDER | L17: NOS | M17: 1 | N17: MRP&Rollup | O17: CBESFG | P17: 70 | Q17: I | R17: SFG-RTHTMT-MEM-HANDLE | S17: Restonic Hotel Motel Memory Handle | T17: MTR | U17: 0.64 | V17: CBESFG | W17: Backflush | X17: Active | Y17: =RIGHT(E17,8) -> 72X39X08 | Z17: =LEFT(Y17,2) -> 72 | AA17: =MID(Y17,4,2) -> 39 | AB17: =RIGHT(Y17,2) -> 08 | AC17: =AC16 -> 72 | AD17: =AD16 -> 39 | AG17: =U17 -> 0.64 | AH17: =VLOOKUP(R17,'SFG-RM'!A:B,2,0) -> 14.621455 | AI17: =AG17*AH17 -> 9.3577314 | AT17: =AT16 -> 150.676 | AU17: =AU16 -> 170
A18: 17 | B18: 8 | C18: =C17 -> 2 | D18: =D17 -> 28.03.2024 | E18: =E17 -> SFG-FRBNET-MEM-BOR-72X39X08 | F18: =F17 -> Restonic Hotel Motel Bonnell Euro Top Memory Border 72X39X08 | G18: =G17 -> SFG-FRBNET-MEM-BOR-72X39X08 | H18: =H17 -> Restonic Hotel Motel Bonnell Euro Top Memory Border 72X39X08 | I18: Standard | J18: Production | K18: TAIL-BORDER | L18: NOS | M18: 1 | N18: MRP&Rollup | O18: CBESFG | P18: 80 | Q18: I | R18: RMI-BREATHER-GOLD | S18: BREATHER SET GOLD ROUND | T18: SET | U18: 2 | V18: CBEWIP | W18: Backflush | X18: Active | Y18: =RIGHT(E18,8) -> 72X39X08 | Z18: =LEFT(Y18,2) -> 72 | AA18: =MID(Y18,4,2) -> 39 | AB18: =RIGHT(Y18,2) -> 08 | AC18: =AC17 -> 72 | AD18: =AD17 -> 39 | AG18: =U18 -> 2 | AH18: =VLOOKUP(R18,'Rm-feb-24'!B:P,15,0) -> 4.6721 | AI18: =AG18*AH18 -> 9.3442 | AT18: =AT17 -> 150.676 | AU18: =AU17 -> 170
A19: 18
A20: 19 | B20: 1 | C20: 3 | D20: 28.03.2024 | E20: SFG-FRBNET-MEM-BOR-72X45X08 | F20: Restonic Hotel Motel Bonnell Euro Top Memory Border 72X45X08 | G20: =E20 -> SFG-FRBNET-MEM-BOR-72X45X08 | H20: =F20 -> Restonic Hotel Motel Bonnell Euro Top Memory Border 72X45X08 | I20: Standard | J20: Production | K20: TAIL-BORDER | L20: NOS | M20: 1 | N20: MRP&Rollup | O20: CBESFG | P20: 10 | Q20: I | R20: RM-THRD-QS-TKT40 | S20: THREAD TKT40 210D/3 PLY 10000MTS | T20: MTR | U20: 5.6 | V20: CBEWIP | W20: Backflush | X20: Active | Y20: =RIGHT(E20,8) -> 72X45X08 | Z20: =LEFT(Y20,2) -> 72 | AA20: =MID(Y20,4,2) -> 45 | AB20: =RIGHT(Y20,2) -> 08 | AC20: =Z20 -> 72 | AD20: =AA20 -> 45 | AG20: =U20/10000 -> 0.00056 | AH20: =VLOOKUP(R20,'Rm-feb-24'!B:P,15,0) -> 231.1423 | AI20: =AG20*AH20 -> 0.12943969 | AJ20: =SUM(AI20:AI27) -> 157.22614 | AK20: =ROUND(AJ20,3) -> 157.226 | AL20: =AK20 -> 157.226 | AM20: =+AL20+AR20 -> 176.68256 | AN20: =+SUM(((AL20*3%*18%))) -> 0.8490204 | AO20: =+SUM(((AL20*14.33%*53%))) -> 11.941157 | AP20: =+SUM(((AL20*5.92%*53%))) -> 4.933123 | AQ20: =+SUM(((AL20*2.08%*53%))) -> 1.7332594 | AR20: =SUM(AN20:AQ20) -> 19.45656 | AS20: =ROUNDUP(AM20,0) -> 177 | AT20: =AL20 -> 157.226 | AU20: =AS20 -> 177
A21: 20 | B21: 2 | C21: =C20 -> 3 | D21: =D20 -> 28.03.2024 | E21: =E20 -> SFG-FRBNET-MEM-BOR-72X45X08 | F21: =F20 -> Restonic Hotel Motel Bonnell Euro Top Memory Border 72X45X08 | G21: =G20 -> SFG-FRBNET-MEM-BOR-72X45X08 | H21: =H20 -> Restonic Hotel Motel Bonnell Euro Top Memory Border 72X45X08 | I21: Standard | J21: Production | K21: TAIL-BORDER | L21: NOS | M21: 1 | N21: MRP&Rollup | O21: CBESFG | P21: 20 | Q21: I | R21: HW-CTON-THREAD | S21: COTTON THREAD WHITE 3PLY | T21: MTR | U21: 5 | V21: CBEWIP | W21: Backflush | X21: Active | Y21: =RIGHT(E21,8) -> 72X45X08 | Z21: =LEFT(Y21,2) -> 72 | AA21: =MID(Y21,4,2) -> 45 | AB21: =RIGHT(Y21,2) -> 08 | AC21: =AC20 -> 72 | AD21: =AD20 -> 45 | AG21: =U21/5000 -> 0.001 | AH21: =VLOOKUP(R21,'Rm-feb-24'!B:P,15,0) -> 58 | AI21: =AG21*AH21 -> 0.058 | AT21: =AT20 -> 157.226 | AU21: =AU20 -> 177
A22: 21 | B22: 3 | C22: =C21 -> 3 | D22: =D21 -> 28.03.2024 | E22: =E21 -> SFG-FRBNET-MEM-BOR-72X45X08 | F22: =F21 -> Restonic Hotel Motel Bonnell Euro Top Memory Border 72X45X08 | G22: =G21 -> SFG-FRBNET-MEM-BOR-72X45X08 | H22: =H21 -> Restonic Hotel Motel Bonnell Euro Top Memory Border 72X45X08 | I22: Standard | J22: Production | K22: TAIL-BORDER | L22: NOS | M22: 1 | N22: MRP&Rollup | O22: CBESFG | P22: 30 | Q22: I | R22: SFG-RTHTMT-BNPK-MEM-BOR-21CM | S22: Hotel Motel Poc ET-8 8MM/16D Pre Foam Memory Border 21 CM Height | T22: MTR | U22: =AE22 -> 6.02 | V22: CBESFG | W22: Backflush | X22: Active | Y22: =RIGHT(E22,8) -> 72X45X08 | Z22: =LEFT(Y22,2) -> 72 | AA22: =MID(Y22,4,2) -> 45 | AB22: =RIGHT(Y22,2) -> 08 | AC22: =AC21 -> 72 | AD22: =AD21 -> 45 | AE22: =ROUNDUP(((((AC22+AD22)*2)+3)*0.0254),3) -> 6.02 | AG22: =U22 -> 6.02 | AH22: =VLOOKUP(R22,'SFG-RM'!A:B,2,0) -> 21.475377 | AI22: =AG22*AH22 -> 129.28177 | AT22: =AT21 -> 157.226 | AU22: =AU21 -> 177
A23: 22 | B23: 4 | C23: =C22 -> 3 | D23: =D22 -> 28.03.2024 | E23: =E22 -> SFG-FRBNET-MEM-BOR-72X45X08 | F23: =F22 -> Restonic Hotel Motel Bonnell Euro Top Memory Border 72X45X08 | G23: =G22 -> SFG-FRBNET-MEM-BOR-72X45X08 | H23: =H22 -> Restonic Hotel Motel Bonnell Euro Top Memory Border 72X45X08 | I23: Standard | J23: Production | K23: TAIL-BORDER | L23: NOS | M23: 1 | N23: MRP&Rollup | O23: CBESFG | P23: 40 | Q23: I | R23: RMI-HCC-SDE-LBL | S23: HOTEL COMFORT CARE SIDE LABEL (IMPORT) | T23: NOS | U23: 1 | V23: CBEWIP | W23: Backflush | X23: Active | Y23: =RIGHT(E23,8) -> 72X45X08 | Z23: =LEFT(Y23,2) -> 72 | AA23: =MID(Y23,4,2) -> 45 | AB23: =RIGHT(Y23,2) -> 08 | AC23: =AC22 -> 72 | AD23: =AD22 -> 45 | AE23: =ROUNDUP(((((72+30)*2)+3)*0.0254),3) -> 5.258 | AG23: =U23 -> 1 | AH23: =VLOOKUP(R23,'Rm-feb-24'!B:P,15,0) -> 5.9957 | AI23: =AG23*AH23 -> 5.9957 | AT23: =AT22 -> 157.226 | AU23: =AU22 -> 177
A24: 23 | B24: 5 | C24: =C23 -> 3 | D24: =D23 -> 28.03.2024 | E24: =E23 -> SFG-FRBNET-MEM-BOR-72X45X08 | F24: =F23 -> Restonic Hotel Motel Bonnell Euro Top Memory Border 72X45X08 | G24: =G23 -> SFG-FRBNET-MEM-BOR-72X45X08 | H24: =H23 -> Restonic Hotel Motel Bonnell Euro Top Memory Border 72X45X08 | I24: Standard | J24: Production | K24: TAIL-BORDER | L24: NOS | M24: 1 | N24: MRP&Rollup | O24: CBESFG | P24: 50 | Q24: I | R24: RML-MRP-BACK-LBL | S24: MRP BACK LABEL(PLAIN) | T24: NOS | U24: 1 | V24: CBEWIP | W24: Backflush | X24: Active | Y24: =RIGHT(E24,8) -> 72X45X08 | Z24: =LEFT(Y24,2) -> 72 | AA24: =MID(Y24,4,2) -> 45 | AB24: =RIGHT(Y24,2) -> 08 | AC24: =AC23 -> 72 | AD24: =AD23 -> 45 | AG24: =U24 -> 1 | AH24: =VLOOKUP(R24,'Rm-feb-24'!B:P,15,0) -> 1.3275 | AI24: =AG24*AH24 -> 1.3275 | AT24: =AT23 -> 157.226 | AU24: =AU23 -> 177
A25: 24 | B25: 6 | C25: =C24 -> 3 | D25: =D24 -> 28.03.2024 | E25: =E24 -> SFG-FRBNET-MEM-BOR-72X45X08 | F25: =F24 -> Restonic Hotel Motel Bonnell Euro Top Memory Border 72X45X08 | G25: =G24 -> SFG-FRBNET-MEM-BOR-72X45X08 | H25: =H24 -> Restonic Hotel Motel Bonnell Euro Top Memory Border 72X45X08 | I25: Standard | J25: Production | K25: TAIL-BORDER | L25: NOS | M25: 1 | N25: MRP&Rollup | O25: CBESFG | P25: 60 | Q25: I | R25: RML-DRN-LBL | S25: DIRECTION LABEL | T25: NOS | U25: 1 | V25: CBEWIP | W25: Backflush | X25: Active | Y25: =RIGHT(E25,8) -> 72X45X08 | Z25: =LEFT(Y25,2) -> 72 | AA25: =MID(Y25,4,2) -> 45 | AB25: =RIGHT(Y25,2) -> 08 | AC25: =AC24 -> 72 | AD25: =AD24 -> 45 | AG25: =U25 -> 1 | AH25: =VLOOKUP(R25,'Rm-feb-24'!B:P,15,0) -> 1.7318 | AI25: =AG25*AH25 -> 1.7318 | AT25: =AT24 -> 157.226 | AU25: =AU24 -> 177
A26: 25 | B26: 7 | C26: =C25 -> 3 | D26: =D25 -> 28.03.2024 | E26: =E25 -> SFG-FRBNET-MEM-BOR-72X45X08 | F26: =F25 -> Restonic Hotel Motel Bonnell Euro Top Memory Border 72X45X08 | G26: =G25 -> SFG-FRBNET-MEM-BOR-72X45X08 | H26: =H25 -> Restonic Hotel Motel Bonnell Euro Top Memory Border 72X45X08 | I26: Standard | J26: Production | K26: TAIL-BORDER | L26: NOS | M26: 1 | N26: MRP&Rollup | O26: CBESFG | P26: 70 | Q26: I | R26: SFG-RTHTMT-MEM-HANDLE | S26: Restonic Hotel Motel Memory Handle | T26: MTR | U26: 0.64 | V26: CBESFG | W26: Backflush | X26: Active | Y26: =RIGHT(E26,8) -> 72X45X08 | Z26: =LEFT(Y26,2) -> 72 | AA26: =MID(Y26,4,2) -> 45 | AB26: =RIGHT(Y26,2) -> 08 | AC26: =AC25 -> 72 | AD26: =AD25 -> 45 | AG26: =U26 -> 0.64 | AH26: =VLOOKUP(R26,'SFG-RM'!A:B,2,0) -> 14.621455 | AI26: =AG26*AH26 -> 9.3577314 | AT26: =AT25 -> 157.226 | AU26: =AU25 -> 177
A27: 26 | B27: 8 | C27: =C26 -> 3 | D27: =D26 -> 28.03.2024 | E27: =E26 -> SFG-FRBNET-MEM-BOR-72X45X08 | F27: =F26 -> Restonic Hotel Motel Bonnell Euro Top Memory Border 72X45X08 | G27: =G26 -> SFG-FRBNET-MEM-BOR-72X45X08 | H27: =H26 -> Restonic Hotel Motel Bonnell Euro Top Memory Border 72X45X08 | I27: Standard | J27: Production | K27: TAIL-BORDER | L27: NOS | M27: 1 | N27: MRP&Rollup | O27: CBESFG | P27: 80 | Q27: I | R27: RMI-BREATHER-GOLD | S27: BREATHER SET GOLD ROUND | T27: SET | U27: 2 | V27: CBEWIP | W27: Backflush | X27: Active | Y27: =RIGHT(E27,8) -> 72X45X08 | Z27: =LEFT(Y27,2) -> 72 | AA27: =MID(Y27,4,2) -> 45 | AB27: =RIGHT(Y27,2) -> 08 | AC27: =AC26 -> 72 | AD27: =AD26 -> 45 | AG27: =U27 -> 2 | AH27: =VLOOKUP(R27,'Rm-feb-24'!B:P,15,0) -> 4.6721 | AI27: =AG27*AH27 -> 9.3442 | AT27: =AT26 -> 157.226 | AU27: =AU26 -> 177
A28: 27
A29: 28 | B29: 1 | C29: 4 | D29: 28.03.2024 | E29: SFG-FRBNET-MEM-BOR-72X51X08 | F29: Restonic Hotel Motel Bonnell Euro Top Memory Border 72X51X08 | G29: =E29 -> SFG-FRBNET-MEM-BOR-72X51X08 | H29: =F29 -> Restonic Hotel Motel Bonnell Euro Top Memory Border 72X51X08 | I29: Standard | J29: Production | K29: TAIL-BORDER | L29: NOS | M29: 1 | N29: MRP&Rollup | O29: CBESFG | P29: 10 | Q29: I | R29: RM-THRD-QS-TKT40 | S29: THREAD TKT40 210D/3 PLY 10000MTS | T29: MTR | U29: 5.6 | V29: CBEWIP | W29: Backflush | X29: Active | Y29: =RIGHT(E29,8) -> 72X51X08 | Z29: =LEFT(Y29,2) -> 72 | AA29: =MID(Y29,4,2) -> 51 | AB29: =RIGHT(Y29,2) -> 08 | AC29: =Z29 -> 72 | AD29: =AA29 -> 51 | AG29: =U29/10000 -> 0.00056 | AH29: =VLOOKUP(R29,'Rm-feb-24'!B:P,15,0) -> 231.1423 | AI29: =AG29*AH29 -> 0.12943969 | AJ29: =SUM(AI29:AI36) -> 163.77613 | AK29: =ROUND(AJ29,3) -> 163.776 | AL29: =AK29 -> 163.776 | AM29: =+AL29+AR29 -> 184.04312 | AN29: =+SUM(((AL29*3%*18%))) -> 0.8843904 | AO29: =+SUM(((AL29*14.33%*53%))) -> 12.438623 | AP29: =+SUM(((AL29*5.92%*53%))) -> 5.1386358 | AQ29: =+SUM(((AL29*2.08%*53%))) -> 1.8054666 | AR29: =SUM(AN29:AQ29) -> 20.267116 | AS29: =ROUNDUP(AM29,0) -> 185 | AT29: =AL29 -> 163.776 | AU29: =AS29 -> 185
A30: 29 | B30: 2 | C30: =C29 -> 4 | D30: =D29 -> 28.03.2024 | E30: =E29 -> SFG-FRBNET-MEM-BOR-72X51X08 | F30: =F29 -> Restonic Hotel Motel Bonnell Euro Top Memory Border 72X51X08 | G30: =G29 -> SFG-FRBNET-MEM-BOR-72X51X08 | H30: =H29 -> Restonic Hotel Motel Bonnell Euro Top Memory Border 72X51X08 | I30: Standard | J30: Production | K30: TAIL-BORDER | L30: NOS | M30: 1 | N30: MRP&Rollup | O30: CBESFG | P30: 20 | Q30: I | R30: HW-CTON-THREAD | S30: COTTON THREAD WHITE 3PLY | T30: MTR | U30: 5 | V30: CBEWIP | W30: Backflush | X30: Active | Y30: =RIGHT(E30,8) -> 72X51X08 | Z30: =LEFT(Y30,2) -> 72 | AA30: =MID(Y30,4,2) -> 51 | AB30: =RIGHT(Y30,2) -> 08 | AC30: =AC29 -> 72 | AD30: =AD29 -> 51 | AG30: =U30/5000 -> 0.001 | AH30: =VLOOKUP(R30,'Rm-feb-24'!B:P,15,0) -> 58 | AI30: =AG30*AH30 -> 0.058 | AT30: =AT29 -> 163.776 | AU30: =AU29 -> 185
A31: 30 | B31: 3 | C31: =C30 -> 4 | D31: =D30 -> 28.03.2024 | E31: =E30 -> SFG-FRBNET-MEM-BOR-72X51X08 | F31: =F30 -> Restonic Hotel Motel Bonnell Euro Top Memory Border 72X51X08 | G31: =G30 -> SFG-FRBNET-MEM-BOR-72X51X08 | H31: =H30 -> Restonic Hotel Motel Bonnell Euro Top Memory Border 72X51X08 | I31: Standard | J31: Production | K31: TAIL-BORDER | L31: NOS | M31: 1 | N31: MRP&Rollup | O31: CBESFG | P31: 30 | Q31: I | R31: SFG-RTHTMT-BNPK-MEM-BOR-21CM | S31: Hotel Motel Poc ET-8 8MM/16D Pre Foam Memory Border 21 CM Height | T31: MTR | U31: =AE31 -> 6.325 | V31: CBESFG | W31: Backflush | X31: Active | Y31: =RIGHT(E31,8) -> 72X51X08 | Z31: =LEFT(Y31,2) -> 72 | AA31: =MID(Y31,4,2) -> 51 | AB31: =RIGHT(Y31,2) -> 08 | AC31: =AC30 -> 72 | AD31: =AD30 -> 51 | AE31: =ROUNDUP(((((AC31+AD31)*2)+3)*0.0254),3) -> 6.325 | AG31: =U31 -> 6.325 | AH31: =VLOOKUP(R31,'SFG-RM'!A:B,2,0) -> 21.475377 | AI31: =AG31*AH31 -> 135.83176 | AT31: =AT30 -> 163.776 | AU31: =AU30 -> 185
A32: 31 | B32: 4 | C32: =C31 -> 4 | D32: =D31 -> 28.03.2024 | E32: =E31 -> SFG-FRBNET-MEM-BOR-72X51X08 | F32: =F31 -> Restonic Hotel Motel Bonnell Euro Top Memory Border 72X51X08 | G32: =G31 -> SFG-FRBNET-MEM-BOR-72X51X08 | H32: =H31 -> Restonic Hotel Motel Bonnell Euro Top Memory Border 72X51X08 | I32: Standard | J32: Production | K32: TAIL-BORDER | L32: NOS | M32: 1 | N32: MRP&Rollup | O32: CBESFG | P32: 40 | Q32: I | R32: RMI-HCC-SDE-LBL | S32: HOTEL COMFORT CARE SIDE LABEL (IMPORT) | T32: NOS | U32: 1 | V32: CBEWIP | W32: Backflush | X32: Active | Y32: =RIGHT(E32,8) -> 72X51X08 | Z32: =LEFT(Y32,2) -> 72 | AA32: =MID(Y32,4,2) -> 51 | AB32: =RIGHT(Y32,2) -> 08 | AC32: =AC31 -> 72 | AD32: =AD31 -> 51 | AE32: =ROUNDUP(((((72+30)*2)+3)*0.0254),3) -> 5.258 | AG32: =U32 -> 1 | AH32: =VLOOKUP(R32,'Rm-feb-24'!B:P,15,0) -> 5.9957 | AI32: =AG32*AH32 -> 5.9957 | AT32: =AT31 -> 163.776 | AU32: =AU31 -> 185
A33: 32 | B33: 5 | C33: =C32 -> 4 | D33: =D32 -> 28.03.2024 | E33: =E32 -> SFG-FRBNET-MEM-BOR-72X51X08 | F33: =F32 -> Restonic Hotel Motel Bonnell Euro Top Memory Border 72X51X08 | G33: =G32 -> SFG-FRBNET-MEM-BOR-72X51X08 | H33: =H32 -> Restonic Hotel Motel Bonnell Euro Top Memory Border 72X51X08 | I33: Standard | J33: Production | K33: TAIL-BORDER | L33: NOS | M33: 1 | N33: MRP&Rollup | O33: CBESFG | P33: 50 | Q33: I | R33: RML-MRP-BACK-LBL | S33: MRP BACK LABEL(PLAIN) | T33: NOS | U33: 1 | V33: CBEWIP | W33: Backflush | X33: Active | Y33: =RIGHT(E33,8) -> 72X51X08 | Z33: =LEFT(Y33,2) -> 72 | AA33: =MID(Y33,4,2) -> 51 | AB33: =RIGHT(Y33,2) -> 08 | AC33: =AC32 -> 72 | AD33: =AD32 -> 51 | AG33: =U33 -> 1 | AH33: =VLOOKUP(R33,'Rm-feb-24'!B:P,15,0) -> 1.3275 | AI33: =AG33*AH33 -> 1.3275 | AT33: =AT32 -> 163.776 | AU33: =AU32 -> 185
A34: 33 | B34: 6 | C34: =C33 -> 4 | D34: =D33 -> 28.03.2024 | E34: =E33 -> SFG-FRBNET-MEM-BOR-72X51X08 | F34: =F33 -> Restonic Hotel Motel Bonnell Euro Top Memory Border 72X51X08 | G34: =G33 -> SFG-FRBNET-MEM-BOR-72X51X08 | H34: =H33 -> Restonic Hotel Motel Bonnell Euro Top Memory Border 72X51X08 | I34: Standard | J34: Production | K34: TAIL-BORDER | L34: NOS | M34: 1 | N34: MRP&Rollup | O34: CBESFG | P34: 60 | Q34: I | R34: RML-DRN-LBL | S34: DIRECTION LABEL | T34: NOS | U34: 1 | V34: CBEWIP | W34: Backflush | X34: Active | Y34: =RIGHT(E34,8) -> 72X51X08 | Z34: =LEFT(Y34,2) -> 72 | AA34: =MID(Y34,4,2) -> 51 | AB34: =RIGHT(Y34,2) -> 08 | AC34: =AC33 -> 72 | AD34: =AD33 -> 51 | AG34: =U34 -> 1 | AH34: =VLOOKUP(R34,'Rm-feb-24'!B:P,15,0) -> 1.7318 | AI34: =AG34*AH34 -> 1.7318 | AT34: =AT33 -> 163.776 | AU34: =AU33 -> 185
A35: 34 | B35: 7 | C35: =C34 -> 4 | D35: =D34 -> 28.03.2024 | E35: =E34 -> SFG-FRBNET-MEM-BOR-72X51X08 | F35: =F34 -> Restonic Hotel Motel Bonnell Euro Top Memory Border 72X51X08 | G35: =G34 -> SFG-FRBNET-MEM-BOR-72X51X08 | H35: =H34 -> Restonic Hotel Motel Bonnell Euro Top Memory Border 72X51X08 | I35: Standard | J35: Production | K35: TAIL-BORDER | L35: NOS | M35: 1 | N35: MRP&Rollup | O35: CBESFG | P35: 70 | Q35: I | R35: SFG-RTHTMT-MEM-HANDLE | S35: Restonic Hotel Motel Memory Handle | T35: MTR | U35: 0.64 | V35: CBESFG | W35: Backflush | X35: Active | Y35: =RIGHT(E35,8) -> 72X51X08 | Z35: =LEFT(Y35,2) -> 72 | AA35: =MID(Y35,4,2) -> 51 | AB35: =RIGHT(Y35,2) -> 08 | AC35: =AC34 -> 72 | AD35: =AD34 -> 51 | AG35: =U35 -> 0.64 | AH35: =VLOOKUP(R35,'SFG-RM'!A:B,2,0) -> 14.621455 | AI35: =AG35*AH35 -> 9.3577314 | AT35: =AT34 -> 163.776 | AU35: =AU34 -> 185
A36: 35 | B36: 8 | C36: =C35 -> 4 | D36: =D35 -> 28.03.2024 | E36: =E35 -> SFG-FRBNET-MEM-BOR-72X51X08 | F36: =F35 -> Restonic Hotel Motel Bonnell Euro Top Memory Border 72X51X08 | G36: =G35 -> SFG-FRBNET-MEM-BOR-72X51X08 | H36: =H35 -> Restonic Hotel Motel Bonnell Euro Top Memory Border 72X51X08 | I36: Standard | J36: Production | K36: TAIL-BORDER | L36: NOS | M36: 1 | N36: MRP&Rollup | O36: CBESFG | P36: 80 | Q36: I | R36: RMI-BREATHER-GOLD | S36: BREATHER SET GOLD ROUND | T36: SET | U36: 2 | V36: CBEWIP | W36: Backflush | X36: Active | Y36: =RIGHT(E36,8) -> 72X51X08 | Z36: =LEFT(Y36,2) -> 72 | AA36: =MID(Y36,4,2) -> 51 | AB36: =RIGHT(Y36,2) -> 08 | AC36: =AC35 -> 72 | AD36: =AD35 -> 51 | AG36: =U36 -> 2 | AH36: =VLOOKUP(R36,'Rm-feb-24'!B:P,15,0) -> 4.6721 | AI36: =AG36*AH36 -> 9.3442 | AT36: =AT35 -> 163.776 | AU36: =AU35 -> 185
A37: 36
A38: 37 | B38: 1 | C38: 5 | D38: 28.03.2024 | E38: SFG-FRBNET-MEM-BOR-72X54X08 | F38: Restonic Hotel Motel Bonnell Euro Top Memory Border 72X54X08 | G38: =E38 -> SFG-FRBNET-MEM-BOR-72X54X08 | H38: =F38 -> Restonic Hotel Motel Bonnell Euro Top Memory Border 72X54X08 | I38: Standard | J38: Production | K38: TAIL-BORDER | L38: NOS | M38: 1 | N38: MRP&Rollup | O38: CBESFG | P38: 10 | Q38: I | R38: RM-THRD-QS-TKT40 | S38: THREAD TKT40 210D/3 PLY 10000MTS | T38: MTR | U38: 5.6 | V38: CBEWIP | W38: Backflush | X38: Active | Y38: =RIGHT(E38,8) -> 72X54X08 | Z38: =LEFT(Y38,2) -> 72 | AA38: =MID(Y38,4,2) -> 54 | AB38: =RIGHT(Y38,2) -> 08 | AC38: =Z38 -> 72 | AD38: =AA38 -> 54 | AG38: =U38/10000 -> 0.00056 | AH38: =VLOOKUP(R38,'Rm-feb-24'!B:P,15,0) -> 231.1423 | AI38: =AG38*AH38 -> 0.12943969 | AJ38: =SUM(AI38:AI45) -> 167.04039 | AK38: =ROUND(AJ38,3) -> 167.04 | AL38: =AK38 -> 167.04 | AM38: =+AL38+AR38 -> 187.71103 | AN38: =+SUM(((AL38*3%*18%))) -> 0.902016 | AO38: =+SUM(((AL38*14.33%*53%))) -> 12.686521 | AP38: =+SUM(((AL38*5.92%*53%))) -> 5.241047 | AQ38: =+SUM(((AL38*2.08%*53%))) -> 1.841449 | AR38: =SUM(AN38:AQ38) -> 20.671033 | AS38: =ROUNDUP(AM38,0) -> 188 | AT38: =AL38 -> 167.04 | AU38: =AS38 -> 188
A39: 38 | B39: 2 | C39: =C38 -> 5 | D39: =D38 -> 28.03.2024 | E39: =E38 -> SFG-FRBNET-MEM-BOR-72X54X08 | F39: =F38 -> Restonic Hotel Motel Bonnell Euro Top Memory Border 72X54X08 | G39: =G38 -> SFG-FRBNET-MEM-BOR-72X54X08 | H39: =H38 -> Restonic Hotel Motel Bonnell Euro Top Memory Border 72X54X08 | I39: Standard | J39: Production | K39: TAIL-BORDER | L39: NOS | M39: 1 | N39: MRP&Rollup | O39: CBESFG | P39: 20 | Q39: I | R39: HW-CTON-THREAD | S39: COTTON THREAD WHITE 3PLY | T39: MTR | U39: 5 | V39: CBEWIP | W39: Backflush | X39: Active | Y39: =RIGHT(E39,8) -> 72X54X08 | Z39: =LEFT(Y39,2) -> 72 | AA39: =MID(Y39,4,2) -> 54 | AB39: =RIGHT(Y39,2) -> 08 | AC39: =AC38 -> 72 | AD39: =AD38 -> 54 | AG39: =U39/5000 -> 0.001 | AH39: =VLOOKUP(R39,'Rm-feb-24'!B:P,15,0) -> 58 | AI39: =AG39*AH39 -> 0.058 | AT39: =AT38 -> 167.04 | AU39: =AU38 -> 188
A40: 39 | B40: 3 | C40: =C39 -> 5 | D40: =D39 -> 28.03.2024 | E40: =E39 -> SFG-FRBNET-MEM-BOR-72X54X08 | F40: =F39 -> Restonic Hotel Motel Bonnell Euro Top Memory Border 72X54X08 | G40: =G39 -> SFG-FRBNET-MEM-BOR-72X54X08 | H40: =H39 -> Restonic Hotel Motel Bonnell Euro Top Memory Border 72X54X08 | I40: Standard | J40: Production | K40: TAIL-BORDER | L40: NOS | M40: 1 | N40: MRP&Rollup | O40: CBESFG | P40: 30 | Q40: I | R40: SFG-RTHTMT-BNPK-MEM-BOR-21CM | S40: Hotel Motel Poc ET-8 8MM/16D Pre Foam Memory Border 21 CM Height | T40: MTR | U40: =AE40 -> 6.477 | V40: CBESFG | W40: Backflush | X40: Active | Y40: =RIGHT(E40,8) -> 72X54X08 | Z40: =LEFT(Y40,2) -> 72 | AA40: =MID(Y40,4,2) -> 54 | AB40: =RIGHT(Y40,2) -> 08 | AC40: =AC39 -> 72 | AD40: =AD39 -> 54 | AE40: =ROUNDUP(((((AC40+AD40)*2)+3)*0.0254),3) -> 6.477 | AG40: =U40 -> 6.477 | AH40: =VLOOKUP(R40,'SFG-RM'!A:B,2,0) -> 21.475377 | AI40: =AG40*AH40 -> 139.09602 | AT40: =AT39 -> 167.04 | AU40: =AU39 -> 188
A41: 40 | B41: 4 | C41: =C40 -> 5 | D41: =D40 -> 28.03.2024 | E41: =E40 -> SFG-FRBNET-MEM-BOR-72X54X08 | F41: =F40 -> Restonic Hotel Motel Bonnell Euro Top Memory Border 72X54X08 | G41: =G40 -> SFG-FRBNET-MEM-BOR-72X54X08 | H41: =H40 -> Restonic Hotel Motel Bonnell Euro Top Memory Border 72X54X08 | I41: Standard | J41: Production | K41: TAIL-BORDER | L41: NOS | M41: 1 | N41: MRP&Rollup | O41: CBESFG | P41: 40 | Q41: I | R41: RMI-HCC-SDE-LBL | S41: HOTEL COMFORT CARE SIDE LABEL (IMPORT) | T41: NOS | U41: 1 | V41: CBEWIP | W41: Backflush | X41: Active | Y41: =RIGHT(E41,8) -> 72X54X08 | Z41: =LEFT(Y41,2) -> 72 | AA41: =MID(Y41,4,2) -> 54 | AB41: =RIGHT(Y41,2) -> 08 | AC41: =AC40 -> 72 | AD41: =AD40 -> 54 | AE41: =ROUNDUP(((((72+30)*2)+3)*0.0254),3) -> 5.258 | AG41: =U41 -> 1 | AH41: =VLOOKUP(R41,'Rm-feb-24'!B:P,15,0) -> 5.9957 | AI41: =AG41*AH41 -> 5.9957 | AT41: =AT40 -> 167.04 | AU41: =AU40 -> 188
A42: 41 | B42: 5 | C42: =C41 -> 5 | D42: =D41 -> 28.03.2024 | E42: =E41 -> SFG-FRBNET-MEM-BOR-72X54X08 | F42: =F41 -> Restonic Hotel Motel Bonnell Euro Top Memory Border 72X54X08 | G42: =G41 -> SFG-FRBNET-MEM-BOR-72X54X08 | H42: =H41 -> Restonic Hotel Motel Bonnell Euro Top Memory Border 72X54X08 | I42: Standard | J42: Production | K42: TAIL-BORDER | L42: NOS | M42: 1 | N42: MRP&Rollup | O42: CBESFG | P42: 50 | Q42: I | R42: RML-MRP-BACK-LBL | S42: MRP BACK LABEL(PLAIN) | T42: NOS | U42: 1 | V42: CBEWIP | W42: Backflush | X42: Active | Y42: =RIGHT(E42,8) -> 72X54X08 | Z42: =LEFT(Y42,2) -> 72 | AA42: =MID(Y42,4,2) -> 54 | AB42: =RIGHT(Y42,2) -> 08 | AC42: =AC41 -> 72 | AD42: =AD41 -> 54 | AG42: =U42 -> 1 | AH42: =VLOOKUP(R42,'Rm-feb-24'!B:P,15,0) -> 1.3275 | AI42: =AG42*AH42 -> 1.3275 | AT42: =AT41 -> 167.04 | AU42: =AU41 -> 188
A43: 42 | B43: 6 | C43: =C42 -> 5 | D43: =D42 -> 28.03.2024 | E43: =E42 -> SFG-FRBNET-MEM-BOR-72X54X08 | F43: =F42 -> Restonic Hotel Motel Bonnell Euro Top Memory Border 72X54X08 | G43: =G42 -> SFG-FRBNET-MEM-BOR-72X54X08 | H43: =H42 -> Restonic Hotel Motel Bonnell Euro Top Memory Border 72X54X08 | I43: Standard | J43: Production | K43: TAIL-BORDER | L43: NOS | M43: 1 | N43: MRP&Rollup | O43: CBESFG | P43: 60 | Q43: I | R43: RML-DRN-LBL | S43: DIRECTION LABEL | T43: NOS | U43: 1 | V43: CBEWIP | W43: Backflush | X43: Active | Y43: =RIGHT(E43,8) -> 72X54X08 | Z43: =LEFT(Y43,2) -> 72 | AA43: =MID(Y43,4,2) -> 54 | AB43: =RIGHT(Y43,2) -> 08 | AC43: =AC42 -> 72 | AD43: =AD42 -> 54 | AG43: =U43 -> 1 | AH43: =VLOOKUP(R43,'Rm-feb-24'!B:P,15,0) -> 1.7318 | AI43: =AG43*AH43 -> 1.7318 | AT43: =AT42 -> 167.04 | AU43: =AU42 -> 188
A44: 43 | B44: 7 | C44: =C43 -> 5 | D44: =D43 -> 28.03.2024 | E44: =E43 -> SFG-FRBNET-MEM-BOR-72X54X08 | F44: =F43 -> Restonic Hotel Motel Bonnell Euro Top Memory Border 72X54X08 | G44: =G43 -> SFG-FRBNET-MEM-BOR-72X54X08 | H44: =H43 -> Restonic Hotel Motel Bonnell Euro Top Memory Border 72X54X08 | I44: Standard | J44: Production | K44: TAIL-BORDER | L44: NOS | M44: 1 | N44: MRP&Rollup | O44: CBESFG | P44: 70 | Q44: I | R44: SFG-RTHTMT-MEM-HANDLE | S44: Restonic Hotel Motel Memory Handle | T44: MTR | U44: 0.64 | V44: CBESFG | W44: Backflush | X44: Active | Y44: =RIGHT(E44,8) -> 72X54X08 | Z44: =LEFT(Y44,2) -> 72 | AA44: =MID(Y44,4,2) -> 54 | AB44: =RIGHT(Y44,2) -> 08 | AC44: =AC43 -> 72 | AD44: =AD43 -> 54 | AG44: =U44 -> 0.64 | AH44: =VLOOKUP(R44,'SFG-RM'!A:B,2,0) -> 14.621455 | AI44: =AG44*AH44 -> 9.3577314 | AT44: =AT43 -> 167.04 | AU44: =AU43 -> 188
A45: 44 | B45: 8 | C45: =C44 -> 5 | D45: =D44 -> 28.03.2024 | E45: =E44 -> SFG-FRBNET-MEM-BOR-72X54X08 | F45: =F44 -> Restonic Hotel Motel Bonnell Euro Top Memory Border 72X54X08 | G45: =G44 -> SFG-FRBNET-MEM-BOR-72X54X08 | H45: =H44 -> Restonic Hotel Motel Bonnell Euro Top Memory Border 72X54X08 | I45: Standard | J45: Production | K45: TAIL-BORDER | L45: NOS | M45: 1 | N45: MRP&Rollup | O45: CBESFG | P45: 80 | Q45: I | R45: RMI-BREATHER-GOLD | S45: BREATHER SET GOLD ROUND | T45: SET | U45: 2 | V45: CBEWIP | W45: Backflush | X45: Active | Y45: =RIGHT(E45,8) -> 72X54X08 | Z45: =LEFT(Y45,2) -> 72 | AA45: =MID(Y45,4,2) -> 54 | AB45: =RIGHT(Y45,2) -> 08 | AC45: =AC44 -> 72 | AD45: =AD44 -> 54 | AG45: =U45 -> 2 | AH45: =VLOOKUP(R45,'Rm-feb-24'!B:P,15,0) -> 4.6721 | AI45: =AG45*AH45 -> 9.3442 | AT45: =AT44 -> 167.04 | AU45: =AU44 -> 188
A46: 45
A47: 46 | B47: 1 | C47: 6 | D47: 28.03.2024 | E47: SFG-FRBNET-MEM-BOR-72X57X08 | F47: Restonic Hotel Motel Bonnell Euro Top Memory Border 72X57X08 | G47: =E47 -> SFG-FRBNET-MEM-BOR-72X57X08 | H47: =F47 -> Restonic Hotel Motel Bonnell Euro Top Memory Border 72X57X08 | I47: Standard | J47: Production | K47: TAIL-BORDER | L47: NOS | M47: 1 | N47: MRP&Rollup | O47: CBESFG | P47: 10 | Q47: I | R47: RM-THRD-QS-TKT40 | S47: THREAD TKT40 210D/3 PLY 10000MTS | T47: MTR | U47: 5.6 | V47: CBEWIP | W47: Backflush | X47: Active | Y47: =RIGHT(E47,8) -> 72X57X08 | Z47: =LEFT(Y47,2) -> 72 | AA47: =MID(Y47,4,2) -> 57 | AB47: =RIGHT(Y47,2) -> 08 | AC47: =Z47 -> 72 | AD47: =AA47 -> 57 | AG47: =U47/10000 -> 0.00056 | AH47: =VLOOKUP(R47,'Rm-feb-24'!B:P,15,0) -> 231.1423 | AI47: =AG47*AH47 -> 0.12943969 | AJ47: =SUM(AI47:AI54) -> 170.32612 | AK47: =ROUND(AJ47,3) -> 170.326 | AL47: =AK47 -> 170.326 | AM47: =+AL47+AR47 -> 191.40367 | AN47: =+SUM(((AL47*3%*18%))) -> 0.9197604 | AO47: =+SUM(((AL47*14.33%*53%))) -> 12.936089 | AP47: =+SUM(((AL47*5.92%*53%))) -> 5.3441486 | AQ47: =+SUM(((AL47*2.08%*53%))) -> 1.8776738 | AR47: =SUM(AN47:AQ47) -> 21.077672 | AS47: =ROUNDUP(AM47,0) -> 192 | AT47: =AL47 -> 170.326 | AU47: =AS47 -> 192
A48: 47 | B48: 2 | C48: =C47 -> 6 | D48: =D47 -> 28.03.2024 | E48: =E47 -> SFG-FRBNET-MEM-BOR-72X57X08 | F48: =F47 -> Restonic Hotel Motel Bonnell Euro Top Memory Border 72X57X08 | G48: =G47 -> SFG-FRBNET-MEM-BOR-72X57X08 | H48: =H47 -> Restonic Hotel Motel Bonnell Euro Top Memory Border 72X57X08 | I48: Standard | J48: Production | K48: TAIL-BORDER | L48: NOS | M48: 1 | N48: MRP&Rollup | O48: CBESFG | P48: 20 | Q48: I | R48: HW-CTON-THREAD | S48: COTTON THREAD WHITE 3PLY | T48: MTR | U48: 5 | V48: CBEWIP | W48: Backflush | X48: Active | Y48: =RIGHT(E48,8) -> 72X57X08 | Z48: =LEFT(Y48,2) -> 72 | AA48: =MID(Y48,4,2) -> 57 | AB48: =RIGHT(Y48,2) -> 08 | AC48: =AC47 -> 72 | AD48: =AD47 -> 57 | AG48: =U48/5000 -> 0.001 | AH48: =VLOOKUP(R48,'Rm-feb-24'!B:P,15,0) -> 58 | AI48: =AG48*AH48 -> 0.058 | AT48: =AT47 -> 170.326 | AU48: =AU47 -> 192
A49: 48 | B49: 3 | C49: =C48 -> 6 | D49: =D48 -> 28.03.2024 | E49: =E48 -> SFG-FRBNET-MEM-BOR-72X57X08 | F49: =F48 -> Restonic Hotel Motel Bonnell Euro Top Memory Border 72X57X08 | G49: =G48 -> SFG-FRBNET-MEM-BOR-72X57X08 | H49: =H48 -> Restonic Hotel Motel Bonnell Euro Top Memory Border 72X57X08 | I49: Standard | J49: Production | K49: TAIL-BORDER | L49: NOS | M49: 1 | N49: MRP&Rollup | O49: CBESFG | P49: 30 | Q49: I | R49: SFG-RTHTMT-BNPK-MEM-BOR-21CM | S49: Hotel Motel Poc ET-8 8MM/16D Pre Foam Memory Border 21 CM Height | T49: MTR | U49: =AE49 -> 6.63 | V49: CBESFG | W49: Backflush | X49: Active | Y49: =RIGHT(E49,8) -> 72X57X08 | Z49: =LEFT(Y49,2) -> 72 | AA49: =MID(Y49,4,2) -> 57 | AB49: =RIGHT(Y49,2) -> 08 | AC49: =AC48 -> 72 | AD49: =AD48 -> 57 | AE49: =ROUNDUP(((((AC49+AD49)*2)+3)*0.0254),3) -> 6.63 | AG49: =U49 -> 6.63 | AH49: =VLOOKUP(R49,'SFG-RM'!A:B,2,0) -> 21.475377 | AI49: =AG49*AH49 -> 142.38175 | AT49: =AT48 -> 170.326 | AU49: =AU48 -> 192
A50: 49 | B50: 4 | C50: =C49 -> 6 | D50: =D49 -> 28.03.2024 | E50: =E49 -> SFG-FRBNET-MEM-BOR-72X57X08 | F50: =F49 -> Restonic Hotel Motel Bonnell Euro Top Memory Border 72X57X08 | G50: =G49 -> SFG-FRBNET-MEM-BOR-72X57X08 | H50: =H49 -> Restonic Hotel Motel Bonnell Euro Top Memory Border 72X57X08 | I50: Standard | J50: Production | K50: TAIL-BORDER | L50: NOS | M50: 1 | N50: MRP&Rollup | O50: CBESFG | P50: 40 | Q50: I | R50: RMI-HCC-SDE-LBL | S50: HOTEL COMFORT CARE SIDE LABEL (IMPORT) | T50: NOS | U50: 1 | V50: CBEWIP | W50: Backflush | X50: Active | Y50: =RIGHT(E50,8) -> 72X57X08 | Z50: =LEFT(Y50,2) -> 72 | AA50: =MID(Y50,4,2) -> 57 | AB50: =RIGHT(Y50,2) -> 08 | AC50: =AC49 -> 72 | AD50: =AD49 -> 57 | AE50: =ROUNDUP(((((72+30)*2)+3)*0.0254),3) -> 5.258 | AG50: =U50 -> 1 | AH50: =VLOOKUP(R50,'Rm-feb-24'!B:P,15,0) -> 5.9957 | AI50: =AG50*AH50 -> 5.9957 | AT50: =AT49 -> 170.326 | AU50: =AU49 -> 192
A51: 50 | B51: 5 | C51: =C50 -> 6 | D51: =D50 -> 28.03.2024 | E51: =E50 -> SFG-FRBNET-MEM-BOR-72X57X08 | F51: =F50 -> Restonic Hotel Motel Bonnell Euro Top Memory Border 72X57X08 | G51: =G50 -> SFG-FRBNET-MEM-BOR-72X57X08 | H51: =H50 -> Restonic Hotel Motel Bonnell Euro Top Memory Border 72X57X08 | I51: Standard | J51: Production | K51: TAIL-BORDER | L51: NOS | M51: 1 | N51: MRP&Rollup | O51: CBESFG | P51: 50 | Q51: I | R51: RML-MRP-BACK-LBL | S51: MRP BACK LABEL(PLAIN) | T51: NOS | U51: 1 | V51: CBEWIP | W51: Backflush | X51: Active | Y51: =RIGHT(E51,8) -> 72X57X08 | Z51: =LEFT(Y51,2) -> 72 | AA51: =MID(Y51,4,2) -> 57 | AB51: =RIGHT(Y51,2) -> 08 | AC51: =AC50 -> 72 | AD51: =AD50 -> 57 | AG51: =U51 -> 1 | AH51: =VLOOKUP(R51,'Rm-feb-24'!B:P,15,0) -> 1.3275 | AI51: =AG51*AH51 -> 1.3275 | AT51: =AT50 -> 170.326 | AU51: =AU50 -> 192
A52: 51 | B52: 6 | C52: =C51 -> 6 | D52: =D51 -> 28.03.2024 | E52: =E51 -> SFG-FRBNET-MEM-BOR-72X57X08 | F52: =F51 -> Restonic Hotel Motel Bonnell Euro Top Memory Border 72X57X08 | G52: =G51 -> SFG-FRBNET-MEM-BOR-72X57X08 | H52: =H51 -> Restonic Hotel Motel Bonnell Euro Top Memory Border 72X57X08 | I52: Standard | J52: Production | K52: TAIL-BORDER | L52: NOS | M52: 1 | N52: MRP&Rollup | O52: CBESFG | P52: 60 | Q52: I | R52: RML-DRN-LBL | S52: DIRECTION LABEL | T52: NOS | U52: 1 | V52: CBEWIP | W52: Backflush | X52: Active | Y52: =RIGHT(E52,8) -> 72X57X08 | Z52: =LEFT(Y52,2) -> 72 | AA52: =MID(Y52,4,2) -> 57 | AB52: =RIGHT(Y52,2) -> 08 | AC52: =AC51 -> 72 | AD52: =AD51 -> 57 | AG52: =U52 -> 1 | AH52: =VLOOKUP(R52,'Rm-feb-24'!B:P,15,0) -> 1.7318 | AI52: =AG52*AH52 -> 1.7318 | AT52: =AT51 -> 170.326 | AU52: =AU51 -> 192
A53: 52 | B53: 7 | C53: =C52 -> 6 | D53: =D52 -> 28.03.2024 | E53: =E52 -> SFG-FRBNET-MEM-BOR-72X57X08 | F53: =F52 -> Restonic Hotel Motel Bonnell Euro Top Memory Border 72X57X08 | G53: =G52 -> SFG-FRBNET-MEM-BOR-72X57X08 | H53: =H52 -> Restonic Hotel Motel Bonnell Euro Top Memory Border 72X57X08 | I53: Standard | J53: Production | K53: TAIL-BORDER | L53: NOS | M53: 1 | N53: MRP&Rollup | O53: CBESFG | P53: 70 | Q53: I | R53: SFG-RTHTMT-MEM-HANDLE | S53: Restonic Hotel Motel Memory Handle | T53: MTR | U53: 0.64 | V53: CBESFG | W53: Backflush | X53: Active | Y53: =RIGHT(E53,8) -> 72X57X08 | Z53: =LEFT(Y53,2) -> 72 | AA53: =MID(Y53,4,2) -> 57 | AB53: =RIGHT(Y53,2) -> 08 | AC53: =AC52 -> 72 | AD53: =AD52 -> 57 | AG53: =U53 -> 0.64 | AH53: =VLOOKUP(R53,'SFG-RM'!A:B,2,0) -> 14.621455 | AI53: =AG53*AH53 -> 9.3577314 | AT53: =AT52 -> 170.326 | AU53: =AU52 -> 192
A54: 53 | B54: 8 | C54: =C53 -> 6 | D54: =D53 -> 28.03.2024 | E54: =E53 -> SFG-FRBNET-MEM-BOR-72X57X08 | F54: =F53 -> Restonic Hotel Motel Bonnell Euro Top Memory Border 72X57X08 | G54: =G53 -> SFG-FRBNET-MEM-BOR-72X57X08 | H54: =H53 -> Restonic Hotel Motel Bonnell Euro Top Memory Border 72X57X08 | I54: Standard | J54: Production | K54: TAIL-BORDER | L54: NOS | M54: 1 | N54: MRP&Rollup | O54: CBESFG | P54: 80 | Q54: I | R54: RMI-BREATHER-GOLD | S54: BREATHER SET GOLD ROUND | T54: SET | U54: 2 | V54: CBEWIP | W54: Backflush | X54: Active | Y54: =RIGHT(E54,8) -> 72X57X08 | Z54: =LEFT(Y54,2) -> 72 | AA54: =MID(Y54,4,2) -> 57 | AB54: =RIGHT(Y54,2) -> 08 | AC54: =AC53 -> 72 | AD54: =AD53 -> 57 | AG54: =U54 -> 2 | AH54: =VLOOKUP(R54,'Rm-feb-24'!B:P,15,0) -> 4.6721 | AI54: =AG54*AH54 -> 9.3442 | AT54: =AT53 -> 170.326 | AU54: =AU53 -> 192
A55: 54
A56: 55 | B56: 1 | C56: 7 | D56: 28.03.2024 | E56: SFG-FRBNET-MEM-BOR-72X63X08 | F56: Restonic Hotel Motel Bonnell Euro Top Memory Border 72X63X08 | G56: =E56 -> SFG-FRBNET-MEM-BOR-72X63X08 | H56: =F56 -> Restonic Hotel Motel Bonnell Euro Top Memory Border 72X63X08 | I56: Standard | J56: Production | K56: TAIL-BORDER | L56: NOS | M56: 1 | N56: MRP&Rollup | O56: CBESFG | P56: 10 | Q56: I | R56: RM-THRD-QS-TKT40 | S56: THREAD TKT40 210D/3 PLY 10000MTS | T56: MTR | U56: 5.6 | V56: CBEWIP | W56: Backflush | X56: Active | Y56: =RIGHT(E56,8) -> 72X63X08 | Z56: =LEFT(Y56,2) -> 72 | AA56: =MID(Y56,4,2) -> 63 | AB56: =RIGHT(Y56,2) -> 08 | AC56: =Z56 -> 72 | AD56: =AA56 -> 63 | AG56: =U56/10000 -> 0.00056 | AH56: =VLOOKUP(R56,'Rm-feb-24'!B:P,15,0) -> 231.1423 | AI56: =AG56*AH56 -> 0.12943969 | AJ56: =SUM(AI56:AI63) -> 176.87611 | AK56: =ROUND(AJ56,3) -> 176.876 | AL56: =AK56 -> 176.876 | AM56: =+AL56+AR56 -> 198.76423 | AN56: =+SUM(((AL56*3%*18%))) -> 0.9551304 | AO56: =+SUM(((AL56*14.33%*53%))) -> 13.433555 | AP56: =+SUM(((AL56*5.92%*53%))) -> 5.5496614 | AQ56: =+SUM(((AL56*2.08%*53%))) -> 1.949881 | AR56: =SUM(AN56:AQ56) -> 21.888228 | AS56: =ROUNDUP(AM56,0) -> 199 | AT56: =AL56 -> 176.876 | AU56: =AS56 -> 199
A57: 56 | B57: 2 | C57: =C56 -> 7 | D57: =D56 -> 28.03.2024 | E57: =E56 -> SFG-FRBNET-MEM-BOR-72X63X08 | F57: =F56 -> Restonic Hotel Motel Bonnell Euro Top Memory Border 72X63X08 | G57: =G56 -> SFG-FRBNET-MEM-BOR-72X63X08 | H57: =H56 -> Restonic Hotel Motel Bonnell Euro Top Memory Border 72X63X08 | I57: Standard | J57: Production | K57: TAIL-BORDER | L57: NOS | M57: 1 | N57: MRP&Rollup | O57: CBESFG | P57: 20 | Q57: I | R57: HW-CTON-THREAD | S57: COTTON THREAD WHITE 3PLY | T57: MTR | U57: 5 | V57: CBEWIP | W57: Backflush | X57: Active | Y57: =RIGHT(E57,8) -> 72X63X08 | Z57: =LEFT(Y57,2) -> 72 | AA57: =MID(Y57,4,2) -> 63 | AB57: =RIGHT(Y57,2) -> 08 | AC57: =AC56 -> 72 | AD57: =AD56 -> 63 | AG57: =U57/5000 -> 0.001 | AH57: =VLOOKUP(R57,'Rm-feb-24'!B:P,15,0) -> 58 | AI57: =AG57*AH57 -> 0.058 | AT57: =AT56 -> 176.876 | AU57: =AU56 -> 199
A58: 57 | B58: 3 | C58: =C57 -> 7 | D58: =D57 -> 28.03.2024 | E58: =E57 -> SFG-FRBNET-MEM-BOR-72X63X08 | F58: =F57 -> Restonic Hotel Motel Bonnell Euro Top Memory Border 72X63X08 | G58: =G57 -> SFG-FRBNET-MEM-BOR-72X63X08 | H58: =H57 -> Restonic Hotel Motel Bonnell Euro Top Memory Border 72X63X08 | I58: Standard | J58: Production | K58: TAIL-BORDER | L58: NOS | M58: 1 | N58: MRP&Rollup | O58: CBESFG | P58: 30 | Q58: I | R58: SFG-RTHTMT-BNPK-MEM-BOR-21CM | S58: Hotel Motel Poc ET-8 8MM/16D Pre Foam Memory Border 21 CM Height | T58: MTR | U58: =AE58 -> 6.935 | V58: CBESFG | W58: Backflush | X58: Active | Y58: =RIGHT(E58,8) -> 72X63X08 | Z58: =LEFT(Y58,2) -> 72 | AA58: =MID(Y58,4,2) -> 63 | AB58: =RIGHT(Y58,2) -> 08 | AC58: =AC57 -> 72 | AD58: =AD57 -> 63 | AE58: =ROUNDUP(((((AC58+AD58)*2)+3)*0.0254),3) -> 6.935 | AG58: =U58 -> 6.935 | AH58: =VLOOKUP(R58,'SFG-RM'!A:B,2,0) -> 21.475377 | AI58: =AG58*AH58 -> 148.93174 | AT58: =AT57 -> 176.876 | AU58: =AU57 -> 199
A59: 58 | B59: 4 | C59: =C58 -> 7 | D59: =D58 -> 28.03.2024 | E59: =E58 -> SFG-FRBNET-MEM-BOR-72X63X08 | F59: =F58 -> Restonic Hotel Motel Bonnell Euro Top Memory Border 72X63X08 | G59: =G58 -> SFG-FRBNET-MEM-BOR-72X63X08 | H59: =H58 -> Restonic Hotel Motel Bonnell Euro Top Memory Border 72X63X08 | I59: Standard | J59: Production | K59: TAIL-BORDER | L59: NOS | M59: 1 | N59: MRP&Rollup | O59: CBESFG | P59: 40 | Q59: I | R59: RMI-HCC-SDE-LBL | S59: HOTEL COMFORT CARE SIDE LABEL (IMPORT) | T59: NOS | U59: 1 | V59: CBEWIP | W59: Backflush | X59: Active | Y59: =RIGHT(E59,8) -> 72X63X08 | Z59: =LEFT(Y59,2) -> 72 | AA59: =MID(Y59,4,2) -> 63 | AB59: =RIGHT(Y59,2) -> 08 | AC59: =AC58 -> 72 | AD59: =AD58 -> 63 | AE59: =ROUNDUP(((((72+30)*2)+3)*0.0254),3) -> 5.258 | AG59: =U59 -> 1 | AH59: =VLOOKUP(R59,'Rm-feb-24'!B:P,15,0) -> 5.9957 | AI59: =AG59*AH59 -> 5.9957 | AT59: =AT58 -> 176.876 | AU59: =AU58 -> 199
A60: 59 | B60: 5 | C60: =C59 -> 7 | D60: =D59 -> 28.03.2024 | E60: =E59 -> SFG-FRBNET-MEM-BOR-72X63X08 | F60: =F59 -> Restonic Hotel Motel Bonnell Euro Top Memory Border 72X63X08 | G60: =G59 -> SFG-FRBNET-MEM-BOR-72X63X08 | H60: =H59 -> Restonic Hotel Motel Bonnell Euro Top Memory Border 72X63X08 | I60: Standard | J60: Production | K60: TAIL-BORDER | L60: NOS | M60: 1 | N60: MRP&Rollup | O60: CBESFG | P60: 50 | Q60: I | R60: RML-MRP-BACK-LBL | S60: MRP BACK LABEL(PLAIN) | T60: NOS | U60: 1 | V60: CBEWIP | W60: Backflush | X60: Active | Y60: =RIGHT(E60,8) -> 72X63X08 | Z60: =LEFT(Y60,2) -> 72 | AA60: =MID(Y60,4,2) -> 63 | AB60: =RIGHT(Y60,2) -> 08 | AC60: =AC59 -> 72 | AD60: =AD59 -> 63 | AG60: =U60 -> 1 | AH60: =VLOOKUP(R60,'Rm-feb-24'!B:P,15,0) -> 1.3275 | AI60: =AG60*AH60 -> 1.3275 | AT60: =AT59 -> 176.876 | AU60: =AU59 -> 199
A61: 60 | B61: 6 | C61: =C60 -> 7 | D61: =D60 -> 28.03.2024 | E61: =E60 -> SFG-FRBNET-MEM-BOR-72X63X08 | F61: =F60 -> Restonic Hotel Motel Bonnell Euro Top Memory Border 72X63X08 | G61: =G60 -> SFG-FRBNET-MEM-BOR-72X63X08 | H61: =H60 -> Restonic Hotel Motel Bonnell Euro Top Memory Border 72X63X08 | I61: Standard | J61: Production | K61: TAIL-BORDER | L61: NOS | M61: 1 | N61: MRP&Rollup | O61: CBESFG | P61: 60 | Q61: I | R61: RML-DRN-LBL | S61: DIRECTION LABEL | T61: NOS | U61: 1 | V61: CBEWIP | W61: Backflush | X61: Active | Y61: =RIGHT(E61,8) -> 72X63X08 | Z61: =LEFT(Y61,2) -> 72 | AA61: =MID(Y61,4,2) -> 63 | AB61: =RIGHT(Y61,2) -> 08 | AC61: =AC60 -> 72 | AD61: =AD60 -> 63 | AG61: =U61 -> 1 | AH61: =VLOOKUP(R61,'Rm-feb-24'!B:P,15,0) -> 1.7318 | AI61: =AG61*AH61 -> 1.7318 | AT61: =AT60 -> 176.876 | AU61: =AU60 -> 199
A62: 61 | B62: 7 | C62: =C61 -> 7 | D62: =D61 -> 28.03.2024 | E62: =E61 -> SFG-FRBNET-MEM-BOR-72X63X08 | F62: =F61 -> Restonic Hotel Motel Bonnell Euro Top Memory Border 72X63X08 | G62: =G61 -> SFG-FRBNET-MEM-BOR-72X63X08 | H62: =H61 -> Restonic Hotel Motel Bonnell Euro Top Memory Border 72X63X08 | I62: Standard | J62: Production | K62: TAIL-BORDER | L62: NOS | M62: 1 | N62: MRP&Rollup | O62: CBESFG | P62: 70 | Q62: I | R62: SFG-RTHTMT-MEM-HANDLE | S62: Restonic Hotel Motel Memory Handle | T62: MTR | U62: 0.64 | V62: CBESFG | W62: Backflush | X62: Active | Y62: =RIGHT(E62,8) -> 72X63X08 | Z62: =LEFT(Y62,2) -> 72 | AA62: =MID(Y62,4,2) -> 63 | AB62: =RIGHT(Y62,2) -> 08 | AC62: =AC61 -> 72 | AD62: =AD61 -> 63 | AG62: =U62 -> 0.64 | AH62: =VLOOKUP(R62,'SFG-RM'!A:B,2,0) -> 14.621455 | AI62: =AG62*AH62 -> 9.3577314 | AT62: =AT61 -> 176.876 | AU62: =AU61 -> 199
A63: 62 | B63: 8 | C63: =C62 -> 7 | D63: =D62 -> 28.03.2024 | E63: =E62 -> SFG-FRBNET-MEM-BOR-72X63X08 | F63: =F62 -> Restonic Hotel Motel Bonnell Euro Top Memory Border 72X63X08 | G63: =G62 -> SFG-FRBNET-MEM-BOR-72X63X08 | H63: =H62 -> Restonic Hotel Motel Bonnell Euro Top Memory Border 72X63X08 | I63: Standard | J63: Production | K63: TAIL-BORDER | L63: NOS | M63: 1 | N63: MRP&Rollup | O63: CBESFG | P63: 80 | Q63: I | R63: RMI-BREATHER-GOLD | S63: BREATHER SET GOLD ROUND | T63: SET | U63: 2 | V63: CBEWIP | W63: Backflush | X63: Active | Y63: =RIGHT(E63,8) -> 72X63X08 | Z63: =LEFT(Y63,2) -> 72 | AA63: =MID(Y63,4,2) -> 63 | AB63: =RIGHT(Y63,2) -> 08 | AC63: =AC62 -> 72 | AD63: =AD62 -> 63 | AG63: =U63 -> 2 | AH63: =VLOOKUP(R63,'Rm-feb-24'!B:P,15,0) -> 4.6721 | AI63: =AG63*AH63 -> 9.3442 | AT63: =AT62 -> 176.876 | AU63: =AU62 -> 199
A64: 63
A65: 64 | B65: 1 | C65: 8 | D65: 28.03.2024 | E65: SFG-FRBNET-MEM-BOR-72X69X08 | F65: Restonic Hotel Motel Bonnell Euro Top Memory Border 72X69X08 | G65: =E65 -> SFG-FRBNET-MEM-BOR-72X69X08 | H65: =F65 -> Restonic Hotel Motel Bonnell Euro Top Memory Border 72X69X08 | I65: Standard | J65: Production | K65: TAIL-BORDER | L65: NOS | M65: 1 | N65: MRP&Rollup | O65: CBESFG | P65: 10 | Q65: I | R65: RM-THRD-QS-TKT40 | S65: THREAD TKT40 210D/3 PLY 10000MTS | T65: MTR | U65: 5.6 | V65: CBEWIP | W65: Backflush | X65: Active | Y65: =RIGHT(E65,8) -> 72X69X08 | Z65: =LEFT(Y65,2) -> 72 | AA65: =MID(Y65,4,2) -> 69 | AB65: =RIGHT(Y65,2) -> 08 | AC65: =Z65 -> 72 | AD65: =AA65 -> 69 | AG65: =U65/10000 -> 0.00056 | AH65: =VLOOKUP(R65,'Rm-feb-24'!B:P,15,0) -> 231.1423 | AI65: =AG65*AH65 -> 0.12943969 | AJ65: =SUM(AI65:AI72) -> 183.40463 | AK65: =ROUND(AJ65,3) -> 183.405 | AL65: =AK65 -> 183.405 | AM65: =+AL65+AR65 -> 206.10119 | AN65: =+SUM(((AL65*3%*18%))) -> 0.990387 | AO65: =+SUM(((AL65*14.33%*53%))) -> 13.929426 | AP65: =+SUM(((AL65*5.92%*53%))) -> 5.7545153 | AQ65: =+SUM(((AL65*2.08%*53%))) -> 2.0218567 | AR65: =SUM(AN65:AQ65) -> 22.696185 | AS65: =ROUNDUP(AM65,0) -> 207 | AT65: =AL65 -> 183.405 | AU65: =AS65 -> 207
A66: 65 | B66: 2 | C66: =C65 -> 8 | D66: =D65 -> 28.03.2024 | E66: =E65 -> SFG-FRBNET-MEM-BOR-72X69X08 | F66: =F65 -> Restonic Hotel Motel Bonnell Euro Top Memory Border 72X69X08 | G66: =G65 -> SFG-FRBNET-MEM-BOR-72X69X08 | H66: =H65 -> Restonic Hotel Motel Bonnell Euro Top Memory Border 72X69X08 | I66: Standard | J66: Production | K66: TAIL-BORDER | L66: NOS | M66: 1 | N66: MRP&Rollup | O66: CBESFG | P66: 20 | Q66: I | R66: HW-CTON-THREAD | S66: COTTON THREAD WHITE 3PLY | T66: MTR | U66: 5 | V66: CBEWIP | W66: Backflush | X66: Active | Y66: =RIGHT(E66,8) -> 72X69X08 | Z66: =LEFT(Y66,2) -> 72 | AA66: =MID(Y66,4,2) -> 69 | AB66: =RIGHT(Y66,2) -> 08 | AC66: =AC65 -> 72 | AD66: =AD65 -> 69 | AG66: =U66/5000 -> 0.001 | AH66: =VLOOKUP(R66,'Rm-feb-24'!B:P,15,0) -> 58 | AI66: =AG66*AH66 -> 0.058 | AT66: =AT65 -> 183.405 | AU66: =AU65 -> 207
A67: 66 | B67: 3 | C67: =C66 -> 8 | D67: =D66 -> 28.03.2024 | E67: =E66 -> SFG-FRBNET-MEM-BOR-72X69X08 | F67: =F66 -> Restonic Hotel Motel Bonnell Euro Top Memory Border 72X69X08 | G67: =G66 -> SFG-FRBNET-MEM-BOR-72X69X08 | H67: =H66 -> Restonic Hotel Motel Bonnell Euro Top Memory Border 72X69X08 | I67: Standard | J67: Production | K67: TAIL-BORDER | L67: NOS | M67: 1 | N67: MRP&Rollup | O67: CBESFG | P67: 30 | Q67: I | R67: SFG-RTHTMT-BNPK-MEM-BOR-21CM | S67: Hotel Motel Poc ET-8 8MM/16D Pre Foam Memory Border 21 CM Height | T67: MTR | U67: =AE67 -> 7.239 | V67: CBESFG | W67: Backflush | X67: Active | Y67: =RIGHT(E67,8) -> 72X69X08 | Z67: =LEFT(Y67,2) -> 72 | AA67: =MID(Y67,4,2) -> 69 | AB67: =RIGHT(Y67,2) -> 08 | AC67: =AC66 -> 72 | AD67: =AD66 -> 69 | AE67: =ROUNDUP(((((AC67+AD67)*2)+3)*0.0254),3) -> 7.239 | AG67: =U67 -> 7.239 | AH67: =VLOOKUP(R67,'SFG-RM'!A:B,2,0) -> 21.475377 | AI67: =AG67*AH67 -> 155.46026 | AT67: =AT66 -> 183.405 | AU67: =AU66 -> 207
A68: 67 | B68: 4 | C68: =C67 -> 8 | D68: =D67 -> 28.03.2024 | E68: =E67 -> SFG-FRBNET-MEM-BOR-72X69X08 | F68: =F67 -> Restonic Hotel Motel Bonnell Euro Top Memory Border 72X69X08 | G68: =G67 -> SFG-FRBNET-MEM-BOR-72X69X08 | H68: =H67 -> Restonic Hotel Motel Bonnell Euro Top Memory Border 72X69X08 | I68: Standard | J68: Production | K68: TAIL-BORDER | L68: NOS | M68: 1 | N68: MRP&Rollup | O68: CBESFG | P68: 40 | Q68: I | R68: RMI-HCC-SDE-LBL | S68: HOTEL COMFORT CARE SIDE LABEL (IMPORT) | T68: NOS | U68: 1 | V68: CBEWIP | W68: Backflush | X68: Active | Y68: =RIGHT(E68,8) -> 72X69X08 | Z68: =LEFT(Y68,2) -> 72 | AA68: =MID(Y68,4,2) -> 69 | AB68: =RIGHT(Y68,2) -> 08 | AC68: =AC67 -> 72 | AD68: =AD67 -> 69 | AE68: =ROUNDUP(((((72+30)*2)+3)*0.0254),3) -> 5.258 | AG68: =U68 -> 1 | AH68: =VLOOKUP(R68,'Rm-feb-24'!B:P,15,0) -> 5.9957 | AI68: =AG68*AH68 -> 5.9957 | AT68: =AT67 -> 183.405 | AU68: =AU67 -> 207
A69: 68 | B69: 5 | C69: =C68 -> 8 | D69: =D68 -> 28.03.2024 | E69: =E68 -> SFG-FRBNET-MEM-BOR-72X69X08 | F69: =F68 -> Restonic Hotel Motel Bonnell Euro Top Memory Border 72X69X08 | G69: =G68 -> SFG-FRBNET-MEM-BOR-72X69X08 | H69: =H68 -> Restonic Hotel Motel Bonnell Euro Top Memory Border 72X69X08 | I69: Standard | J69: Production | K69: TAIL-BORDER | L69: NOS | M69: 1 | N69: MRP&Rollup | O69: CBESFG | P69: 50 | Q69: I | R69: RML-MRP-BACK-LBL | S69: MRP BACK LABEL(PLAIN) | T69: NOS | U69: 1 | V69: CBEWIP | W69: Backflush | X69: Active | Y69: =RIGHT(E69,8) -> 72X69X08 | Z69: =LEFT(Y69,2) -> 72 | AA69: =MID(Y69,4,2) -> 69 | AB69: =RIGHT(Y69,2) -> 08 | AC69: =AC68 -> 72 | AD69: =AD68 -> 69 | AG69: =U69 -> 1 | AH69: =VLOOKUP(R69,'Rm-feb-24'!B:P,15,0) -> 1.3275 | AI69: =AG69*AH69 -> 1.3275 | AT69: =AT68 -> 183.405 | AU69: =AU68 -> 207
A70: 69 | B70: 6 | C70: =C69 -> 8 | D70: =D69 -> 28.03.2024 | E70: =E69 -> SFG-FRBNET-MEM-BOR-72X69X08 | F70: =F69 -> Restonic Hotel Motel Bonnell Euro Top Memory Border 72X69X08 | G70: =G69 -> SFG-FRBNET-MEM-BOR-72X69X08 | H70: =H69 -> Restonic Hotel Motel Bonnell Euro Top Memory Border 72X69X08 | I70: Standard | J70: Production | K70: TAIL-BORDER | L70: NOS | M70: 1 | N70: MRP&Rollup | O70: CBESFG | P70: 60 | Q70: I | R70: RML-DRN-LBL | S70: DIRECTION LABEL | T70: NOS | U70: 1 | V70: CBEWIP | W70: Backflush | X70: Active | Y70: =RIGHT(E70,8) -> 72X69X08 | Z70: =LEFT(Y70,2) -> 72 | AA70: =MID(Y70,4,2) -> 69 | AB70: =RIGHT(Y70,2) -> 08 | AC70: =AC69 -> 72 | AD70: =AD69 -> 69 | AG70: =U70 -> 1 | AH70: =VLOOKUP(R70,'Rm-feb-24'!B:P,15,0) -> 1.7318 | AI70: =AG70*AH70 -> 1.7318 | AT70: =AT69 -> 183.405 | AU70: =AU69 -> 207
A71: 70 | B71: 7 | C71: =C70 -> 8 | D71: =D70 -> 28.03.2024 | E71: =E70 -> SFG-FRBNET-MEM-BOR-72X69X08 | F71: =F70 -> Restonic Hotel Motel Bonnell Euro Top Memory Border 72X69X08 | G71: =G70 -> SFG-FRBNET-MEM-BOR-72X69X08 | H71: =H70 -> Restonic Hotel Motel Bonnell Euro Top Memory Border 72X69X08 | I71: Standard | J71: Production | K71: TAIL-BORDER | L71: NOS | M71: 1 | N71: MRP&Rollup | O71: CBESFG | P71: 70 | Q71: I | R71: SFG-RTHTMT-MEM-HANDLE | S71: Restonic Hotel Motel Memory Handle | T71: MTR | U71: 0.64 | V71: CBESFG | W71: Backflush | X71: Active | Y71: =RIGHT(E71,8) -> 72X69X08 | Z71: =LEFT(Y71,2) -> 72 | AA71: =MID(Y71,4,2) -> 69 | AB71: =RIGHT(Y71,2) -> 08 | AC71: =AC70 -> 72 | AD71: =AD70 -> 69 | AG71: =U71 -> 0.64 | AH71: =VLOOKUP(R71,'SFG-RM'!A:B,2,0) -> 14.621455 | AI71: =AG71*AH71 -> 9.3577314 | AT71: =AT70 -> 183.405 | AU71: =AU70 -> 207
A72: 71 | B72: 8 | C72: =C71 -> 8 | D72: =D71 -> 28.03.2024 | E72: =E71 -> SFG-FRBNET-MEM-BOR-72X69X08 | F72: =F71 -> Restonic Hotel Motel Bonnell Euro Top Memory Border 72X69X08 | G72: =G71 -> SFG-FRBNET-MEM-BOR-72X69X08 | H72: =H71 -> Restonic Hotel Motel Bonnell Euro Top Memory Border 72X69X08 | I72: Standard | J72: Production | K72: TAIL-BORDER | L72: NOS | M72: 1 | N72: MRP&Rollup | O72: CBESFG | P72: 80 | Q72: I | R72: RMI-BREATHER-GOLD | S72: BREATHER SET GOLD ROUND | T72: SET | U72: 2 | V72: CBEWIP | W72: Backflush | X72: Active | Y72: =RIGHT(E72,8) -> 72X69X08 | Z72: =LEFT(Y72,2) -> 72 | AA72: =MID(Y72,4,2) -> 69 | AB72: =RIGHT(Y72,2) -> 08 | AC72: =AC71 -> 72 | AD72: =AD71 -> 69 | AG72: =U72 -> 2 | AH72: =VLOOKUP(R72,'Rm-feb-24'!B:P,15,0) -> 4.6721 | AI72: =AG72*AH72 -> 9.3442 | AT72: =AT71 -> 183.405 | AU72: =AU71 -> 207
A73: 72
A74: 73 | B74: 1 | C74: 9 | D74: 28.03.2024 | E74: SFG-FRBNET-MEM-BOR-75X33X08 | F74: Restonic Hotel Motel Bonnell Euro Top Memory Border 75X33X08 | G74: =E74 -> SFG-FRBNET-MEM-BOR-75X33X08 | H74: =F74 -> Restonic Hotel Motel Bonnell Euro Top Memory Border 75X33X08 | I74: Standard | J74: Production | K74: TAIL-BORDER | L74: NOS | M74: 1 | N74: MRP&Rollup | O74: CBESFG | P74: 10 | Q74: I | R74: RM-THRD-QS-TKT40 | S74: THREAD TKT40 210D/3 PLY 10000MTS | T74: MTR | U74: 5.6 | V74: CBEWIP | W74: Backflush | X74: Active | Y74: =RIGHT(E74,8) -> 75X33X08 | Z74: =LEFT(Y74,2) -> 75 | AA74: =MID(Y74,4,2) -> 33 | AB74: =RIGHT(Y74,2) -> 08 | AC74: =Z74 -> 75 | AD74: =AA74 -> 33 | AG74: =U74/10000 -> 0.00056 | AH74: =VLOOKUP(R74,'Rm-feb-24'!B:P,15,0) -> 231.1423 | AI74: =AG74*AH74 -> 0.12943969 | AJ74: =SUM(AI74:AI81) -> 147.41189 | AK74: =ROUND(AJ74,3) -> 147.412 | AL74: =AK74 -> 147.412 | AM74: =+AL74+AR74 -> 165.65409 | AN74: =+SUM(((AL74*3%*18%))) -> 0.7960248 | AO74: =+SUM(((AL74*14.33%*53%))) -> 11.195794 | AP74: =+SUM(((AL74*5.92%*53%))) -> 4.6251989 | AQ74: =+SUM(((AL74*2.08%*53%))) -> 1.6250699 | AR74: =SUM(AN74:AQ74) -> 18.242088 | AS74: =ROUNDUP(AM74,0) -> 166 | AT74: =AL74 -> 147.412 | AU74: =AS74 -> 166
A75: 74 | B75: 2 | C75: =C74 -> 9 | D75: =D74 -> 28.03.2024 | E75: =E74 -> SFG-FRBNET-MEM-BOR-75X33X08 | F75: =F74 -> Restonic Hotel Motel Bonnell Euro Top Memory Border 75X33X08 | G75: =G74 -> SFG-FRBNET-MEM-BOR-75X33X08 | H75: =H74 -> Restonic Hotel Motel Bonnell Euro Top Memory Border 75X33X08 | I75: Standard | J75: Production | K75: TAIL-BORDER | L75: NOS | M75: 1 | N75: MRP&Rollup | O75: CBESFG | P75: 20 | Q75: I | R75: HW-CTON-THREAD | S75: COTTON THREAD WHITE 3PLY | T75: MTR | U75: 5 | V75: CBEWIP | W75: Backflush | X75: Active | Y75: =RIGHT(E75,8) -> 75X33X08 | Z75: =LEFT(Y75,2) -> 75 | AA75: =MID(Y75,4,2) -> 33 | AB75: =RIGHT(Y75,2) -> 08 | AC75: =AC74 -> 75 | AD75: =AD74 -> 33 | AG75: =U75/5000 -> 0.001 | AH75: =VLOOKUP(R75,'Rm-feb-24'!B:P,15,0) -> 58 | AI75: =AG75*AH75 -> 0.058 | AT75: =AT74 -> 147.412 | AU75: =AU74 -> 166
A76: 75 | B76: 3 | C76: =C75 -> 9 | D76: =D75 -> 28.03.2024 | E76: =E75 -> SFG-FRBNET-MEM-BOR-75X33X08 | F76: =F75 -> Restonic Hotel Motel Bonnell Euro Top Memory Border 75X33X08 | G76: =G75 -> SFG-FRBNET-MEM-BOR-75X33X08 | H76: =H75 -> Restonic Hotel Motel Bonnell Euro Top Memory Border 75X33X08 | I76: Standard | J76: Production | K76: TAIL-BORDER | L76: NOS | M76: 1 | N76: MRP&Rollup | O76: CBESFG | P76: 30 | Q76: I | R76: SFG-RTHTMT-BNPK-MEM-BOR-21CM | S76: Hotel Motel Poc ET-8 8MM/16D Pre Foam Memory Border 21 CM Height | T76: MTR | U76: =AE76 -> 5.563 | V76: CBESFG | W76: Backflush | X76: Active | Y76: =RIGHT(E76,8) -> 75X33X08 | Z76: =LEFT(Y76,2) -> 75 | AA76: =MID(Y76,4,2) -> 33 | AB76: =RIGHT(Y76,2) -> 08 | AC76: =AC75 -> 75 | AD76: =AD75 -> 33 | AE76: =ROUNDUP(((((AC76+AD76)*2)+3)*0.0254),3) -> 5.563 | AG76: =U76 -> 5.563 | AH76: =VLOOKUP(R76,'SFG-RM'!A:B,2,0) -> 21.475377 | AI76: =AG76*AH76 -> 119.46752 | AT76: =AT75 -> 147.412 | AU76: =AU75 -> 166
A77: 76 | B77: 4 | C77: =C76 -> 9 | D77: =D76 -> 28.03.2024 | E77: =E76 -> SFG-FRBNET-MEM-BOR-75X33X08 | F77: =F76 -> Restonic Hotel Motel Bonnell Euro Top Memory Border 75X33X08 | G77: =G76 -> SFG-FRBNET-MEM-BOR-75X33X08 | H77: =H76 -> Restonic Hotel Motel Bonnell Euro Top Memory Border 75X33X08 | I77: Standard | J77: Production | K77: TAIL-BORDER | L77: NOS | M77: 1 | N77: MRP&Rollup | O77: CBESFG | P77: 40 | Q77: I | R77: RMI-HCC-SDE-LBL | S77: HOTEL COMFORT CARE SIDE LABEL (IMPORT) | T77: NOS | U77: 1 | V77: CBEWIP | W77: Backflush | X77: Active | Y77: =RIGHT(E77,8) -> 75X33X08 | Z77: =LEFT(Y77,2) -> 75 | AA77: =MID(Y77,4,2) -> 33 | AB77: =RIGHT(Y77,2) -> 08 | AC77: =AC76 -> 75 | AD77: =AD76 -> 33 | AE77: =ROUNDUP(((((72+30)*2)+3)*0.0254),3) -> 5.258 | AG77: =U77 -> 1 | AH77: =VLOOKUP(R77,'Rm-feb-24'!B:P,15,0) -> 5.9957 | AI77: =AG77*AH77 -> 5.9957 | AT77: =AT76 -> 147.412 | AU77: =AU76 -> 166
A78: 77 | B78: 5 | C78: =C77 -> 9 | D78: =D77 -> 28.03.2024 | E78: =E77 -> SFG-FRBNET-MEM-BOR-75X33X08 | F78: =F77 -> Restonic Hotel Motel Bonnell Euro Top Memory Border 75X33X08 | G78: =G77 -> SFG-FRBNET-MEM-BOR-75X33X08 | H78: =H77 -> Restonic Hotel Motel Bonnell Euro Top Memory Border 75X33X08 | I78: Standard | J78: Production | K78: TAIL-BORDER | L78: NOS | M78: 1 | N78: MRP&Rollup | O78: CBESFG | P78: 50 | Q78: I | R78: RML-MRP-BACK-LBL | S78: MRP BACK LABEL(PLAIN) | T78: NOS | U78: 1 | V78: CBEWIP | W78: Backflush | X78: Active | Y78: =RIGHT(E78,8) -> 75X33X08 | Z78: =LEFT(Y78,2) -> 75 | AA78: =MID(Y78,4,2) -> 33 | AB78: =RIGHT(Y78,2) -> 08 | AC78: =AC77 -> 75 | AD78: =AD77 -> 33 | AG78: =U78 -> 1 | AH78: =VLOOKUP(R78,'Rm-feb-24'!B:P,15,0) -> 1.3275 | AI78: =AG78*AH78 -> 1.3275 | AT78: =AT77 -> 147.412 | AU78: =AU77 -> 166
A79: 78 | B79: 6 | C79: =C78 -> 9 | D79: =D78 -> 28.03.2024 | E79: =E78 -> SFG-FRBNET-MEM-BOR-75X33X08 | F79: =F78 -> Restonic Hotel Motel Bonnell Euro Top Memory Border 75X33X08 | G79: =G78 -> SFG-FRBNET-MEM-BOR-75X33X08 | H79: =H78 -> Restonic Hotel Motel Bonnell Euro Top Memory Border 75X33X08 | I79: Standard | J79: Production | K79: TAIL-BORDER | L79: NOS | M79: 1 | N79: MRP&Rollup | O79: CBESFG | P79: 60 | Q79: I | R79: RML-DRN-LBL | S79: DIRECTION LABEL | T79: NOS | U79: 1 | V79: CBEWIP | W79: Backflush | X79: Active | Y79: =RIGHT(E79,8) -> 75X33X08 | Z79: =LEFT(Y79,2) -> 75 | AA79: =MID(Y79,4,2) -> 33 | AB79: =RIGHT(Y79,2) -> 08 | AC79: =AC78 -> 75 | AD79: =AD78 -> 33 | AG79: =U79 -> 1 | AH79: =VLOOKUP(R79,'Rm-feb-24'!B:P,15,0) -> 1.7318 | AI79: =AG79*AH79 -> 1.7318 | AT79: =AT78 -> 147.412 | AU79: =AU78 -> 166
A80: 79 | B80: 7 | C80: =C79 -> 9 | D80: =D79 -> 28.03.2024 | E80: =E79 -> SFG-FRBNET-MEM-BOR-75X33X08 | F80: =F79 -> Restonic Hotel Motel Bonnell Euro Top Memory Border 75X33X08 | G80: =G79 -> SFG-FRBNET-MEM-BOR-75X33X08 | H80: =H79 -> Restonic Hotel Motel Bonnell Euro Top Memory Border 75X33X08 | I80: Standard | J80: Production | K80: TAIL-BORDER | L80: NOS | M80: 1 | N80: MRP&Rollup | O80: CBESFG | P80: 70 | Q80: I | R80: SFG-RTHTMT-MEM-HANDLE | S80: Restonic Hotel Motel Memory Handle | T80: MTR | U80: 0.64 | V80: CBESFG | W80: Backflush | X80: Active | Y80: =RIGHT(E80,8) -> 75X33X08 | Z80: =LEFT(Y80,2) -> 75 | AA80: =MID(Y80,4,2) -> 33 | AB80: =RIGHT(Y80,2) -> 08 | AC80: =AC79 -> 75 | AD80: =AD79 -> 33 | AG80: =U80 -> 0.64 | AH80: =VLOOKUP(R80,'SFG-RM'!A:B,2,0) -> 14.621455 | AI80: =AG80*AH80 -> 9.3577314 | AT80: =AT79 -> 147.412 | AU80: =AU79 -> 166
A81: 80 | B81: 8 | C81: =C80 -> 9 | D81: =D80 -> 28.03.2024 | E81: =E80 -> SFG-FRBNET-MEM-BOR-75X33X08 | F81: =F80 -> Restonic Hotel Motel Bonnell Euro Top Memory Border 75X33X08 | G81: =G80 -> SFG-FRBNET-MEM-BOR-75X33X08 | H81: =H80 -> Restonic Hotel Motel Bonnell Euro Top Memory Border 75X33X08 | I81: Standard | J81: Production | K81: TAIL-BORDER | L81: NOS | M81: 1 | N81: MRP&Rollup | O81: CBESFG | P81: 80 | Q81: I | R81: RMI-BREATHER-GOLD | S81: BREATHER SET GOLD ROUND | T81: SET | U81: 2 | V81: CBEWIP | W81: Backflush | X81: Active | Y81: =RIGHT(E81,8) -> 75X33X08 | Z81: =LEFT(Y81,2) -> 75 | AA81: =MID(Y81,4,2) -> 33 | AB81: =RIGHT(Y81,2) -> 08 | AC81: =AC80 -> 75 | AD81: =AD80 -> 33 | AG81: =U81 -> 2 | AH81: =VLOOKUP(R81,'Rm-feb-24'!B:P,15,0) -> 4.6721 | AI81: =AG81*AH81 -> 9.3442 | AT81: =AT80 -> 147.412 | AU81: =AU80 -> 166
A82: 81
A83: 82 | B83: 1 | C83: 10 | D83: 28.03.2024 | E83: SFG-FRBNET-MEM-BOR-75X39X08 | F83: Restonic Hotel Motel Bonnell Euro Top Memory Border 75X39X08 | G83: =E83 -> SFG-FRBNET-MEM-BOR-75X39X08 | H83: =F83 -> Restonic Hotel Motel Bonnell Euro Top Memory Border 75X39X08 | I83: Standard | J83: Production | K83: TAIL-BORDER | L83: NOS | M83: 1 | N83: MRP&Rollup | O83: CBESFG | P83: 10 | Q83: I | R83: RM-THRD-QS-TKT40 | S83: THREAD TKT40 210D/3 PLY 10000MTS | T83: MTR | U83: 5.6 | V83: CBEWIP | W83: Backflush | X83: Active | Y83: =RIGHT(E83,8) -> 75X39X08 | Z83: =LEFT(Y83,2) -> 75 | AA83: =MID(Y83,4,2) -> 39 | AB83: =RIGHT(Y83,2) -> 08 | AC83: =Z83 -> 75 | AD83: =AA83 -> 39 | AG83: =U83/10000 -> 0.00056 | AH83: =VLOOKUP(R83,'Rm-feb-24'!B:P,15,0) -> 231.1423 | AI83: =AG83*AH83 -> 0.12943969 | AJ83: =SUM(AI83:AI90) -> 153.96188 | AK83: =ROUND(AJ83,3) -> 153.962 | AL83: =AK83 -> 153.962 | AM83: =+AL83+AR83 -> 173.01464 | AN83: =+SUM(((AL83*3%*18%))) -> 0.8313948 | AO83: =+SUM(((AL83*14.33%*53%))) -> 11.69326 | AP83: =+SUM(((AL83*5.92%*53%))) -> 4.8307117 | AQ83: =+SUM(((AL83*2.08%*53%))) -> 1.6972771 | AR83: =SUM(AN83:AQ83) -> 19.052644 | AS83: =ROUNDUP(AM83,0) -> 174 | AT83: =AL83 -> 153.962 | AU83: =AS83 -> 174
A84: 83 | B84: 2 | C84: =C83 -> 10 | D84: =D83 -> 28.03.2024 | E84: =E83 -> SFG-FRBNET-MEM-BOR-75X39X08 | F84: =F83 -> Restonic Hotel Motel Bonnell Euro Top Memory Border 75X39X08 | G84: =G83 -> SFG-FRBNET-MEM-BOR-75X39X08 | H84: =H83 -> Restonic Hotel Motel Bonnell Euro Top Memory Border 75X39X08 | I84: Standard | J84: Production | K84: TAIL-BORDER | L84: NOS | M84: 1 | N84: MRP&Rollup | O84: CBESFG | P84: 20 | Q84: I | R84: HW-CTON-THREAD | S84: COTTON THREAD WHITE 3PLY | T84: MTR | U84: 5 | V84: CBEWIP | W84: Backflush | X84: Active | Y84: =RIGHT(E84,8) -> 75X39X08 | Z84: =LEFT(Y84,2) -> 75 | AA84: =MID(Y84,4,2) -> 39 | AB84: =RIGHT(Y84,2) -> 08 | AC84: =AC83 -> 75 | AD84: =AD83 -> 39 | AG84: =U84/5000 -> 0.001 | AH84: =VLOOKUP(R84,'Rm-feb-24'!B:P,15,0) -> 58 | AI84: =AG84*AH84 -> 0.058 | AT84: =AT83 -> 153.962 | AU84: =AU83 -> 174
A85: 84 | B85: 3 | C85: =C84 -> 10 | D85: =D84 -> 28.03.2024 | E85: =E84 -> SFG-FRBNET-MEM-BOR-75X39X08 | F85: =F84 -> Restonic Hotel Motel Bonnell Euro Top Memory Border 75X39X08 | G85: =G84 -> SFG-FRBNET-MEM-BOR-75X39X08 | H85: =H84 -> Restonic Hotel Motel Bonnell Euro Top Memory Border 75X39X08 | I85: Standard | J85: Production | K85: TAIL-BORDER | L85: NOS | M85: 1 | N85: MRP&Rollup | O85: CBESFG | P85: 30 | Q85: I | R85: SFG-RTHTMT-BNPK-MEM-BOR-21CM | S85: Hotel Motel Poc ET-8 8MM/16D Pre Foam Memory Border 21 CM Height | T85: MTR | U85: =AE85 -> 5.868 | V85: CBESFG | W85: Backflush | X85: Active | Y85: =RIGHT(E85,8) -> 75X39X08 | Z85: =LEFT(Y85,2) -> 75 | AA85: =MID(Y85,4,2) -> 39 | AB85: =RIGHT(Y85,2) -> 08 | AC85: =AC84 -> 75 | AD85: =AD84 -> 39 | AE85: =ROUNDUP(((((AC85+AD85)*2)+3)*0.0254),3) -> 5.868 | AG85: =U85 -> 5.868 | AH85: =VLOOKUP(R85,'SFG-RM'!A:B,2,0) -> 21.475377 | AI85: =AG85*AH85 -> 126.01751 | AT85: =AT84 -> 153.962 | AU85: =AU84 -> 174
A86: 85 | B86: 4 | C86: =C85 -> 10 | D86: =D85 -> 28.03.2024 | E86: =E85 -> SFG-FRBNET-MEM-BOR-75X39X08 | F86: =F85 -> Restonic Hotel Motel Bonnell Euro Top Memory Border 75X39X08 | G86: =G85 -> SFG-FRBNET-MEM-BOR-75X39X08 | H86: =H85 -> Restonic Hotel Motel Bonnell Euro Top Memory Border 75X39X08 | I86: Standard | J86: Production | K86: TAIL-BORDER | L86: NOS | M86: 1 | N86: MRP&Rollup | O86: CBESFG | P86: 40 | Q86: I | R86: RMI-HCC-SDE-LBL | S86: HOTEL COMFORT CARE SIDE LABEL (IMPORT) | T86: NOS | U86: 1 | V86: CBEWIP | W86: Backflush | X86: Active | Y86: =RIGHT(E86,8) -> 75X39X08 | Z86: =LEFT(Y86,2) -> 75 | AA86: =MID(Y86,4,2) -> 39 | AB86: =RIGHT(Y86,2) -> 08 | AC86: =AC85 -> 75 | AD86: =AD85 -> 39 | AE86: =ROUNDUP(((((72+30)*2)+3)*0.0254),3) -> 5.258 | AG86: =U86 -> 1 | AH86: =VLOOKUP(R86,'Rm-feb-24'!B:P,15,0) -> 5.9957 | AI86: =AG86*AH86 -> 5.9957 | AT86: =AT85 -> 153.962 | AU86: =AU85 -> 174
A87: 86 | B87: 5 | C87: =C86 -> 10 | D87: =D86 -> 28.03.2024 | E87: =E86 -> SFG-FRBNET-MEM-BOR-75X39X08 | F87: =F86 -> Restonic Hotel Motel Bonnell Euro Top Memory Border 75X39X08 | G87: =G86 -> SFG-FRBNET-MEM-BOR-75X39X08 | H87: =H86 -> Restonic Hotel Motel Bonnell Euro Top Memory Border 75X39X08 | I87: Standard | J87: Production | K87: TAIL-BORDER | L87: NOS | M87: 1 | N87: MRP&Rollup | O87: CBESFG | P87: 50 | Q87: I | R87: RML-MRP-BACK-LBL | S87: MRP BACK LABEL(PLAIN) | T87: NOS | U87: 1 | V87: CBEWIP | W87: Backflush | X87: Active | Y87: =RIGHT(E87,8) -> 75X39X08 | Z87: =LEFT(Y87,2) -> 75 | AA87: =MID(Y87,4,2) -> 39 | AB87: =RIGHT(Y87,2) -> 08 | AC87: =AC86 -> 75 | AD87: =AD86 -> 39 | AG87: =U87 -> 1 | AH87: =VLOOKUP(R87,'Rm-feb-24'!B:P,15,0) -> 1.3275 | AI87: =AG87*AH87 -> 1.3275 | AT87: =AT86 -> 153.962 | AU87: =AU86 -> 174
A88: 87 | B88: 6 | C88: =C87 -> 10 | D88: =D87 -> 28.03.2024 | E88: =E87 -> SFG-FRBNET-MEM-BOR-75X39X08 | F88: =F87 -> Restonic Hotel Motel Bonnell Euro Top Memory Border 75X39X08 | G88: =G87 -> SFG-FRBNET-MEM-BOR-75X39X08 | H88: =H87 -> Restonic Hotel Motel Bonnell Euro Top Memory Border 75X39X08 | I88: Standard | J88: Production | K88: TAIL-BORDER | L88: NOS | M88: 1 | N88: MRP&Rollup | O88: CBESFG | P88: 60 | Q88: I | R88: RML-DRN-LBL | S88: DIRECTION LABEL | T88: NOS | U88: 1 | V88: CBEWIP | W88: Backflush | X88: Active | Y88: =RIGHT(E88,8) -> 75X39X08 | Z88: =LEFT(Y88,2) -> 75 | AA88: =MID(Y88,4,2) -> 39 | AB88: =RIGHT(Y88,2) -> 08 | AC88: =AC87 -> 75 | AD88: =AD87 -> 39 | AG88: =U88 -> 1 | AH88: =VLOOKUP(R88,'Rm-feb-24'!B:P,15,0) -> 1.7318 | AI88: =AG88*AH88 -> 1.7318 | AT88: =AT87 -> 153.962 | AU88: =AU87 -> 174
A89: 88 | B89: 7 | C89: =C88 -> 10 | D89: =D88 -> 28.03.2024 | E89: =E88 -> SFG-FRBNET-MEM-BOR-75X39X08 | F89: =F88 -> Restonic Hotel Motel Bonnell Euro Top Memory Border 75X39X08 | G89: =G88 -> SFG-FRBNET-MEM-BOR-75X39X08 | H89: =H88 -> Restonic Hotel Motel Bonnell Euro Top Memory Border 75X39X08 | I89: Standard | J89: Production | K89: TAIL-BORDER | L89: NOS | M89: 1 | N89: MRP&Rollup | O89: CBESFG | P89: 70 | Q89: I | R89: SFG-RTHTMT-MEM-HANDLE | S89: Restonic Hotel Motel Memory Handle | T89: MTR | U89: 0.64 | V89: CBESFG | W89: Backflush | X89: Active | Y89: =RIGHT(E89,8) -> 75X39X08 | Z89: =LEFT(Y89,2) -> 75 | AA89: =MID(Y89,4,2) -> 39 | AB89: =RIGHT(Y89,2) -> 08 | AC89: =AC88 -> 75 | AD89: =AD88 -> 39 | AG89: =U89 -> 0.64 | AH89: =VLOOKUP(R89,'SFG-RM'!A:B,2,0) -> 14.621455 | AI89: =AG89*AH89 -> 9.3577314 | AT89: =AT88 -> 153.962 | AU89: =AU88 -> 174
A90: 89 | B90: 8 | C90: =C89 -> 10 | D90: =D89 -> 28.03.2024 | E90: =E89 -> SFG-FRBNET-MEM-BOR-75X39X08 | F90: =F89 -> Restonic Hotel Motel Bonnell Euro Top Memory Border 75X39X08 | G90: =G89 -> SFG-FRBNET-MEM-BOR-75X39X08 | H90: =H89 -> Restonic Hotel Motel Bonnell Euro Top Memory Border 75X39X08 | I90: Standard | J90: Production | K90: TAIL-BORDER | L90: NOS | M90: 1 | N90: MRP&Rollup | O90: CBESFG | P90: 80 | Q90: I | R90: RMI-BREATHER-GOLD | S90: BREATHER SET GOLD ROUND | T90: SET | U90: 2 | V90: CBEWIP | W90: Backflush | X90: Active | Y90: =RIGHT(E90,8) -> 75X39X08 | Z90: =LEFT(Y90,2) -> 75 | AA90: =MID(Y90,4,2) -> 39 | AB90: =RIGHT(Y90,2) -> 08 | AC90: =AC89 -> 75 | AD90: =AD89 -> 39 | AG90: =U90 -> 2 | AH90: =VLOOKUP(R90,'Rm-feb-24'!B:P,15,0) -> 4.6721 | AI90: =AG90*AH90 -> 9.3442 | AT90: =AT89 -> 153.962 | AU90: =AU89 -> 174
A91: 90
A92: 91 | B92: 1 | C92: 11 | D92: 28.03.2024 | E92: SFG-FRBNET-MEM-BOR-75X45X08 | F92: Restonic Hotel Motel Bonnell Euro Top Memory Border 75X45X08 | G92: =E92 -> SFG-FRBNET-MEM-BOR-75X45X08 | H92: =F92 -> Restonic Hotel Motel Bonnell Euro Top Memory Border 75X45X08 | I92: Standard | J92: Production | K92: TAIL-BORDER | L92: NOS | M92: 1 | N92: MRP&Rollup | O92: CBESFG | P92: 10 | Q92: I | R92: RM-THRD-QS-TKT40 | S92: THREAD TKT40 210D/3 PLY 10000MTS | T92: MTR | U92: 5.6 | V92: CBEWIP | W92: Backflush | X92: Active | Y92: =RIGHT(E92,8) -> 75X45X08 | Z92: =LEFT(Y92,2) -> 75 | AA92: =MID(Y92,4,2) -> 45 | AB92: =RIGHT(Y92,2) -> 08 | AC92: =Z92 -> 75 | AD92: =AA92 -> 45 | AG92: =U92/10000 -> 0.00056 | AH92: =VLOOKUP(R92,'Rm-feb-24'!B:P,15,0) -> 231.1423 | AI92: =AG92*AH92 -> 0.12943969 | AJ92: =SUM(AI92:AI99) -> 160.51187 | AK92: =ROUND(AJ92,3) -> 160.512 | AL92: =AK92 -> 160.512 | AM92: =+AL92+AR92 -> 180.3752 | AN92: =+SUM(((AL92*3%*18%))) -> 0.8667648 | AO92: =+SUM(((AL92*14.33%*53%))) -> 12.190726 | AP92: =+SUM(((AL92*5.92%*53%))) -> 5.0362245 | AQ92: =+SUM(((AL92*2.08%*53%))) -> 1.7694843 | AR92: =SUM(AN92:AQ92) -> 19.863199 | AS92: =ROUNDUP(AM92,0) -> 181 | AT92: =AL92 -> 160.512 | AU92: =AS92 -> 181
A93: 92 | B93: 2 | C93: =C92 -> 11 | D93: =D92 -> 28.03.2024 | E93: =E92 -> SFG-FRBNET-MEM-BOR-75X45X08 | F93: =F92 -> Restonic Hotel Motel Bonnell Euro Top Memory Border 75X45X08 | G93: =G92 -> SFG-FRBNET-MEM-BOR-75X45X08 | H93: =H92 -> Restonic Hotel Motel Bonnell Euro Top Memory Border 75X45X08 | I93: Standard | J93: Production | K93: TAIL-BORDER | L93: NOS | M93: 1 | N93: MRP&Rollup | O93: CBESFG | P93: 20 | Q93: I | R93: HW-CTON-THREAD | S93: COTTON THREAD WHITE 3PLY | T93: MTR | U93: 5 | V93: CBEWIP | W93: Backflush | X93: Active | Y93: =RIGHT(E93,8) -> 75X45X08 | Z93: =LEFT(Y93,2) -> 75 | AA93: =MID(Y93,4,2) -> 45 | AB93: =RIGHT(Y93,2) -> 08 | AC93: =AC92 -> 75 | AD93: =AD92 -> 45 | AG93: =U93/5000 -> 0.001 | AH93: =VLOOKUP(R93,'Rm-feb-24'!B:P,15,0) -> 58 | AI93: =AG93*AH93 -> 0.058 | AT93: =AT92 -> 160.512 | AU93: =AU92 -> 181
A94: 93 | B94: 3 | C94: =C93 -> 11 | D94: =D93 -> 28.03.2024 | E94: =E93 -> SFG-FRBNET-MEM-BOR-75X45X08 | F94: =F93 -> Restonic Hotel Motel Bonnell Euro Top Memory Border 75X45X08 | G94: =G93 -> SFG-FRBNET-MEM-BOR-75X45X08 | H94: =H93 -> Restonic Hotel Motel Bonnell Euro Top Memory Border 75X45X08 | I94: Standard | J94: Production | K94: TAIL-BORDER | L94: NOS | M94: 1 | N94: MRP&Rollup | O94: CBESFG | P94: 30 | Q94: I | R94: SFG-RTHTMT-BNPK-MEM-BOR-21CM | S94: Hotel Motel Poc ET-8 8MM/16D Pre Foam Memory Border 21 CM Height | T94: MTR | U94: =AE94 -> 6.173 | V94: CBESFG | W94: Backflush | X94: Active | Y94: =RIGHT(E94,8) -> 75X45X08 | Z94: =LEFT(Y94,2) -> 75 | AA94: =MID(Y94,4,2) -> 45 | AB94: =RIGHT(Y94,2) -> 08 | AC94: =AC93 -> 75 | AD94: =AD93 -> 45 | AE94: =ROUNDUP(((((AC94+AD94)*2)+3)*0.0254),3) -> 6.173 | AG94: =U94 -> 6.173 | AH94: =VLOOKUP(R94,'SFG-RM'!A:B,2,0) -> 21.475377 | AI94: =AG94*AH94 -> 132.5675 | AT94: =AT93 -> 160.512 | AU94: =AU93 -> 181
A95: 94 | B95: 4 | C95: =C94 -> 11 | D95: =D94 -> 28.03.2024 | E95: =E94 -> SFG-FRBNET-MEM-BOR-75X45X08 | F95: =F94 -> Restonic Hotel Motel Bonnell Euro Top Memory Border 75X45X08 | G95: =G94 -> SFG-FRBNET-MEM-BOR-75X45X08 | H95: =H94 -> Restonic Hotel Motel Bonnell Euro Top Memory Border 75X45X08 | I95: Standard | J95: Production | K95: TAIL-BORDER | L95: NOS | M95: 1 | N95: MRP&Rollup | O95: CBESFG | P95: 40 | Q95: I | R95: RMI-HCC-SDE-LBL | S95: HOTEL COMFORT CARE SIDE LABEL (IMPORT) | T95: NOS | U95: 1 | V95: CBEWIP | W95: Backflush | X95: Active | Y95: =RIGHT(E95,8) -> 75X45X08 | Z95: =LEFT(Y95,2) -> 75 | AA95: =MID(Y95,4,2) -> 45 | AB95: =RIGHT(Y95,2) -> 08 | AC95: =AC94 -> 75 | AD95: =AD94 -> 45 | AE95: =ROUNDUP(((((72+30)*2)+3)*0.0254),3) -> 5.258 | AG95: =U95 -> 1 | AH95: =VLOOKUP(R95,'Rm-feb-24'!B:P,15,0) -> 5.9957 | AI95: =AG95*AH95 -> 5.9957 | AT95: =AT94 -> 160.512 | AU95: =AU94 -> 181
A96: 95 | B96: 5 | C96: =C95 -> 11 | D96: =D95 -> 28.03.2024 | E96: =E95 -> SFG-FRBNET-MEM-BOR-75X45X08 | F96: =F95 -> Restonic Hotel Motel Bonnell Euro Top Memory Border 75X45X08 | G96: =G95 -> SFG-FRBNET-MEM-BOR-75X45X08 | H96: =H95 -> Restonic Hotel Motel Bonnell Euro Top Memory Border 75X45X08 | I96: Standard | J96: Production | K96: TAIL-BORDER | L96: NOS | M96: 1 | N96: MRP&Rollup | O96: CBESFG | P96: 50 | Q96: I | R96: RML-MRP-BACK-LBL | S96: MRP BACK LABEL(PLAIN) | T96: NOS | U96: 1 | V96: CBEWIP | W96: Backflush | X96: Active | Y96: =RIGHT(E96,8) -> 75X45X08 | Z96: =LEFT(Y96,2) -> 75 | AA96: =MID(Y96,4,2) -> 45 | AB96: =RIGHT(Y96,2) -> 08 | AC96: =AC95 -> 75 | AD96: =AD95 -> 45 | AG96: =U96 -> 1 | AH96: =VLOOKUP(R96,'Rm-feb-24'!B:P,15,0) -> 1.3275 | AI96: =AG96*AH96 -> 1.3275 | AT96: =AT95 -> 160.512 | AU96: =AU95 -> 181
A97: 96 | B97: 6 | C97: =C96 -> 11 | D97: =D96 -> 28.03.2024 | E97: =E96 -> SFG-FRBNET-MEM-BOR-75X45X08 | F97: =F96 -> Restonic Hotel Motel Bonnell Euro Top Memory Border 75X45X08 | G97: =G96 -> SFG-FRBNET-MEM-BOR-75X45X08 | H97: =H96 -> Restonic Hotel Motel Bonnell Euro Top Memory Border 75X45X08 | I97: Standard | J97: Production | K97: TAIL-BORDER | L97: NOS | M97: 1 | N97: MRP&Rollup | O97: CBESFG | P97: 60 | Q97: I | R97: RML-DRN-LBL | S97: DIRECTION LABEL | T97: NOS | U97: 1 | V97: CBEWIP | W97: Backflush | X97: Active | Y97: =RIGHT(E97,8) -> 75X45X08 | Z97: =LEFT(Y97,2) -> 75 | AA97: =MID(Y97,4,2) -> 45 | AB97: =RIGHT(Y97,2) -> 08 | AC97: =AC96 -> 75 | AD97: =AD96 -> 45 | AG97: =U97 -> 1 | AH97: =VLOOKUP(R97,'Rm-feb-24'!B:P,15,0) -> 1.7318 | AI97: =AG97*AH97 -> 1.7318 | AT97: =AT96 -> 160.512 | AU97: =AU96 -> 181
A98: 97 | B98: 7 | C98: =C97 -> 11 | D98: =D97 -> 28.03.2024 | E98: =E97 -> SFG-FRBNET-MEM-BOR-75X45X08 | F98: =F97 -> Restonic Hotel Motel Bonnell Euro Top Memory Border 75X45X08 | G98: =G97 -> SFG-FRBNET-MEM-BOR-75X45X08 | H98: =H97 -> Restonic Hotel Motel Bonnell Euro Top Memory Border 75X45X08 | I98: Standard | J98: Production | K98: TAIL-BORDER | L98: NOS | M98: 1 | N98: MRP&Rollup | O98: CBESFG | P98: 70 | Q98: I | R98: SFG-RTHTMT-MEM-HANDLE | S98: Restonic Hotel Motel Memory Handle | T98: MTR | U98: 0.64 | V98: CBESFG | W98: Backflush | X98: Active | Y98: =RIGHT(E98,8) -> 75X45X08 | Z98: =LEFT(Y98,2) -> 75 | AA98: =MID(Y98,4,2) -> 45 | AB98: =RIGHT(Y98,2) -> 08 | AC98: =AC97 -> 75 | AD98: =AD97 -> 45 | AG98: =U98 -> 0.64 | AH98: =VLOOKUP(R98,'SFG-RM'!A:B,2,0) -> 14.621455 | AI98: =AG98*AH98 -> 9.3577314 | AT98: =AT97 -> 160.512 | AU98: =AU97 -> 181
A99: 98 | B99: 8 | C99: =C98 -> 11 | D99: =D98 -> 28.03.2024 | E99: =E98 -> SFG-FRBNET-MEM-BOR-75X45X08 | F99: =F98 -> Restonic Hotel Motel Bonnell Euro Top Memory Border 75X45X08 | G99: =G98 -> SFG-FRBNET-MEM-BOR-75X45X08 | H99: =H98 -> Restonic Hotel Motel Bonnell Euro Top Memory Border 75X45X08 | I99: Standard | J99: Production | K99: TAIL-BORDER | L99: NOS | M99: 1 | N99: MRP&Rollup | O99: CBESFG | P99: 80 | Q99: I | R99: RMI-BREATHER-GOLD | S99: BREATHER SET GOLD ROUND | T99: SET | U99: 2 | V99: CBEWIP | W99: Backflush | X99: Active | Y99: =RIGHT(E99,8) -> 75X45X08 | Z99: =LEFT(Y99,2) -> 75 | AA99: =MID(Y99,4,2) -> 45 | AB99: =RIGHT(Y99,2) -> 08 | AC99: =AC98 -> 75 | AD99: =AD98 -> 45 | AG99: =U99 -> 2 | AH99: =VLOOKUP(R99,'Rm-feb-24'!B:P,15,0) -> 4.6721 | AI99: =AG99*AH99 -> 9.3442 | AT99: =AT98 -> 160.512 | AU99: =AU98 -> 181
A100: 99
...

Sheet SFG-RM
A1: Row Labels | B1: Sum of Feb-24-Total
A2: BNAS-106X72X130 | B2: 1650.0082
A3: BNAS-13X13X100 | B3: 27.727734
A4: BNAS-13X13X130 | B4: 32.182134
A5: BNAS-13X13X150 | B5: 36.559734
A6: BNAS-13X13X90 | B6: 27.113334
A7: BNAS-18X18X100 | B7: 47.467619
A8: BNAS-18X18X130 | B8: 54.891619
A9: BNAS-20X18X100 | B9: 55.968766
A10: BNAS-20X18X130 | B10: 64.877566
A11: BNAS-20X18X150 | B11: 73.632766
A12: BNAS-20X18X90 | B12: 54.739966
A13: BNAS-24X60X130 | B13: 273.74261
... A29219: Grand Total | B29219: 18179053

Sheet Rm-feb-24
A1: SI.No | B1: Item Code | C1: Item Desc | D1: UOM | E1: Warehouse | F1: Opening Stock Qty | G1: Opening Stock Rate | H1: Opening Stock Value | I1: Stock In Qty | J1: Stock In Rate | K1: Stock In Value | L1: Stock Out Qty | M1: Stock Out Rate | N1: Stock Out Value | O1: Closing Stock Qty | P1: Closing Stock Rate | Q1: Closing Stock Value | R1: Item Account Group | S1: Item Account Group Desc | T1: Item Category
A2: 33 | B2: RML-CS-RTC-PLUSH-7.5 | C2: CORNER SHOES RESTONIC PLUSH - 7.5" | D2: NOS | E2: CBERM | F2: 900 | G2: 10.2033 | H2: 9182.97 | I2: 600 | J2: 10 | K2: 6000 | L2: 300 | M2: 10.1452 | N2: 3043.57 | O2: 1200 | P2: 10.1162 | Q2: 12139.4 | R2: LCE | S2: Label,CnrShoe,CentreBand,EdgeTape-10195 | T2: MATRESS
A3: 35 | B3: RML-CS-RTC-PLUSH-9.5 | C3: CORNER SHOES RESTONIC PLUSH - 9.5" | D3: NOS | E3: CBERM | F3: 1000 | G3: 10.3332 | H3: 10333.16 | I3: 500 | J3: 12.3 | K3: 6150 | L3: 200 | M3: 10.9888 | N3: 2197.76 | O3: 1300 | P3: 10.9888 | Q3: 14285.4 | R3: LCE | S3: Label,CnrShoe,CentreBand,EdgeTape-10195 | T3: MATRESS
A4: 37 | B4: RML-CS-SPG-6.5" | C4: CORNER SHOES. SPINE GUARD - 6.5" | D4: NOS | E4: CBERM | F4: 1200 | G4: 10.7018 | H4: 12842.19 | I4: 0 | K4: 0 | L4: 200 | M4: 10.7018 | N4: 2140.36 | O4: 1000 | P4: 10.7018 | Q4: 10701.83 | R4: LCE | S4: Label,CnrShoe,CentreBand,EdgeTape-10195 | T4: MATRESS
A5: 42 | B5: RML-CS-SPG-7.5" | C5: CORNER SHOES. SPINE GUARD - 7.5" | D5: NOS | E5: CBERM | F5: 1300 | G5: 10 | H5: 13000 | I5: 4800 | J5: 10 | K5: 48000 | L5: 3300 | M5: 10 | N5: 33000 | O5: 2800 | P5: 10 | Q5: 28000 | R5: LCE | S5: Label,CnrShoe,CentreBand,EdgeTape-10195 | T5: MATRESS
A6: 48 | B6: RML-CS-SPG-9.5" | C6: CORNER SHOES. SPINE GUARD - 9.5" | D6: NOS | E6: CBERM | F6: 1100 | G6: 10.48 | H6: 11528 | I6: 1000 | J6: 10.48 | K6: 10480 | L6: 1600 | M6: 10.48 | N6: 16768 | O6: 500 | P6: 10.48 | Q6: 5240 | R6: LCE | S6: Label,CnrShoe,CentreBand,EdgeTape-10195 | T6: MATRESS
A7: 56 | B7: RML-CS-SPK-10.5" | C7: CORNER SHOES. SPK - 10.5" | D7: NOS | E7: CBERM | F7: 1389 | G7: 9.7779 | H7: 13581.54 | I7: 0 | K7: 0 | L7: 0 | N7: 0 | O7: 1389 | P7: 9.7779 | Q7: 13581.54 | R7: LCE | S7: Label,CnrShoe,CentreBand,EdgeTape-10195 | T7: MATRESS
A8: 59 | B8: RML-CS-SPK-8.5" | C8: CORNER SHOES. SPK - 8.5" | D8: NOS | E8: CBERM | F8: 1000 | G8: 10.3146 | H8: 10314.55 | I8: 0 | K8: 0 | L8: 0 | N8: 0 | O8: 1000 | P8: 10.3146 | Q8: 10314.55 | R8: LCE | S8: Label,CnrShoe,CentreBand,EdgeTape-10195 | T8: MATRESS
A9: 63 | B9: RML-CS-SPK-BG-10.5 | C9: CORNER SHOES SPRINGKOIL BEIGE -10.5" | D9: NOS | E9: CBERM | F9: 400 | G9: 12.5 | H9: 5000 | I9: 0 | K9: 0 | L9: 0 | N9: 0 | O9: 400 | P9: 12.5 | Q9: 5000 | R9: LCE | S9: Label,CnrShoe,CentreBand,EdgeTape-10195 | T9: MATRESS
A10: 66 | B10: RML-CS-SPK-BG-7 | C10: CORNER SHOES SPRINGKOIL BEIGE -7" | D10: NOS | E10: CBERM | F10: 6500 | G10: 10 | H10: 65000 | I10: 0 | K10: 0 | L10: 400 | M10: 10 | N10: 4000 | O10: 6100 | P10: 10 | Q10: 61000 | R10: LCE | S10: Label,CnrShoe,CentreBand,EdgeTape-10195 | T10: MATRESS
A11: 67 | B11: RML-CS-SPK-BG-8.5 | C11: CORNER SHOES SPRINGKOIL BEIGE -8.5" | D11: NOS | E11: CBERM | F11: 3300 | G11: 10 | H11: 33000 | I11: 0 | K11: 0 | L11: 0 | N11: 0 | O11: 3300 | P11: 10 | Q11: 33000 | R11: LCE | S11: Label,CnrShoe,CentreBand,EdgeTape-10195 | T11: MATRESS
A12: 69 | B12: RML-CS-SPK-BL-10.5 | C12: CORNER SHOES SPRINGKOIL BLUE -10.5" | D12: NOS | E12: CBERM | F12: 500 | G12: 11.5625 | H12: 5781.25 | I12: 0 | K12: 0 | L12: 0 | N12: 0 | O12: 500 | P12: 11.5625 | Q12: 5781.25 | R12: LCE | S12: Label,CnrShoe,CentreBand,EdgeTape-10195 | T12: MATRESS
A13: 71 | B13: RML-CS-SPK-BL-6 | C13: CORNER SHOES SPRINGKOIL BLUE -6" | D13: NOS | E13: CBERM | F13: 2900 | G13: 10 | H13: 29000 | I13: 0 | K13: 0 | L13: 200 | M13: 10 | N13: 2000 | O13: 2700 | P13: 10 | Q13: 27000 | R13: LCE | S13: Label,CnrShoe,CentreBand,EdgeTape-10195 | T13: MATRESS
A14: 73 | B14: RML-CS-SPK-BL-7 | C14: CORNER SHOES SPRINGKOIL BLUE -7" | D14: NOS | E14: CBERM | F14: 21800 | G14: 8.6732 | H14: 189076.19 | I14: 50 | J14: 8.6732 | K14: 433.66 | L14: 6600 | M14: 8.6732 | N14: 57243.12 | O14: 15250 | P14: 8.6732 | Q14: 132266.73 | R14: LCE | S14: Label,CnrShoe,CentreBand,EdgeTape-10195 | T14: MATRESS
A15: 75 | B15: RML-CS-SPK-BL-7.5 | C15: CORNER SHOES SPRINGKOIL BLUE -7.5" | D15: NOS | E15: CBERM | F15: 1065 | G15: 10 | H15: 10650 | I15: 0 | K15: 0 | L15: 0 | N15: 0 | O15: 1065 | P15: 10 | Q15: 10650 | R15: LCE | S15: Label,CnrShoe,CentreBand,EdgeTape-10195 | T15: MATRESS
A16: 77 | B16: RML-CS-SPK-BL-8.5 | C16: CORNER SHOES SPRINGKOIL BLUE -8.5" | D16: NOS | E16: CBERM | F16: 4000 | G16: 10.2861 | H16: 41144.42 | I16: 100 | J16: 10.2861 | K16: 1028.61 | L16: 300 | M16: 10.2861 | N16: 3085.83 | O16: 3800 | P16: 10.2861 | Q16: 39087.2 | R16: LCE | S16: Label,CnrShoe,CentreBand,EdgeTape-10195 | T16: MATRESS
A17: 78 | B17: RML-CS-SPK-BW-10.5 | C17: CORNER SHOES SPRINGKOIL BROWN -10.5" | D17: NOS | E17: CBERM | F17: 800 | G17: 11.5625 | H17: 9250 | I17: 0 | K17: 0 | L17: 0 | N17: 0 | O17: 800 | P17: 11.5625 | Q17: 9250 | R17: LCE | S17: Label,CnrShoe,CentreBand,EdgeTape-10195 | T17: MATRESS
A18: 81 | B18: RML-CS-SPK-BW-6 | C18: CORNER SHOES SPRINGKOIL BROWN -6" | D18: NOS | E18: CBERM | F18: 500 | G18: 10 | H18: 5000 | I18: 0 | K18: 0 | L18: 100 | M18: 10 | N18: 1000 | O18: 400 | P18: 10 | Q18: 4000 | R18: LCE | S18: Label,CnrShoe,CentreBand,EdgeTape-10195 | T18: MATRESS
A19: 82 | B19: RML-CS-SPK-BW-7 | C19: CORNER SHOES SPRINGKOIL BROWN -7" | D19: NOS | E19: CBERM | F19: 4400 | G19: 10 | H19: 44000 | I19: 1000 | J19: 10 | K19: 10000 | L19: 2700 | M19: 10 | N19: 27000 | O19: 2700 | P19: 10 | Q19: 27000 | R19: LCE | S19: Label,CnrShoe,CentreBand,EdgeTape-10195 | T19: MATRESS
A20: 84 | B20: RML-CS-SPK-BW-7.5 | C20: CORNER SHOES SPRINGKOIL BROWN -7.5" | D20: NOS | E20: CBERM | F20: 555 | G20: 10 | H20: 5550 | I20: 0 | K20: 0 | L20: 0 | N20: 0 | O20: 555 | P20: 10 | Q20: 5550 | R20: LCE | S20: Label,CnrShoe,CentreBand,EdgeTape-10195 | T20: MATRESS
A21: 85 | B21: RML-CS-SPK-BW-8.5 | C21: CORNER SHOES SPRINGKOIL BROWN -8.5" | D21: NOS | E21: CBERM | F21: 3348 | G21: 10 | H21: 33480 | I21: 0 | K21: 0 | L21: 0 | N21: 0 | O21: 3348 | P21: 10 | Q21: 33480 | R21: LCE | S21: Label,CnrShoe,CentreBand,EdgeTape-10195 | T21: MATRESS
A22: 87 | B22: RML-CS-SPK-CR-10.5 | C22: CORNER SHOES SPRINGKOIL CREAM -10.5" | D22: NOS | E22: CBERM | F22: 800 | G22: 11.3889 | H22: 9111.11 | I22: 0 | K22: 0 | L22: 0 | N22: 0 | O22: 800 | P22: 11.3889 | Q22: 9111.11 | R22: LCE | S22: Label,CnrShoe,CentreBand,EdgeTape-10195 | T22: MATRESS
A23: 89 | B23: RML-CS-SPK-CR-6 | C23: CORNER SHOES SPRINGKOIL CREAM -6" | D23: NOS | E23: CBERM | F23: 400 | G23: 10 | H23: 4000 | I23: 0 | K23: 0 | L23: 100 | M23: 10 | N23: 1000 | O23: 300 | P23: 10 | Q23: 3000 | R23: LCE | S23: Label,CnrShoe,CentreBand,EdgeTape-10195 | T23: MATRESS
A24: 92 | B24: RML-CS-SPK-CR-7 | C24: CORNER SHOES SPRINGKOIL CREAM -7" | D24: NOS | E24: CBERM | F24: 4600 | G24: 10 | H24: 46000 | I24: 0 | K24: 0 | L24: 500 | M24: 10 | N24: 5000 | O24: 4100 | P24: 10 | Q24: 41000 | R24: LCE | S24: Label,CnrShoe,CentreBand,EdgeTape-10195 | T24: MATRESS
A25: 93 | B25: RML-CS-SPK-CR-7.5 | C25: CORNER SHOES SPRINGKOIL CREAM -7.5" | D25: NOS | E25: CBERM | F25: 280 | G25: 10 | H25: 2800 | I25: 0 | K25: 0 | L25: 0 | N25: 0 | O25: 280 | P25: 10 | Q25: 2800 | R25: LCE | S25: Label,CnrShoe,CentreBand,EdgeTape-10195 | T25: MATRESS
A26: 94 | B26: RML-CS-SPK-CR-8.5 | C26: CORNER SHOES SPRINGKOIL CREAM -8.5" | D26: NOS | E26: CBERM | F26: 2900 | G26: 10 | H26: 29000 | I26: 0 | K26: 0 | L26: 0 | N26: 0 | O26: 2900 | P26: 10 | Q26: 29000 | R26: LCE | S26: Label,CnrShoe,CentreBand,EdgeTape-10195 | T26: MATRESS
A27: 97 | B27: RML-CS-SPK-CT-6 | C27: PEPS SPRINGKOIL CROWN TOP CORNER SHOES 6" | D27: NOS | E27: CBERM | F27: 2000 | G27: 8.65 | H27: 17300 | I27: 14000 | J27: 8.65 | K27: 121100 | L27: 2400 | M27: 8.65 | N27: 20760 | O27: 13600 | P27: 8.65 | Q27: 117640 | R27: LCE | S27: Label,CnrShoe,CentreBand,EdgeTape-10195 | T27: MATRESS
A28: 102 | B28: RML-CS-SPK-CT-7.5 | C28: PEPS SPRINGKOIL CROWN TOP CORNER SHOES 7.5" | D28: NOS | E28: CBERM | F28: 1400 | G28: 9.9 | H28: 13860 | I28: 0 | K28: 0 | L28: 200 | M28: 9.9 | N28: 1980 | O28: 1200 | P28: 9.9 | Q28: 11880 | R28: LCE | S28: Label,CnrShoe,CentreBand,EdgeTape-10195 | T28: MATRESS
A29: 108 | B29: RML-CS-SPK-CT-9.25 | C29: PEPS SPRINGKOIL CROWN TOP CORNER SHOES 9.25" | D29: NOS | E29: CBERM | F29: 850 | G29: 15.3 | H29: 13005 | I29: 0 | K29: 0 | L29: 100 | M29: 15.3 | N29: 1530 | O29: 750 | P29: 15.3 | Q29: 11475 | R29: LCE | S29: Label,CnrShoe,CentreBand,EdgeTape-10195 | T29: MATRESS
A30: 110 | B30: RML-CS-SPK-GR-10.5 | C30: CORNER SHOES SPRINGKOIL GREY -10.5" | D30: NOS | E30: CBERM | F30: 400 | G30: 12.5 | H30: 5000 | I30: 0 | K30: 0 | L30: 0 | N30: 0 | O30: 400 | P30: 12.5 | Q30: 5000 | R30: LCE | S30: Label,CnrShoe,CentreBand,EdgeTape-10195 | T30: MATRESS
A31: 113 | B31: RML-CS-SPK-GR-7 | C31: CORNER SHOES SPRINGKOIL GREY -7" | D31: NOS | E31: CBERM | F31: 6600 | G31: 10 | H31: 66000 | I31: 0 | K31: 0 | L31: 1700 | M31: 10 | N31: 17000 | O31: 4900 | P31: 10 | Q31: 49000 | R31: LCE | S31: Label,CnrShoe,CentreBand,EdgeTape-10195 | T31: MATRESS
A32: 115 | B32: RML-CS-SPK-GR-8.5 | C32: CORNER SHOES SPRINGKOIL GREY -8.5" | D32: NOS | E32: CBERM | F32: 4400 | G32: 10 | H32: 44000 | I32: 0 | K32: 0 | L32: 100 | M32: 10 | N32: 1000 | O32: 4300 | P32: 10 | Q32: 43000 | R32: LCE | S32: Label,CnrShoe,CentreBand,EdgeTape-10195 | T32: MATRESS
A33: 116 | B33: RML-CS-SPK-MR-10.5 | C33: CORNER SHOES SPRINGKOIL MAROON -10.5" | D33: NOS | E33: CBERM | F33: 1100 | G33: 11.5385 | H33: 12692.3 | I33: 0 | K33: 0 | L33: 200 | M33: 11.5385 | N33: 2307.7 | O33: 900 | P33: 11.5384 | Q33: 10384.6 | R33: LCE | S33: Label,CnrShoe,CentreBand,EdgeTape-10195 | T33: MATRESS
A34: 118 | B34: RML-CS-SPK-MR-6 | C34: CORNER SHOES SPRINGKOIL MAROON -6" | D34: NOS | E34: CBERM | F34: 4100 | G34: 10 | H34: 41000 | I34: 0 | K34: 0 | L34: 300 | M34: 10 | N34: 3000 | O34: 3800 | P34: 10 | Q34: 38000 | R34: LCE | S34: Label,CnrShoe,CentreBand,EdgeTape-10195 | T34: MATRESS
A35: 120 | B35: RML-CS-SPK-MR-7 | C35: CORNER SHOES SPRINGKOIL MAROON -7" | D35: NOS | E35: CBERM | F35: 16500 | G35: 8.6704 | H35: 143061.16 | I35: 0 | K35: 0 | L35: 7500 | M35: 8.6704 | N35: 65028 | O35: 9000 | P35: 8.6704 | Q35: 78033.16 | R35: LCE | S35: Label,CnrShoe,CentreBand,EdgeTape-10195 | T35: MATRESS
A36: 122 | B36: RML-CS-SPK-MR-7.5 | C36: CORNER SHOES SPRINGKOIL MAROON -7.5" | D36: NOS | E36: CBERM | F36: 1145 | G36: 10 | H36: 11450 | I36: 0 | K36: 0 | L36: 0 | N36: 0 | O36: 1145 | P36: 10 | Q36: 11450 | R36: LCE | S36: Label,CnrShoe,CentreBand,EdgeTape-10195 | T36: MATRESS
A37: 124 | B37: RML-CS-SPK-MR-8.5 | C37: CORNER SHOES SPRINGKOIL MAROON -8.5" | D37: NOS | E37: CBERM | F37: 3160 | G37: 10.3345 | H37: 32657.08 | I37: 600 | J37: 10.0477 | K37: 6028.62 | L37: 560 | M37: 10.3034 | N37: 5769.93 | O37: 3200 | P37: 10.2862 | Q37: 32915.77 | R37: LCE | S37: Label,CnrShoe,CentreBand,EdgeTape-10195 | T37: MATRESS
A38: 126 | B38: RML-CS-TRT-7 | C38: CORNER SHOES. TARTANIA-7" | D38: NOS | E38: CBERM | F38: 3500 | G38: 10.2299 | H38: 35804.78 | I38: 0 | K38: 0 | L38: 300 | M38: 10.2299 | N38: 3068.97 | O38: 3200 | P38: 10.2299 | Q38: 32735.81 | R38: LCE | S38: Label,CnrShoe,CentreBand,EdgeTape-10195 | T38: MATRESS
A39: 253 | B39: 100D-RB-FOAM-77X71X25MM | C39: 100D-Rebonded Foam Sheet-77X71X25mm | D39: KGS | E39: CBERM | F39: 0 | H39: 0 | I39: 865.5 | J39: 92 | K39: 79626 | L39: 865.5 | M39: 92 | N39: 79626 | O39: 0 | Q39: 0 | R39: FMREBOND | S39: FOAM REBONDED -10181 | T39: FOAM
A40: 627 | B40: SBLGPS | C40: Knurling Bush | D40: NOS | E40: CBERM | F40: 1220 | G40: 25 | H40: 30500 | I40: 80 | J40: 25 | K40: 2000 | L40: 900 | M40: 25 | N40: 22500 | O40: 400 | P40: 25 | Q40: 10000 | R40: LCE | S40: Label,CnrShoe,CentreBand,EdgeTape-10195 | T40: MATRESS
A41: 629 | B41: SCRAP-COIR-BLOCK | C41: Coir Block Waste Scrop | D41: KGS | E41: CBERM | F41: 0 | H41: 0 | I41: 80.3 | J41: 28 | K41: 2248.4 | L41: 80.3 | M41: 28 | N41: 2248.4 | O41: 0 | Q41: 0 | R41: SEMIQUILT | S41: SEMI FINISHED QUILT SECTION -10198 | T41: MATRESS
A42: 701 | B42: RML-FTD-SHT-75X60 | C42: PEPS FITTED SHEET 75X60 | D42: NOS | E42: CBERM | F42: 42 | G42: 627 | H42: 26334 | I42: 0 | K42: 0 | L42: 0 | N42: 0 | O42: 42 | P42: 627 | Q42: 26334 | R42: ALIPROD | S42: Allied Products-13015 | T42: MATRESS
A43: 709 | B43: RML-FTD-SHT-75X72 | C43: PEPS FITTED SHEET 75X72 | D43: NOS | E43: CBERM | F43: 20 | G43: 752 | H43: 15040 | I43: 0 | K43: 0 | L43: 0 | N43: 0 | O43: 20 | P43: 752 | Q43: 15040 | R43: ALIPROD | S43: Allied Products-13015 | T43: MATRESS
A44: 721 | B44: RML-FTD-SHT-78X60 | C44: PEPS FITTED SHEET 78X60 | D44: NOS | E44: CBERM | F44: 22 | G44: 652 | H44: 14344 | I44: 0 | K44: 0 | L44: 0 | N44: 0 | O44: 22 | P44: 652 | Q44: 14344 | R44: ALIPROD | S44: Allied Products-13015 | T44: MATRESS
A45: 743 | B45: RML-FTD-SHT-78X72 | C45: PEPS FITTED SHEET 78X72 | D45: NOS | E45: CBERM | F45: 21 | G45: 782 | H45: 16422 | I45: 0 | K45: 0 | L45: 0 | N45: 0 | O45: 21 | P45: 782 | Q45: 16422 | R45: ALIPROD | S45: Allied Products-13015 | T45: MATRESS
A46: 795 | B46: RML-HNDL-ALLURA-BLUE | C46: PEPS ALLURA BLUE HANDLE | D46: NOS | E46: CBERM | F46: 600 | G46: 5.5 | H46: 3300 | I46: 0 | K46: 0 | L46: 0 | N46: 0 | O46: 600 | P46: 5.5 | Q46: 3300 | R46: LCE | S46: Label,CnrShoe,CentreBand,EdgeTape-10195 | T46: MATRESS
A47: 796 | B47: RML-HNDL-ALLURA-OR | C47: PEPS ALLURA ORANGE HANDLE | D47: NOS | E47: CBERM | F47: 1465 | G47: 5.5 | H47: 8057.5 | I47: 0 | K47: 0 | L47: 0 | N47: 0 | O47: 1465 | P47: 5.5 | Q47: 8057.5 | R47: LCE | S47: Label,CnrShoe,CentreBand,EdgeTape-10195 | T47: MATRESS
A48: 801 | B48: RML-HNDL-ARD-BRN | C48: RESTONIC ARDENE BROWN HANDLE | D48: NOS | E48: CBERM | F48: 2150 | G48: 12.2002 | H48: 26230.46 | I48: 1875 | J48: 12.2 | K48: 22875 | L48: 350 | M48: 12.2001 | N48: 4270.05 | O48: 3675 | P48: 12.2001 | Q48: 44835.41 | R48: LCE | S48: Label,CnrShoe,CentreBand,EdgeTape-10195 | T48: MATRESS
A49: 805 | B49: RML-HNDL-ARD-GREY | C49: RESTONIC ARDENE GREY HANDLE | D49: NOS | E49: CBERM | F49: 700 | G49: 9.3642 | H49: 6554.91 | I49: 0 | K49: 0 | L49: 150 | M49: 9.3642 | N49: 1404.63 | O49: 550 | P49: 9.3641 | Q49: 5150.28 | R49: LCE | S49: Label,CnrShoe,CentreBand,EdgeTape-10195 | T49: MATRESS
A50: 810 | B50: RML-HNDL-CAR-BLUE | C50: RESTONIC CAROUSEL BLUE HANDLE | D50: NOS | E50: CBERM | F50: 13036 | G50: 6.115 | H50: 79714.67 | I50: 0 | K50: 0 | L50: 1100 | M50: 6.1149 | N50: 6726.39 | O50: 11936 | P50: 6.115 | Q50: 72988.28 | R50: LCE | S50: Label,CnrShoe,CentreBand,EdgeTape-10195 | T50: MATRESS
A51: 814 | B51: RML-HNDL-CAR-CRM | C51: RESTONIC CAROUSEL CREAM HANDLE | D51: NOS | E51: CBERM | F51: 2300 | G51: 6.25 | H51: 14375.05 | I51: 2500 | J51: 6.25 | K51: 15625 | L51: 1800 | M51: 6.25 | N51: 11250 | O51: 3000 | P51: 6.25 | Q51: 18750.05 | R51: LCE | S51: Label,CnrShoe,CentreBand,EdgeTape-10195 | T51: MATRESS
A52: 820 | B52: RML-HNDL-CAR-PL-CRM | C52: RESTONIC CAROUSEL PLUSH CREAM HANDLE | D52: NOS | E52: CBERM | F52: 1725 | G52: 6.7498 | H52: 11643.36 | I52: 500 | J52: 6.75 | K52: 3375 | L52: 675 | M52: 6.7498 | N52: 4556.12 | O52: 1550 | P52: 6.7498 | Q52: 10462.24 | R52: LCE | S52: Label,CnrShoe,CentreBand,EdgeTape-10195 | T52: MATRESS
A53: 882 | B53: RML-KOM-COM-MRP-LBL | C53: KOMFFY FEATHER SOFT COMFORTER MRP LABEL | D53: NOS | E53: CBERM | F53: 190 | G53: 2.9247 | H53: 555.7 | I53: 0 | K53: 0 | L53: 0 | N53: 0 | O53: 190 | P53: 2.9247 | Q53: 555.7 | R53: LCE | S53: Label,CnrShoe,CentreBand,EdgeTape-10195 | T53: MATRESS
A54: 883 | B54: RML-KOM-COM-PVC-CVR | C54: KOMFFY COMFORTER PVC COVER (12MIC PET+75MIC LDPE N ,750MMX490MM) | D54: NOS | E54: CBERM | F54: 4515 | G54: 18 | H54: 81270 | I54: 10408 | J54: 18 | K54: 187344 | L54: 500 | M54: 18 | N54: 9000 | O54: 14423 | P54: 18 | Q54: 259614 | R54: PML | S54: Packing Material-10195 | T54: MATRESS
A55: 884 | B55: RML-KOM-GRIP-INS | C55: KOMFFY GRIPSTER INSERTER | D55: NOS | E55: CBERM | F55: 1000 | G55: 19.1 | H55: 19100 | I55: 0 | K55: 0 | L55: 0 | N55: 0 | O55: 1000 | P55: 19.1 | Q55: 19100 | R55: LCE | S55: Label,CnrShoe,CentreBand,EdgeTape-10195 | T55: MATRESS
A56: 924 | B56: RML-KOM-PL-BED-SHT-105X120 | C56: KOMFFY PLUS BED SHEET SUPER KING- 105"X120" (RTC) | D56: NOS | E56: CBERM | F56: 5396 | G56: 429 | H56: 2314884 | I56: 0 | K56: 0 | L56: 192 | M56: 429 | N56: 82368 | O56: 5204 | P56: 429 | Q56: 2232516 | R56: SCHEME | S56: Scheme Materials-13015 | T56: MATRESS
A57: 992 | B57: RML-CUT-RES-GLS | C57: CUTTING RESISTANCE GLOVES | D57: PRS | E57: CBERM | F57: 26 | G57: 175 | H57: 4550 | I57: 25 | J57: 175 | K57: 4375 | L57: 25 | M57: 175 | N57: 4375 | O57: 26 | P57: 175 | Q57: 4550 | R57: PML | S57: Packing Material-10195 | T57: MATRESS
A58: 999 | B58: RML-DDR-SDE-LBL | C58: DOUBLE DECKER SIDE LABEL (RUBBER PATCH) | D58: NOS | E58: CBERM | F58: 1343 | G58: 115.9205 | H58: 155681.17 | I58: 0 | K58: 0 | L58: 2 | M58: 115.92 | N58: 231.84 | O58: 1341 | P58: 115.9205 | Q58: 155449.33 | R58: LCE | S58: Label,CnrShoe,CentreBand,EdgeTape-10195 | T58: MATRESS
A59: 1000 | B59: RML-DD-WCRD | C59: PEPS DOUBLE DECKER WARRANTY CARD | D59: NOS | E59: CBERM | F59: 1095 | G59: 13.8549 | H59: 15171.17 | I59: 5 | J59: 13.854 | K59: 69.27 | L59: 0 | N59: 0 | O59: 1100 | P59: 13.8549 | Q59: 15240.44 | R59: LCE | S59: Label,CnrShoe,CentreBand,EdgeTape-10195 | T59: MATRESS
A60: 1005 | B60: RM-LDPE-50"TUBE-PLAIN | C60: LDPE TUBE 58"X50.MIC | D60: KGS | E60: CBERM | F60: 519.4 | G60: 127.0259 | H60: 65977.26 | I60: 211.9 | J60: 130 | K60: 27547 | L60: 312.1 | M60: 127.4226 | N60: 39768.6 | O60: 419.2 | P60: 128.2339 | Q60: 53755.66 | R60: PML | S60: Packing Material-10195 | T60: MATRESS
A61: 1096 | B61: RML-FIT-SHT-INS-DOUBLE | C61: PEPS POLAR FLEECE BLANKET INSERTER- DOUBLE | D61: NOS | E61: CBERM | F61: 515 | G61: 17.9391 | H61: 9238.64 | I61: 0 | K61: 0 | L61: 13 | M61: 17.9392 | N61: 233.21 | O61: 502 | P61: 17.9391 | Q61: 9005.43 | R61: LCE | S61: Label,CnrShoe,CentreBand,EdgeTape-10195 | T61: FOAM
A62: 1098 | B62: RML-FIT-SHT-INS-SINGLE | C62: PEPS POLAR FLEECE BLANKET INSERTER- SINGLE | D62: NOS | E62: CBERM | F62: 286 | G62: 16.4821 | H62: 4713.88 | I62: 0 | K62: 0 | L62: 15 | M62: 16.482 | N62: 247.23 | O62: 271 | P62: 16.4821 | Q62: 4466.65 | R62: LCE | S62: Label,CnrShoe,CentreBand,EdgeTape-10195 | T62: FOAM
A63: 1099 | B63: RML-FIX-BRACKET | C63: BASE AND HB FIXING BRACKET | D63: SET | E63: CBERM | F63: 708 | G63: 76.5997 | H63: 54232.56 | I63: 0 | K63: 0 | L63: 60 | M63: 76.5997 | N63: 4595.98 | O63: 648 | P63: 76.5997 | Q63: 49636.58 | R63: BASHB | S63: Base and Head Board -10181 | T63: FOAM
A64: 1101 | B64: RML-FLN-BLNK-60X85 | C64: PEPS Flano Printed blanket Single- Size:60x85 Inch | D64: NOS | E64: CBERM | F64: 64 | G64: 255 | H64: 16320 | I64: 0 | K64: 0 | L64: 0 | N64: 0 | O64: 64 | P64: 255 | Q64: 16320 | R64: ALIPROD | S64: Allied Products-13015 | T64: MATRESS
A65: 1103 | B65: RML-FLN-BLNK-85X95 | C65: PEPS FLANO PRINTED BLANKET DOUBLE- SIZE:85X95 INCH | D65: NOS | E65: CBERM | F65: 58 | G65: 265 | H65: 15370 | I65: 0 | K65: 0 | L65: 0 | N65: 0 | O65: 58 | P65: 265 | Q65: 15370 | R65: ALIPROD | S65: Allied Products-13015 | T65: MATRESS
A66: 1107 | B66: RML-FLXI-NECK-PLW-CTN-ROPE | C66: FLEXI NECK PILLOW COTTON ROPE - 2.5MM | D66: KGS | E66: CBERM | F66: 16.98 | G66: 185 | H66: 3141.3 | I66: 0 | K66: 0 | L66: 5.92 | M66: 185 | N66: 1095.2 | O66: 11.06 | P66: 185 | Q66: 2046.1 | R66: LCE | S66: Label,CnrShoe,CentreBand,EdgeTape-10195 | T66: MATRESS
A67: 1109 | B67: RML-FLXI-NECK-PLW-MRP-LBL | C67: FLEXI NECK PILLOW MRP LABEL | D67: NOS | E67: CBERM | F67: 100 | G67: 11 | H67: 1100 | I67: 700 | J67: 11 | K67: 7700 | L67: 200 | M67: 11 | N67: 2200 | O67: 600 | P67: 11 | Q67: 6600 | R67: LCE | S67: Label,CnrShoe,CentreBand,EdgeTape-10195 | T67: MATRESS
A68: 1111 | B68: RML-FLXI-NECK-PLW-PVC-BAG | C68: FLEXI NECK PILLOW PVC BAG 11.25" Wx11.5" Hx4" G | D68: NOS | E68: CBERM | F68: 1325 | G68: 27 | H68: 35775 | I68: 575 | J68: 27 | K68: 15525 | L68: 50 | M68: 27 | N68: 1350 | O68: 1850 | P68: 27 | Q68: 49950 | R68: PML | S68: Packing Material-10195 | T68: MATRESS
A69: 1113 | B69: RML-FLXI-NECK-PLW-WSCR-LBL | C69: FLEXI NECK PILLOW WASH CARE LABEL | D69: NOS | E69: CBERM | F69: 500 | G69: 0.8 | H69: 400 | I69: 0 | K69: 0 | L69: 0 | N69: 0 | O69: 500 | P69: 0.8 | Q69: 400 | R69: LCE | S69: Label,CnrShoe,CentreBand,EdgeTape-10195 | T69: MATRESS
A70: 1115 | B70: RML-FLXI-SPN-LDPE-7X30+4FX75MIC | C70: FLEXI SPINE LDPE PLAIN SEAL KING BAG 7"X 30"+ 4"F X 75MIC | D70: NOS | E70: CBERM | F70: 1500 | G70: 2.4 | H70: 3600 | I70: 0 | K70: 0 | L70: 0 | N70: 0 | O70: 1500 | P70: 2.4 | Q70: 3600 | R70: PML | S70: Packing Material-10195 | T70: MATRESS
A71: 1116 | B71: RML-FLXI-SPN-PLW-BOX | C71: FLEXI SPINE PILLOW BOX 27"x5"x4" - 3 Ply | D71: NOS | E71: CBERM | F71: 600 | G71: 44 | H71: 26400 | I71: 500 | J71: 44 | K71: 22000 | L71: 75 | M71: 44 | N71: 3300 | O71: 1025 | P71: 44 | Q71: 45100 | R71: PML | S71: Packing Material-10195 | T71: MATRESS
A72: 1119 | B72: RML-FLXI-SPN-PLW-WSCR-LBL | C72: FLEXI SPINE PILLOW WASH CARE LABEL | D72: NOS | E72: CBERM | F72: 750 | G72: 0.8 | H72: 600 | I72: 0 | K72: 0 | L72: 0 | N72: 0 | O72: 750 | P72: 0.8 | Q72: 600 | R72: LCE | S72: Label,CnrShoe,CentreBand,EdgeTape-10195 | T72: MATRESS
A73: 1121 | B73: RML-FLXI-SPN-PVC-HOSE | C73: FLEXI SPINE PVC HOSE 1/2" X 26" | D73: NOS | E73: CBERM | F73: 689 | G73: 164.5714 | H73: 113389.71 | I73: 0 | K73: 0 | L73: 0 | N73: 0 | O73: 689 | P73: 164.5714 | Q73: 113389.71 | R73: CPG | S73: Clips, Polygel & Glue-10195 | T73: MATRESS
A74: 1122 | B74: RML-FLX-STRAP-GRY | C74: FLEXI SPINE PILLOW STRAP GREY-12MM | D74: MTR | E74: CBERM | F74: 60 | G74: 33.33 | H74: 1999.8 | I74: 0 | K74: 0 | L74: 0 | N74: 0 | O74: 60 | P74: 33.33 | Q74: 1999.8 | R74: PML | S74: Packing Material-10195 | T74: MATRESS
A75: 1123 | B75: RML-FLX-STRAP-NVBL | C75: FLEXI SPINE PILLOW STRAP NAVY BLUE-12MM | D75: MTR | E75: CBERM | F75: 60 | G75: 33.33 | H75: 1999.8 | I75: 0 | K75: 0 | L75: 0 | N75: 0 | O75: 60 | P75: 33.33 | Q75: 1999.8 | R75: PML | S75: Packing Material-10195 | T75: MATRESS
A76: 1124 | B76: RML-FM-WHT-HANDLE | C76: FOAM MATTRESS WHITE WITH CREAM HANDLE | D76: NOS | E76: CBERM | F76: 2150 | G76: 5.2502 | H76: 11287.86 | I76: 250 | J76: 5.25 | K76: 1312.5 | L76: 325 | M76: 5.2502 | N76: 1706.32 | O76: 2075 | P76: 5.2501 | Q76: 10894.04 | R76: LCE | S76: Label,CnrShoe,CentreBand,EdgeTape-10195 | T76: MATRESS
A77: 1130 | B77: RML-FOAMERA-WCRD | C77: FOAMERA 7 YEARS WARRANTY CARD | D77: NOS | E77: CBERM | F77: 1250 | G77: 5.4498 | H77: 6812.23 | I77: 0 | K77: 0 | L77: 0 | N77: 0 | O77: 1250 | P77: 5.4498 | Q77: 6812.23 | R77: LCE | S77: Label,CnrShoe,CentreBand,EdgeTape-10195 | T77: MATRESS
A78: 1142 | B78: RML-FOL-ROLWAY-COT | C78: FOLDING ROLLWAY COT 72"X36" | D78: NOS | E78: CBERM | F78: 8 | G78: 6963.7175 | H78: 55709.74 | I78: 0 | K78: 0 | L78: 6 | M78: 6963.72 | N78: 41782.32 | O78: 2 | P78: 6963.71 | Q78: 13927.42 | R78: SPARE | S78: SPARES Inventory - 10698 | T78: MATRESS
A79: 1681 | B79: RML-KOM-PTR-78X30 | C79: KOMFFY MATTRESSES PROTECTOR 78X30 | D79: NOS | E79: CBERM | F79: 5 | G79: 416 | H79: 2080 | I79: 0 | K79: 0 | L79: 0 | N79: 0 | O79: 5 | P79: 416 | Q79: 2080 | R79: SCHEME | S79: Scheme Materials-13015 | T79: MATRESS
A80: 1685 | B80: RML-KOM-PTR-78X36 | C80: KOMFFY MATTRESSES PROTECTOR 78X36 | D80: NOS | E80: CBERM | F80: 123 | G80: 498 | H80: 61254 | I80: 0 | K80: 0 | L80: 0 | N80: 0 | O80: 123 | P80: 498 | Q80: 61254 | R80: SCHEME | S80: Scheme Materials-13015 | T80: MATRESS
A81: 1692 | B81: RML-KOM-PTR-78X48 | C81: KOMFFY MATTRESSES PROTECTOR 78X48 | D81: NOS | E81: CBERM | F81: 308 | G81: 590 | H81: 181720 | I81: 0 | K81: 0 | L81: 0 | N81: 0 | O81: 308 | P81: 590 | Q81: 181720 | R81: SCHEME | S81: Scheme Materials-13015 | T81: MATRESS
A82: 1703 | B82: RML-KOM-PTR-78X60 | C82: KOMFFY MATTRESSES PROTECTOR 78X60 | D82: NOS | E82: CBERM | F82: 691 | G82: 592 | H82: 409072 | I82: 2 | J82: 592 | K82: 1184 | L82: 0 | N82: 0 | O82: 693 | P82: 592 | Q82: 410256 | R82: SCHEME | S82: Scheme Materials-13015 | T82: MATRESS
A83: 1731 | B83: RML-KOM-PTR-84X72 | C83: KOMFFY MATTRESSES PROTECTOR 84X72 | D83: NOS | E83: CBERM | F83: 13 | G83: 1030 | H83: 13390 | I83: 0 | K83: 0 | L83: 0 | N83: 0 | O83: 13 | P83: 1030 | Q83: 13390 | R83: SCHEME | S83: Scheme Materials-13015 | T83: MATRESS
A84: 1734 | B84: RML-KOM-PTR-INS | C84: KOMFFY PROTECTOR INSERTER | D84: NOS | E84: CBERM | F84: 3950 | G84: 7.2601 | H84: 28677.42 | I84: 0 | K84: 0 | L84: 0 | N84: 0 | O84: 3950 | P84: 7.2601 | Q84: 28677.42 | R84: LCE | S84: Label,CnrShoe,CentreBand,EdgeTape-10195 | T84: FOAM
A85: 1737 | B85: RML-KOM-PTR-MRP-LBL | C85: KOMFFY PROTECTOR MRP LABEL | D85: NOS | E85: CBERM | F85: 11400 | G85: 0.9693 | H85: 11049.86 | I85: 0 | K85: 0 | L85: 0 | N85: 0 | O85: 11400 | P85: 0.9693 | Q85: 11049.86 | R85: LCE | S85: Label,CnrShoe,CentreBand,EdgeTape-10195 | T85: FOAM
A86: 1784 | B86: RML-KOM-WSCR-LBL-CNTR-PLW | C86: KOMFFY MEMORY CONTOUR PILLOW WASH CARE LABEL | D86: NOS | E86: CBERM | F86: 7500 | G86: 0.5995 | H86: 4496.6 | I86: 0 | K86: 0 | L86: 0 | N86: 0 | O86: 7500 | P86: 0.5995 | Q86: 4496.6 | R86: LCE | S86: Label,CnrShoe,CentreBand,EdgeTape-10195 | T86: FOAM
A87: 1785 | B87: RML-KOZBRE-SDE-LBL | C87: KOZYBREEZ SIDE LABEL | D87: NOS | E87: CBERM | F87: 3100 | G87: 8.8006 | H87: 27281.9 | I87: 0 | K87: 0 | L87: 100 | M87: 8.8006 | N87: 880.06 | O87: 3000 | P87: 8.8006 | Q87: 26401.84 | R87: LCE | S87: Label,CnrShoe,CentreBand,EdgeTape-10195 | T87: MATRESS
A88: 1789 | B88: RML-KOZBRE-WCRD | C88: KOZYBREEZ WARRANTY CARD | D88: NOS | E88: CBERM | F88: 1973 | G88: 3.2768 | H88: 6465.22 | I88: 300 | J88: 11 | K88: 3300 | L88: 0 | N88: 0 | O88: 2273 | P88: 4.2962 | Q88: 9765.22 | R88: LCE | S88: Label,CnrShoe,CentreBand,EdgeTape-10195 | T88: MATRESS
A89: 1792 | B89: RML-LAT-MAS-PIL-BOX | C89: LATEX MASSAGE PILLOW BOX | D89: NOS | E89: CBERM | F89: 240 | G89: 103.3256 | H89: 24798.15 | I89: 0 | K89: 0 | L89: 56 | M89: 103.3257 | N89: 5786.24 | O89: 184 | P89: 103.3256 | Q89: 19011.91 | R89: PML | S89: Packing Material-10195 | T89: MATRESS
A90: 1796 | B90: RML-LCORNER-PAD-15 | C90: 15X15 INCH L CORNER PAD | D90: NOS | E90: CBERM | F90: 2350 | G90: 12.4986 | H90: 29371.76 | I90: 0 | K90: 0 | L90: 1550 | M90: 12.4986 | N90: 19372.83 | O90: 800 | P90: 12.4987 | Q90: 9998.93 | R90: PML | S90: Packing Material-10195 | T90: MATRESS
A91: 1831 | B91: RML-NET-PADDING | C91: HDPE KNITTED FABRIC ( MOSQUITO NET) | D91: MTR | E91: CBERM | F91: 81374 | G91: 6.4828 | H91: 527533.33 | I91: 71387 | J91: 6.4889 | K91: 463225.54 | L91: 72551 | M91: 6.4852 | N91: 470508.36 | O91: 80210 | P91: 6.4861 | Q91: 520250.51 | R91: NET | S91: Net-10195 | T91: MATRESS
A92: 1836 | B92: RML-NET-PADDING-TNDR | C92: TNDR - HDPE KNITTED FABRIC ( MOSQUITO NET) | D92: MTR | E92: CBERM | F92: 45928 | G92: 6 | H92: 275568 | I92: 0 | K92: 0 | L92: 45928 | M92: 6 | N92: 275568 | O92: 0 | Q92: 0 | R92: NET | S92: Net-10195 | T92: MATRESS
A93: 1838 | B93: RML-NET-PADDING-WHT | C93: HDPE KNITTED FABRIC - WHITE (MOSQUITO NET) | D93: MTR | E93: CBERM | F93: 1425 | G93: 8.5 | H93: 12112.5 | I93: 1920 | J93: 8.5 | K93: 16320 | L93: 1425 | M93: 8.5 | N93: 12112.5 | O93: 1920 | P93: 8.5 | Q93: 16320 | R93: LCE | S93: Label,CnrShoe,CentreBand,EdgeTape-10195 | T93: MATRESS
A94: 1839 | B94: RML-NONSTANDARD-SKR | C94: NON STANDARD STICKER | D94: NOS | E94: CBERM | F94: 950 | G94: 0.51 | H94: 484.51 | I94: 1000 | J94: 0.8 | K94: 800 | L94: 700 | M94: 0.6197 | N94: 433.8 | O94: 1250 | P94: 0.6806 | Q94: 850.71 | R94: LCE | S94: Label,CnrShoe,CentreBand,EdgeTape-10195 | T94: MATRESS
A95: 1841 | B95: RML-NWN-70GSMX76" | C95: NON WOVEN FABRIC 70 GSM x 76 INCH - WHITE | D95: KGS | E95: CBERM | F95: 607.8 | G95: 112.8872 | H95: 68612.82 | I95: 0 | K95: 0 | L95: 191 | M95: 112.8872 | N95: 21561.45 | O95: 416.8 | P95: 112.8872 | Q95: 47051.37 | R95: NW | S95: Non Woven Fabric-10195 | T95: MATRESS
A96: 1846 | B96: RML-NWN-70GSMX79" | C96: NON WOVEN FABRIC 70 GSM x 79 INCH - WHITE | D96: KGS | E96: CBERM | F96: 715.4 | G96: 113.6458 | H96: 81302.17 | I96: 3985.4 | J96: 114 | K96: 454335.43 | L96: 2965 | M96: 113.9235 | N96: 337783.29 | O96: 1735.8 | P96: 113.9845 | Q96: 197854.31 | R96: NW | S96: Non Woven Fabric-10195 | T96: MATRESS
A97: 1850 | B97: RML-NWN-80GSMX8" | C97: NON WOVEN FABRIC 80 GSM x 8 INCH - WHITE | D97: KGS | E97: CBERM | F97: 285.8 | G97: 111.0368 | H97: 31734.32 | I97: 0 | K97: 0 | L97: 0 | N97: 0 | O97: 285.8 | P97: 111.0368 | Q97: 31734.32 | R97: NW | S97: Non Woven Fabric-10195 | T97: MATRESS
A98: 1851 | B98: RML-NWN-80GSMX82BLK | C98: NON WOVEN FABRIC 80 GSM x 82 INCH - BLACK | D98: KGS | E98: CBERM | F98: 441.6 | G98: 123.9498 | H98: 54736.25 | I98: 0 | K98: 0 | L98: 81.8 | M98: 123.95 | N98: 10139.11 | O98: 359.8 | P98: 123.9498 | Q98: 44597.14 | R98: NW | S98: Non Woven Fabric-10195 | T98: MATRESS
A99: 1854 | B99: RML-NYLONBUSH-50X100 | C99: NYLON BUSH WHITE COLOR | D99: NOS | E99: CBERM | F99: 1047 | G99: 17.7208 | H99: 18553.71 | I99: 0 | K99: 0 | L99: 2 | M99: 17.72 | N99: 35.44 | O99: 1045 | P99: 17.7208 | Q99: 18518.27 | R99: CPG | S99: Clips, Polygel & Glue-10195 | T99: MATRESS
A100: 1858 | B100: RML-OGA-WCRD | C100: PEPS ORGANICA WARRANTY CARD | D100: NOS | E100: CBERM | F100: 7630 | G100: 9.4147 | H100: 71834.51 | I100: 0 | K100: 0 | L100: 160 | M100: 9.4148 | N100: 1506.37 | O100: 7470 | P100: 9.4147 | Q100: 70328.14 | R100: LCE | S100: Label,CnrShoe,CentreBand,EdgeTape-10195 | T100: MATRESS
...

Sheet Item code
A1: S.no | B1: R.no | C1: Date | D1: Item | E1: PS Desc. | F1: PS Usage | G1: PS Category | H1: Process Plan | I1: Uom | J1: Qty | K1: Default For | L1: Wh Code | M1: RM-COST | N1: PRO-RATE
A2: 1 | B2: 1 | C2: 28.03.2024 | D2: SFG-FRBNET-MEM-BOR-72X33X08 | E2: Restonic Hotel Motel Bonnell Euro Top Memory Border 72X33X08 | F2: Standard | G2: Production | H2: TAIL-BORDER | I2: NOS | J2: 1 | K2: MRP&Rollup | L2: CBESFG | M2: 144.148 | N2: 162
A3: 2 | B3: 2 | C3: 28.03.2024 | D3: SFG-FRBNET-MEM-BOR-72X39X08 | E3: Restonic Hotel Motel Bonnell Euro Top Memory Border 72X39X08 | F3: Standard | G3: Production | H3: TAIL-BORDER | I3: NOS | J3: 1 | K3: MRP&Rollup | L3: CBESFG | M3: 150.676 | N3: 170
A4: 3 | B4: 3 | C4: 28.03.2024 | D4: SFG-FRBNET-MEM-BOR-72X45X08 | E4: Restonic Hotel Motel Bonnell Euro Top Memory Border 72X45X08 | F4: Standard | G4: Production | H4: TAIL-BORDER | I4: NOS | J4: 1 | K4: MRP&Rollup | L4: CBESFG | M4: 157.226 | N4: 177
A5: 4 | B5: 4 | C5: 28.03.2024 | D5: SFG-FRBNET-MEM-BOR-72X51X08 | E5: Restonic Hotel Motel Bonnell Euro Top Memory Border 72X51X08 | F5: Standard | G5: Production | H5: TAIL-BORDER | I5: NOS | J5: 1 | K5: MRP&Rollup | L5: CBESFG | M5: 163.776 | N5: 185
A6: 5 | B6: 5 | C6: 28.03.2024 | D6: SFG-FRBNET-MEM-BOR-72X54X08 | E6: Restonic Hotel Motel Bonnell Euro Top Memory Border 72X54X08 | F6: Standard | G6: Production | H6: TAIL-BORDER | I6: NOS | J6: 1 | K6: MRP&Rollup | L6: CBESFG | M6: 167.04 | N6: 188
A7: 6 | B7: 6 | C7: 28.03.2024 | D7: SFG-FRBNET-MEM-BOR-72X57X08 | E7: Restonic Hotel Motel Bonnell Euro Top Memory Border 72X57X08 | F7: Standard | G7: Production | H7: TAIL-BORDER | I7: NOS | J7: 1 | K7: MRP&Rollup | L7: CBESFG | M7: 170.326 | N7: 192
A8: 7 | B8: 7 | C8: 28.03.2024 | D8: SFG-FRBNET-MEM-BOR-72X63X08 | E8: Restonic Hotel Motel Bonnell Euro Top Memory Border 72X63X08 | F8: Standard | G8: Production | H8: TAIL-BORDER | I8: NOS | J8: 1 | K8: MRP&Rollup | L8: CBESFG | M8: 176.876 | N8: 199
A9: 8 | B9: 8 | C9: 28.03.2024 | D9: SFG-FRBNET-MEM-BOR-72X69X08 | E9: Restonic Hotel Motel Bonnell Euro Top Memory Border 72X69X08 | F9: Standard | G9: Production | H9: TAIL-BORDER | I9: NOS | J9: 1 | K9: MRP&Rollup | L9: CBESFG | M9: 183.405 | N9: 207
A10: 9 | B10: 9 | C10: 28.03.2024 | D10: SFG-FRBNET-MEM-BOR-75X33X08 | E10: Restonic Hotel Motel Bonnell Euro Top Memory Border 75X33X08 | F10: Standard | G10: Production | H10: TAIL-BORDER | I10: NOS | J10: 1 | K10: MRP&Rollup | L10: CBESFG | M10: 147.412 | N10: 166
A11: 10 | B11: 10 | C11: 28.03.2024 | D11: SFG-FRBNET-MEM-BOR-75X39X08 | E11: Restonic Hotel Motel Bonnell Euro Top Memory Border 75X39X08 | F11: Standard | G11: Production | H11: TAIL-BORDER | I11: NOS | J11: 1 | K11: MRP&Rollup | L11: CBESFG | M11: 153.962 | N11: 174
A12: 11 | B12: 11 | C12: 28.03.2024 | D12: SFG-FRBNET-MEM-BOR-75X45X08 | E12: Restonic Hotel Motel Bonnell Euro Top Memory Border 75X45X08 | F12: Standard | G12: Production | H12: TAIL-BORDER | I12: NOS | J12: 1 | K12: MRP&Rollup | L12: CBESFG | M12: 160.512 | N12: 181
A13: 12 | B13: 12 | C13: 28.03.2024 | D13: SFG-FRBNET-MEM-BOR-75X51X08 | E13: Restonic Hotel Motel Bonnell Euro Top Memory Border 75X51X08 | F13: Standard | G13: Production | H13: TAIL-BORDER | I13: NOS | J13: 1 | K13: MRP&Rollup | L13: CBESFG | M13: 167.04 | N13: 188
... A41: 40 | B41: 40 | C41: 28.03.2024 | D41: SFG-FRBNET-MEM-BOR-84X69X08 | E41: Restonic Hotel Motel Bonnell Euro Top Memory Border 84X69X08 | F41: Standard | G41: Production | H41: TAIL-BORDER | I41: NOS | J41: 1 | K41: MRP&Rollup | L41: CBESFG | M41: 196.505 | N41: 221

Sheet pro.stru
A1: S.no | B1: R.no | C1: Date | D1: Bom Code/PS.No | E1: PS Desc. | F1: Item | G1: PS Desc. | H1: PS Usage | I1: PS Category | J1: Process Plan | K1: Uom | L1: Qty | M1: Default For | N1: Wh Code | O1: PS Seq | P1: I/O Flag | Q1: Issue Item | R1: Item Desc | S1: Uom | T1: Qty | U1: Std Wh Code | V1: Backflush | W1: Status
A2: 1 | B2: 1 | C2: 28.03.2024 | D2: SFG-FRBNET-MEM-BOR-72X33X08 | E2: Restonic Hotel Motel Bonnell Euro Top Memory Border 72X33X08 | F2: SFG-FRBNET-MEM-BOR-72X33X08 | G2: Restonic Hotel Motel Bonnell Euro Top Memory Border 72X33X08 | H2: Standard | I2: Production | J2: TAIL-BORDER | K2: NOS | L2: 1 | M2: MRP&Rollup | N2: CBESFG | O2: 10 | P2: I | Q2: RM-THRD-QS-TKT40 | R2: THREAD TKT40 210D/3 PLY 10000MTS | S2: MTR | T2: 5.6 | U2: CBEWIP | V2: Backflush | W2: Active
A3: 2 | B3: 1 | C3: 28.03.2024 | D3: SFG-FRBNET-MEM-BOR-72X33X08 | E3: Restonic Hotel Motel Bonnell Euro Top Memory Border 72X33X08 | F3: SFG-FRBNET-MEM-BOR-72X33X08 | G3: Restonic Hotel Motel Bonnell Euro Top Memory Border 72X33X08 | H3: Standard | I3: Production | J3: TAIL-BORDER | K3: NOS | L3: 1 | M3: MRP&Rollup | N3: CBESFG | O3: 20 | P3: I | Q3: HW-CTON-THREAD | R3: COTTON THREAD WHITE 3PLY | S3: MTR | T3: 5 | U3: CBEWIP | V3: Backflush | W3: Active
A4: 3 | B4: 1 | C4: 28.03.2024 | D4: SFG-FRBNET-MEM-BOR-72X33X08 | E4: Restonic Hotel Motel Bonnell Euro Top Memory Border 72X33X08 | F4: SFG-FRBNET-MEM-BOR-72X33X08 | G4: Restonic Hotel Motel Bonnell Euro Top Memory Border 72X33X08 | H4: Standard | I4: Production | J4: TAIL-BORDER | K4: NOS | L4: 1 | M4: MRP&Rollup | N4: CBESFG | O4: 30 | P4: I | Q4: SFG-RTHTMT-BNPK-MEM-BOR-21CM | R4: Hotel Motel Poc ET-8 8MM/16D Pre Foam Memory Border 21 CM Height | S4: MTR | T4: 5.411 | U4: CBESFG | V4: Backflush | W4: Active
A5: 4 | B5: 1 | C5: 28.03.2024 | D5: SFG-FRBNET-MEM-BOR-72X33X08 | E5: Restonic Hotel Motel Bonnell Euro Top Memory Border 72X33X08 | F5: SFG-FRBNET-MEM-BOR-72X33X08 | G5: Restonic Hotel Motel Bonnell Euro Top Memory Border 72X33X08 | H5: Standard | I5: Production | J5: TAIL-BORDER | K5: NOS | L5: 1 | M5: MRP&Rollup | N5: CBESFG | O5: 40 | P5: I | Q5: RMI-HCC-SDE-LBL | R5: HOTEL COMFORT CARE SIDE LABEL (IMPORT) | S5: NOS | T5: 1 | U5: CBEWIP | V5: Backflush | W5: Active
A6: 5 | B6: 1 | C6: 28.03.2024 | D6: SFG-FRBNET-MEM-BOR-72X33X08 | E6: Restonic Hotel Motel Bonnell Euro Top Memory Border 72X33X08 | F6: SFG-FRBNET-MEM-BOR-72X33X08 | G6: Restonic Hotel Motel Bonnell Euro Top Memory Border 72X33X08 | H6: Standard | I6: Production | J6: TAIL-BORDER | K6: NOS | L6: 1 | M6: MRP&Rollup | N6: CBESFG | O6: 50 | P6: I | Q6: RML-MRP-BACK-LBL | R6: MRP BACK LABEL(PLAIN) | S6: NOS | T6: 1 | U6: CBEWIP | V6: Backflush | W6: Active
A7: 6 | B7: 1 | C7: 28.03.2024 | D7: SFG-FRBNET-MEM-BOR-72X33X08 | E7: Restonic Hotel Motel Bonnell Euro Top Memory Border 72X33X08 | F7: SFG-FRBNET-MEM-BOR-72X33X08 | G7: Restonic Hotel Motel Bonnell Euro Top Memory Border 72X33X08 | H7: Standard | I7: Production | J7: TAIL-BORDER | K7: NOS | L7: 1 | M7: MRP&Rollup | N7: CBESFG | O7: 60 | P7: I | Q7: RML-DRN-LBL | R7: DIRECTION LABEL | S7: NOS | T7: 1 | U7: CBEWIP | V7: Backflush | W7: Active
A8: 7 | B8: 1 | C8: 28.03.2024 | D8: SFG-FRBNET-MEM-BOR-72X33X08 | E8: Restonic Hotel Motel Bonnell Euro Top Memory Border 72X33X08 | F8: SFG-FRBNET-MEM-BOR-72X33X08 | G8: Restonic Hotel Motel Bonnell Euro Top Memory Border 72X33X08 | H8: Standard | I8: Production | J8: TAIL-BORDER | K8: NOS | L8: 1 | M8: MRP&Rollup | N8: CBESFG | O8: 70 | P8: I | Q8: SFG-RTHTMT-MEM-HANDLE | R8: Restonic Hotel Motel Memory Handle | S8: MTR | T8: 0.64 | U8: CBESFG | V8: Backflush | W8: Active
A9: 8 | B9: 1 | C9: 28.03.2024 | D9: SFG-FRBNET-MEM-BOR-72X33X08 | E9: Restonic Hotel Motel Bonnell Euro Top Memory Border 72X33X08 | F9: SFG-FRBNET-MEM-BOR-72X33X08 | G9: Restonic Hotel Motel Bonnell Euro Top Memory Border 72X33X08 | H9: Standard | I9: Production | J9: TAIL-BORDER | K9: NOS | L9: 1 | M9: MRP&Rollup | N9: CBESFG | O9: 80 | P9: I | Q9: RMI-BREATHER-GOLD | R9: BREATHER SET GOLD ROUND | S9: SET | T9: 2 | U9: CBEWIP | V9: Backflush | W9: Active
A10: 9 | B10: 2 | C10: 28.03.2024 | D10: SFG-FRBNET-MEM-BOR-72X39X08 | E10: Restonic Hotel Motel Bonnell Euro Top Memory Border 72X39X08 | F10: SFG-FRBNET-MEM-BOR-72X39X08 | G10: Restonic Hotel Motel Bonnell Euro Top Memory Border 72X39X08 | H10: Standard | I10: Production | J10: TAIL-BORDER | K10: NOS | L10: 1 | M10: MRP&Rollup | N10: CBESFG | O10: 10 | P10: I | Q10: RM-THRD-QS-TKT40 | R10: THREAD TKT40 210D/3 PLY 10000MTS | S10: MTR | T10: 5.6 | U10: CBEWIP | V10: Backflush | W10: Active
A11: 10 | B11: 2 | C11: 28.03.2024 | D11: SFG-FRBNET-MEM-BOR-72X39X08 | E11: Restonic Hotel Motel Bonnell Euro Top Memory Border 72X39X08 | F11: SFG-FRBNET-MEM-BOR-72X39X08 | G11: Restonic Hotel Motel Bonnell Euro Top Memory Border 72X39X08 | H11: Standard | I11: Production | J11: TAIL-BORDER | K11: NOS | L11: 1 | M11: MRP&Rollup | N11: CBESFG | O11: 20 | P11: I | Q11: HW-CTON-THREAD | R11: COTTON THREAD WHITE 3PLY | S11: MTR | T11: 5 | U11: CBEWIP | V11: Backflush | W11: Active
A12: 11 | B12: 2 | C12: 28.03.2024 | D12: SFG-FRBNET-MEM-BOR-72X39X08 | E12: Restonic Hotel Motel Bonnell Euro Top Memory Border 72X39X08 | F12: SFG-FRBNET-MEM-BOR-72X39X08 | G12: Restonic Hotel Motel Bonnell Euro Top Memory Border 72X39X08 | H12: Standard | I12: Production | J12: TAIL-BORDER | K12: NOS | L12: 1 | M12: MRP&Rollup | N12: CBESFG | O12: 30 | P12: I | Q12: SFG-RTHTMT-BNPK-MEM-BOR-21CM | R12: Hotel Motel Poc ET-8 8MM/16D Pre Foam Memory Border 21 CM Height | S12: MTR | T12: 5.715 | U12: CBESFG | V12: Backflush | W12: Active
A13: 12 | B13: 2 | C13: 28.03.2024 | D13: SFG-FRBNET-MEM-BOR-72X39X08 | E13: Restonic Hotel Motel Bonnell Euro Top Memory Border 72X39X08 | F13: SFG-FRBNET-MEM-BOR-72X39X08 | G13: Restonic Hotel Motel Bonnell Euro Top Memory Border 72X39X08 | H13: Standard | I13: Production | J13: TAIL-BORDER | K13: NOS | L13: 1 | M13: MRP&Rollup | N13: CBESFG | O13: 40 | P13: I | Q13: RMI-HCC-SDE-LBL | R13: HOTEL COMFORT CARE SIDE LABEL (IMPORT) | S13: NOS | T13: 1 | U13: CBEWIP | V13: Backflush | W13: Active
... A321: 320 | B321: 40 | C321: 28.03.2024 | D321: SFG-FRBNET-MEM-BOR-84X69X08 | E321: Restonic Hotel Motel Bonnell Euro Top Memory Border 84X69X08 | F321: SFG-FRBNET-MEM-BOR-84X69X08 | G321: Restonic Hotel Motel Bonnell Euro Top Memory Border 84X69X08 | H321: Standard | I321: Production | J321: TAIL-BORDER | K321: NOS | L321: 1 | M321: MRP&Rollup | N321: CBESFG | O321: 80 | P321: I | Q321: RMI-BREATHER-GOLD | R321: BREATHER SET GOLD ROUND | S321: SET | T321: 2 | U321: CBEWIP | V321: Backflush | W321: Active
