Workbook

Sheet Item codes
A1: S.NO | B1: ITEM CODE | C1: ITEM DESC
A2: 1 | B2: RTHTMTBNET72X33X06 | C2: Peps Restonic Hotel Motel Bonnell Euro Top 72X33X06 | Q2: RTHTMTPKET72X30X06 | R2: Peps Restonic Hotel Motel Pocketed Euro Top 72X30X06 | S2: RTHTMTPKET72X30X08 | T2: Peps Restonic Hotel Motel Pocketed Euro Top 72X30X08 | U2: RTHTMTPKET72X30X10 | V2: Peps Restonic Hotel Motel Pocketed Euro Top 72X30X10 | W2: RTHTMTPKMFET72X30X06 | X2: Peps Restonic Hotel Motel Pocketed Memory Foam Euro Top 72X30X06 | Y2: RTHTMTPKMFET72X30X08 | Z2: Peps Restonic Hotel Motel Pocketed Memory Foam Euro Top 72X30X08 | AA2: RTHTMTPKMFET72X30X10 | AB2: Peps Restonic Hotel Motel Pocketed Memory Foam Euro Top 72X30X10 | AC2: RTHTMTPKMFRG72X30X06 | AD2: Peps Restonic Hotel Motel Pocketed Memory Foam Regular 72X30X06 | AE2: RTHTMTPKMFRG72X30X08 | AF2: Peps Restonic Hotel Motel Pocketed Memory Foam Regular 72X30X08 | AG2: RTHTMTPKMFRG72X30X10 | AH2: Peps Restonic Hotel Motel Pocketed Memory Foam Regular 72X30X10 | AI2: RTHTMTPKMFRG72X30X12 | AJ2: Peps Restonic Hotel Motel Pocketed Memory Foam Regular 72X30X12 | AK2: RTHTMTPKPT72X30X06 | AL2: Peps Restonic Hotel Motel Pocketed Pillow Top 72X30X06 | AM2: RTHTMTPKPT72X30X08 | AN2: Peps Restonic Hotel Motel Pocketed Pillow Top 72X30X08 | AO2: RTHTMTPKPT72X30X10 | AP2: Peps Restonic Hotel Motel Pocketed Pillow Top 72X30X10 | AQ2: RTHTMTPKRG72X30X06 | AR2: Peps Restonic Hotel Motel Pocketed Regular 72X30X06 | AS2: RTHTMTPKRG72X30X08 | AT2: Peps Restonic Hotel Motel Pocketed Regular 72X30X08 | AU2: RTHTMTPKRG72X30X10 | AV2: Peps Restonic Hotel Motel Pocketed Regular 72X30X10 | AW2: RTHTMTPKRG72X30X12 | AX2: Peps Restonic Hotel Motel Pocketed Regular 72X30X12
A3: 2 | B3: RTHTMTBNET72X39X06 | C3: Peps Restonic Hotel Motel Bonnell Euro Top 72X39X06
A4: 3 | B4: RTHTMTBNET72X45X06 | C4: Peps Restonic Hotel Motel Bonnell Euro Top 72X45X06
A5: 4 | B5: RTHTMTBNET72X51X06 | C5: Peps Restonic Hotel Motel Bonnell Euro Top 72X51X06
A6: 5 | B6: RTHTMTBNET72X54X06 | C6: Peps Restonic Hotel Motel Bonnell Euro Top 72X54X06
A7: 6 | B7: RTHTMTBNET72X57X06 | C7: Peps Restonic Hotel Motel Bonnell Euro Top 72X57X06
A8: 7 | B8: RTHTMTBNET72X63X06 | C8: Peps Restonic Hotel Motel Bonnell Euro Top 72X63X06
A9: 8 | B9: RTHTMTBNET72X69X06 | C9: Peps Restonic Hotel Motel Bonnell Euro Top 72X69X06
A10: 9 | B10: RTHTMTBNET75X33X06 | C10: Peps Restonic Hotel Motel Bonnell Euro Top 75X33X06
A11: 10 | B11: RTHTMTBNET75X39X06 | C11: Peps Restonic Hotel Motel Bonnell Euro Top 75X39X06
A12: 11 | B12: RTHTMTBNET75X45X06 | C12: Peps Restonic Hotel Motel Bonnell Euro Top 75X45X06
A13: 12 | B13: RTHTMTBNET75X51X06 | C13: Peps Restonic Hotel Motel Bonnell Euro Top 75X51X06
A14: 13 | B14: RTHTMTBNET75X54X06 | C14: Peps Restonic Hotel Motel Bonnell Euro Top 75X54X06
... A1361: 1360 | B1361: RTHTMTPKRG84X69X12 | C1361: Peps Restonic Hotel Motel Pocketed Regular 84X69X12

Sheet Workings
A1: S.no | B1: R.no | C1: Date | D1: Bom Code/PS.No | E1: PS Desc. | F1: Item | G1: PS Desc. | H1: PS Usage | I1: PS Category | J1: Process Plan | K1: Uom | L1: Qty | M1: Default For | N1: Wh Code | O1: PS Seq | P1: I/O Flag | Q1: Issue Item | R1: Item Desc | S1: Uom | T1: Qty | U1: Std Wh Code | V1: Backflush | W1: Status | X1: CC | Y1: LENGTH | Z1: WIDTH | AA1: HE | AB1: Length | AC1: width | AD1: condition | AF1: Conv | AG1: rate | AH1: sub.tot | AI1: tot | AJ1: round | AK1: rm-rate | AL1: PRO-RATE | AM1: Wastage | AN1: DL | AO1: MOH | AP1: Dep | AQ1: Standard Cost | AR1: R-UP | AS1: RM-COST | AT1: PRO-RATE
A2: 1 | B2: 1 | C2: 28.03.2024 | D2: SFG-FRBNRG-BOR-78X60X10 | E2: Restonic Hotel Motel Bonnell Regular Border 78X60X10 | F2: =D2 -> SFG-FRBNRG-BOR-78X60X10 | G2: =E2 -> Restonic Hotel Motel Bonnell Regular Border 78X60X10 | H2: Standard | I2: Production | J2: TAIL-BORDER | K2: NOS | L2: 1 | M2: MRP&Rollup | N2: CBESFG | O2: 10 | P2: I | Q2: RM-THRD-QS-TKT40 | R2: THREAD TKT40 210D/3 PLY 10000MTS | S2: MTR | T2: 5.6 | U2: CBEWIP | V2: Backflush | W2: Active | X2: =RIGHT(D2,8) -> 78X60X10 | Y2: =LEFT(X2,2) -> 78 | Z2: =MID(X2,4,2) -> 60 | AA2: =RIGHT(X2,2) -> 10 | AB2: =Y2 -> 78 | AC2: =Z2 -> 60 | AF2: =T2/10000 -> 0.00056 | AG2: =VLOOKUP(Q2,'Rm-feb-24'!B:P,15,0) -> 231.1423 | AH2: =AF2*AG2 -> 0.12943969 | AI2: =SUM(AH2:AH9) -> 188.80969 | AJ2: =ROUND(AI2,3) -> 188.81 | AK2: =AJ2 -> 188.81 | AL2: =+AK2+AQ2 -> 212.17505 | AM2: =+SUM(((AK2*3%*18%))) -> 1.019574 | AN2: =+SUM(((AK2*14.33%*53%))) -> 14.339931 | AO2: =+SUM(((AK2*5.92%*53%))) -> 5.9241026 | AP2: =+SUM(((AK2*2.08%*53%))) -> 2.0814414 | AQ2: =SUM(AM2:AP2) -> 23.365049 | AR2: =ROUNDUP(AL2,0) -> 213 | AS2: =AK2 -> 188.81 | AT2: =AR2 -> 213
A3: 2 | B3: =B2 -> 1 | C3: =C2 -> 28.03.2024 | D3: =D2 -> SFG-FRBNRG-BOR-78X60X10 | E3: =E2 -> Restonic Hotel Motel Bonnell Regular Border 78X60X10 | F3: =F2 -> SFG-FRBNRG-BOR-78X60X10 | G3: =G2 -> Restonic Hotel Motel Bonnell Regular Border 78X60X10 | H3: Standard | I3: Production | J3: TAIL-BORDER | K3: NOS | L3: 1 | M3: MRP&Rollup | N3: CBESFG | O3: 20 | P3: I | Q3: HW-CTON-THREAD | R3: COTTON THREAD WHITE 3PLY | S3: MTR | T3: 5 | U3: CBEWIP | V3: Backflush | W3: Active | X3: =RIGHT(D3,8) -> 78X60X10 | Y3: =LEFT(X3,2) -> 78 | Z3: =MID(X3,4,2) -> 60 | AA3: =RIGHT(X3,2) -> 10 | AB3: =AB2 -> 78 | AC3: =AC2 -> 60 | AF3: =T3/5000 -> 0.001 | AG3: =VLOOKUP(Q3,'Rm-feb-24'!B:P,15,0) -> 58 | AH3: =AF3*AG3 -> 0.058 | AS3: =AS2 -> 188.81 | AT3: =AT2 -> 213
A4: 3 | B4: =B3 -> 1 | C4: =C3 -> 28.03.2024 | D4: =D3 -> SFG-FRBNRG-BOR-78X60X10 | E4: =E3 -> Restonic Hotel Motel Bonnell Regular Border 78X60X10 | F4: =F3 -> SFG-FRBNRG-BOR-78X60X10 | G4: =G3 -> Restonic Hotel Motel Bonnell Regular Border 78X60X10 | H4: Standard | I4: Production | J4: TAIL-BORDER | K4: NOS | L4: 1 | M4: MRP&Rollup | N4: CBESFG | O4: 30 | P4: I | Q4: SFG-RTHTMT-BNPK-BOR-29CM | R4: Hotel Motel Poc 8MM/16D Pre Foam Border 29 CM Height | S4: MTR | T4: =AD4 -> 7.087 | U4: CBESFG | V4: Backflush | W4: Active | X4: =RIGHT(D4,8) -> 78X60X10 | Y4: =LEFT(X4,2) -> 78 | Z4: =MID(X4,4,2) -> 60 | AA4: =RIGHT(X4,2) -> 10 | AB4: =AB3 -> 78 | AC4: =AC3 -> 60 | AD4: =ROUNDUP(((((AB4+AC4)*2)+3)*0.0254),3) -> 7.087 | AF4: =T4 -> 7.087 | AG4: =VLOOKUP(Q4,'SFG-RM'!A:B,2,0) -> 22.495284 | AH4: =AF4*AG4 -> 159.42408 | AS4: =AS3 -> 188.81 | AT4: =AT3 -> 213
A5: 4 | B5: =B4 -> 1 | C5: =C4 -> 28.03.2024 | D5: =D4 -> SFG-FRBNRG-BOR-78X60X10 | E5: =E4 -> Restonic Hotel Motel Bonnell Regular Border 78X60X10 | F5: =F4 -> SFG-FRBNRG-BOR-78X60X10 | G5: =G4 -> Restonic Hotel Motel Bonnell Regular Border 78X60X10 | H5: Standard | I5: Production | J5: TAIL-BORDER | K5: NOS | L5: 1 | M5: MRP&Rollup | N5: CBESFG | O5: 40 | P5: I | Q5: RMI-HCC-SDE-LBL | R5: HOTEL COMFORT CARE SIDE LABEL (IMPORT) | S5: NOS | T5: 1 | U5: CBEWIP | V5: Backflush | W5: Active | X5: =RIGHT(D5,8) -> 78X60X10 | Y5: =LEFT(X5,2) -> 78 | Z5: =MID(X5,4,2) -> 60 | AA5: =RIGHT(X5,2) -> 10 | AB5: =AB4 -> 78 | AC5: =AC4 -> 60 | AD5: =ROUNDUP(((((72+30)*2)+3)*0.0254),3) -> 5.258 | AF5: =T5 -> 1 | AG5: =VLOOKUP(Q5,'Rm-feb-24'!B:P,15,0) -> 5.9957 | AH5: =AF5*AG5 -> 5.9957 | AS5: =AS4 -> 188.81 | AT5: =AT4 -> 213
A6: 5 | B6: =B5 -> 1 | C6: =C5 -> 28.03.2024 | D6: =D5 -> SFG-FRBNRG-BOR-78X60X10 | E6: =E5 -> Restonic Hotel Motel Bonnell Regular Border 78X60X10 | F6: =F5 -> SFG-FRBNRG-BOR-78X60X10 | G6: =G5 -> Restonic Hotel Motel Bonnell Regular Border 78X60X10 | H6: Standard | I6: Production | J6: TAIL-BORDER | K6: NOS | L6: 1 | M6: MRP&Rollup | N6: CBESFG | O6: 50 | P6: I | Q6: RML-MRP-BACK-LBL | R6: MRP BACK LABEL(PLAIN) | S6: NOS | T6: 1 | U6: CBEWIP | V6: Backflush | W6: Active | X6: =RIGHT(D6,8) -> 78X60X10 | Y6: =LEFT(X6,2) -> 78 | Z6: =MID(X6,4,2) -> 60 | AA6: =RIGHT(X6,2) -> 10 | AB6: =AB5 -> 78 | AC6: =AC5 -> 60 | AF6: =T6 -> 1 | AG6: =VLOOKUP(Q6,'Rm-feb-24'!B:P,15,0) -> 1.3275 | AH6: =AF6*AG6 -> 1.3275 | AS6: =AS5 -> 188.81 | AT6: =AT5 -> 213
A7: 6 | B7: =B6 -> 1 | C7: =C6 -> 28.03.2024 | D7: =D6 -> SFG-FRBNRG-BOR-78X60X10 | E7: =E6 -> Restonic Hotel Motel Bonnell Regular Border 78X60X10 | F7: =F6 -> SFG-FRBNRG-BOR-78X60X10 | G7: =G6 -> Restonic Hotel Motel Bonnell Regular Border 78X60X10 | H7: Standard | I7: Production | J7: TAIL-BORDER | K7: NOS | L7: 1 | M7: MRP&Rollup | N7: CBESFG | O7: 60 | P7: I | Q7: RML-DRN-LBL | R7: DIRECTION LABEL | S7: NOS | T7: 1 | U7: CBEWIP | V7: Backflush | W7: Active | X7: =RIGHT(D7,8) -> 78X60X10 | Y7: =LEFT(X7,2) -> 78 | Z7: =MID(X7,4,2) -> 60 | AA7: =RIGHT(X7,2) -> 10 | AB7: =AB6 -> 78 | AC7: =AC6 -> 60 | AF7: =T7 -> 1 | AG7: =VLOOKUP(Q7,'Rm-feb-24'!B:P,15,0) -> 1.7318 | AH7: =AF7*AG7 -> 1.7318 | AS7: =AS6 -> 188.81 | AT7: =AT6 -> 213
A8: 7 | B8: =B7 -> 1 | C8: =C7 -> 28.03.2024 | D8: =D7 -> SFG-FRBNRG-BOR-78X60X10 | E8: =E7 -> Restonic Hotel Motel Bonnell Regular Border 78X60X10 | F8: =F7 -> SFG-FRBNRG-BOR-78X60X10 | G8: =G7 -> Restonic Hotel Motel Bonnell Regular Border 78X60X10 | H8: Standard | I8: Production | J8: TAIL-BORDER | K8: NOS | L8: 1 | M8: MRP&Rollup | N8: CBESFG | O8: 70 | P8: I | Q8: SFG-RTHTMT-HANDLE | R8: Restonic Hotel Motel Handle | S8: MTR | T8: 1.16 | U8: CBESFG | V8: Backflush | W8: Active | X8: =RIGHT(D8,8) -> 78X60X10 | Y8: =LEFT(X8,2) -> 78 | Z8: =MID(X8,4,2) -> 60 | AA8: =RIGHT(X8,2) -> 10 | AB8: =AB7 -> 78 | AC8: =AC7 -> 60 | AF8: =T8 -> 1.16 | AG8: =VLOOKUP(Q8,'SFG-RM'!A:B,2,0) -> 9.3094553 | AH8: =AF8*AG8 -> 10.798968 | AS8: =AS7 -> 188.81 | AT8: =AT7 -> 213
A9: 8 | B9: =B8 -> 1 | C9: =C8 -> 28.03.2024 | D9: =D8 -> SFG-FRBNRG-BOR-78X60X10 | E9: =E8 -> Restonic Hotel Motel Bonnell Regular Border 78X60X10 | F9: =F8 -> SFG-FRBNRG-BOR-78X60X10 | G9: =G8 -> Restonic Hotel Motel Bonnell Regular Border 78X60X10 | H9: Standard | I9: Production | J9: TAIL-BORDER | K9: NOS | L9: 1 | M9: MRP&Rollup | N9: CBESFG | O9: 80 | P9: I | Q9: RMI-BREATHER-GOLD | R9: BREATHER SET GOLD ROUND | S9: SET | T9: 2 | U9: CBEWIP | V9: Backflush | W9: Active | X9: =RIGHT(D9,8) -> 78X60X10 | Y9: =LEFT(X9,2) -> 78 | Z9: =MID(X9,4,2) -> 60 | AA9: =RIGHT(X9,2) -> 10 | AB9: =AB8 -> 78 | AC9: =AC8 -> 60 | AF9: =T9 -> 2 | AG9: =VLOOKUP(Q9,'Rm-feb-24'!B:P,15,0) -> 4.6721 | AH9: =AF9*AG9 -> 9.3442 | AS9: =AS8 -> 188.81 | AT9: =AT8 -> 213

Sheet SFG-RM
A1: Row Labels | B1: Sum of Feb-24-Total
A2: BNAS-106X72X130 | B2: 1650.0082
A3: BNAS-13X13X100 | B3: 27.727734
A4: BNAS-13X13X130 | B4: 32.182134
A5: BNAS-13X13X150 | B5: 36.559734
A6: BNAS-13X13X90 | B6: 27.113334
A7: BNAS-18X18X100 | B7: 47.467619
A8: BNAS-18X18X130 | B8: 54.891619
A9: BNAS-20X18X100 | B9: 55.968766
A10: BNAS-20X18X130 | B10: 64.877566
A11: BNAS-20X18X150 | B11: 73.632766
A12: BNAS-20X18X90 | B12: 54.739966
A13: BNAS-24X60X130 | B13: 273.74261
... A29219: Grand Total | B29219: 18179053

Sheet Rm-feb-24
A1: SI.No | B1: Item Code | C1: Item Desc | D1: UOM | E1: Warehouse | F1: Opening Stock Qty | G1: Opening Stock Rate | H1: Opening Stock Value | I1: Stock In Qty | J1: Stock In Rate | K1: Stock In Value | L1: Stock Out Qty | M1: Stock Out Rate | N1: Stock Out Value | O1: Closing Stock Qty | P1: Closing Stock Rate | Q1: Closing Stock Value | R1: Item Account Group | S1: Item Account Group Desc | T1: Item Category
A2: 33 | B2: RML-CS-RTC-PLUSH-7.5 | C2: CORNER SHOES RESTONIC PLUSH - 7.5" | D2: NOS | E2: CBERM | F2: 900 | G2: 10.2033 | H2: 9182.97 | I2: 600 | J2: 10 | K2: 6000 | L2: 300 | M2: 10.1452 | N2: 3043.57 | O2: 1200 | P2: 10.1162 | Q2: 12139.4 | R2: LCE | S2: Label,CnrShoe,CentreBand,EdgeTape-10195 | T2: MATRESS
A3: 35 | B3: RML-CS-RTC-PLUSH-9.5 | C3: CORNER SHOES RESTONIC PLUSH - 9.5" | D3: NOS | E3: CBERM | F3: 1000 | G3: 10.3332 | H3: 10333.16 | I3: 500 | J3: 12.3 | K3: 6150 | L3: 200 | M3: 10.9888 | N3: 2197.76 | O3: 1300 | P3: 10.9888 | Q3: 14285.4 | R3: LCE | S3: Label,CnrShoe,CentreBand,EdgeTape-10195 | T3: MATRESS
A4: 37 | B4: RML-CS-SPG-6.5" | C4: CORNER SHOES. SPINE GUARD - 6.5" | D4: NOS | E4: CBERM | F4: 1200 | G4: 10.7018 | H4: 12842.19 | I4: 0 | K4: 0 | L4: 200 | M4: 10.7018 | N4: 2140.36 | O4: 1000 | P4: 10.7018 | Q4: 10701.83 | R4: LCE | S4: Label,CnrShoe,CentreBand,EdgeTape-10195 | T4: MATRESS
A5: 42 | B5: RML-CS-SPG-7.5" | C5: CORNER SHOES. SPINE GUARD - 7.5" | D5: NOS | E5: CBERM | F5: 1300 | G5: 10 | H5: 13000 | I5: 4800 | J5: 10 | K5: 48000 | L5: 3300 | M5: 10 | N5: 33000 | O5: 2800 | P5: 10 | Q5: 28000 | R5: LCE | S5: Label,CnrShoe,CentreBand,EdgeTape-10195 | T5: MATRESS
A6: 48 | B6: RML-CS-SPG-9.5" | C6: CORNER SHOES. SPINE GUARD - 9.5" | D6: NOS | E6: CBERM | F6: 1100 | G6: 10.48 | H6: 11528 | I6: 1000 | J6: 10.48 | K6: 10480 | L6: 1600 | M6: 10.48 | N6: 16768 | O6: 500 | P6: 10.48 | Q6: 5240 | R6: LCE | S6: Label,CnrShoe,CentreBand,EdgeTape-10195 | T6: MATRESS
A7: 56 | B7: RML-CS-SPK-10.5" | C7: CORNER SHOES. SPK - 10.5" | D7: NOS | E7: CBERM | F7: 1389 | G7: 9.7779 | H7: 13581.54 | I7: 0 | K7: 0 | L7: 0 | N7: 0 | O7: 1389 | P7: 9.7779 | Q7: 13581.54 | R7: LCE | S7: Label,CnrShoe,CentreBand,EdgeTape-10195 | T7: MATRESS
A8: 59 | B8: RML-CS-SPK-8.5" | C8: CORNER SHOES. SPK - 8.5" | D8: NOS | E8: CBERM | F8: 1000 | G8: 10.3146 | H8: 10314.55 | I8: 0 | K8: 0 | L8: 0 | N8: 0 | O8: 1000 | P8: 10.3146 | Q8: 10314.55 | R8: LCE | S8: Label,CnrShoe,CentreBand,EdgeTape-10195 | T8: MATRESS
A9: 63 | B9: RML-CS-SPK-BG-10.5 | C9: CORNER SHOES SPRINGKOIL BEIGE -10.5" | D9: NOS | E9: CBERM | F9: 400 | G9: 12.5 | H9: 5000 | I9: 0 | K9: 0 | L9: 0 | N9: 0 | O9: 400 | P9: 12.5 | Q9: 5000 | R9: LCE | S9: Label,CnrShoe,CentreBand,EdgeTape-10195 | T9: MATRESS
A10: 66 | B10: RML-CS-SPK-BG-7 | C10: CORNER SHOES SPRINGKOIL BEIGE -7" | D10: NOS | E10: CBERM | F10: 6500 | G10: 10 | H10: 65000 | I10: 0 | K10: 0 | L10: 400 | M10: 10 | N10: 4000 | O10: 6100 | P10: 10 | Q10: 61000 | R10: LCE | S10: Label,CnrShoe,CentreBand,EdgeTape-10195 | T10: MATRESS
A11: 67 | B11: RML-CS-SPK-BG-8.5 | C11: CORNER SHOES SPRINGKOIL BEIGE -8.5" | D11: NOS | E11: CBERM | F11: 3300 | G11: 10 | H11: 33000 | I11: 0 | K11: 0 | L11: 0 | N11: 0 | O11: 3300 | P11: 10 | Q11: 33000 | R11: LCE | S11: Label,CnrShoe,CentreBand,EdgeTape-10195 | T11: MATRESS
A12: 69 | B12: RML-CS-SPK-BL-10.5 | C12: CORNER SHOES SPRINGKOIL BLUE -10.5" | D12: NOS | E12: CBERM | F12: 500 | G12: 11.5625 | H12: 5781.25 | I12: 0 | K12: 0 | L12: 0 | N12: 0 | O12: 500 | P12: 11.5625 | Q12: 5781.25 | R12: LCE | S12: Label,CnrShoe,CentreBand,EdgeTape-10195 | T12: MATRESS
A13: 71 | B13: RML-CS-SPK-BL-6 | C13: CORNER SHOES SPRINGKOIL BLUE -6" | D13: NOS | E13: CBERM | F13: 2900 | G13: 10 | H13: 29000 | I13: 0 | K13: 0 | L13: 200 | M13: 10 | N13: 2000 | O13: 2700 | P13: 10 | Q13: 27000 | R13: LCE | S13: Label,CnrShoe,CentreBand,EdgeTape-10195 | T13: MATRESS
A14: 73 | B14: RML-CS-SPK-BL-7 | C14: CORNER SHOES SPRINGKOIL BLUE -7" | D14: NOS | E14: CBERM | F14: 21800 | G14: 8.6732 | H14: 189076.19 | I14: 50 | J14: 8.6732 | K14: 433.66 | L14: 6600 | M14: 8.6732 | N14: 57243.12 | O14: 15250 | P14: 8.6732 | Q14: 132266.73 | R14: LCE | S14: Label,CnrShoe,CentreBand,EdgeTape-10195 | T14: MATRESS
A15: 75 | B15: RML-CS-SPK-BL-7.5 | C15: CORNER SHOES SPRINGKOIL BLUE -7.5" | D15: NOS | E15: CBERM | F15: 1065 | G15: 10 | H15: 10650 | I15: 0 | K15: 0 | L15: 0 | N15: 0 | O15: 1065 | P15: 10 | Q15: 10650 | R15: LCE | S15: Label,CnrShoe,CentreBand,EdgeTape-10195 | T15: MATRESS
A16: 77 | B16: RML-CS-SPK-BL-8.5 | C16: CORNER SHOES SPRINGKOIL BLUE -8.5" | D16: NOS | E16: CBERM | F16: 4000 | G16: 10.2861 | H16: 41144.42 | I16: 100 | J16: 10.2861 | K16: 1028.61 | L16: 300 | M16: 10.2861 | N16: 3085.83 | O16: 3800 | P16: 10.2861 | Q16: 39087.2 | R16: LCE | S16: Label,CnrShoe,CentreBand,EdgeTape-10195 | T16: MATRESS
A17: 78 | B17: RML-CS-SPK-BW-10.5 | C17: CORNER SHOES SPRINGKOIL BROWN -10.5" | D17: NOS | E17: CBERM | F17: 800 | G17: 11.5625 | H17: 9250 | I17: 0 | K17: 0 | L17: 0 | N17: 0 | O17: 800 | P17: 11.5625 | Q17: 9250 | R17: LCE | S17: Label,CnrShoe,CentreBand,EdgeTape-10195 | T17: MATRESS
A18: 81 | B18: RML-CS-SPK-BW-6 | C18: CORNER SHOES SPRINGKOIL BROWN -6" | D18: NOS | E18: CBERM | F18: 500 | G18: 10 | H18: 5000 | I18: 0 | K18: 0 | L18: 100 | M18: 10 | N18: 1000 | O18: 400 | P18: 10 | Q18: 4000 | R18: LCE | S18: Label,CnrShoe,CentreBand,EdgeTape-10195 | T18: MATRESS
A19: 82 | B19: RML-CS-SPK-BW-7 | C19: CORNER SHOES SPRINGKOIL BROWN -7" | D19: NOS | E19: CBERM | F19: 4400 | G19: 10 | H19: 44000 | I19: 1000 | J19: 10 | K19: 10000 | L19: 2700 | M19: 10 | N19: 27000 | O19: 2700 | P19: 10 | Q19: 27000 | R19: LCE | S19: Label,CnrShoe,CentreBand,EdgeTape-10195 | T19: MATRESS
A20: 84 | B20: RML-CS-SPK-BW-7.5 | C20: CORNER SHOES SPRINGKOIL BROWN -7.5" | D20: NOS | E20: CBERM | F20: 555 | G20: 10 | H20: 5550 | I20: 0 | K20: 0 | L20: 0 | N20: 0 | O20: 555 | P20: 10 | Q20: 5550 | R20: LCE | S20: Label,CnrShoe,CentreBand,EdgeTape-10195 | T20: MATRESS
A21: 85 | B21: RML-CS-SPK-BW-8.5 | C21: CORNER SHOES SPRINGKOIL BROWN -8.5" | D21: NOS | E21: CBERM | F21: 3348 | G21: 10 | H21: 33480 | I21: 0 | K21: 0 | L21: 0 | N21: 0 | O21: 3348 | P21: 10 | Q21: 33480 | R21: LCE | S21: Label,CnrShoe,CentreBand,EdgeTape-10195 | T21: MATRESS
A22: 87 | B22: RML-CS-SPK-CR-10.5 | C22: CORNER SHOES SPRINGKOIL CREAM -10.5" | D22: NOS | E22: CBERM | F22: 800 | G22: 11.3889 | H22: 9111.11 | I22: 0 | K22: 0 | L22: 0 | N22: 0 | O22: 800 | P22: 11.3889 | Q22: 9111.11 | R22: LCE | S22: Label,CnrShoe,CentreBand,EdgeTape-10195 | T22: MATRESS
A23: 89 | B23: RML-CS-SPK-CR-6 | C23: CORNER SHOES SPRINGKOIL CREAM -6" | D23: NOS | E23: CBERM | F23: 400 | G23: 10 | H23: 4000 | I23: 0 | K23: 0 | L23: 100 | M23: 10 | N23: 1000 | O23: 300 | P23: 10 | Q23: 3000 | R23: LCE | S23: Label,CnrShoe,CentreBand,EdgeTape-10195 | T23: MATRESS
A24: 92 | B24: RML-CS-SPK-CR-7 | C24: CORNER SHOES SPRINGKOIL CREAM -7" | D24: NOS | E24: CBERM | F24: 4600 | G24: 10 | H24: 46000 | I24: 0 | K24: 0 | L24: 500 | M24: 10 | N24: 5000 | O24: 4100 | P24: 10 | Q24: 41000 | R24: LCE | S24: Label,CnrShoe,CentreBand,EdgeTape-10195 | T24: MATRESS
A25: 93 | B25: RML-CS-SPK-CR-7.5 | C25: CORNER SHOES SPRINGKOIL CREAM -7.5" | D25: NOS | E25: CBERM | F25: 280 | G25: 10 | H25: 2800 | I25: 0 | K25: 0 | L25: 0 | N25: 0 | O25: 280 | P25: 10 | Q25: 2800 | R25: LCE | S25: Label,CnrShoe,CentreBand,EdgeTape-10195 | T25: MATRESS
A26: 94 | B26: RML-CS-SPK-CR-8.5 | C26: CORNER SHOES SPRINGKOIL CREAM -8.5" | D26: NOS | E26: CBERM | F26: 2900 | G26: 10 | H26: 29000 | I26: 0 | K26: 0 | L26: 0 | N26: 0 | O26: 2900 | P26: 10 | Q26: 29000 | R26: LCE | S26: Label,CnrShoe,CentreBand,EdgeTape-10195 | T26: MATRESS
A27: 97 | B27: RML-CS-SPK-CT-6 | C27: PEPS SPRINGKOIL CROWN TOP CORNER SHOES 6" | D27: NOS | E27: CBERM | F27: 2000 | G27: 8.65 | H27: 17300 | I27: 14000 | J27: 8.65 | K27: 121100 | L27: 2400 | M27: 8.65 | N27: 20760 | O27: 13600 | P27: 8.65 | Q27: 117640 | R27: LCE | S27: Label,CnrShoe,CentreBand,EdgeTape-10195 | T27: MATRESS
A28: 102 | B28: RML-CS-SPK-CT-7.5 | C28: PEPS SPRINGKOIL CROWN TOP CORNER SHOES 7.5" | D28: NOS | E28: CBERM | F28: 1400 | G28: 9.9 | H28: 13860 | I28: 0 | K28: 0 | L28: 200 | M28: 9.9 | N28: 1980 | O28: 1200 | P28: 9.9 | Q28: 11880 | R28: LCE | S28: Label,CnrShoe,CentreBand,EdgeTape-10195 | T28: MATRESS
A29: 108 | B29: RML-CS-SPK-CT-9.25 | C29: PEPS SPRINGKOIL CROWN TOP CORNER SHOES 9.25" | D29: NOS | E29: CBERM | F29: 850 | G29: 15.3 | H29: 13005 | I29: 0 | K29: 0 | L29: 100 | M29: 15.3 | N29: 1530 | O29: 750 | P29: 15.3 | Q29: 11475 | R29: LCE | S29: Label,CnrShoe,CentreBand,EdgeTape-10195 | T29: MATRESS
A30: 110 | B30: RML-CS-SPK-GR-10.5 | C30: CORNER SHOES SPRINGKOIL GREY -10.5" | D30: NOS | E30: CBERM | F30: 400 | G30: 12.5 | H30: 5000 | I30: 0 | K30: 0 | L30: 0 | N30: 0 | O30: 400 | P30: 12.5 | Q30: 5000 | R30: LCE | S30: Label,CnrShoe,CentreBand,EdgeTape-10195 | T30: MATRESS
A31: 113 | B31: RML-CS-SPK-GR-7 | C31: CORNER SHOES SPRINGKOIL GREY -7" | D31: NOS | E31: CBERM | F31: 6600 | G31: 10 | H31: 66000 | I31: 0 | K31: 0 | L31: 1700 | M31: 10 | N31: 17000 | O31: 4900 | P31: 10 | Q31: 49000 | R31: LCE | S31: Label,CnrShoe,CentreBand,EdgeTape-10195 | T31: MATRESS
A32: 115 | B32: RML-CS-SPK-GR-8.5 | C32: CORNER SHOES SPRINGKOIL GREY -8.5" | D32: NOS | E32: CBERM | F32: 4400 | G32: 10 | H32: 44000 | I32: 0 | K32: 0 | L32: 100 | M32: 10 | N32: 1000 | O32: 4300 | P32: 10 | Q32: 43000 | R32: LCE | S32: Label,CnrShoe,CentreBand,EdgeTape-10195 | T32: MATRESS
A33: 116 | B33: RML-CS-SPK-MR-10.5 | C33: CORNER SHOES SPRINGKOIL MAROON -10.5" | D33: NOS | E33: CBERM | F33: 1100 | G33: 11.5385 | H33: 12692.3 | I33: 0 | K33: 0 | L33: 200 | M33: 11.5385 | N33: 2307.7 | O33: 900 | P33: 11.5384 | Q33: 10384.6 | R33: LCE | S33: Label,CnrShoe,CentreBand,EdgeTape-10195 | T33: MATRESS
A34: 118 | B34: RML-CS-SPK-MR-6 | C34: CORNER SHOES SPRINGKOIL MAROON -6" | D34: NOS | E34: CBERM | F34: 4100 | G34: 10 | H34: 41000 | I34: 0 | K34: 0 | L34: 300 | M34: 10 | N34: 3000 | O34: 3800 | P34: 10 | Q34: 38000 | R34: LCE | S34: Label,CnrShoe,CentreBand,EdgeTape-10195 | T34: MATRESS
A35: 120 | B35: RML-CS-SPK-MR-7 | C35: CORNER SHOES SPRINGKOIL MAROON -7" | D35: NOS | E35: CBERM | F35: 16500 | G35: 8.6704 | H35: 143061.16 | I35: 0 | K35: 0 | L35: 7500 | M35: 8.6704 | N35: 65028 | O35: 9000 | P35: 8.6704 | Q35: 78033.16 | R35: LCE | S35: Label,CnrShoe,CentreBand,EdgeTape-10195 | T35: MATRESS
A36: 122 | B36: RML-CS-SPK-MR-7.5 | C36: CORNER SHOES SPRINGKOIL MAROON -7.5" | D36: NOS | E36: CBERM | F36: 1145 | G36: 10 | H36: 11450 | I36: 0 | K36: 0 | L36: 0 | N36: 0 | O36: 1145 | P36: 10 | Q36: 11450 | R36: LCE | S36: Label,CnrShoe,CentreBand,EdgeTape-10195 | T36: MATRESS
A37: 124 | B37: RML-CS-SPK-MR-8.5 | C37: CORNER SHOES SPRINGKOIL MAROON -8.5" | D37: NOS | E37: CBERM | F37: 3160 | G37: 10.3345 | H37: 32657.08 | I37: 600 | J37: 10.0477 | K37: 6028.62 | L37: 560 | M37: 10.3034 | N37: 5769.93 | O37: 3200 | P37: 10.2862 | Q37: 32915.77 | R37: LCE | S37: Label,CnrShoe,CentreBand,EdgeTape-10195 | T37: MATRESS
A38: 126 | B38: RML-CS-TRT-7 | C38: CORNER SHOES. TARTANIA-7" | D38: NOS | E38: CBERM | F38: 3500 | G38: 10.2299 | H38: 35804.78 | I38: 0 | K38: 0 | L38: 300 | M38: 10.2299 | N38: 3068.97 | O38: 3200 | P38: 10.2299 | Q38: 32735.81 | R38: LCE | S38: Label,CnrShoe,CentreBand,EdgeTape-10195 | T38: MATRESS
A39: 253 | B39: 100D-RB-FOAM-77X71X25MM | C39: 100D-Rebonded Foam Sheet-77X71X25mm | D39: KGS | E39: CBERM | F39: 0 | H39: 0 | I39: 865.5 | J39: 92 | K39: 79626 | L39: 865.5 | M39: 92 | N39: 79626 | O39: 0 | Q39: 0 | R39: FMREBOND | S39: FOAM REBONDED -10181 | T39: FOAM
A40: 627 | B40: SBLGPS | C40: Knurling Bush | D40: NOS | E40: CBERM | F40: 1220 | G40: 25 | H40: 30500 | I40: 80 | J40: 25 | K40: 2000 | L40: 900 | M40: 25 | N40: 22500 | O40: 400 | P40: 25 | Q40: 10000 | R40: LCE | S40: Label,CnrShoe,CentreBand,EdgeTape-10195 | T40: MATRESS
A41: 629 | B41: SCRAP-COIR-BLOCK | C41: Coir Block Waste Scrop | D41: KGS | E41: CBERM | F41: 0 | H41: 0 | I41: 80.3 | J41: 28 | K41: 2248.4 | L41: 80.3 | M41: 28 | N41: 2248.4 | O41: 0 | Q41: 0 | R41: SEMIQUILT | S41: SEMI FINISHED QUILT SECTION -10198 | T41: MATRESS
A42: 701 | B42: RML-FTD-SHT-75X60 | C42: PEPS FITTED SHEET 75X60 | D42: NOS | E42: CBERM | F42: 42 | G42: 627 | H42: 26334 | I42: 0 | K42: 0 | L42: 0 | N42: 0 | O42: 42 | P42: 627 | Q42: 26334 | R42: ALIPROD | S42: Allied Products-13015 | T42: MATRESS
A43: 709 | B43: RML-FTD-SHT-75X72 | C43: PEPS FITTED SHEET 75X72 | D43: NOS | E43: CBERM | F43: 20 | G43: 752 | H43: 15040 | I43: 0 | K43: 0 | L43: 0 | N43: 0 | O43: 20 | P43: 752 | Q43: 15040 | R43: ALIPROD | S43: Allied Products-13015 | T43: MATRESS
A44: 721 | B44: RML-FTD-SHT-78X60 | C44: PEPS FITTED SHEET 78X60 | D44: NOS | E44: CBERM | F44: 22 | G44: 652 | H44: 14344 | I44: 0 | K44: 0 | L44: 0 | N44: 0 | O44: 22 | P44: 652 | Q44: 14344 | R44: ALIPROD | S44: Allied Products-13015 | T44: MATRESS
A45: 743 | B45: RML-FTD-SHT-78X72 | C45: PEPS FITTED SHEET 78X72 | D45: NOS | E45: CBERM | F45: 21 | G45: 782 | H45: 16422 | I45: 0 | K45: 0 | L45: 0 | N45: 0 | O45: 21 | P45: 782 | Q45: 16422 | R45: ALIPROD | S45: Allied Products-13015 | T45: MATRESS
A46: 795 | B46: RML-HNDL-ALLURA-BLUE | C46: PEPS ALLURA BLUE HANDLE | D46: NOS | E46: CBERM | F46: 600 | G46: 5.5 | H46: 3300 | I46: 0 | K46: 0 | L46: 0 | N46: 0 | O46: 600 | P46: 5.5 | Q46: 3300 | R46: LCE | S46: Label,CnrShoe,CentreBand,EdgeTape-10195 | T46: MATRESS
A47: 796 | B47: RML-HNDL-ALLURA-OR | C47: PEPS ALLURA ORANGE HANDLE | D47: NOS | E47: CBERM | F47: 1465 | G47: 5.5 | H47: 8057.5 | I47: 0 | K47: 0 | L47: 0 | N47: 0 | O47: 1465 | P47: 5.5 | Q47: 8057.5 | R47: LCE | S47: Label,CnrShoe,CentreBand,EdgeTape-10195 | T47: MATRESS
A48: 801 | B48: RML-HNDL-ARD-BRN | C48: RESTONIC ARDENE BROWN HANDLE | D48: NOS | E48: CBERM | F48: 2150 | G48: 12.2002 | H48: 26230.46 | I48: 1875 | J48: 12.2 | K48: 22875 | L48: 350 | M48: 12.2001 | N48: 4270.05 | O48: 3675 | P48: 12.2001 | Q48: 44835.41 | R48: LCE | S48: Label,CnrShoe,CentreBand,EdgeTape-10195 | T48: MATRESS
A49: 805 | B49: RML-HNDL-ARD-GREY | C49: RESTONIC ARDENE GREY HANDLE | D49: NOS | E49: CBERM | F49: 700 | G49: 9.3642 | H49: 6554.91 | I49: 0 | K49: 0 | L49: 150 | M49: 9.3642 | N49: 1404.63 | O49: 550 | P49: 9.3641 | Q49: 5150.28 | R49: LCE | S49: Label,CnrShoe,CentreBand,EdgeTape-10195 | T49: MATRESS
A50: 810 | B50: RML-HNDL-CAR-BLUE | C50: RESTONIC CAROUSEL BLUE HANDLE | D50: NOS | E50: CBERM | F50: 13036 | G50: 6.115 | H50: 79714.67 | I50: 0 | K50: 0 | L50: 1100 | M50: 6.1149 | N50: 6726.39 | O50: 11936 | P50: 6.115 | Q50: 72988.28 | R50: LCE | S50: Label,CnrShoe,CentreBand,EdgeTape-10195 | T50: MATRESS
A51: 814 | B51: RML-HNDL-CAR-CRM | C51: RESTONIC CAROUSEL CREAM HANDLE | D51: NOS | E51: CBERM | F51: 2300 | G51: 6.25 | H51: 14375.05 | I51: 2500 | J51: 6.25 | K51: 15625 | L51: 1800 | M51: 6.25 | N51: 11250 | O51: 3000 | P51: 6.25 | Q51: 18750.05 | R51: LCE | S51: Label,CnrShoe,CentreBand,EdgeTape-10195 | T51: MATRESS
A52: 820 | B52: RML-HNDL-CAR-PL-CRM | C52: RESTONIC CAROUSEL PLUSH CREAM HANDLE | D52: NOS | E52: CBERM | F52: 1725 | G52: 6.7498 | H52: 11643.36 | I52: 500 | J52: 6.75 | K52: 3375 | L52: 675 | M52: 6.7498 | N52: 4556.12 | O52: 1550 | P52: 6.7498 | Q52: 10462.24 | R52: LCE | S52: Label,CnrShoe,CentreBand,EdgeTape-10195 | T52: MATRESS
A53: 882 | B53: RML-KOM-COM-MRP-LBL | C53: KOMFFY FEATHER SOFT COMFORTER MRP LABEL | D53: NOS | E53: CBERM | F53: 190 | G53: 2.9247 | H53: 555.7 | I53: 0 | K53: 0 | L53: 0 | N53: 0 | O53: 190 | P53: 2.9247 | Q53: 555.7 | R53: LCE | S53: Label,CnrShoe,CentreBand,EdgeTape-10195 | T53: MATRESS
A54: 883 | B54: RML-KOM-COM-PVC-CVR | C54: KOMFFY COMFORTER PVC COVER (12MIC PET+75MIC LDPE N ,750MMX490MM) | D54: NOS | E54: CBERM | F54: 4515 | G54: 18 | H54: 81270 | I54: 10408 | J54: 18 | K54: 187344 | L54: 500 | M54: 18 | N54: 9000 | O54: 14423 | P54: 18 | Q54: 259614 | R54: PML | S54: Packing Material-10195 | T54: MATRESS
A55: 884 | B55: RML-KOM-GRIP-INS | C55: KOMFFY GRIPSTER INSERTER | D55: NOS | E55: CBERM | F55: 1000 | G55: 19.1 | H55: 19100 | I55: 0 | K55: 0 | L55: 0 | N55: 0 | O55: 1000 | P55: 19.1 | Q55: 19100 | R55: LCE | S55: Label,CnrShoe,CentreBand,EdgeTape-10195 | T55: MATRESS
A56: 924 | B56: RML-KOM-PL-BED-SHT-105X120 | C56: KOMFFY PLUS BED SHEET SUPER KING- 105"X120" (RTC) | D56: NOS | E56: CBERM | F56: 5396 | G56: 429 | H56: 2314884 | I56: 0 | K56: 0 | L56: 192 | M56: 429 | N56: 82368 | O56: 5204 | P56: 429 | Q56: 2232516 | R56: SCHEME | S56: Scheme Materials-13015 | T56: MATRESS
A57: 992 | B57: RML-CUT-RES-GLS | C57: CUTTING RESISTANCE GLOVES | D57: PRS | E57: CBERM | F57: 26 | G57: 175 | H57: 4550 | I57: 25 | J57: 175 | K57: 4375 | L57: 25 | M57: 175 | N57: 4375 | O57: 26 | P57: 175 | Q57: 4550 | R57: PML | S57: Packing Material-10195 | T57: MATRESS
A58: 999 | B58: RML-DDR-SDE-LBL | C58: DOUBLE DECKER SIDE LABEL (RUBBER PATCH) | D58: NOS | E58: CBERM | F58: 1343 | G58: 115.9205 | H58: 155681.17 | I58: 0 | K58: 0 | L58: 2 | M58: 115.92 | N58: 231.84 | O58: 1341 | P58: 115.9205 | Q58: 155449.33 | R58: LCE | S58: Label,CnrShoe,CentreBand,EdgeTape-10195 | T58: MATRESS
A59: 1000 | B59: RML-DD-WCRD | C59: PEPS DOUBLE DECKER WARRANTY CARD | D59: NOS | E59: CBERM | F59: 1095 | G59: 13.8549 | H59: 15171.17 | I59: 5 | J59: 13.854 | K59: 69.27 | L59: 0 | N59: 0 | O59: 1100 | P59: 13.8549 | Q59: 15240.44 | R59: LCE | S59: Label,CnrShoe,CentreBand,EdgeTape-10195 | T59: MATRESS
A60: 1005 | B60: RM-LDPE-50"TUBE-PLAIN | C60: LDPE TUBE 58"X50.MIC | D60: KGS | E60: CBERM | F60: 519.4 | G60: 127.0259 | H60: 65977.26 | I60: 211.9 | J60: 130 | K60: 27547 | L60: 312.1 | M60: 127.4226 | N60: 39768.6 | O60: 419.2 | P60: 128.2339 | Q60: 53755.66 | R60: PML | S60: Packing Material-10195 | T60: MATRESS
A61: 1096 | B61: RML-FIT-SHT-INS-DOUBLE | C61: PEPS POLAR FLEECE BLANKET INSERTER- DOUBLE | D61: NOS | E61: CBERM | F61: 515 | G61: 17.9391 | H61: 9238.64 | I61: 0 | K61: 0 | L61: 13 | M61: 17.9392 | N61: 233.21 | O61: 502 | P61: 17.9391 | Q61: 9005.43 | R61: LCE | S61: Label,CnrShoe,CentreBand,EdgeTape-10195 | T61: FOAM
A62: 1098 | B62: RML-FIT-SHT-INS-SINGLE | C62: PEPS POLAR FLEECE BLANKET INSERTER- SINGLE | D62: NOS | E62: CBERM | F62: 286 | G62: 16.4821 | H62: 4713.88 | I62: 0 | K62: 0 | L62: 15 | M62: 16.482 | N62: 247.23 | O62: 271 | P62: 16.4821 | Q62: 4466.65 | R62: LCE | S62: Label,CnrShoe,CentreBand,EdgeTape-10195 | T62: FOAM
A63: 1099 | B63: RML-FIX-BRACKET | C63: BASE AND HB FIXING BRACKET | D63: SET | E63: CBERM | F63: 708 | G63: 76.5997 | H63: 54232.56 | I63: 0 | K63: 0 | L63: 60 | M63: 76.5997 | N63: 4595.98 | O63: 648 | P63: 76.5997 | Q63: 49636.58 | R63: BASHB | S63: Base and Head Board -10181 | T63: FOAM
A64: 1101 | B64: RML-FLN-BLNK-60X85 | C64: PEPS Flano Printed blanket Single- Size:60x85 Inch | D64: NOS | E64: CBERM | F64: 64 | G64: 255 | H64: 16320 | I64: 0 | K64: 0 | L64: 0 | N64: 0 | O64: 64 | P64: 255 | Q64: 16320 | R64: ALIPROD | S64: Allied Products-13015 | T64: MATRESS
A65: 1103 | B65: RML-FLN-BLNK-85X95 | C65: PEPS FLANO PRINTED BLANKET DOUBLE- SIZE:85X95 INCH | D65: NOS | E65: CBERM | F65: 58 | G65: 265 | H65: 15370 | I65: 0 | K65: 0 | L65: 0 | N65: 0 | O65: 58 | P65: 265 | Q65: 15370 | R65: ALIPROD | S65: Allied Products-13015 | T65: MATRESS
A66: 1107 | B66: RML-FLXI-NECK-PLW-CTN-ROPE | C66: FLEXI NECK PILLOW COTTON ROPE - 2.5MM | D66: KGS | E66: CBERM | F66: 16.98 | G66: 185 | H66: 3141.3 | I66: 0 | K66: 0 | L66: 5.92 | M66: 185 | N66: 1095.2 | O66: 11.06 | P66: 185 | Q66: 2046.1 | R66: LCE | S66: Label,CnrShoe,CentreBand,EdgeTape-10195 | T66: MATRESS
A67: 1109 | B67: RML-FLXI-NECK-PLW-MRP-LBL | C67: FLEXI NECK PILLOW MRP LABEL | D67: NOS | E67: CBERM | F67: 100 | G67: 11 | H67: 1100 | I67: 700 | J67: 11 | K67: 7700 | L67: 200 | M67: 11 | N67: 2200 | O67: 600 | P67: 11 | Q67: 6600 | R67: LCE | S67: Label,CnrShoe,CentreBand,EdgeTape-10195 | T67: MATRESS
A68: 1111 | B68: RML-FLXI-NECK-PLW-PVC-BAG | C68: FLEXI NECK PILLOW PVC BAG 11.25" Wx11.5" Hx4" G | D68: NOS | E68: CBERM | F68: 1325 | G68: 27 | H68: 35775 | I68: 575 | J68: 27 | K68: 15525 | L68: 50 | M68: 27 | N68: 1350 | O68: 1850 | P68: 27 | Q68: 49950 | R68: PML | S68: Packing Material-10195 | T68: MATRESS
A69: 1113 | B69: RML-FLXI-NECK-PLW-WSCR-LBL | C69: FLEXI NECK PILLOW WASH CARE LABEL | D69: NOS | E69: CBERM | F69: 500 | G69: 0.8 | H69: 400 | I69: 0 | K69: 0 | L69: 0 | N69: 0 | O69: 500 | P69: 0.8 | Q69: 400 | R69: LCE | S69: Label,CnrShoe,CentreBand,EdgeTape-10195 | T69: MATRESS
A70: 1115 | B70: RML-FLXI-SPN-LDPE-7X30+4FX75MIC | C70: FLEXI SPINE LDPE PLAIN SEAL KING BAG 7"X 30"+ 4"F X 75MIC | D70: NOS | E70: CBERM | F70: 1500 | G70: 2.4 | H70: 3600 | I70: 0 | K70: 0 | L70: 0 | N70: 0 | O70: 1500 | P70: 2.4 | Q70: 3600 | R70: PML | S70: Packing Material-10195 | T70: MATRESS
A71: 1116 | B71: RML-FLXI-SPN-PLW-BOX | C71: FLEXI SPINE PILLOW BOX 27"x5"x4" - 3 Ply | D71: NOS | E71: CBERM | F71: 600 | G71: 44 | H71: 26400 | I71: 500 | J71: 44 | K71: 22000 | L71: 75 | M71: 44 | N71: 3300 | O71: 1025 | P71: 44 | Q71: 45100 | R71: PML | S71: Packing Material-10195 | T71: MATRESS
A72: 1119 | B72: RML-FLXI-SPN-PLW-WSCR-LBL | C72: FLEXI SPINE PILLOW WASH CARE LABEL | D72: NOS | E72: CBERM | F72: 750 | G72: 0.8 | H72: 600 | I72: 0 | K72: 0 | L72: 0 | N72: 0 | O72: 750 | P72: 0.8 | Q72: 600 | R72: LCE | S72: Label,CnrShoe,CentreBand,EdgeTape-10195 | T72: MATRESS
A73: 1121 | B73: RML-FLXI-SPN-PVC-HOSE | C73: FLEXI SPINE PVC HOSE 1/2" X 26" | D73: NOS | E73: CBERM | F73: 689 | G73: 164.5714 | H73: 113389.71 | I73: 0 | K73: 0 | L73: 0 | N73: 0 | O73: 689 | P73: 164.5714 | Q73: 113389.71 | R73: CPG | S73: Clips, Polygel & Glue-10195 | T73: MATRESS
A74: 1122 | B74: RML-FLX-STRAP-GRY | C74: FLEXI SPINE PILLOW STRAP GREY-12MM | D74: MTR | E74: CBERM | F74: 60 | G74: 33.33 | H74: 1999.8 | I74: 0 | K74: 0 | L74: 0 | N74: 0 | O74: 60 | P74: 33.33 | Q74: 1999.8 | R74: PML | S74: Packing Material-10195 | T74: MATRESS
A75: 1123 | B75: RML-FLX-STRAP-NVBL | C75: FLEXI SPINE PILLOW STRAP NAVY BLUE-12MM | D75: MTR | E75: CBERM | F75: 60 | G75: 33.33 | H75: 1999.8 | I75: 0 | K75: 0 | L75: 0 | N75: 0 | O75: 60 | P75: 33.33 | Q75: 1999.8 | R75: PML | S75: Packing Material-10195 | T75: MATRESS
A76: 1124 | B76: RML-FM-WHT-HANDLE | C76: FOAM MATTRESS WHITE WITH CREAM HANDLE | D76: NOS | E76: CBERM | F76: 2150 | G76: 5.2502 | H76: 11287.86 | I76: 250 | J76: 5.25 | K76: 1312.5 | L76: 325 | M76: 5.2502 | N76: 1706.32 | O76: 2075 | P76: 5.2501 | Q76: 10894.04 | R76: LCE | S76: Label,CnrShoe,CentreBand,EdgeTape-10195 | T76: MATRESS
A77: 1130 | B77: RML-FOAMERA-WCRD | C77: FOAMERA 7 YEARS WARRANTY CARD | D77: NOS | E77: CBERM | F77: 1250 | G77: 5.4498 | H77: 6812.23 | I77: 0 | K77: 0 | L77: 0 | N77: 0 | O77: 1250 | P77: 5.4498 | Q77: 6812.23 | R77: LCE | S77: Label,CnrShoe,CentreBand,EdgeTape-10195 | T77: MATRESS
A78: 1142 | B78: RML-FOL-ROLWAY-COT | C78: FOLDING ROLLWAY COT 72"X36" | D78: NOS | E78: CBERM | F78: 8 | G78: 6963.7175 | H78: 55709.74 | I78: 0 | K78: 0 | L78: 6 | M78: 6963.72 | N78: 41782.32 | O78: 2 | P78: 6963.71 | Q78: 13927.42 | R78: SPARE | S78: SPARES Inventory - 10698 | T78: MATRESS
A79: 1681 | B79: RML-KOM-PTR-78X30 | C79: KOMFFY MATTRESSES PROTECTOR 78X30 | D79: NOS | E79: CBERM | F79: 5 | G79: 416 | H79: 2080 | I79: 0 | K79: 0 | L79: 0 | N79: 0 | O79: 5 | P79: 416 | Q79: 2080 | R79: SCHEME | S79: Scheme Materials-13015 | T79: MATRESS
A80: 1685 | B80: RML-KOM-PTR-78X36 | C80: KOMFFY MATTRESSES PROTECTOR 78X36 | D80: NOS | E80: CBERM | F80: 123 | G80: 498 | H80: 61254 | I80: 0 | K80: 0 | L80: 0 | N80: 0 | O80: 123 | P80: 498 | Q80: 61254 | R80: SCHEME | S80: Scheme Materials-13015 | T80: MATRESS
A81: 1692 | B81: RML-KOM-PTR-78X48 | C81: KOMFFY MATTRESSES PROTECTOR 78X48 | D81: NOS | E81: CBERM | F81: 308 | G81: 590 | H81: 181720 | I81: 0 | K81: 0 | L81: 0 | N81: 0 | O81: 308 | P81: 590 | Q81: 181720 | R81: SCHEME | S81: Scheme Materials-13015 | T81: MATRESS
A82: 1703 | B82: RML-KOM-PTR-78X60 | C82: KOMFFY MATTRESSES PROTECTOR 78X60 | D82: NOS | E82: CBERM | F82: 691 | G82: 592 | H82: 409072 | I82: 2 | J82: 592 | K82: 1184 | L82: 0 | N82: 0 | O82: 693 | P82: 592 | Q82: 410256 | R82: SCHEME | S82: Scheme Materials-13015 | T82: MATRESS
A83: 1731 | B83: RML-KOM-PTR-84X72 | C83: KOMFFY MATTRESSES PROTECTOR 84X72 | D83: NOS | E83: CBERM | F83: 13 | G83: 1030 | H83: 13390 | I83: 0 | K83: 0 | L83: 0 | N83: 0 | O83: 13 | P83: 1030 | Q83: 13390 | R83: SCHEME | S83: Scheme Materials-13015 | T83: MATRESS
A84: 1734 | B84: RML-KOM-PTR-INS | C84: KOMFFY PROTECTOR INSERTER | D84: NOS | E84: CBERM | F84: 3950 | G84: 7.2601 | H84: 28677.42 | I84: 0 | K84: 0 | L84: 0 | N84: 0 | O84: 3950 | P84: 7.2601 | Q84: 28677.42 | R84: LCE | S84: Label,CnrShoe,CentreBand,EdgeTape-10195 | T84: FOAM
A85: 1737 | B85: RML-KOM-PTR-MRP-LBL | C85: KOMFFY PROTECTOR MRP LABEL | D85: NOS | E85: CBERM | F85: 11400 | G85: 0.9693 | H85: 11049.86 | I85: 0 | K85: 0 | L85: 0 | N85: 0 | O85: 11400 | P85: 0.9693 | Q85: 11049.86 | R85: LCE | S85: Label,CnrShoe,CentreBand,EdgeTape-10195 | T85: FOAM
A86: 1784 | B86: RML-KOM-WSCR-LBL-CNTR-PLW | C86: KOMFFY MEMORY CONTOUR PILLOW WASH CARE LABEL | D86: NOS | E86: CBERM | F86: 7500 | G86: 0.5995 | H86: 4496.6 | I86: 0 | K86: 0 | L86: 0 | N86: 0 | O86: 7500 | P86: 0.5995 | Q86: 4496.6 | R86: LCE | S86: Label,CnrShoe,CentreBand,EdgeTape-10195 | T86: FOAM
A87: 1785 | B87: RML-KOZBRE-SDE-LBL | C87: KOZYBREEZ SIDE LABEL | D87: NOS | E87: CBERM | F87: 3100 | G87: 8.8006 | H87: 27281.9 | I87: 0 | K87: 0 | L87: 100 | M87: 8.8006 | N87: 880.06 | O87: 3000 | P87: 8.8006 | Q87: 26401.84 | R87: LCE | S87: Label,CnrShoe,CentreBand,EdgeTape-10195 | T87: MATRESS
A88: 1789 | B88: RML-KOZBRE-WCRD | C88: KOZYBREEZ WARRANTY CARD | D88: NOS | E88: CBERM | F88: 1973 | G88: 3.2768 | H88: 6465.22 | I88: 300 | J88: 11 | K88: 3300 | L88: 0 | N88: 0 | O88: 2273 | P88: 4.2962 | Q88: 9765.22 | R88: LCE | S88: Label,CnrShoe,CentreBand,EdgeTape-10195 | T88: MATRESS
A89: 1792 | B89: RML-LAT-MAS-PIL-BOX | C89: LATEX MASSAGE PILLOW BOX | D89: NOS | E89: CBERM | F89: 240 | G89: 103.3256 | H89: 24798.15 | I89: 0 | K89: 0 | L89: 56 | M89: 103.3257 | N89: 5786.24 | O89: 184 | P89: 103.3256 | Q89: 19011.91 | R89: PML | S89: Packing Material-10195 | T89: MATRESS
A90: 1796 | B90: RML-LCORNER-PAD-15 | C90: 15X15 INCH L CORNER PAD | D90: NOS | E90: CBERM | F90: 2350 | G90: 12.4986 | H90: 29371.76 | I90: 0 | K90: 0 | L90: 1550 | M90: 12.4986 | N90: 19372.83 | O90: 800 | P90: 12.4987 | Q90: 9998.93 | R90: PML | S90: Packing Material-10195 | T90: MATRESS
A91: 1831 | B91: RML-NET-PADDING | C91: HDPE KNITTED FABRIC ( MOSQUITO NET) | D91: MTR | E91: CBERM | F91: 81374 | G91: 6.4828 | H91: 527533.33 | I91: 71387 | J91: 6.4889 | K91: 463225.54 | L91: 72551 | M91: 6.4852 | N91: 470508.36 | O91: 80210 | P91: 6.4861 | Q91: 520250.51 | R91: NET | S91: Net-10195 | T91: MATRESS
A92: 1836 | B92: RML-NET-PADDING-TNDR | C92: TNDR - HDPE KNITTED FABRIC ( MOSQUITO NET) | D92: MTR | E92: CBERM | F92: 45928 | G92: 6 | H92: 275568 | I92: 0 | K92: 0 | L92: 45928 | M92: 6 | N92: 275568 | O92: 0 | Q92: 0 | R92: NET | S92: Net-10195 | T92: MATRESS
A93: 1838 | B93: RML-NET-PADDING-WHT | C93: HDPE KNITTED FABRIC - WHITE (MOSQUITO NET) | D93: MTR | E93: CBERM | F93: 1425 | G93: 8.5 | H93: 12112.5 | I93: 1920 | J93: 8.5 | K93: 16320 | L93: 1425 | M93: 8.5 | N93: 12112.5 | O93: 1920 | P93: 8.5 | Q93: 16320 | R93: LCE | S93: Label,CnrShoe,CentreBand,EdgeTape-10195 | T93: MATRESS
A94: 1839 | B94: RML-NONSTANDARD-SKR | C94: NON STANDARD STICKER | D94: NOS | E94: CBERM | F94: 950 | G94: 0.51 | H94: 484.51 | I94: 1000 | J94: 0.8 | K94: 800 | L94: 700 | M94: 0.6197 | N94: 433.8 | O94: 1250 | P94: 0.6806 | Q94: 850.71 | R94: LCE | S94: Label,CnrShoe,CentreBand,EdgeTape-10195 | T94: MATRESS
A95: 1841 | B95: RML-NWN-70GSMX76" | C95: NON WOVEN FABRIC 70 GSM x 76 INCH - WHITE | D95: KGS | E95: CBERM | F95: 607.8 | G95: 112.8872 | H95: 68612.82 | I95: 0 | K95: 0 | L95: 191 | M95: 112.8872 | N95: 21561.45 | O95: 416.8 | P95: 112.8872 | Q95: 47051.37 | R95: NW | S95: Non Woven Fabric-10195 | T95: MATRESS
A96: 1846 | B96: RML-NWN-70GSMX79" | C96: NON WOVEN FABRIC 70 GSM x 79 INCH - WHITE | D96: KGS | E96: CBERM | F96: 715.4 | G96: 113.6458 | H96: 81302.17 | I96: 3985.4 | J96: 114 | K96: 454335.43 | L96: 2965 | M96: 113.9235 | N96: 337783.29 | O96: 1735.8 | P96: 113.9845 | Q96: 197854.31 | R96: NW | S96: Non Woven Fabric-10195 | T96: MATRESS
A97: 1850 | B97: RML-NWN-80GSMX8" | C97: NON WOVEN FABRIC 80 GSM x 8 INCH - WHITE | D97: KGS | E97: CBERM | F97: 285.8 | G97: 111.0368 | H97: 31734.32 | I97: 0 | K97: 0 | L97: 0 | N97: 0 | O97: 285.8 | P97: 111.0368 | Q97: 31734.32 | R97: NW | S97: Non Woven Fabric-10195 | T97: MATRESS
A98: 1851 | B98: RML-NWN-80GSMX82BLK | C98: NON WOVEN FABRIC 80 GSM x 82 INCH - BLACK | D98: KGS | E98: CBERM | F98: 441.6 | G98: 123.9498 | H98: 54736.25 | I98: 0 | K98: 0 | L98: 81.8 | M98: 123.95 | N98: 10139.11 | O98: 359.8 | P98: 123.9498 | Q98: 44597.14 | R98: NW | S98: Non Woven Fabric-10195 | T98: MATRESS
A99: 1854 | B99: RML-NYLONBUSH-50X100 | C99: NYLON BUSH WHITE COLOR | D99: NOS | E99: CBERM | F99: 1047 | G99: 17.7208 | H99: 18553.71 | I99: 0 | K99: 0 | L99: 2 | M99: 17.72 | N99: 35.44 | O99: 1045 | P99: 17.7208 | Q99: 18518.27 | R99: CPG | S99: Clips, Polygel & Glue-10195 | T99: MATRESS
A100: 1858 | B100: RML-OGA-WCRD | C100: PEPS ORGANICA WARRANTY CARD | D100: NOS | E100: CBERM | F100: 7630 | G100: 9.4147 | H100: 71834.51 | I100: 0 | K100: 0 | L100: 160 | M100: 9.4148 | N100: 1506.37 | O100: 7470 | P100: 9.4147 | Q100: 70328.14 | R100: LCE | S100: Label,CnrShoe,CentreBand,EdgeTape-10195 | T100: MATRESS
...

Sheet Item code
A1: S.no | B1: R.no | C1: Date | D1: Item | E1: PS Desc. | F1: PS Usage | G1: PS Category | H1: Process Plan | I1: Uom | J1: Qty | K1: Default For | L1: Wh Code | M1: PRO-RATE
A2: 1 | B2: 1 | C2: 07.03.2024 | D2: SFG-SPKKFNLMR-BOR-72X33X05 | E2: SpringKoil Knit Normal Maroon Border 72X33X05 | F2: Standard | G2: Production | H2: TAIL-BORDER | I2: NOS | J2: 1 | K2: MRP&Rollup | L2: CBESFG | M2: 117
A3: 2 | B3: 2 | C3: 07.03.2024 | D3: SFG-SPKKFNLMR-BOR-72X39X05 | E3: SpringKoil Knit Normal Maroon Border 72X39X05 | F3: Standard | G3: Production | H3: TAIL-BORDER | I3: NOS | J3: 1 | K3: MRP&Rollup | L3: CBESFG | M3: 123
A4: 3 | B4: 3 | C4: 07.03.2024 | D4: SFG-SPKKFNLMR-BOR-72X45X05 | E4: SpringKoil Knit Normal Maroon Border 72X45X05 | F4: Standard | G4: Production | H4: TAIL-BORDER | I4: NOS | J4: 1 | K4: MRP&Rollup | L4: CBESFG | M4: 128
A5: 4 | B5: 4 | C5: 07.03.2024 | D5: SFG-SPKKFNLMR-BOR-72X51X05 | E5: SpringKoil Knit Normal Maroon Border 72X51X05 | F5: Standard | G5: Production | H5: TAIL-BORDER | I5: NOS | J5: 1 | K5: MRP&Rollup | L5: CBESFG | M5: 133
A6: 5 | B6: 5 | C6: 07.03.2024 | D6: SFG-SPKKFNLMR-BOR-72X54X05 | E6: SpringKoil Knit Normal Maroon Border 72X54X05 | F6: Standard | G6: Production | H6: TAIL-BORDER | I6: NOS | J6: 1 | K6: MRP&Rollup | L6: CBESFG | M6: 135

Sheet pro.stru
A1: S.no | B1: R.no | C1: Date | D1: Bom Code/PS.No | E1: PS Desc. | F1: Item | G1: PS Desc. | H1: PS Usage | I1: PS Category | J1: Process Plan | K1: Uom | L1: Qty | M1: Default For | N1: Wh Code | O1: PS Seq | P1: I/O Flag | Q1: Issue Item | R1: Item Desc | S1: Uom | T1: Qty | U1: Std Wh Code | V1: Backflush | W1: Status
A2: 1 | B2: 1 | C2: 07.03.2024 | D2: SFG-SPKKFNLMR-BOR-72X33X05 | E2: SpringKoil Knit Normal Maroon Border 72X33X05 | F2: SFG-SPKKFNLMR-BOR-72X33X05 | G2: SpringKoil Knit Normal Maroon Border 72X33X05 | H2: Standard | I2: Production | J2: TAIL-BORDER | K2: NOS | L2: 1 | M2: MRP&Rollup | N2: CBESFG | O2: 10 | P2: I | Q2: RM-THRD-QS-TKT40 | R2: THREAD TKT40 210D/3 PLY 10000MTS | S2: MTR | T2: 5.6 | U2: CBEWIP | V2: Backflush | W2: Active
A3: 2 | B3: 1 | C3: 07.03.2024 | D3: SFG-SPKKFNLMR-BOR-72X33X05 | E3: SpringKoil Knit Normal Maroon Border 72X33X05 | F3: SFG-SPKKFNLMR-BOR-72X33X05 | G3: SpringKoil Knit Normal Maroon Border 72X33X05 | H3: Standard | I3: Production | J3: TAIL-BORDER | K3: NOS | L3: 1 | M3: MRP&Rollup | N3: CBESFG | O3: 20 | P3: I | Q3: HW-CTON-THREAD | R3: COTTON THREAD WHITE 3PLY | S3: MTR | T3: 5 | U3: CBEWIP | V3: Backflush | W3: Active
A4: 3 | B4: 1 | C4: 07.03.2024 | D4: SFG-SPKKFNLMR-BOR-72X33X05 | E4: SpringKoil Knit Normal Maroon Border 72X33X05 | F4: SFG-SPKKFNLMR-BOR-72X33X05 | G4: SpringKoil Knit Normal Maroon Border 72X33X05 | H4: Standard | I4: Production | J4: TAIL-BORDER | K4: NOS | L4: 1 | M4: MRP&Rollup | N4: CBESFG | O4: 30 | P4: I | Q4: SFG-SPKKFMR-BOR-18CM | R4: Maroon Knit 8MM/18D PU Foam Border 18 CM Height | S4: MTR | T4: 5.411 | U4: CBESFG | V4: Backflush | W4: Active
A5: 4 | B5: 1 | C5: 07.03.2024 | D5: SFG-SPKKFNLMR-BOR-72X33X05 | E5: SpringKoil Knit Normal Maroon Border 72X33X05 | F5: SFG-SPKKFNLMR-BOR-72X33X05 | G5: SpringKoil Knit Normal Maroon Border 72X33X05 | H5: Standard | I5: Production | J5: TAIL-BORDER | K5: NOS | L5: 1 | M5: MRP&Rollup | N5: CBESFG | O5: 40 | P5: I | Q5: RML-MRP-BACK-LBL | R5: MRP BACK LABEL(PLAIN) | S5: NOS | T5: 1 | U5: CBEWIP | V5: Backflush | W5: Active
A6: 5 | B6: 1 | C6: 07.03.2024 | D6: SFG-SPKKFNLMR-BOR-72X33X05 | E6: SpringKoil Knit Normal Maroon Border 72X33X05 | F6: SFG-SPKKFNLMR-BOR-72X33X05 | G6: SpringKoil Knit Normal Maroon Border 72X33X05 | H6: Standard | I6: Production | J6: TAIL-BORDER | K6: NOS | L6: 1 | M6: MRP&Rollup | N6: CBESFG | O6: 50 | P6: I | Q6: RML-FUSI-LBL | R6: SPRINGKOIL SIDE LABEL (IMPORT) | S6: NOS | T6: 1 | U6: CBEWIP | V6: Backflush | W6: Active
A7: 6 | B7: 1 | C7: 07.03.2024 | D7: SFG-SPKKFNLMR-BOR-72X33X05 | E7: SpringKoil Knit Normal Maroon Border 72X33X05 | F7: SFG-SPKKFNLMR-BOR-72X33X05 | G7: SpringKoil Knit Normal Maroon Border 72X33X05 | H7: Standard | I7: Production | J7: TAIL-BORDER | K7: NOS | L7: 1 | M7: MRP&Rollup | N7: CBESFG | O7: 60 | P7: I | Q7: RML-DRN-LBL | R7: DIRECTION LABEL | S7: NOS | T7: 1 | U7: CBEWIP | V7: Backflush | W7: Active
A8: 7 | B8: 1 | C8: 07.03.2024 | D8: SFG-SPKKFNLMR-BOR-72X33X05 | E8: SpringKoil Knit Normal Maroon Border 72X33X05 | F8: SFG-SPKKFNLMR-BOR-72X33X05 | G8: SpringKoil Knit Normal Maroon Border 72X33X05 | H8: Standard | I8: Production | J8: TAIL-BORDER | K8: NOS | L8: 1 | M8: MRP&Rollup | N8: CBESFG | O8: 70 | P8: I | Q8: SFG-SPKKFMR-HANDLE | R8: Springkoil Knit Maroon Handle | S8: MTR | T8: 1 | U8: CBESFG | V8: Backflush | W8: Active
A9: 8 | B9: 1 | C9: 07.03.2024 | D9: SFG-SPKKFNLMR-BOR-72X33X05 | E9: SpringKoil Knit Normal Maroon Border 72X33X05 | F9: SFG-SPKKFNLMR-BOR-72X33X05 | G9: SpringKoil Knit Normal Maroon Border 72X33X05 | H9: Standard | I9: Production | J9: TAIL-BORDER | K9: NOS | L9: 1 | M9: MRP&Rollup | N9: CBESFG | O9: 80 | P9: I | Q9: RMI-BREATHER-GOLD | R9: BREATHER SET GOLD ROUND | S9: SET | T9: 2 | U9: CBEWIP | V9: Backflush | W9: Active
A10: 10 | B10: 2 | C10: 07.03.2024 | D10: SFG-SPKKFNLMR-BOR-72X39X05 | E10: SpringKoil Knit Normal Maroon Border 72X39X05 | F10: SFG-SPKKFNLMR-BOR-72X39X05 | G10: SpringKoil Knit Normal Maroon Border 72X39X05 | H10: Standard | I10: Production | J10: TAIL-BORDER | K10: NOS | L10: 1 | M10: MRP&Rollup | N10: CBESFG | O10: 10 | P10: I | Q10: RM-THRD-QS-TKT40 | R10: THREAD TKT40 210D/3 PLY 10000MTS | S10: MTR | T10: 5.6 | U10: CBEWIP | V10: Backflush | W10: Active
A11: 11 | B11: 2 | C11: 07.03.2024 | D11: SFG-SPKKFNLMR-BOR-72X39X05 | E11: SpringKoil Knit Normal Maroon Border 72X39X05 | F11: SFG-SPKKFNLMR-BOR-72X39X05 | G11: SpringKoil Knit Normal Maroon Border 72X39X05 | H11: Standard | I11: Production | J11: TAIL-BORDER | K11: NOS | L11: 1 | M11: MRP&Rollup | N11: CBESFG | O11: 20 | P11: I | Q11: HW-CTON-THREAD | R11: COTTON THREAD WHITE 3PLY | S11: MTR | T11: 5 | U11: CBEWIP | V11: Backflush | W11: Active
A12: 12 | B12: 2 | C12: 07.03.2024 | D12: SFG-SPKKFNLMR-BOR-72X39X05 | E12: SpringKoil Knit Normal Maroon Border 72X39X05 | F12: SFG-SPKKFNLMR-BOR-72X39X05 | G12: SpringKoil Knit Normal Maroon Border 72X39X05 | H12: Standard | I12: Production | J12: TAIL-BORDER | K12: NOS | L12: 1 | M12: MRP&Rollup | N12: CBESFG | O12: 30 | P12: I | Q12: SFG-SPKKFMR-BOR-18CM | R12: Maroon Knit 8MM/18D PU Foam Border 18 CM Height | S12: MTR | T12: 5.715 | U12: CBESFG | V12: Backflush | W12: Active
A13: 13 | B13: 2 | C13: 07.03.2024 | D13: SFG-SPKKFNLMR-BOR-72X39X05 | E13: SpringKoil Knit Normal Maroon Border 72X39X05 | F13: SFG-SPKKFNLMR-BOR-72X39X05 | G13: SpringKoil Knit Normal Maroon Border 72X39X05 | H13: Standard | I13: Production | J13: TAIL-BORDER | K13: NOS | L13: 1 | M13: MRP&Rollup | N13: CBESFG | O13: 40 | P13: I | Q13: RML-MRP-BACK-LBL | R13: MRP BACK LABEL(PLAIN) | S13: NOS | T13: 1 | U13: CBEWIP | V13: Backflush | W13: Active
... A41: 44 | B41: 5 | C41: 07.03.2024 | D41: SFG-SPKKFNLMR-BOR-72X54X05 | E41: SpringKoil Knit Normal Maroon Border 72X54X05 | F41: SFG-SPKKFNLMR-BOR-72X54X05 | G41: SpringKoil Knit Normal Maroon Border 72X54X05 | H41: Standard | I41: Production | J41: TAIL-BORDER | K41: NOS | L41: 1 | M41: MRP&Rollup | N41: CBESFG | O41: 80 | P41: I | Q41: RMI-BREATHER-GOLD | R41: BREATHER SET GOLD ROUND | S41: SET | T41: 2 | U41: CBEWIP | V41: Backflush | W41: Active
