Workbook

Sheet Matt-FON Et
A1: S.NO | B1: ITEM CODE | C1: ITEM DESC
A2: 1 | B2: RTHTMTBNET72X33X06 | C2: Peps Restonic Hotel Motel Bonnell Euro Top 72X33X06
A3: 2 | B3: RTHTMTBNET72X39X06 | C3: Peps Restonic Hotel Motel Bonnell Euro Top 72X39X06
A4: 3 | B4: RTHTMTBNET72X45X06 | C4: Peps Restonic Hotel Motel Bonnell Euro Top 72X45X06
A5: 4 | B5: RTHTMTBNET72X51X06 | C5: Peps Restonic Hotel Motel Bonnell Euro Top 72X51X06
A6: 5 | B6: RTHTMTBNET72X54X06 | C6: Peps Restonic Hotel Motel Bonnell Euro Top 72X54X06
A7: 6 | B7: RTHTMTBNET72X57X06 | C7: Peps Restonic Hotel Motel Bonnell Euro Top 72X57X06
A8: 7 | B8: RTHTMTBNET72X63X06 | C8: Peps Restonic Hotel Motel Bonnell Euro Top 72X63X06
A9: 8 | B9: RTHTMTBNET72X69X06 | C9: Peps Restonic Hotel Motel Bonnell Euro Top 72X69X06
A10: 9 | B10: RTHTMTBNET75X33X06 | C10: Peps Restonic Hotel Motel Bonnell Euro Top 75X33X06
A11: 10 | B11: RTHTMTBNET75X39X06 | C11: Peps Restonic Hotel Motel Bonnell Euro Top 75X39X06
A12: 11 | B12: RTHTMTBNET75X45X06 | C12: Peps Restonic Hotel Motel Bonnell Euro Top 75X45X06
A13: 12 | B13: RTHTMTBNET75X51X06 | C13: Peps Restonic Hotel Motel Bonnell Euro Top 75X51X06
... A121: 120 | B121: RTHTMTBNET84X69X10 | C121: Peps Restonic Hotel Motel Bonnell Euro Top 84X69X10

Sheet Manual
B2: 72X30 | C2: RM-NWN-70GSMX6INCH | D2: 0.051 | F2: RML-NWN-70GSMX76" | G2: 0.104
B3: 72X33 | C3: RM-NWN-70GSMX6INCH | D3: 0.052 | F3: RML-NWN-70GSMX76" | G3: 0.113
B4: 72X36 | C4: RM-NWN-70GSMX6INCH | D4: 0.054 | F4: RML-NWN-70GSMX76" | G4: 0.124
B5: 72X39 | C5: RM-NWN-70GSMX6INCH | D5: 0.056 | F5: RML-NWN-70GSMX76" | G5: 0.133
B6: 72X42 | C6: RM-NWN-70GSMX6INCH | D6: 0.057 | F6: RML-NWN-70GSMX76" | G6: 0.144
B7: 72X45 | C7: RM-NWN-70GSMX6INCH | D7: 0.058 | F7: RML-NWN-70GSMX76" | G7: 0.157
B8: 72X48 | C8: RM-NWN-70GSMX6INCH | D8: 0.06 | F8: RML-NWN-70GSMX76" | G8: 0.169
B9: 72X51 | C9: RM-NWN-70GSMX6INCH | D9: 0.061 | F9: RML-NWN-70GSMX76" | G9: 0.173
B10: 72X54 | C10: RM-NWN-70GSMX6INCH | D10: 0.063 | F10: RML-NWN-70GSMX76" | G10: 0.185
B11: 72X57 | C11: RM-NWN-70GSMX6INCH | D11: 0.065 | F11: RML-NWN-70GSMX76" | G11: 0.196
B12: 72X60 | C12: RM-NWN-70GSMX6INCH | D12: 0.067 | F12: RML-NWN-70GSMX76" | G12: 0.209
B13: 72X63 | C13: RM-NWN-70GSMX6INCH | D13: 0.068 | F13: RML-NWN-70GSMX76" | G13: 0.219
... B80: 84X72 | C80: RM-NWN-70GSMX6INCH | D80: 0.079 | F80: RML-NWN-70GSMX79" | G80: 0.304

Sheet Workings
A1: S.no | B1: R.no | C1: VARIETIES | D1: Col | E1: Matt item Code | F1: REF1 | G1: REF2 | H1: REF3 | I1: REF4 | J1: REF5 | K1: LENGTH | L1: WIDTH | M1: HEIGHT | N1: Bom Code/PS.No | P1: Consum | Q1: CTN THREAD | S1: PS Desc. | T1: Item | W1: Item Desc | X1: PS Usage | Y1: PS Category | Z1: Process Plan | AA1: Uom | AB1: Qty | AC1: Default For | AD1: Wh Code | AE1: PS Seq | AF1: I/O Flag | AG1: Issue Item | AH1: Item Desc | AI1: Uom | AJ1: Qty | AK1: Std Wh Code | AL1: Backflush | AM1: Status | AN1: CONV | AO1: RATE | AP1: SUB.TOT | AQ1: TOT | AR1: ROUNDUP | AS1: Rm-cost | AT1: PRO-RATE | AU1: Wastage | AV1: DL | AW1: MOH | AX1: Dep | AY1: Standard Cost | AZ1: R-UP | BA1: PRO-RATE
A2: 1 | B2: 1 | C2: ET-COVER | D2: =MID(E2,9,2) -> PT | E2: RTHTMTBNPT72X33X10 | F2: =LEFT(E2,MIN(FIND({0,1,2,3,4,5,6,7,8,9},E2&"0123456789"))-1) -> RTHTMTBNPT | G2: =SUBSTITUTE(E2,F2,"") -> 72X33X10 | H2: =IFERROR(LEFT(G2,FIND("-",G2)-1),G2) -> 72X33X10 | I2: =SEARCH("X",H2) -> 3 | J2: =SEARCH("X",H2,I2+1) -> 6 | K2: =LEFT(G2,SEARCH("x",G2)-1) -> 72 | L2: =MID(H2,I2+1,J2-I2-1) -> 33 | M2: =MID(H2,J2+1,20) -> 10 | N2: ="SFG-FRBNPK-ET-CVR-"&K2&"X"&L2&"X"&M2 -> SFG-FRBNPK-ET-CVR-72X33X10 | P2: =ROUND(((((K2+L2+K2+L2)+3)*0.0254)*5.3196),3) -> 28.78 | Q2: 0 | R2: =P2+Q2 -> 28.78 | S2: ="Restonic Hotel Motel ET Cover "&K2&"X"&L2&"X"&M2 -> Restonic Hotel Motel ET Cover 72X33X10 | T2: =N2 -> SFG-FRBNPK-ET-CVR-72X33X10 | U2: =T2=N2 -> TRUE | V2: =S2=W2 -> TRUE | W2: =S2 -> Restonic Hotel Motel ET Cover 72X33X10 | X2: Standard | Y2: Production | Z2: TAIL-ET-PT | AA2: NOS | AB2: 1 | AC2: MRP&Rollup | AD2: CBESFG | AE2: 10 | AF2: I | AG2: RM-THRD-QS-TKT40 | AH2: THREAD TKT40 210D/3 PLY 10000MTS | AI2: MTR | AJ2: =R2 -> 28.78 | AK2: CBEWIP | AL2: Backflush | AM2: Active | AN2: =AJ2/10000 -> 0.002878 | AO2: =VLOOKUP(AG2,'RM-cost - feb-24'!B:P,15,0) -> 231.1423 | AP2: =AO2*AN2 -> 0.66522754 | AQ2: =SUM(AP2:AP6) -> 125.51946 | AR2: =ROUND(AQ2,0) -> 126 | AS2: =AR2 -> 126 | AT2: =+AS2+AY2 -> 141.59237 | AU2: =+SUM(((AS2*3%*18%))) -> 0.6804 | AV2: =+SUM(((AS2*14.33%*53%))) -> 9.569574 | AW2: =+SUM(((AS2*5.92%*53%))) -> 3.953376 | AX2: =+SUM(((AS2*2.08%*53%))) -> 1.389024 | AY2: =SUM(AU2:AX6) -> 15.592374 | AZ2: =ROUNDUP(AT2,0) -> 142 | BA2: =AZ2 -> 142
A3: 2 | B3: =B2 -> 1 | C3: =C2 -> ET-COVER | D3: =MID(E3,9,2) -> PT | E3: =E2 -> RTHTMTBNPT72X33X10 | F3: =F2 -> RTHTMTBNPT | G3: =G2 -> 72X33X10 | H3: =H2 -> 72X33X10 | I3: =I2 -> 3 | J3: =J2 -> 6 | K3: =K2 -> 72 | L3: =L2 -> 33 | M3: =M2 -> 10 | N3: ="SFG-FRBNPK-ET-CVR-"&K3&"X"&L3&"X"&M3 -> SFG-FRBNPK-ET-CVR-72X33X10 | O3: =K3*L3/144 -> 16.5 | P3: =ROUNDUP((((K3*L3/144)*0.003)),3) -> 0.05 | S3: ="Restonic Hotel Motel ET Cover "&K3&"X"&L3&"X"&M3 -> Restonic Hotel Motel ET Cover 72X33X10 | T3: =T2 -> SFG-FRBNPK-ET-CVR-72X33X10 | U3: =T3=N3 -> TRUE | V3: =S3=W3 -> TRUE | W3: =W2 -> Restonic Hotel Motel ET Cover 72X33X10 | X3: Standard | Y3: Production | Z3: TAIL-ET-PT | AA3: NOS | AB3: 1 | AC3: MRP&Rollup | AD3: CBESFG | AE3: 20 | AF3: I | AG3: RM-NWN-70GSMX6INCH | AH3: NON WOVEN FABRIC 70GSMX6" | AI3: KGS | AJ3: 0.052 | AK3: CBEWIP | AL3: Backflush | AM3: Active | AN3: =AJ3 -> 0.052 | AO3: =VLOOKUP(AG3,'RM-cost - feb-24'!B:P,15,0) -> 113.786 | AP3: =AO3*AN3 -> 5.916872 | AS3: =AS2 -> 126
A4: 3 | B4: =B3 -> 1 | C4: =C3 -> ET-COVER | D4: =MID(E4,9,2) -> PT | E4: =E3 -> RTHTMTBNPT72X33X10 | F4: =F3 -> RTHTMTBNPT | G4: =G3 -> 72X33X10 | H4: =H3 -> 72X33X10 | I4: =I3 -> 3 | J4: =J3 -> 6 | K4: =K3 -> 72 | L4: =L3 -> 33 | M4: =M3 -> 10 | N4: ="SFG-FRBNPK-ET-CVR-"&K4&"X"&L4&"X"&M4 -> SFG-FRBNPK-ET-CVR-72X33X10 | P4: =ROUNDUP((((K4*L4/144)*0.00692)),3) -> 0.115 | Q4: =P4=AJ4 -> FALSE | S4: ="Restonic Hotel Motel ET Cover "&K4&"X"&L4&"X"&M4 -> Restonic Hotel Motel ET Cover 72X33X10 | T4: =T3 -> SFG-FRBNPK-ET-CVR-72X33X10 | U4: =T4=N4 -> TRUE | V4: =S4=W4 -> TRUE | W4: =W3 -> Restonic Hotel Motel ET Cover 72X33X10 | X4: Standard | Y4: Production | Z4: TAIL-ET-PT | AA4: NOS | AB4: 1 | AC4: MRP&Rollup | AD4: CBESFG | AE4: 30 | AF4: I | AG4: RML-NWN-70GSMX76" | AH4: NON WOVEN FABRIC WHITE 70 GSM 76 INCH | AI4: KGS | AJ4: 0.113 | AK4: CBEWIP | AL4: Backflush | AM4: Active | AN4: =AJ4 -> 0.113 | AO4: =VLOOKUP(AG4,'RM-cost - feb-24'!B:P,15,0) -> 112.8872 | AP4: =AO4*AN4 -> 12.756254 | AS4: =AS3 -> 126
A5: 4 | B5: =B4 -> 1 | C5: =C4 -> ET-COVER | D5: =MID(E5,9,2) -> PT | E5: =E4 -> RTHTMTBNPT72X33X10 | F5: =F4 -> RTHTMTBNPT | G5: =G4 -> 72X33X10 | H5: =H4 -> 72X33X10 | I5: =I4 -> 3 | J5: =J4 -> 6 | K5: =K4 -> 72 | L5: =L4 -> 33 | M5: =M4 -> 10 | N5: ="SFG-FRBNPK-ET-CVR-"&K5&"X"&L5&"X"&M5 -> SFG-FRBNPK-ET-CVR-72X33X10 | P5: =ROUND(((((K5+L5+K5+L5)+3))*0.0254),3) -> 5.41 | Q5: =P5=AJ5 -> TRUE | S5: ="Restonic Hotel Motel ET Cover "&K5&"X"&L5&"X"&M5 -> Restonic Hotel Motel ET Cover 72X33X10 | T5: =T4 -> SFG-FRBNPK-ET-CVR-72X33X10 | U5: =T5=N5 -> TRUE | V5: =S5=W5 -> TRUE | W5: =W4 -> Restonic Hotel Motel ET Cover 72X33X10 | X5: Standard | Y5: Production | Z5: TAIL-ET-PT | AA5: NOS | AB5: 1 | AC5: MRP&Rollup | AD5: CBESFG | AE5: 40 | AF5: I | AG5: SFG-RTHTMT-BNPK-ETBOR-11CM | AH5: Hotel Motel Poc ET-10 & 12 8MM/16D Pre Foam Border 11 CM Height | AI5: MTR | AJ5: =P5 -> 5.41 | AK5: CBESFG | AL5: Backflush | AM5: Active | AN5: =AJ5 -> 5.41 | AO5: =VLOOKUP(AG5,'SFG-rate rm - feb-24'!A:B,2,0) -> 19.60538 | AP5: =AO5*AN5 -> 106.06511 | AS5: =AS4 -> 126
A6: 5 | B6: =B5 -> 1 | C6: =C5 -> ET-COVER | D6: =MID(E6,9,2) -> PT | E6: =E5 -> RTHTMTBNPT72X33X10 | F6: =F5 -> RTHTMTBNPT | G6: =G5 -> 72X33X10 | H6: =H5 -> 72X33X10 | I6: =I5 -> 3 | J6: =J5 -> 6 | K6: =K5 -> 72 | L6: =L5 -> 33 | M6: =M5 -> 10 | N6: ="SFG-FRBNPK-ET-CVR-"&K6&"X"&L6&"X"&M6 -> SFG-FRBNPK-ET-CVR-72X33X10 | P6: 10 | Q6: =P6=AJ6 -> TRUE | S6: ="Restonic Hotel Motel ET Cover "&K6&"X"&L6&"X"&M6 -> Restonic Hotel Motel ET Cover 72X33X10 | T6: =T5 -> SFG-FRBNPK-ET-CVR-72X33X10 | U6: =T6=N6 -> TRUE | V6: =S6=W6 -> TRUE | W6: =W5 -> Restonic Hotel Motel ET Cover 72X33X10 | X6: Standard | Y6: Production | Z6: TAIL-ET-PT | AA6: NOS | AB6: 1 | AC6: MRP&Rollup | AD6: CBESFG | AE6: 50 | AF6: I | AG6: HW-CTON-THREAD | AH6: COTTON THREAD WHITE 3PLY | AI6: MTR | AJ6: =P6 -> 10 | AK6: CBEWIP | AL6: Backflush | AM6: Active | AN6: =AJ6/5000 -> 0.002 | AO6: =VLOOKUP(AG6,'RM-cost - feb-24'!B:P,15,0) -> 58 | AP6: =AO6*AN6 -> 0.116 | AS6: =AS5 -> 126
A8: 1 | B8: 2 | C8: ET-COVER | D8: =MID(E8,9,2) -> PT | E8: RTHTMTBNPT72X39X10 | F8: =LEFT(E8,MIN(FIND({0,1,2,3,4,5,6,7,8,9},E8&"0123456789"))-1) -> RTHTMTBNPT | G8: =SUBSTITUTE(E8,F8,"") -> 72X39X10 | H8: =IFERROR(LEFT(G8,FIND("-",G8)-1),G8) -> 72X39X10 | I8: =SEARCH("X",H8) -> 3 | J8: =SEARCH("X",H8,I8+1) -> 6 | K8: =LEFT(G8,SEARCH("x",G8)-1) -> 72 | L8: =MID(H8,I8+1,J8-I8-1) -> 39 | M8: =MID(H8,J8+1,20) -> 10 | N8: ="SFG-FRBNPK-ET-CVR-"&K8&"X"&L8&"X"&M8 -> SFG-FRBNPK-ET-CVR-72X39X10 | P8: =ROUND(((((K8+L8+K8+L8)+3)*0.0254)*5.3196),3) -> 30.402 | Q8: 0 | R8: =P8+Q8 -> 30.402 | S8: ="Restonic Hotel Motel ET Cover "&K8&"X"&L8&"X"&M8 -> Restonic Hotel Motel ET Cover 72X39X10 | T8: =N8 -> SFG-FRBNPK-ET-CVR-72X39X10 | U8: =T8=N8 -> TRUE | V8: =S8=W8 -> TRUE | W8: =S8 -> Restonic Hotel Motel ET Cover 72X39X10 | X8: Standard | Y8: Production | Z8: TAIL-ET-PT | AA8: NOS | AB8: 1 | AC8: MRP&Rollup | AD8: CBESFG | AE8: 10 | AF8: I | AG8: RM-THRD-QS-TKT40 | AH8: THREAD TKT40 210D/3 PLY 10000MTS | AI8: MTR | AJ8: =R8 -> 30.402 | AK8: CBEWIP | AL8: Backflush | AM8: Active | AN8: =AJ8/10000 -> 0.0030402 | AO8: =VLOOKUP(AG8,'RM-cost - feb-24'!B:P,15,0) -> 231.1423 | AP8: =AO8*AN8 -> 0.70271882 | AQ8: =SUM(AP8:AP12) -> 134.24948 | AR8: =ROUND(AQ8,0) -> 134 | AS8: =AR8 -> 134 | AT8: =+AS8+AY8 -> 150.58237 | AU8: =+SUM(((AS8*3%*18%))) -> 0.7236 | AV8: =+SUM(((AS8*14.33%*53%))) -> 10.177166 | AW8: =+SUM(((AS8*5.92%*53%))) -> 4.204384 | AX8: =+SUM(((AS8*2.08%*53%))) -> 1.477216 | AY8: =SUM(AU8:AX12) -> 16.582366 | AZ8: =ROUNDUP(AT8,0) -> 151 | BA8: =AZ8 -> 151
A9: 2 | B9: =B8 -> 2 | C9: =C8 -> ET-COVER | D9: =MID(E9,9,2) -> PT | E9: =E8 -> RTHTMTBNPT72X39X10 | F9: =F8 -> RTHTMTBNPT | G9: =G8 -> 72X39X10 | H9: =H8 -> 72X39X10 | I9: =I8 -> 3 | J9: =J8 -> 6 | K9: =K8 -> 72 | L9: =L8 -> 39 | M9: =M8 -> 10 | N9: ="SFG-FRBNPK-ET-CVR-"&K9&"X"&L9&"X"&M9 -> SFG-FRBNPK-ET-CVR-72X39X10 | O9: =K9*L9/144 -> 19.5 | P9: =ROUNDUP((((K9*L9/144)*0.003)),3) -> 0.059 | S9: ="Restonic Hotel Motel ET Cover "&K9&"X"&L9&"X"&M9 -> Restonic Hotel Motel ET Cover 72X39X10 | T9: =T8 -> SFG-FRBNPK-ET-CVR-72X39X10 | U9: =T9=N9 -> TRUE | V9: =S9=W9 -> TRUE | W9: =W8 -> Restonic Hotel Motel ET Cover 72X39X10 | X9: Standard | Y9: Production | Z9: TAIL-ET-PT | AA9: NOS | AB9: 1 | AC9: MRP&Rollup | AD9: CBESFG | AE9: 20 | AF9: I | AG9: RM-NWN-70GSMX6INCH | AH9: NON WOVEN FABRIC 70GSMX6" | AI9: KGS | AJ9: 0.056 | AK9: CBEWIP | AL9: Backflush | AM9: Active | AN9: =AJ9 -> 0.056 | AO9: =VLOOKUP(AG9,'RM-cost - feb-24'!B:P,15,0) -> 113.786 | AP9: =AO9*AN9 -> 6.372016 | AS9: =AS8 -> 134
A10: 3 | B10: =B9 -> 2 | C10: =C9 -> ET-COVER | D10: =MID(E10,9,2) -> PT | E10: =E9 -> RTHTMTBNPT72X39X10 | F10: =F9 -> RTHTMTBNPT | G10: =G9 -> 72X39X10 | H10: =H9 -> 72X39X10 | I10: =I9 -> 3 | J10: =J9 -> 6 | K10: =K9 -> 72 | L10: =L9 -> 39 | M10: =M9 -> 10 | N10: ="SFG-FRBNPK-ET-CVR-"&K10&"X"&L10&"X"&M10 -> SFG-FRBNPK-ET-CVR-72X39X10 | P10: =ROUNDUP((((K10*L10/144)*0.00692)),3) -> 0.135 | Q10: =P10=AJ10 -> FALSE | S10: ="Restonic Hotel Motel ET Cover "&K10&"X"&L10&"X"&M10 -> Restonic Hotel Motel ET Cover 72X39X10 | T10: =T9 -> SFG-FRBNPK-ET-CVR-72X39X10 | U10: =T10=N10 -> TRUE | V10: =S10=W10 -> TRUE | W10: =W9 -> Restonic Hotel Motel ET Cover 72X39X10 | X10: Standard | Y10: Production | Z10: TAIL-ET-PT | AA10: NOS | AB10: 1 | AC10: MRP&Rollup | AD10: CBESFG | AE10: 30 | AF10: I | AG10: RML-NWN-70GSMX76" | AH10: NON WOVEN FABRIC WHITE 70 GSM 76 INCH | AI10: KGS | AJ10: 0.133 | AK10: CBEWIP | AL10: Backflush | AM10: Active | AN10: =AJ10 -> 0.133 | AO10: =VLOOKUP(AG10,'RM-cost - feb-24'!B:P,15,0) -> 112.8872 | AP10: =AO10*AN10 -> 15.013998 | AS10: =AS9 -> 134
A11: 4 | B11: =B10 -> 2 | C11: =C10 -> ET-COVER | D11: =MID(E11,9,2) -> PT | E11: =E10 -> RTHTMTBNPT72X39X10 | F11: =F10 -> RTHTMTBNPT | G11: =G10 -> 72X39X10 | H11: =H10 -> 72X39X10 | I11: =I10 -> 3 | J11: =J10 -> 6 | K11: =K10 -> 72 | L11: =L10 -> 39 | M11: =M10 -> 10 | N11: ="SFG-FRBNPK-ET-CVR-"&K11&"X"&L11&"X"&M11 -> SFG-FRBNPK-ET-CVR-72X39X10 | P11: =ROUND(((((K11+L11+K11+L11)+3))*0.0254),3) -> 5.715 | Q11: =P11=AJ11 -> TRUE | S11: ="Restonic Hotel Motel ET Cover "&K11&"X"&L11&"X"&M11 -> Restonic Hotel Motel ET Cover 72X39X10 | T11: =T10 -> SFG-FRBNPK-ET-CVR-72X39X10 | U11: =T11=N11 -> TRUE | V11: =S11=W11 -> TRUE | W11: =W10 -> Restonic Hotel Motel ET Cover 72X39X10 | X11: Standard | Y11: Production | Z11: TAIL-ET-PT | AA11: NOS | AB11: 1 | AC11: MRP&Rollup | AD11: CBESFG | AE11: 40 | AF11: I | AG11: SFG-RTHTMT-BNPK-ETBOR-11CM | AH11: Hotel Motel Poc ET-10 & 12 8MM/16D Pre Foam Border 11 CM Height | AI11: MTR | AJ11: =P11 -> 5.715 | AK11: CBESFG | AL11: Backflush | AM11: Active | AN11: =AJ11 -> 5.715 | AO11: =VLOOKUP(AG11,'SFG-rate rm - feb-24'!A:B,2,0) -> 19.60538 | AP11: =AO11*AN11 -> 112.04475 | AS11: =AS10 -> 134
A12: 5 | B12: =B11 -> 2 | C12: =C11 -> ET-COVER | D12: =MID(E12,9,2) -> PT | E12: =E11 -> RTHTMTBNPT72X39X10 | F12: =F11 -> RTHTMTBNPT | G12: =G11 -> 72X39X10 | H12: =H11 -> 72X39X10 | I12: =I11 -> 3 | J12: =J11 -> 6 | K12: =K11 -> 72 | L12: =L11 -> 39 | M12: =M11 -> 10 | N12: ="SFG-FRBNPK-ET-CVR-"&K12&"X"&L12&"X"&M12 -> SFG-FRBNPK-ET-CVR-72X39X10 | P12: 10 | Q12: =P12=AJ12 -> TRUE | S12: ="Restonic Hotel Motel ET Cover "&K12&"X"&L12&"X"&M12 -> Restonic Hotel Motel ET Cover 72X39X10 | T12: =T11 -> SFG-FRBNPK-ET-CVR-72X39X10 | U12: =T12=N12 -> TRUE | V12: =S12=W12 -> TRUE | W12: =W11 -> Restonic Hotel Motel ET Cover 72X39X10 | X12: Standard | Y12: Production | Z12: TAIL-ET-PT | AA12: NOS | AB12: 1 | AC12: MRP&Rollup | AD12: CBESFG | AE12: 50 | AF12: I | AG12: HW-CTON-THREAD | AH12: COTTON THREAD WHITE 3PLY | AI12: MTR | AJ12: =P12 -> 10 | AK12: CBEWIP | AL12: Backflush | AM12: Active | AN12: =AJ12/5000 -> 0.002 | AO12: =VLOOKUP(AG12,'RM-cost - feb-24'!B:P,15,0) -> 58 | AP12: =AO12*AN12 -> 0.116 | AS12: =AS11 -> 134
A14: 1 | B14: 3 | C14: ET-COVER | D14: =MID(E14,9,2) -> PT | E14: RTHTMTBNPT72X45X10 | F14: =LEFT(E14,MIN(FIND({0,1,2,3,4,5,6,7,8,9},E14&"0123456789"))-1) -> RTHTMTBNPT | G14: =SUBSTITUTE(E14,F14,"") -> 72X45X10 | H14: =IFERROR(LEFT(G14,FIND("-",G14)-1),G14) -> 72X45X10 | I14: =SEARCH("X",H14) -> 3 | J14: =SEARCH("X",H14,I14+1) -> 6 | K14: =LEFT(G14,SEARCH("x",G14)-1) -> 72 | L14: =MID(H14,I14+1,J14-I14-1) -> 45 | M14: =MID(H14,J14+1,20) -> 10 | N14: ="SFG-FRBNPK-ET-CVR-"&K14&"X"&L14&"X"&M14 -> SFG-FRBNPK-ET-CVR-72X45X10 | P14: =ROUND(((((K14+L14+K14+L14)+3)*0.0254)*5.3196),3) -> 32.023 | Q14: 0 | R14: =P14+Q14 -> 32.023 | S14: ="Restonic Hotel Motel ET Cover "&K14&"X"&L14&"X"&M14 -> Restonic Hotel Motel ET Cover 72X45X10 | T14: =N14 -> SFG-FRBNPK-ET-CVR-72X45X10 | U14: =T14=N14 -> TRUE | V14: =S14=W14 -> TRUE | W14: =S14 -> Restonic Hotel Motel ET Cover 72X45X10 | X14: Standard | Y14: Production | Z14: TAIL-ET-PT | AA14: NOS | AB14: 1 | AC14: MRP&Rollup | AD14: CBESFG | AE14: 10 | AF14: I | AG14: RM-THRD-QS-TKT40 | AH14: THREAD TKT40 210D/3 PLY 10000MTS | AI14: MTR | AJ14: =R14 -> 32.023 | AK14: CBEWIP | AL14: Backflush | AM14: Active | AN14: =AJ14/10000 -> 0.0032023 | AO14: =VLOOKUP(AG14,'RM-cost - feb-24'!B:P,15,0) -> 231.1423 | AP14: =AO14*AN14 -> 0.74018699 | AQ14: =SUM(AP14:AP18) -> 143.20345 | AR14: =ROUND(AQ14,0) -> 143 | AS14: =AR14 -> 143 | AT14: =+AS14+AY14 -> 160.69611 | AU14: =+SUM(((AS14*3%*18%))) -> 0.7722 | AV14: =+SUM(((AS14*14.33%*53%))) -> 10.860707 | AW14: =+SUM(((AS14*5.92%*53%))) -> 4.486768 | AX14: =+SUM(((AS14*2.08%*53%))) -> 1.576432 | AY14: =SUM(AU14:AX18) -> 17.696107 | AZ14: =ROUNDUP(AT14,0) -> 161 | BA14: =AZ14 -> 161
A15: 2 | B15: =B14 -> 3 | C15: =C14 -> ET-COVER | D15: =MID(E15,9,2) -> PT | E15: =E14 -> RTHTMTBNPT72X45X10 | F15: =F14 -> RTHTMTBNPT | G15: =G14 -> 72X45X10 | H15: =H14 -> 72X45X10 | I15: =I14 -> 3 | J15: =J14 -> 6 | K15: =K14 -> 72 | L15: =L14 -> 45 | M15: =M14 -> 10 | N15: ="SFG-FRBNPK-ET-CVR-"&K15&"X"&L15&"X"&M15 -> SFG-FRBNPK-ET-CVR-72X45X10 | O15: =K15*L15/144 -> 22.5 | P15: =ROUNDUP((((K15*L15/144)*0.003)),3) -> 0.068 | S15: ="Restonic Hotel Motel ET Cover "&K15&"X"&L15&"X"&M15 -> Restonic Hotel Motel ET Cover 72X45X10 | T15: =T14 -> SFG-FRBNPK-ET-CVR-72X45X10 | U15: =T15=N15 -> TRUE | V15: =S15=W15 -> TRUE | W15: =W14 -> Restonic Hotel Motel ET Cover 72X45X10 | X15: Standard | Y15: Production | Z15: TAIL-ET-PT | AA15: NOS | AB15: 1 | AC15: MRP&Rollup | AD15: CBESFG | AE15: 20 | AF15: I | AG15: RM-NWN-70GSMX6INCH | AH15: NON WOVEN FABRIC 70GSMX6" | AI15: KGS | AJ15: 0.058 | AK15: CBEWIP | AL15: Backflush | AM15: Active | AN15: =AJ15 -> 0.058 | AO15: =VLOOKUP(AG15,'RM-cost - feb-24'!B:P,15,0) -> 113.786 | AP15: =AO15*AN15 -> 6.599588 | AS15: =AS14 -> 143
A16: 3 | B16: =B15 -> 3 | C16: =C15 -> ET-COVER | D16: =MID(E16,9,2) -> PT | E16: =E15 -> RTHTMTBNPT72X45X10 | F16: =F15 -> RTHTMTBNPT | G16: =G15 -> 72X45X10 | H16: =H15 -> 72X45X10 | I16: =I15 -> 3 | J16: =J15 -> 6 | K16: =K15 -> 72 | L16: =L15 -> 45 | M16: =M15 -> 10 | N16: ="SFG-FRBNPK-ET-CVR-"&K16&"X"&L16&"X"&M16 -> SFG-FRBNPK-ET-CVR-72X45X10 | P16: =ROUNDUP((((K16*L16/144)*0.00692)),3) -> 0.156 | Q16: =P16=AJ16 -> FALSE | S16: ="Restonic Hotel Motel ET Cover "&K16&"X"&L16&"X"&M16 -> Restonic Hotel Motel ET Cover 72X45X10 | T16: =T15 -> SFG-FRBNPK-ET-CVR-72X45X10 | U16: =T16=N16 -> TRUE | V16: =S16=W16 -> TRUE | W16: =W15 -> Restonic Hotel Motel ET Cover 72X45X10 | X16: Standard | Y16: Production | Z16: TAIL-ET-PT | AA16: NOS | AB16: 1 | AC16: MRP&Rollup | AD16: CBESFG | AE16: 30 | AF16: I | AG16: RML-NWN-70GSMX76" | AH16: NON WOVEN FABRIC WHITE 70 GSM 76 INCH | AI16: KGS | AJ16: 0.157 | AK16: CBEWIP | AL16: Backflush | AM16: Active | AN16: =AJ16 -> 0.157 | AO16: =VLOOKUP(AG16,'RM-cost - feb-24'!B:P,15,0) -> 112.8872 | AP16: =AO16*AN16 -> 17.72329 | AS16: =AS15 -> 143
A17: 4 | B17: =B16 -> 3 | C17: =C16 -> ET-COVER | D17: =MID(E17,9,2) -> PT | E17: =E16 -> RTHTMTBNPT72X45X10 | F17: =F16 -> RTHTMTBNPT | G17: =G16 -> 72X45X10 | H17: =H16 -> 72X45X10 | I17: =I16 -> 3 | J17: =J16 -> 6 | K17: =K16 -> 72 | L17: =L16 -> 45 | M17: =M16 -> 10 | N17: ="SFG-FRBNPK-ET-CVR-"&K17&"X"&L17&"X"&M17 -> SFG-FRBNPK-ET-CVR-72X45X10 | P17: =ROUND(((((K17+L17+K17+L17)+3))*0.0254),3) -> 6.02 | Q17: =P17=AJ17 -> TRUE | S17: ="Restonic Hotel Motel ET Cover "&K17&"X"&L17&"X"&M17 -> Restonic Hotel Motel ET Cover 72X45X10 | T17: =T16 -> SFG-FRBNPK-ET-CVR-72X45X10 | U17: =T17=N17 -> TRUE | V17: =S17=W17 -> TRUE | W17: =W16 -> Restonic Hotel Motel ET Cover 72X45X10 | X17: Standard | Y17: Production | Z17: TAIL-ET-PT | AA17: NOS | AB17: 1 | AC17: MRP&Rollup | AD17: CBESFG | AE17: 40 | AF17: I | AG17: SFG-RTHTMT-BNPK-ETBOR-11CM | AH17: Hotel Motel Poc ET-10 & 12 8MM/16D Pre Foam Border 11 CM Height | AI17: MTR | AJ17: =P17 -> 6.02 | AK17: CBESFG | AL17: Backflush | AM17: Active | AN17: =AJ17 -> 6.02 | AO17: =VLOOKUP(AG17,'SFG-rate rm - feb-24'!A:B,2,0) -> 19.60538 | AP17: =AO17*AN17 -> 118.02439 | AS17: =AS16 -> 143
A18: 5 | B18: =B17 -> 3 | C18: =C17 -> ET-COVER | D18: =MID(E18,9,2) -> PT | E18: =E17 -> RTHTMTBNPT72X45X10 | F18: =F17 -> RTHTMTBNPT | G18: =G17 -> 72X45X10 | H18: =H17 -> 72X45X10 | I18: =I17 -> 3 | J18: =J17 -> 6 | K18: =K17 -> 72 | L18: =L17 -> 45 | M18: =M17 -> 10 | N18: ="SFG-FRBNPK-ET-CVR-"&K18&"X"&L18&"X"&M18 -> SFG-FRBNPK-ET-CVR-72X45X10 | P18: 10 | Q18: =P18=AJ18 -> TRUE | S18: ="Restonic Hotel Motel ET Cover "&K18&"X"&L18&"X"&M18 -> Restonic Hotel Motel ET Cover 72X45X10 | T18: =T17 -> SFG-FRBNPK-ET-CVR-72X45X10 | U18: =T18=N18 -> TRUE | V18: =S18=W18 -> TRUE | W18: =W17 -> Restonic Hotel Motel ET Cover 72X45X10 | X18: Standard | Y18: Production | Z18: TAIL-ET-PT | AA18: NOS | AB18: 1 | AC18: MRP&Rollup | AD18: CBESFG | AE18: 50 | AF18: I | AG18: HW-CTON-THREAD | AH18: COTTON THREAD WHITE 3PLY | AI18: MTR | AJ18: =P18 -> 10 | AK18: CBEWIP | AL18: Backflush | AM18: Active | AN18: =AJ18/5000 -> 0.002 | AO18: =VLOOKUP(AG18,'RM-cost - feb-24'!B:P,15,0) -> 58 | AP18: =AO18*AN18 -> 0.116 | AS18: =AS17 -> 143
A20: 1 | B20: 4 | C20: ET-COVER | D20: =MID(E20,9,2) -> PT | E20: RTHTMTBNPT72X51X10 | F20: =LEFT(E20,MIN(FIND({0,1,2,3,4,5,6,7,8,9},E20&"0123456789"))-1) -> RTHTMTBNPT | G20: =SUBSTITUTE(E20,F20,"") -> 72X51X10 | H20: =IFERROR(LEFT(G20,FIND("-",G20)-1),G20) -> 72X51X10 | I20: =SEARCH("X",H20) -> 3 | J20: =SEARCH("X",H20,I20+1) -> 6 | K20: =LEFT(G20,SEARCH("x",G20)-1) -> 72 | L20: =MID(H20,I20+1,J20-I20-1) -> 51 | M20: =MID(H20,J20+1,20) -> 10 | N20: ="SFG-FRBNPK-ET-CVR-"&K20&"X"&L20&"X"&M20 -> SFG-FRBNPK-ET-CVR-72X51X10 | P20: =ROUND(((((K20+L20+K20+L20)+3)*0.0254)*5.3196),3) -> 33.644 | Q20: 0 | R20: =P20+Q20 -> 33.644 | S20: ="Restonic Hotel Motel ET Cover "&K20&"X"&L20&"X"&M20 -> Restonic Hotel Motel ET Cover 72X51X10 | T20: =N20 -> SFG-FRBNPK-ET-CVR-72X51X10 | U20: =T20=N20 -> TRUE | V20: =S20=W20 -> TRUE | W20: =S20 -> Restonic Hotel Motel ET Cover 72X51X10 | X20: Standard | Y20: Production | Z20: TAIL-ET-PT | AA20: NOS | AB20: 1 | AC20: MRP&Rollup | AD20: CBESFG | AE20: 10 | AF20: I | AG20: RM-THRD-QS-TKT40 | AH20: THREAD TKT40 210D/3 PLY 10000MTS | AI20: MTR | AJ20: =R20 -> 33.644 | AK20: CBEWIP | AL20: Backflush | AM20: Active | AN20: =AJ20/10000 -> 0.0033644 | AO20: =VLOOKUP(AG20,'RM-cost - feb-24'!B:P,15,0) -> 231.1423 | AP20: =AO20*AN20 -> 0.77765515 | AQ20: =SUM(AP20:AP24) -> 151.36812 | AR20: =ROUND(AQ20,0) -> 151 | AS20: =AR20 -> 151 | AT20: =+AS20+AY20 -> 169.6861 | AU20: =+SUM(((AS20*3%*18%))) -> 0.8154 | AV20: =+SUM(((AS20*14.33%*53%))) -> 11.468299 | AW20: =+SUM(((AS20*5.92%*53%))) -> 4.737776 | AX20: =+SUM(((AS20*2.08%*53%))) -> 1.664624 | AY20: =SUM(AU20:AX24) -> 18.686099 | AZ20: =ROUNDUP(AT20,0) -> 170 | BA20: =AZ20 -> 170
A21: 2 | B21: =B20 -> 4 | C21: =C20 -> ET-COVER | D21: =MID(E21,9,2) -> PT | E21: =E20 -> RTHTMTBNPT72X51X10 | F21: =F20 -> RTHTMTBNPT | G21: =G20 -> 72X51X10 | H21: =H20 -> 72X51X10 | I21: =I20 -> 3 | J21: =J20 -> 6 | K21: =K20 -> 72 | L21: =L20 -> 51 | M21: =M20 -> 10 | N21: ="SFG-FRBNPK-ET-CVR-"&K21&"X"&L21&"X"&M21 -> SFG-FRBNPK-ET-CVR-72X51X10 | O21: =K21*L21/144 -> 25.5 | P21: =ROUNDUP((((K21*L21/144)*0.003)),3) -> 0.077 | S21: ="Restonic Hotel Motel ET Cover "&K21&"X"&L21&"X"&M21 -> Restonic Hotel Motel ET Cover 72X51X10 | T21: =T20 -> SFG-FRBNPK-ET-CVR-72X51X10 | U21: =T21=N21 -> TRUE | V21: =S21=W21 -> TRUE | W21: =W20 -> Restonic Hotel Motel ET Cover 72X51X10 | X21: Standard | Y21: Production | Z21: TAIL-ET-PT | AA21: NOS | AB21: 1 | AC21: MRP&Rollup | AD21: CBESFG | AE21: 20 | AF21: I | AG21: RM-NWN-70GSMX6INCH | AH21: NON WOVEN FABRIC 70GSMX6" | AI21: KGS | AJ21: 0.061 | AK21: CBEWIP | AL21: Backflush | AM21: Active | AN21: =AJ21 -> 0.061 | AO21: =VLOOKUP(AG21,'RM-cost - feb-24'!B:P,15,0) -> 113.786 | AP21: =AO21*AN21 -> 6.940946 | AS21: =AS20 -> 151
A22: 3 | B22: =B21 -> 4 | C22: =C21 -> ET-COVER | D22: =MID(E22,9,2) -> PT | E22: =E21 -> RTHTMTBNPT72X51X10 | F22: =F21 -> RTHTMTBNPT | G22: =G21 -> 72X51X10 | H22: =H21 -> 72X51X10 | I22: =I21 -> 3 | J22: =J21 -> 6 | K22: =K21 -> 72 | L22: =L21 -> 51 | M22: =M21 -> 10 | N22: ="SFG-FRBNPK-ET-CVR-"&K22&"X"&L22&"X"&M22 -> SFG-FRBNPK-ET-CVR-72X51X10 | P22: =ROUNDUP((((K22*L22/144)*0.00692)),3) -> 0.177 | Q22: =P22=AJ22 -> FALSE | S22: ="Restonic Hotel Motel ET Cover "&K22&"X"&L22&"X"&M22 -> Restonic Hotel Motel ET Cover 72X51X10 | T22: =T21 -> SFG-FRBNPK-ET-CVR-72X51X10 | U22: =T22=N22 -> TRUE | V22: =S22=W22 -> TRUE | W22: =W21 -> Restonic Hotel Motel ET Cover 72X51X10 | X22: Standard | Y22: Production | Z22: TAIL-ET-PT | AA22: NOS | AB22: 1 | AC22: MRP&Rollup | AD22: CBESFG | AE22: 30 | AF22: I | AG22: RML-NWN-70GSMX76" | AH22: NON WOVEN FABRIC WHITE 70 GSM 76 INCH | AI22: KGS | AJ22: 0.173 | AK22: CBEWIP | AL22: Backflush | AM22: Active | AN22: =AJ22 -> 0.173 | AO22: =VLOOKUP(AG22,'RM-cost - feb-24'!B:P,15,0) -> 112.8872 | AP22: =AO22*AN22 -> 19.529486 | AS22: =AS21 -> 151
A23: 4 | B23: =B22 -> 4 | C23: =C22 -> ET-COVER | D23: =MID(E23,9,2) -> PT | E23: =E22 -> RTHTMTBNPT72X51X10 | F23: =F22 -> RTHTMTBNPT | G23: =G22 -> 72X51X10 | H23: =H22 -> 72X51X10 | I23: =I22 -> 3 | J23: =J22 -> 6 | K23: =K22 -> 72 | L23: =L22 -> 51 | M23: =M22 -> 10 | N23: ="SFG-FRBNPK-ET-CVR-"&K23&"X"&L23&"X"&M23 -> SFG-FRBNPK-ET-CVR-72X51X10 | P23: =ROUND(((((K23+L23+K23+L23)+3))*0.0254),3) -> 6.325 | Q23: =P23=AJ23 -> TRUE | S23: ="Restonic Hotel Motel ET Cover "&K23&"X"&L23&"X"&M23 -> Restonic Hotel Motel ET Cover 72X51X10 | T23: =T22 -> SFG-FRBNPK-ET-CVR-72X51X10 | U23: =T23=N23 -> TRUE | V23: =S23=W23 -> TRUE | W23: =W22 -> Restonic Hotel Motel ET Cover 72X51X10 | X23: Standard | Y23: Production | Z23: TAIL-ET-PT | AA23: NOS | AB23: 1 | AC23: MRP&Rollup | AD23: CBESFG | AE23: 40 | AF23: I | AG23: SFG-RTHTMT-BNPK-ETBOR-11CM | AH23: Hotel Motel Poc ET-10 & 12 8MM/16D Pre Foam Border 11 CM Height | AI23: MTR | AJ23: =P23 -> 6.325 | AK23: CBESFG | AL23: Backflush | AM23: Active | AN23: =AJ23 -> 6.325 | AO23: =VLOOKUP(AG23,'SFG-rate rm - feb-24'!A:B,2,0) -> 19.60538 | AP23: =AO23*AN23 -> 124.00403 | AS23: =AS22 -> 151
A24: 5 | B24: =B23 -> 4 | C24: =C23 -> ET-COVER | D24: =MID(E24,9,2) -> PT | E24: =E23 -> RTHTMTBNPT72X51X10 | F24: =F23 -> RTHTMTBNPT | G24: =G23 -> 72X51X10 | H24: =H23 -> 72X51X10 | I24: =I23 -> 3 | J24: =J23 -> 6 | K24: =K23 -> 72 | L24: =L23 -> 51 | M24: =M23 -> 10 | N24: ="SFG-FRBNPK-ET-CVR-"&K24&"X"&L24&"X"&M24 -> SFG-FRBNPK-ET-CVR-72X51X10 | P24: 10 | Q24: =P24=AJ24 -> TRUE | S24: ="Restonic Hotel Motel ET Cover "&K24&"X"&L24&"X"&M24 -> Restonic Hotel Motel ET Cover 72X51X10 | T24: =T23 -> SFG-FRBNPK-ET-CVR-72X51X10 | U24: =T24=N24 -> TRUE | V24: =S24=W24 -> TRUE | W24: =W23 -> Restonic Hotel Motel ET Cover 72X51X10 | X24: Standard | Y24: Production | Z24: TAIL-ET-PT | AA24: NOS | AB24: 1 | AC24: MRP&Rollup | AD24: CBESFG | AE24: 50 | AF24: I | AG24: HW-CTON-THREAD | AH24: COTTON THREAD WHITE 3PLY | AI24: MTR | AJ24: =P24 -> 10 | AK24: CBEWIP | AL24: Backflush | AM24: Active | AN24: =AJ24/5000 -> 0.002 | AO24: =VLOOKUP(AG24,'RM-cost - feb-24'!B:P,15,0) -> 58 | AP24: =AO24*AN24 -> 0.116 | AS24: =AS23 -> 151
A26: 1 | B26: 5 | C26: ET-COVER | D26: =MID(E26,9,2) -> PT | E26: RTHTMTBNPT72X54X10 | F26: =LEFT(E26,MIN(FIND({0,1,2,3,4,5,6,7,8,9},E26&"0123456789"))-1) -> RTHTMTBNPT | G26: =SUBSTITUTE(E26,F26,"") -> 72X54X10 | H26: =IFERROR(LEFT(G26,FIND("-",G26)-1),G26) -> 72X54X10 | I26: =SEARCH("X",H26) -> 3 | J26: =SEARCH("X",H26,I26+1) -> 6 | K26: =LEFT(G26,SEARCH("x",G26)-1) -> 72 | L26: =MID(H26,I26+1,J26-I26-1) -> 54 | M26: =MID(H26,J26+1,20) -> 10 | N26: ="SFG-FRBNPK-ET-CVR-"&K26&"X"&L26&"X"&M26 -> SFG-FRBNPK-ET-CVR-72X54X10 | P26: =ROUND(((((K26+L26+K26+L26)+3)*0.0254)*5.3196),3) -> 34.455 | Q26: 0 | R26: =P26+Q26 -> 34.455 | S26: ="Restonic Hotel Motel ET Cover "&K26&"X"&L26&"X"&M26 -> Restonic Hotel Motel ET Cover 72X54X10 | T26: =N26 -> SFG-FRBNPK-ET-CVR-72X54X10 | U26: =T26=N26 -> TRUE | V26: =S26=W26 -> TRUE | W26: =S26 -> Restonic Hotel Motel ET Cover 72X54X10 | X26: Standard | Y26: Production | Z26: TAIL-ET-PT | AA26: NOS | AB26: 1 | AC26: MRP&Rollup | AD26: CBESFG | AE26: 10 | AF26: I | AG26: RM-THRD-QS-TKT40 | AH26: THREAD TKT40 210D/3 PLY 10000MTS | AI26: MTR | AJ26: =R26 -> 34.455 | AK26: CBEWIP | AL26: Backflush | AM26: Active | AN26: =AJ26/10000 -> 0.0034455 | AO26: =VLOOKUP(AG26,'RM-cost - feb-24'!B:P,15,0) -> 231.1423 | AP26: =AO26*AN26 -> 0.79640079 | AQ26: =SUM(AP26:AP30) -> 155.9491 | AR26: =ROUND(AQ26,0) -> 156 | AS26: =AR26 -> 156 | AT26: =+AS26+AY26 -> 175.30484 | AU26: =+SUM(((AS26*3%*18%))) -> 0.8424 | AV26: =+SUM(((AS26*14.33%*53%))) -> 11.848044 | AW26: =+SUM(((AS26*5.92%*53%))) -> 4.894656 | AX26: =+SUM(((AS26*2.08%*53%))) -> 1.719744 | AY26: =SUM(AU26:AX30) -> 19.304844 | AZ26: =ROUNDUP(AT26,0) -> 176 | BA26: =AZ26 -> 176
A27: 2 | B27: =B26 -> 5 | C27: =C26 -> ET-COVER | D27: =MID(E27,9,2) -> PT | E27: =E26 -> RTHTMTBNPT72X54X10 | F27: =F26 -> RTHTMTBNPT | G27: =G26 -> 72X54X10 | H27: =H26 -> 72X54X10 | I27: =I26 -> 3 | J27: =J26 -> 6 | K27: =K26 -> 72 | L27: =L26 -> 54 | M27: =M26 -> 10 | N27: ="SFG-FRBNPK-ET-CVR-"&K27&"X"&L27&"X"&M27 -> SFG-FRBNPK-ET-CVR-72X54X10 | O27: =K27*L27/144 -> 27 | P27: =ROUNDUP((((K27*L27/144)*0.003)),3) -> 0.081 | S27: ="Restonic Hotel Motel ET Cover "&K27&"X"&L27&"X"&M27 -> Restonic Hotel Motel ET Cover 72X54X10 | T27: =T26 -> SFG-FRBNPK-ET-CVR-72X54X10 | U27: =T27=N27 -> TRUE | V27: =S27=W27 -> TRUE | W27: =W26 -> Restonic Hotel Motel ET Cover 72X54X10 | X27: Standard | Y27: Production | Z27: TAIL-ET-PT | AA27: NOS | AB27: 1 | AC27: MRP&Rollup | AD27: CBESFG | AE27: 20 | AF27: I | AG27: RM-NWN-70GSMX6INCH | AH27: NON WOVEN FABRIC 70GSMX6" | AI27: KGS | AJ27: 0.063 | AK27: CBEWIP | AL27: Backflush | AM27: Active | AN27: =AJ27 -> 0.063 | AO27: =VLOOKUP(AG27,'RM-cost - feb-24'!B:P,15,0) -> 113.786 | AP27: =AO27*AN27 -> 7.168518 | AS27: =AS26 -> 156
A28: 3 | B28: =B27 -> 5 | C28: =C27 -> ET-COVER | D28: =MID(E28,9,2) -> PT | E28: =E27 -> RTHTMTBNPT72X54X10 | F28: =F27 -> RTHTMTBNPT | G28: =G27 -> 72X54X10 | H28: =H27 -> 72X54X10 | I28: =I27 -> 3 | J28: =J27 -> 6 | K28: =K27 -> 72 | L28: =L27 -> 54 | M28: =M27 -> 10 | N28: ="SFG-FRBNPK-ET-CVR-"&K28&"X"&L28&"X"&M28 -> SFG-FRBNPK-ET-CVR-72X54X10 | P28: =ROUNDUP((((K28*L28/144)*0.00692)),3) -> 0.187 | Q28: =P28=AJ28 -> FALSE | S28: ="Restonic Hotel Motel ET Cover "&K28&"X"&L28&"X"&M28 -> Restonic Hotel Motel ET Cover 72X54X10 | T28: =T27 -> SFG-FRBNPK-ET-CVR-72X54X10 | U28: =T28=N28 -> TRUE | V28: =S28=W28 -> TRUE | W28: =W27 -> Restonic Hotel Motel ET Cover 72X54X10 | X28: Standard | Y28: Production | Z28: TAIL-ET-PT | AA28: NOS | AB28: 1 | AC28: MRP&Rollup | AD28: CBESFG | AE28: 30 | AF28: I | AG28: RML-NWN-70GSMX76" | AH28: NON WOVEN FABRIC WHITE 70 GSM 76 INCH | AI28: KGS | AJ28: 0.185 | AK28: CBEWIP | AL28: Backflush | AM28: Active | AN28: =AJ28 -> 0.185 | AO28: =VLOOKUP(AG28,'RM-cost - feb-24'!B:P,15,0) -> 112.8872 | AP28: =AO28*AN28 -> 20.884132 | AS28: =AS27 -> 156
A29: 4 | B29: =B28 -> 5 | C29: =C28 -> ET-COVER | D29: =MID(E29,9,2) -> PT | E29: =E28 -> RTHTMTBNPT72X54X10 | F29: =F28 -> RTHTMTBNPT | G29: =G28 -> 72X54X10 | H29: =H28 -> 72X54X10 | I29: =I28 -> 3 | J29: =J28 -> 6 | K29: =K28 -> 72 | L29: =L28 -> 54 | M29: =M28 -> 10 | N29: ="SFG-FRBNPK-ET-CVR-"&K29&"X"&L29&"X"&M29 -> SFG-FRBNPK-ET-CVR-72X54X10 | P29: =ROUND(((((K29+L29+K29+L29)+3))*0.0254),3) -> 6.477 | Q29: =P29=AJ29 -> TRUE | S29: ="Restonic Hotel Motel ET Cover "&K29&"X"&L29&"X"&M29 -> Restonic Hotel Motel ET Cover 72X54X10 | T29: =T28 -> SFG-FRBNPK-ET-CVR-72X54X10 | U29: =T29=N29 -> TRUE | V29: =S29=W29 -> TRUE | W29: =W28 -> Restonic Hotel Motel ET Cover 72X54X10 | X29: Standard | Y29: Production | Z29: TAIL-ET-PT | AA29: NOS | AB29: 1 | AC29: MRP&Rollup | AD29: CBESFG | AE29: 40 | AF29: I | AG29: SFG-RTHTMT-BNPK-ETBOR-11CM | AH29: Hotel Motel Poc ET-10 & 12 8MM/16D Pre Foam Border 11 CM Height | AI29: MTR | AJ29: =P29 -> 6.477 | AK29: CBESFG | AL29: Backflush | AM29: Active | AN29: =AJ29 -> 6.477 | AO29: =VLOOKUP(AG29,'SFG-rate rm - feb-24'!A:B,2,0) -> 19.60538 | AP29: =AO29*AN29 -> 126.98405 | AS29: =AS28 -> 156
A30: 5 | B30: =B29 -> 5 | C30: =C29 -> ET-COVER | D30: =MID(E30,9,2) -> PT | E30: =E29 -> RTHTMTBNPT72X54X10 | F30: =F29 -> RTHTMTBNPT | G30: =G29 -> 72X54X10 | H30: =H29 -> 72X54X10 | I30: =I29 -> 3 | J30: =J29 -> 6 | K30: =K29 -> 72 | L30: =L29 -> 54 | M30: =M29 -> 10 | N30: ="SFG-FRBNPK-ET-CVR-"&K30&"X"&L30&"X"&M30 -> SFG-FRBNPK-ET-CVR-72X54X10 | P30: 10 | Q30: =P30=AJ30 -> TRUE | S30: ="Restonic Hotel Motel ET Cover "&K30&"X"&L30&"X"&M30 -> Restonic Hotel Motel ET Cover 72X54X10 | T30: =T29 -> SFG-FRBNPK-ET-CVR-72X54X10 | U30: =T30=N30 -> TRUE | V30: =S30=W30 -> TRUE | W30: =W29 -> Restonic Hotel Motel ET Cover 72X54X10 | X30: Standard | Y30: Production | Z30: TAIL-ET-PT | AA30: NOS | AB30: 1 | AC30: MRP&Rollup | AD30: CBESFG | AE30: 50 | AF30: I | AG30: HW-CTON-THREAD | AH30: COTTON THREAD WHITE 3PLY | AI30: MTR | AJ30: =P30 -> 10 | AK30: CBEWIP | AL30: Backflush | AM30: Active | AN30: =AJ30/5000 -> 0.002 | AO30: =VLOOKUP(AG30,'RM-cost - feb-24'!B:P,15,0) -> 58 | AP30: =AO30*AN30 -> 0.116 | AS30: =AS29 -> 156
A32: 1 | B32: 6 | C32: ET-COVER | D32: =MID(E32,9,2) -> PT | E32: RTHTMTBNPT72X57X10 | F32: =LEFT(E32,MIN(FIND({0,1,2,3,4,5,6,7,8,9},E32&"0123456789"))-1) -> RTHTMTBNPT | G32: =SUBSTITUTE(E32,F32,"") -> 72X57X10 | H32: =IFERROR(LEFT(G32,FIND("-",G32)-1),G32) -> 72X57X10 | I32: =SEARCH("X",H32) -> 3 | J32: =SEARCH("X",H32,I32+1) -> 6 | K32: =LEFT(G32,SEARCH("x",G32)-1) -> 72 | L32: =MID(H32,I32+1,J32-I32-1) -> 57 | M32: =MID(H32,J32+1,20) -> 10 | N32: ="SFG-FRBNPK-ET-CVR-"&K32&"X"&L32&"X"&M32 -> SFG-FRBNPK-ET-CVR-72X57X10 | P32: =ROUND(((((K32+L32+K32+L32)+3)*0.0254)*5.3196),3) -> 35.266 | Q32: 0 | R32: =P32+Q32 -> 35.266 | S32: ="Restonic Hotel Motel ET Cover "&K32&"X"&L32&"X"&M32 -> Restonic Hotel Motel ET Cover 72X57X10 | T32: =N32 -> SFG-FRBNPK-ET-CVR-72X57X10 | U32: =T32=N32 -> TRUE | V32: =S32=W32 -> TRUE | W32: =S32 -> Restonic Hotel Motel ET Cover 72X57X10 | X32: Standard | Y32: Production | Z32: TAIL-ET-PT | AA32: NOS | AB32: 1 | AC32: MRP&Rollup | AD32: CBESFG | AE32: 10 | AF32: I | AG32: RM-THRD-QS-TKT40 | AH32: THREAD TKT40 210D/3 PLY 10000MTS | AI32: MTR | AJ32: =R32 -> 35.266 | AK32: CBEWIP | AL32: Backflush | AM32: Active | AN32: =AJ32/10000 -> 0.0035266 | AO32: =VLOOKUP(AG32,'RM-cost - feb-24'!B:P,15,0) -> 231.1423 | AP32: =AO32*AN32 -> 0.81514644 | AQ32: =SUM(AP32:AP36) -> 160.41719 | AR32: =ROUND(AQ32,0) -> 160 | AS32: =AR32 -> 160 | AT32: =+AS32+AY32 -> 179.79984 | AU32: =+SUM(((AS32*3%*18%))) -> 0.864 | AV32: =+SUM(((AS32*14.33%*53%))) -> 12.15184 | AW32: =+SUM(((AS32*5.92%*53%))) -> 5.02016 | AX32: =+SUM(((AS32*2.08%*53%))) -> 1.76384 | AY32: =SUM(AU32:AX36) -> 19.79984 | AZ32: =ROUNDUP(AT32,0) -> 180 | BA32: =AZ32 -> 180
A33: 2 | B33: =B32 -> 6 | C33: =C32 -> ET-COVER | D33: =MID(E33,9,2) -> PT | E33: =E32 -> RTHTMTBNPT72X57X10 | F33: =F32 -> RTHTMTBNPT | G33: =G32 -> 72X57X10 | H33: =H32 -> 72X57X10 | I33: =I32 -> 3 | J33: =J32 -> 6 | K33: =K32 -> 72 | L33: =L32 -> 57 | M33: =M32 -> 10 | N33: ="SFG-FRBNPK-ET-CVR-"&K33&"X"&L33&"X"&M33 -> SFG-FRBNPK-ET-CVR-72X57X10 | O33: =K33*L33/144 -> 28.5 | P33: =ROUNDUP((((K33*L33/144)*0.003)),3) -> 0.086 | S33: ="Restonic Hotel Motel ET Cover "&K33&"X"&L33&"X"&M33 -> Restonic Hotel Motel ET Cover 72X57X10 | T33: =T32 -> SFG-FRBNPK-ET-CVR-72X57X10 | U33: =T33=N33 -> TRUE | V33: =S33=W33 -> TRUE | W33: =W32 -> Restonic Hotel Motel ET Cover 72X57X10 | X33: Standard | Y33: Production | Z33: TAIL-ET-PT | AA33: NOS | AB33: 1 | AC33: MRP&Rollup | AD33: CBESFG | AE33: 20 | AF33: I | AG33: RM-NWN-70GSMX6INCH | AH33: NON WOVEN FABRIC 70GSMX6" | AI33: KGS | AJ33: 0.065 | AK33: CBEWIP | AL33: Backflush | AM33: Active | AN33: =AJ33 -> 0.065 | AO33: =VLOOKUP(AG33,'RM-cost - feb-24'!B:P,15,0) -> 113.786 | AP33: =AO33*AN33 -> 7.39609 | AS33: =AS32 -> 160
A34: 3 | B34: =B33 -> 6 | C34: =C33 -> ET-COVER | D34: =MID(E34,9,2) -> PT | E34: =E33 -> RTHTMTBNPT72X57X10 | F34: =F33 -> RTHTMTBNPT | G34: =G33 -> 72X57X10 | H34: =H33 -> 72X57X10 | I34: =I33 -> 3 | J34: =J33 -> 6 | K34: =K33 -> 72 | L34: =L33 -> 57 | M34: =M33 -> 10 | N34: ="SFG-FRBNPK-ET-CVR-"&K34&"X"&L34&"X"&M34 -> SFG-FRBNPK-ET-CVR-72X57X10 | P34: =ROUNDUP((((K34*L34/144)*0.00692)),3) -> 0.198 | Q34: =P34=AJ34 -> FALSE | S34: ="Restonic Hotel Motel ET Cover "&K34&"X"&L34&"X"&M34 -> Restonic Hotel Motel ET Cover 72X57X10 | T34: =T33 -> SFG-FRBNPK-ET-CVR-72X57X10 | U34: =T34=N34 -> TRUE | V34: =S34=W34 -> TRUE | W34: =W33 -> Restonic Hotel Motel ET Cover 72X57X10 | X34: Standard | Y34: Production | Z34: TAIL-ET-PT | AA34: NOS | AB34: 1 | AC34: MRP&Rollup | AD34: CBESFG | AE34: 30 | AF34: I | AG34: RML-NWN-70GSMX76" | AH34: NON WOVEN FABRIC WHITE 70 GSM 76 INCH | AI34: KGS | AJ34: 0.196 | AK34: CBEWIP | AL34: Backflush | AM34: Active | AN34: =AJ34 -> 0.196 | AO34: =VLOOKUP(AG34,'RM-cost - feb-24'!B:P,15,0) -> 112.8872 | AP34: =AO34*AN34 -> 22.125891 | AS34: =AS33 -> 160
A35: 4 | B35: =B34 -> 6 | C35: =C34 -> ET-COVER | D35: =MID(E35,9,2) -> PT | E35: =E34 -> RTHTMTBNPT72X57X10 | F35: =F34 -> RTHTMTBNPT | G35: =G34 -> 72X57X10 | H35: =H34 -> 72X57X10 | I35: =I34 -> 3 | J35: =J34 -> 6 | K35: =K34 -> 72 | L35: =L34 -> 57 | M35: =M34 -> 10 | N35: ="SFG-FRBNPK-ET-CVR-"&K35&"X"&L35&"X"&M35 -> SFG-FRBNPK-ET-CVR-72X57X10 | P35: =ROUND(((((K35+L35+K35+L35)+3))*0.0254),3) -> 6.629 | Q35: =P35=AJ35 -> TRUE | S35: ="Restonic Hotel Motel ET Cover "&K35&"X"&L35&"X"&M35 -> Restonic Hotel Motel ET Cover 72X57X10 | T35: =T34 -> SFG-FRBNPK-ET-CVR-72X57X10 | U35: =T35=N35 -> TRUE | V35: =S35=W35 -> TRUE | W35: =W34 -> Restonic Hotel Motel ET Cover 72X57X10 | X35: Standard | Y35: Production | Z35: TAIL-ET-PT | AA35: NOS | AB35: 1 | AC35: MRP&Rollup | AD35: CBESFG | AE35: 40 | AF35: I | AG35: SFG-RTHTMT-BNPK-ETBOR-11CM | AH35: Hotel Motel Poc ET-10 & 12 8MM/16D Pre Foam Border 11 CM Height | AI35: MTR | AJ35: =P35 -> 6.629 | AK35: CBESFG | AL35: Backflush | AM35: Active | AN35: =AJ35 -> 6.629 | AO35: =VLOOKUP(AG35,'SFG-rate rm - feb-24'!A:B,2,0) -> 19.60538 | AP35: =AO35*AN35 -> 129.96407 | AS35: =AS34 -> 160
A36: 5 | B36: =B35 -> 6 | C36: =C35 -> ET-COVER | D36: =MID(E36,9,2) -> PT | E36: =E35 -> RTHTMTBNPT72X57X10 | F36: =F35 -> RTHTMTBNPT | G36: =G35 -> 72X57X10 | H36: =H35 -> 72X57X10 | I36: =I35 -> 3 | J36: =J35 -> 6 | K36: =K35 -> 72 | L36: =L35 -> 57 | M36: =M35 -> 10 | N36: ="SFG-FRBNPK-ET-CVR-"&K36&"X"&L36&"X"&M36 -> SFG-FRBNPK-ET-CVR-72X57X10 | P36: 10 | Q36: =P36=AJ36 -> TRUE | S36: ="Restonic Hotel Motel ET Cover "&K36&"X"&L36&"X"&M36 -> Restonic Hotel Motel ET Cover 72X57X10 | T36: =T35 -> SFG-FRBNPK-ET-CVR-72X57X10 | U36: =T36=N36 -> TRUE | V36: =S36=W36 -> TRUE | W36: =W35 -> Restonic Hotel Motel ET Cover 72X57X10 | X36: Standard | Y36: Production | Z36: TAIL-ET-PT | AA36: NOS | AB36: 1 | AC36: MRP&Rollup | AD36: CBESFG | AE36: 50 | AF36: I | AG36: HW-CTON-THREAD | AH36: COTTON THREAD WHITE 3PLY | AI36: MTR | AJ36: =P36 -> 10 | AK36: CBEWIP | AL36: Backflush | AM36: Active | AN36: =AJ36/5000 -> 0.002 | AO36: =VLOOKUP(AG36,'RM-cost - feb-24'!B:P,15,0) -> 58 | AP36: =AO36*AN36 -> 0.116 | AS36: =AS35 -> 160
A38: 1 | B38: 7 | C38: ET-COVER | D38: =MID(E38,9,2) -> PT | E38: RTHTMTBNPT72X63X10 | F38: =LEFT(E38,MIN(FIND({0,1,2,3,4,5,6,7,8,9},E38&"0123456789"))-1) -> RTHTMTBNPT | G38: =SUBSTITUTE(E38,F38,"") -> 72X63X10 | H38: =IFERROR(LEFT(G38,FIND("-",G38)-1),G38) -> 72X63X10 | I38: =SEARCH("X",H38) -> 3 | J38: =SEARCH("X",H38,I38+1) -> 6 | K38: =LEFT(G38,SEARCH("x",G38)-1) -> 72 | L38: =MID(H38,I38+1,J38-I38-1) -> 63 | M38: =MID(H38,J38+1,20) -> 10 | N38: ="SFG-FRBNPK-ET-CVR-"&K38&"X"&L38&"X"&M38 -> SFG-FRBNPK-ET-CVR-72X63X10 | P38: =ROUND(((((K38+L38+K38+L38)+3)*0.0254)*5.3196),3) -> 36.887 | Q38: 0 | R38: =P38+Q38 -> 36.887 | S38: ="Restonic Hotel Motel ET Cover "&K38&"X"&L38&"X"&M38 -> Restonic Hotel Motel ET Cover 72X63X10 | T38: =N38 -> SFG-FRBNPK-ET-CVR-72X63X10 | U38: =T38=N38 -> TRUE | V38: =S38=W38 -> TRUE | W38: =S38 -> Restonic Hotel Motel ET Cover 72X63X10 | X38: Standard | Y38: Production | Z38: TAIL-ET-PT | AA38: NOS | AB38: 1 | AC38: MRP&Rollup | AD38: CBESFG | AE38: 10 | AF38: I | AG38: RM-THRD-QS-TKT40 | AH38: THREAD TKT40 210D/3 PLY 10000MTS | AI38: MTR | AJ38: =R38 -> 36.887 | AK38: CBEWIP | AL38: Backflush | AM38: Active | AN38: =AJ38/10000 -> 0.0036887 | AO38: =VLOOKUP(AG38,'RM-cost - feb-24'!B:P,15,0) -> 231.1423 | AP38: =AO38*AN38 -> 0.8526146 | AQ38: =SUM(AP38:AP42) -> 169.37207 | AR38: =ROUND(AQ38,0) -> 169 | AS38: =AR38 -> 169 | AT38: =+AS38+AY38 -> 189.91358 | AU38: =+SUM(((AS38*3%*18%))) -> 0.9126 | AV38: =+SUM(((AS38*14.33%*53%))) -> 12.835381 | AW38: =+SUM(((AS38*5.92%*53%))) -> 5.302544 | AX38: =+SUM(((AS38*2.08%*53%))) -> 1.863056 | AY38: =SUM(AU38:AX42) -> 20.913581 | AZ38: =ROUNDUP(AT38,0) -> 190 | BA38: =AZ38 -> 190
A39: 2 | B39: =B38 -> 7 | C39: =C38 -> ET-COVER | D39: =MID(E39,9,2) -> PT | E39: =E38 -> RTHTMTBNPT72X63X10 | F39: =F38 -> RTHTMTBNPT | G39: =G38 -> 72X63X10 | H39: =H38 -> 72X63X10 | I39: =I38 -> 3 | J39: =J38 -> 6 | K39: =K38 -> 72 | L39: =L38 -> 63 | M39: =M38 -> 10 | N39: ="SFG-FRBNPK-ET-CVR-"&K39&"X"&L39&"X"&M39 -> SFG-FRBNPK-ET-CVR-72X63X10 | O39: =K39*L39/144 -> 31.5 | P39: =ROUNDUP((((K39*L39/144)*0.003)),3) -> 0.095 | S39: ="Restonic Hotel Motel ET Cover "&K39&"X"&L39&"X"&M39 -> Restonic Hotel Motel ET Cover 72X63X10 | T39: =T38 -> SFG-FRBNPK-ET-CVR-72X63X10 | U39: =T39=N39 -> TRUE | V39: =S39=W39 -> TRUE | W39: =W38 -> Restonic Hotel Motel ET Cover 72X63X10 | X39: Standard | Y39: Production | Z39: TAIL-ET-PT | AA39: NOS | AB39: 1 | AC39: MRP&Rollup | AD39: CBESFG | AE39: 20 | AF39: I | AG39: RM-NWN-70GSMX6INCH | AH39: NON WOVEN FABRIC 70GSMX6" | AI39: KGS | AJ39: 0.068 | AK39: CBEWIP | AL39: Backflush | AM39: Active | AN39: =AJ39 -> 0.068 | AO39: =VLOOKUP(AG39,'RM-cost - feb-24'!B:P,15,0) -> 113.786 | AP39: =AO39*AN39 -> 7.737448 | AS39: =AS38 -> 169
A40: 3 | B40: =B39 -> 7 | C40: =C39 -> ET-COVER | D40: =MID(E40,9,2) -> PT | E40: =E39 -> RTHTMTBNPT72X63X10 | F40: =F39 -> RTHTMTBNPT | G40: =G39 -> 72X63X10 | H40: =H39 -> 72X63X10 | I40: =I39 -> 3 | J40: =J39 -> 6 | K40: =K39 -> 72 | L40: =L39 -> 63 | M40: =M39 -> 10 | N40: ="SFG-FRBNPK-ET-CVR-"&K40&"X"&L40&"X"&M40 -> SFG-FRBNPK-ET-CVR-72X63X10 | P40: =ROUNDUP((((K40*L40/144)*0.00692)),3) -> 0.218 | Q40: =P40=AJ40 -> FALSE | S40: ="Restonic Hotel Motel ET Cover "&K40&"X"&L40&"X"&M40 -> Restonic Hotel Motel ET Cover 72X63X10 | T40: =T39 -> SFG-FRBNPK-ET-CVR-72X63X10 | U40: =T40=N40 -> TRUE | V40: =S40=W40 -> TRUE | W40: =W39 -> Restonic Hotel Motel ET Cover 72X63X10 | X40: Standard | Y40: Production | Z40: TAIL-ET-PT | AA40: NOS | AB40: 1 | AC40: MRP&Rollup | AD40: CBESFG | AE40: 30 | AF40: I | AG40: RML-NWN-70GSMX76" | AH40: NON WOVEN FABRIC WHITE 70 GSM 76 INCH | AI40: KGS | AJ40: 0.219 | AK40: CBEWIP | AL40: Backflush | AM40: Active | AN40: =AJ40 -> 0.219 | AO40: =VLOOKUP(AG40,'RM-cost - feb-24'!B:P,15,0) -> 112.8872 | AP40: =AO40*AN40 -> 24.722297 | AS40: =AS39 -> 169
A41: 4 | B41: =B40 -> 7 | C41: =C40 -> ET-COVER | D41: =MID(E41,9,2) -> PT | E41: =E40 -> RTHTMTBNPT72X63X10 | F41: =F40 -> RTHTMTBNPT | G41: =G40 -> 72X63X10 | H41: =H40 -> 72X63X10 | I41: =I40 -> 3 | J41: =J40 -> 6 | K41: =K40 -> 72 | L41: =L40 -> 63 | M41: =M40 -> 10 | N41: ="SFG-FRBNPK-ET-CVR-"&K41&"X"&L41&"X"&M41 -> SFG-FRBNPK-ET-CVR-72X63X10 | P41: =ROUND(((((K41+L41+K41+L41)+3))*0.0254),3) -> 6.934 | Q41: =P41=AJ41 -> TRUE | S41: ="Restonic Hotel Motel ET Cover "&K41&"X"&L41&"X"&M41 -> Restonic Hotel Motel ET Cover 72X63X10 | T41: =T40 -> SFG-FRBNPK-ET-CVR-72X63X10 | U41: =T41=N41 -> TRUE | V41: =S41=W41 -> TRUE | W41: =W40 -> Restonic Hotel Motel ET Cover 72X63X10 | X41: Standard | Y41: Production | Z41: TAIL-ET-PT | AA41: NOS | AB41: 1 | AC41: MRP&Rollup | AD41: CBESFG | AE41: 40 | AF41: I | AG41: SFG-RTHTMT-BNPK-ETBOR-11CM | AH41: Hotel Motel Poc ET-10 & 12 8MM/16D Pre Foam Border 11 CM Height | AI41: MTR | AJ41: =P41 -> 6.934 | AK41: CBESFG | AL41: Backflush | AM41: Active | AN41: =AJ41 -> 6.934 | AO41: =VLOOKUP(AG41,'SFG-rate rm - feb-24'!A:B,2,0) -> 19.60538 | AP41: =AO41*AN41 -> 135.94371 | AS41: =AS40 -> 169
A42: 5 | B42: =B41 -> 7 | C42: =C41 -> ET-COVER | D42: =MID(E42,9,2) -> PT | E42: =E41 -> RTHTMTBNPT72X63X10 | F42: =F41 -> RTHTMTBNPT | G42: =G41 -> 72X63X10 | H42: =H41 -> 72X63X10 | I42: =I41 -> 3 | J42: =J41 -> 6 | K42: =K41 -> 72 | L42: =L41 -> 63 | M42: =M41 -> 10 | N42: ="SFG-FRBNPK-ET-CVR-"&K42&"X"&L42&"X"&M42 -> SFG-FRBNPK-ET-CVR-72X63X10 | P42: 10 | Q42: =P42=AJ42 -> TRUE | S42: ="Restonic Hotel Motel ET Cover "&K42&"X"&L42&"X"&M42 -> Restonic Hotel Motel ET Cover 72X63X10 | T42: =T41 -> SFG-FRBNPK-ET-CVR-72X63X10 | U42: =T42=N42 -> TRUE | V42: =S42=W42 -> TRUE | W42: =W41 -> Restonic Hotel Motel ET Cover 72X63X10 | X42: Standard | Y42: Production | Z42: TAIL-ET-PT | AA42: NOS | AB42: 1 | AC42: MRP&Rollup | AD42: CBESFG | AE42: 50 | AF42: I | AG42: HW-CTON-THREAD | AH42: COTTON THREAD WHITE 3PLY | AI42: MTR | AJ42: =P42 -> 10 | AK42: CBEWIP | AL42: Backflush | AM42: Active | AN42: =AJ42/5000 -> 0.002 | AO42: =VLOOKUP(AG42,'RM-cost - feb-24'!B:P,15,0) -> 58 | AP42: =AO42*AN42 -> 0.116 | AS42: =AS41 -> 169
A44: 1 | B44: 8 | C44: ET-COVER | D44: =MID(E44,9,2) -> PT | E44: RTHTMTBNPT72X69X10 | F44: =LEFT(E44,MIN(FIND({0,1,2,3,4,5,6,7,8,9},E44&"0123456789"))-1) -> RTHTMTBNPT | G44: =SUBSTITUTE(E44,F44,"") -> 72X69X10 | H44: =IFERROR(LEFT(G44,FIND("-",G44)-1),G44) -> 72X69X10 | I44: =SEARCH("X",H44) -> 3 | J44: =SEARCH("X",H44,I44+1) -> 6 | K44: =LEFT(G44,SEARCH("x",G44)-1) -> 72 | L44: =MID(H44,I44+1,J44-I44-1) -> 69 | M44: =MID(H44,J44+1,20) -> 10 | N44: ="SFG-FRBNPK-ET-CVR-"&K44&"X"&L44&"X"&M44 -> SFG-FRBNPK-ET-CVR-72X69X10 | P44: =ROUND(((((K44+L44+K44+L44)+3)*0.0254)*5.3196),3) -> 38.509 | Q44: 0 | R44: =P44+Q44 -> 38.509 | S44: ="Restonic Hotel Motel ET Cover "&K44&"X"&L44&"X"&M44 -> Restonic Hotel Motel ET Cover 72X69X10 | T44: =N44 -> SFG-FRBNPK-ET-CVR-72X69X10 | U44: =T44=N44 -> TRUE | V44: =S44=W44 -> TRUE | W44: =S44 -> Restonic Hotel Motel ET Cover 72X69X10 | X44: Standard | Y44: Production | Z44: TAIL-ET-PT | AA44: NOS | AB44: 1 | AC44: MRP&Rollup | AD44: CBESFG | AE44: 10 | AF44: I | AG44: RM-THRD-QS-TKT40 | AH44: THREAD TKT40 210D/3 PLY 10000MTS | AI44: MTR | AJ44: =R44 -> 38.509 | AK44: CBEWIP | AL44: Backflush | AM44: Active | AN44: =AJ44/10000 -> 0.0038509 | AO44: =VLOOKUP(AG44,'RM-cost - feb-24'!B:P,15,0) -> 231.1423 | AP44: =AO44*AN44 -> 0.89010588 | AQ44: =SUM(AP44:AP48) -> 177.87541 | AR44: =ROUND(AQ44,0) -> 178 | AS44: =AR44 -> 178 | AT44: =+AS44+AY44 -> 200.02732 | AU44: =+SUM(((AS44*3%*18%))) -> 0.9612 | AV44: =+SUM(((AS44*14.33%*53%))) -> 13.518922 | AW44: =+SUM(((AS44*5.92%*53%))) -> 5.584928 | AX44: =+SUM(((AS44*2.08%*53%))) -> 1.962272 | AY44: =SUM(AU44:AX48) -> 22.027322 | AZ44: =ROUNDUP(AT44,0) -> 201 | BA44: =AZ44 -> 201
A45: 2 | B45: =B44 -> 8 | C45: =C44 -> ET-COVER | D45: =MID(E45,9,2) -> PT | E45: =E44 -> RTHTMTBNPT72X69X10 | F45: =F44 -> RTHTMTBNPT | G45: =G44 -> 72X69X10 | H45: =H44 -> 72X69X10 | I45: =I44 -> 3 | J45: =J44 -> 6 | K45: =K44 -> 72 | L45: =L44 -> 69 | M45: =M44 -> 10 | N45: ="SFG-FRBNPK-ET-CVR-"&K45&"X"&L45&"X"&M45 -> SFG-FRBNPK-ET-CVR-72X69X10 | O45: =K45*L45/144 -> 34.5 | P45: =ROUNDUP((((K45*L45/144)*0.003)),3) -> 0.104 | S45: ="Restonic Hotel Motel ET Cover "&K45&"X"&L45&"X"&M45 -> Restonic Hotel Motel ET Cover 72X69X10 | T45: =T44 -> SFG-FRBNPK-ET-CVR-72X69X10 | U45: =T45=N45 -> TRUE | V45: =S45=W45 -> TRUE | W45: =W44 -> Restonic Hotel Motel ET Cover 72X69X10 | X45: Standard | Y45: Production | Z45: TAIL-ET-PT | AA45: NOS | AB45: 1 | AC45: MRP&Rollup | AD45: CBESFG | AE45: 20 | AF45: I | AG45: RM-NWN-70GSMX6INCH | AH45: NON WOVEN FABRIC 70GSMX6" | AI45: KGS | AJ45: 0.071 | AK45: CBEWIP | AL45: Backflush | AM45: Active | AN45: =AJ45 -> 0.071 | AO45: =VLOOKUP(AG45,'RM-cost - feb-24'!B:P,15,0) -> 113.786 | AP45: =AO45*AN45 -> 8.078806 | AS45: =AS44 -> 178
A46: 3 | B46: =B45 -> 8 | C46: =C45 -> ET-COVER | D46: =MID(E46,9,2) -> PT | E46: =E45 -> RTHTMTBNPT72X69X10 | F46: =F45 -> RTHTMTBNPT | G46: =G45 -> 72X69X10 | H46: =H45 -> 72X69X10 | I46: =I45 -> 3 | J46: =J45 -> 6 | K46: =K45 -> 72 | L46: =L45 -> 69 | M46: =M45 -> 10 | N46: ="SFG-FRBNPK-ET-CVR-"&K46&"X"&L46&"X"&M46 -> SFG-FRBNPK-ET-CVR-72X69X10 | P46: =ROUNDUP((((K46*L46/144)*0.00692)),3) -> 0.239 | Q46: =P46=AJ46 -> FALSE | S46: ="Restonic Hotel Motel ET Cover "&K46&"X"&L46&"X"&M46 -> Restonic Hotel Motel ET Cover 72X69X10 | T46: =T45 -> SFG-FRBNPK-ET-CVR-72X69X10 | U46: =T46=N46 -> TRUE | V46: =S46=W46 -> TRUE | W46: =W45 -> Restonic Hotel Motel ET Cover 72X69X10 | X46: Standard | Y46: Production | Z46: TAIL-ET-PT | AA46: NOS | AB46: 1 | AC46: MRP&Rollup | AD46: CBESFG | AE46: 30 | AF46: I | AG46: RML-NWN-70GSMX76" | AH46: NON WOVEN FABRIC WHITE 70 GSM 76 INCH | AI46: KGS | AJ46: 0.238 | AK46: CBEWIP | AL46: Backflush | AM46: Active | AN46: =AJ46 -> 0.238 | AO46: =VLOOKUP(AG46,'RM-cost - feb-24'!B:P,15,0) -> 112.8872 | AP46: =AO46*AN46 -> 26.867154 | AS46: =AS45 -> 178
A47: 4 | B47: =B46 -> 8 | C47: =C46 -> ET-COVER | D47: =MID(E47,9,2) -> PT | E47: =E46 -> RTHTMTBNPT72X69X10 | F47: =F46 -> RTHTMTBNPT | G47: =G46 -> 72X69X10 | H47: =H46 -> 72X69X10 | I47: =I46 -> 3 | J47: =J46 -> 6 | K47: =K46 -> 72 | L47: =L46 -> 69 | M47: =M46 -> 10 | N47: ="SFG-FRBNPK-ET-CVR-"&K47&"X"&L47&"X"&M47 -> SFG-FRBNPK-ET-CVR-72X69X10 | P47: =ROUND(((((K47+L47+K47+L47)+3))*0.0254),3) -> 7.239 | Q47: =P47=AJ47 -> TRUE | S47: ="Restonic Hotel Motel ET Cover "&K47&"X"&L47&"X"&M47 -> Restonic Hotel Motel ET Cover 72X69X10 | T47: =T46 -> SFG-FRBNPK-ET-CVR-72X69X10 | U47: =T47=N47 -> TRUE | V47: =S47=W47 -> TRUE | W47: =W46 -> Restonic Hotel Motel ET Cover 72X69X10 | X47: Standard | Y47: Production | Z47: TAIL-ET-PT | AA47: NOS | AB47: 1 | AC47: MRP&Rollup | AD47: CBESFG | AE47: 40 | AF47: I | AG47: SFG-RTHTMT-BNPK-ETBOR-11CM | AH47: Hotel Motel Poc ET-10 & 12 8MM/16D Pre Foam Border 11 CM Height | AI47: MTR | AJ47: =P47 -> 7.239 | AK47: CBESFG | AL47: Backflush | AM47: Active | AN47: =AJ47 -> 7.239 | AO47: =VLOOKUP(AG47,'SFG-rate rm - feb-24'!A:B,2,0) -> 19.60538 | AP47: =AO47*AN47 -> 141.92335 | AS47: =AS46 -> 178
A48: 5 | B48: =B47 -> 8 | C48: =C47 -> ET-COVER | D48: =MID(E48,9,2) -> PT | E48: =E47 -> RTHTMTBNPT72X69X10 | F48: =F47 -> RTHTMTBNPT | G48: =G47 -> 72X69X10 | H48: =H47 -> 72X69X10 | I48: =I47 -> 3 | J48: =J47 -> 6 | K48: =K47 -> 72 | L48: =L47 -> 69 | M48: =M47 -> 10 | N48: ="SFG-FRBNPK-ET-CVR-"&K48&"X"&L48&"X"&M48 -> SFG-FRBNPK-ET-CVR-72X69X10 | P48: 10 | Q48: =P48=AJ48 -> TRUE | S48: ="Restonic Hotel Motel ET Cover "&K48&"X"&L48&"X"&M48 -> Restonic Hotel Motel ET Cover 72X69X10 | T48: =T47 -> SFG-FRBNPK-ET-CVR-72X69X10 | U48: =T48=N48 -> TRUE | V48: =S48=W48 -> TRUE | W48: =W47 -> Restonic Hotel Motel ET Cover 72X69X10 | X48: Standard | Y48: Production | Z48: TAIL-ET-PT | AA48: NOS | AB48: 1 | AC48: MRP&Rollup | AD48: CBESFG | AE48: 50 | AF48: I | AG48: HW-CTON-THREAD | AH48: COTTON THREAD WHITE 3PLY | AI48: MTR | AJ48: =P48 -> 10 | AK48: CBEWIP | AL48: Backflush | AM48: Active | AN48: =AJ48/5000 -> 0.002 | AO48: =VLOOKUP(AG48,'RM-cost - feb-24'!B:P,15,0) -> 58 | AP48: =AO48*AN48 -> 0.116 | AS48: =AS47 -> 178
A50: 1 | B50: 9 | C50: ET-COVER | D50: =MID(E50,9,2) -> PT | E50: RTHTMTBNPT75X33X10 | F50: =LEFT(E50,MIN(FIND({0,1,2,3,4,5,6,7,8,9},E50&"0123456789"))-1) -> RTHTMTBNPT | G50: =SUBSTITUTE(E50,F50,"") -> 75X33X10 | H50: =IFERROR(LEFT(G50,FIND("-",G50)-1),G50) -> 75X33X10 | I50: =SEARCH("X",H50) -> 3 | J50: =SEARCH("X",H50,I50+1) -> 6 | K50: =LEFT(G50,SEARCH("x",G50)-1) -> 75 | L50: =MID(H50,I50+1,J50-I50-1) -> 33 | M50: =MID(H50,J50+1,20) -> 10 | N50: ="SFG-FRBNPK-ET-CVR-"&K50&"X"&L50&"X"&M50 -> SFG-FRBNPK-ET-CVR-75X33X10 | P50: =ROUND(((((K50+L50+K50+L50)+3)*0.0254)*5.3196),3) -> 29.591 | Q50: 0 | R50: =P50+Q50 -> 29.591 | S50: ="Restonic Hotel Motel ET Cover "&K50&"X"&L50&"X"&M50 -> Restonic Hotel Motel ET Cover 75X33X10 | T50: =N50 -> SFG-FRBNPK-ET-CVR-75X33X10 | U50: =T50=N50 -> TRUE | V50: =S50=W50 -> TRUE | W50: =S50 -> Restonic Hotel Motel ET Cover 75X33X10 | X50: Standard | Y50: Production | Z50: TAIL-ET-PT | AA50: NOS | AB50: 1 | AC50: MRP&Rollup | AD50: CBESFG | AE50: 10 | AF50: I | AG50: RM-THRD-QS-TKT40 | AH50: THREAD TKT40 210D/3 PLY 10000MTS | AI50: MTR | AJ50: =R50 -> 29.591 | AK50: CBEWIP | AL50: Backflush | AM50: Active | AN50: =AJ50/10000 -> 0.0029591 | AO50: =VLOOKUP(AG50,'RM-cost - feb-24'!B:P,15,0) -> 231.1423 | AP50: =AO50*AN50 -> 0.68397318 | AQ50: =SUM(AP50:AP54) -> 128.7654 | AR50: =ROUND(AQ50,0) -> 129 | AS50: =AR50 -> 129 | AT50: =+AS50+AY50 -> 144.96362 | AU50: =+SUM(((AS50*3%*18%))) -> 0.6966 | AV50: =+SUM(((AS50*14.33%*53%))) -> 9.797421 | AW50: =+SUM(((AS50*5.92%*53%))) -> 4.047504 | AX50: =+SUM(((AS50*2.08%*53%))) -> 1.422096 | AY50: =SUM(AU50:AX54) -> 15.963621 | AZ50: =ROUNDUP(AT50,0) -> 145 | BA50: =AZ50 -> 145
A51: 2 | B51: =B50 -> 9 | C51: =C50 -> ET-COVER | D51: =MID(E51,9,2) -> PT | E51: =E50 -> RTHTMTBNPT75X33X10 | F51: =F50 -> RTHTMTBNPT | G51: =G50 -> 75X33X10 | H51: =H50 -> 75X33X10 | I51: =I50 -> 3 | J51: =J50 -> 6 | K51: =K50 -> 75 | L51: =L50 -> 33 | M51: =M50 -> 10 | N51: ="SFG-FRBNPK-ET-CVR-"&K51&"X"&L51&"X"&M51 -> SFG-FRBNPK-ET-CVR-75X33X10 | O51: =K51*L51/144 -> 17.1875 | P51: =ROUNDUP((((K51*L51/144)*0.003)),3) -> 0.052 | S51: ="Restonic Hotel Motel ET Cover "&K51&"X"&L51&"X"&M51 -> Restonic Hotel Motel ET Cover 75X33X10 | T51: =T50 -> SFG-FRBNPK-ET-CVR-75X33X10 | U51: =T51=N51 -> TRUE | V51: =S51=W51 -> TRUE | W51: =W50 -> Restonic Hotel Motel ET Cover 75X33X10 | X51: Standard | Y51: Production | Z51: TAIL-ET-PT | AA51: NOS | AB51: 1 | AC51: MRP&Rollup | AD51: CBESFG | AE51: 20 | AF51: I | AG51: RM-NWN-70GSMX6INCH | AH51: NON WOVEN FABRIC 70GSMX6" | AI51: KGS | AJ51: 0.054 | AK51: CBEWIP | AL51: Backflush | AM51: Active | AN51: =AJ51 -> 0.054 | AO51: =VLOOKUP(AG51,'RM-cost - feb-24'!B:P,15,0) -> 113.786 | AP51: =AO51*AN51 -> 6.144444 | AS51: =AS50 -> 129
A52: 3 | B52: =B51 -> 9 | C52: =C51 -> ET-COVER | D52: =MID(E52,9,2) -> PT | E52: =E51 -> RTHTMTBNPT75X33X10 | F52: =F51 -> RTHTMTBNPT | G52: =G51 -> 75X33X10 | H52: =H51 -> 75X33X10 | I52: =I51 -> 3 | J52: =J51 -> 6 | K52: =K51 -> 75 | L52: =L51 -> 33 | M52: =M51 -> 10 | N52: ="SFG-FRBNPK-ET-CVR-"&K52&"X"&L52&"X"&M52 -> SFG-FRBNPK-ET-CVR-75X33X10 | P52: =ROUNDUP((((K52*L52/144)*0.00692)),3) -> 0.119 | Q52: =P52=AJ52 -> FALSE | S52: ="Restonic Hotel Motel ET Cover "&K52&"X"&L52&"X"&M52 -> Restonic Hotel Motel ET Cover 75X33X10 | T52: =T51 -> SFG-FRBNPK-ET-CVR-75X33X10 | U52: =T52=N52 -> TRUE | V52: =S52=W52 -> TRUE | W52: =W51 -> Restonic Hotel Motel ET Cover 75X33X10 | X52: Standard | Y52: Production | Z52: TAIL-ET-PT | AA52: NOS | AB52: 1 | AC52: MRP&Rollup | AD52: CBESFG | AE52: 30 | AF52: I | AG52: RML-NWN-70GSMX76" | AH52: NON WOVEN FABRIC WHITE 70 GSM 76 INCH | AI52: KGS | AJ52: 0.113 | AK52: CBEWIP | AL52: Backflush | AM52: Active | AN52: =AJ52 -> 0.113 | AO52: =VLOOKUP(AG52,'RM-cost - feb-24'!B:P,15,0) -> 112.8872 | AP52: =AO52*AN52 -> 12.756254 | AS52: =AS51 -> 129
A53: 4 | B53: =B52 -> 9 | C53: =C52 -> ET-COVER | D53: =MID(E53,9,2) -> PT | E53: =E52 -> RTHTMTBNPT75X33X10 | F53: =F52 -> RTHTMTBNPT | G53: =G52 -> 75X33X10 | H53: =H52 -> 75X33X10 | I53: =I52 -> 3 | J53: =J52 -> 6 | K53: =K52 -> 75 | L53: =L52 -> 33 | M53: =M52 -> 10 | N53: ="SFG-FRBNPK-ET-CVR-"&K53&"X"&L53&"X"&M53 -> SFG-FRBNPK-ET-CVR-75X33X10 | P53: =ROUND(((((K53+L53+K53+L53)+3))*0.0254),3) -> 5.563 | Q53: =P53=AJ53 -> TRUE | S53: ="Restonic Hotel Motel ET Cover "&K53&"X"&L53&"X"&M53 -> Restonic Hotel Motel ET Cover 75X33X10 | T53: =T52 -> SFG-FRBNPK-ET-CVR-75X33X10 | U53: =T53=N53 -> TRUE | V53: =S53=W53 -> TRUE | W53: =W52 -> Restonic Hotel Motel ET Cover 75X33X10 | X53: Standard | Y53: Production | Z53: TAIL-ET-PT | AA53: NOS | AB53: 1 | AC53: MRP&Rollup | AD53: CBESFG | AE53: 40 | AF53: I | AG53: SFG-RTHTMT-BNPK-ETBOR-11CM | AH53: Hotel Motel Poc ET-10 & 12 8MM/16D Pre Foam Border 11 CM Height | AI53: MTR | AJ53: =P53 -> 5.563 | AK53: CBESFG | AL53: Backflush | AM53: Active | AN53: =AJ53 -> 5.563 | AO53: =VLOOKUP(AG53,'SFG-rate rm - feb-24'!A:B,2,0) -> 19.60538 | AP53: =AO53*AN53 -> 109.06473 | AS53: =AS52 -> 129
A54: 5 | B54: =B53 -> 9 | C54: =C53 -> ET-COVER | D54: =MID(E54,9,2) -> PT | E54: =E53 -> RTHTMTBNPT75X33X10 | F54: =F53 -> RTHTMTBNPT | G54: =G53 -> 75X33X10 | H54: =H53 -> 75X33X10 | I54: =I53 -> 3 | J54: =J53 -> 6 | K54: =K53 -> 75 | L54: =L53 -> 33 | M54: =M53 -> 10 | N54: ="SFG-FRBNPK-ET-CVR-"&K54&"X"&L54&"X"&M54 -> SFG-FRBNPK-ET-CVR-75X33X10 | P54: 10 | Q54: =P54=AJ54 -> TRUE | S54: ="Restonic Hotel Motel ET Cover "&K54&"X"&L54&"X"&M54 -> Restonic Hotel Motel ET Cover 75X33X10 | T54: =T53 -> SFG-FRBNPK-ET-CVR-75X33X10 | U54: =T54=N54 -> TRUE | V54: =S54=W54 -> TRUE | W54: =W53 -> Restonic Hotel Motel ET Cover 75X33X10 | X54: Standard | Y54: Production | Z54: TAIL-ET-PT | AA54: NOS | AB54: 1 | AC54: MRP&Rollup | AD54: CBESFG | AE54: 50 | AF54: I | AG54: HW-CTON-THREAD | AH54: COTTON THREAD WHITE 3PLY | AI54: MTR | AJ54: =P54 -> 10 | AK54: CBEWIP | AL54: Backflush | AM54: Active | AN54: =AJ54/5000 -> 0.002 | AO54: =VLOOKUP(AG54,'RM-cost - feb-24'!B:P,15,0) -> 58 | AP54: =AO54*AN54 -> 0.116 | AS54: =AS53 -> 129
A56: 1 | B56: 10 | C56: ET-COVER | D56: =MID(E56,9,2) -> PT | E56: RTHTMTBNPT75X39X10 | F56: =LEFT(E56,MIN(FIND({0,1,2,3,4,5,6,7,8,9},E56&"0123456789"))-1) -> RTHTMTBNPT | G56: =SUBSTITUTE(E56,F56,"") -> 75X39X10 | H56: =IFERROR(LEFT(G56,FIND("-",G56)-1),G56) -> 75X39X10 | I56: =SEARCH("X",H56) -> 3 | J56: =SEARCH("X",H56,I56+1) -> 6 | K56: =LEFT(G56,SEARCH("x",G56)-1) -> 75 | L56: =MID(H56,I56+1,J56-I56-1) -> 39 | M56: =MID(H56,J56+1,20) -> 10 | N56: ="SFG-FRBNPK-ET-CVR-"&K56&"X"&L56&"X"&M56 -> SFG-FRBNPK-ET-CVR-75X39X10 | P56: =ROUND(((((K56+L56+K56+L56)+3)*0.0254)*5.3196),3) -> 31.212 | Q56: 0 | R56: =P56+Q56 -> 31.212 | S56: ="Restonic Hotel Motel ET Cover "&K56&"X"&L56&"X"&M56 -> Restonic Hotel Motel ET Cover 75X39X10 | T56: =N56 -> SFG-FRBNPK-ET-CVR-75X39X10 | U56: =T56=N56 -> TRUE | V56: =S56=W56 -> TRUE | W56: =S56 -> Restonic Hotel Motel ET Cover 75X39X10 | X56: Standard | Y56: Production | Z56: TAIL-ET-PT | AA56: NOS | AB56: 1 | AC56: MRP&Rollup | AD56: CBESFG | AE56: 10 | AF56: I | AG56: RM-THRD-QS-TKT40 | AH56: THREAD TKT40 210D/3 PLY 10000MTS | AI56: MTR | AJ56: =R56 -> 31.212 | AK56: CBEWIP | AL56: Backflush | AM56: Active | AN56: =AJ56/10000 -> 0.0031212 | AO56: =VLOOKUP(AG56,'RM-cost - feb-24'!B:P,15,0) -> 231.1423 | AP56: =AO56*AN56 -> 0.72144135 | AQ56: =SUM(AP56:AP60) -> 137.36201 | AR56: =ROUND(AQ56,0) -> 137 | AS56: =AR56 -> 137 | AT56: =+AS56+AY56 -> 153.95361 | AU56: =+SUM(((AS56*3%*18%))) -> 0.7398 | AV56: =+SUM(((AS56*14.33%*53%))) -> 10.405013 | AW56: =+SUM(((AS56*5.92%*53%))) -> 4.298512 | AX56: =+SUM(((AS56*2.08%*53%))) -> 1.510288 | AY56: =SUM(AU56:AX60) -> 16.953613 | AZ56: =ROUNDUP(AT56,0) -> 154 | BA56: =AZ56 -> 154
A57: 2 | B57: =B56 -> 10 | C57: =C56 -> ET-COVER | D57: =MID(E57,9,2) -> PT | E57: =E56 -> RTHTMTBNPT75X39X10 | F57: =F56 -> RTHTMTBNPT | G57: =G56 -> 75X39X10 | H57: =H56 -> 75X39X10 | I57: =I56 -> 3 | J57: =J56 -> 6 | K57: =K56 -> 75 | L57: =L56 -> 39 | M57: =M56 -> 10 | N57: ="SFG-FRBNPK-ET-CVR-"&K57&"X"&L57&"X"&M57 -> SFG-FRBNPK-ET-CVR-75X39X10 | O57: =K57*L57/144 -> 20.3125 | P57: =ROUNDUP((((K57*L57/144)*0.003)),3) -> 0.061 | S57: ="Restonic Hotel Motel ET Cover "&K57&"X"&L57&"X"&M57 -> Restonic Hotel Motel ET Cover 75X39X10 | T57: =T56 -> SFG-FRBNPK-ET-CVR-75X39X10 | U57: =T57=N57 -> TRUE | V57: =S57=W57 -> TRUE | W57: =W56 -> Restonic Hotel Motel ET Cover 75X39X10 | X57: Standard | Y57: Production | Z57: TAIL-ET-PT | AA57: NOS | AB57: 1 | AC57: MRP&Rollup | AD57: CBESFG | AE57: 20 | AF57: I | AG57: RM-NWN-70GSMX6INCH | AH57: NON WOVEN FABRIC 70GSMX6" | AI57: KGS | AJ57: 0.057 | AK57: CBEWIP | AL57: Backflush | AM57: Active | AN57: =AJ57 -> 0.057 | AO57: =VLOOKUP(AG57,'RM-cost - feb-24'!B:P,15,0) -> 113.786 | AP57: =AO57*AN57 -> 6.485802 | AS57: =AS56 -> 137
A58: 3 | B58: =B57 -> 10 | C58: =C57 -> ET-COVER | D58: =MID(E58,9,2) -> PT | E58: =E57 -> RTHTMTBNPT75X39X10 | F58: =F57 -> RTHTMTBNPT | G58: =G57 -> 75X39X10 | H58: =H57 -> 75X39X10 | I58: =I57 -> 3 | J58: =J57 -> 6 | K58: =K57 -> 75 | L58: =L57 -> 39 | M58: =M57 -> 10 | N58: ="SFG-FRBNPK-ET-CVR-"&K58&"X"&L58&"X"&M58 -> SFG-FRBNPK-ET-CVR-75X39X10 | P58: =ROUNDUP((((K58*L58/144)*0.00692)),3) -> 0.141 | Q58: =P58=AJ58 -> FALSE | S58: ="Restonic Hotel Motel ET Cover "&K58&"X"&L58&"X"&M58 -> Restonic Hotel Motel ET Cover 75X39X10 | T58: =T57 -> SFG-FRBNPK-ET-CVR-75X39X10 | U58: =T58=N58 -> TRUE | V58: =S58=W58 -> TRUE | W58: =W57 -> Restonic Hotel Motel ET Cover 75X39X10 | X58: Standard | Y58: Production | Z58: TAIL-ET-PT | AA58: NOS | AB58: 1 | AC58: MRP&Rollup | AD58: CBESFG | AE58: 30 | AF58: I | AG58: RML-NWN-70GSMX76" | AH58: NON WOVEN FABRIC WHITE 70 GSM 76 INCH | AI58: KGS | AJ58: 0.133 | AK58: CBEWIP | AL58: Backflush | AM58: Active | AN58: =AJ58 -> 0.133 | AO58: =VLOOKUP(AG58,'RM-cost - feb-24'!B:P,15,0) -> 112.8872 | AP58: =AO58*AN58 -> 15.013998 | AS58: =AS57 -> 137
A59: 4 | B59: =B58 -> 10 | C59: =C58 -> ET-COVER | D59: =MID(E59,9,2) -> PT | E59: =E58 -> RTHTMTBNPT75X39X10 | F59: =F58 -> RTHTMTBNPT | G59: =G58 -> 75X39X10 | H59: =H58 -> 75X39X10 | I59: =I58 -> 3 | J59: =J58 -> 6 | K59: =K58 -> 75 | L59: =L58 -> 39 | M59: =M58 -> 10 | N59: ="SFG-FRBNPK-ET-CVR-"&K59&"X"&L59&"X"&M59 -> SFG-FRBNPK-ET-CVR-75X39X10 | P59: =ROUND(((((K59+L59+K59+L59)+3))*0.0254),3) -> 5.867 | Q59: =P59=AJ59 -> TRUE | S59: ="Restonic Hotel Motel ET Cover "&K59&"X"&L59&"X"&M59 -> Restonic Hotel Motel ET Cover 75X39X10 | T59: =T58 -> SFG-FRBNPK-ET-CVR-75X39X10 | U59: =T59=N59 -> TRUE | V59: =S59=W59 -> TRUE | W59: =W58 -> Restonic Hotel Motel ET Cover 75X39X10 | X59: Standard | Y59: Production | Z59: TAIL-ET-PT | AA59: NOS | AB59: 1 | AC59: MRP&Rollup | AD59: CBESFG | AE59: 40 | AF59: I | AG59: SFG-RTHTMT-BNPK-ETBOR-11CM | AH59: Hotel Motel Poc ET-10 & 12 8MM/16D Pre Foam Border 11 CM Height | AI59: MTR | AJ59: =P59 -> 5.867 | AK59: CBESFG | AL59: Backflush | AM59: Active | AN59: =AJ59 -> 5.867 | AO59: =VLOOKUP(AG59,'SFG-rate rm - feb-24'!A:B,2,0) -> 19.60538 | AP59: =AO59*AN59 -> 115.02477 | AS59: =AS58 -> 137
A60: 5 | B60: =B59 -> 10 | C60: =C59 -> ET-COVER | D60: =MID(E60,9,2) -> PT | E60: =E59 -> RTHTMTBNPT75X39X10 | F60: =F59 -> RTHTMTBNPT | G60: =G59 -> 75X39X10 | H60: =H59 -> 75X39X10 | I60: =I59 -> 3 | J60: =J59 -> 6 | K60: =K59 -> 75 | L60: =L59 -> 39 | M60: =M59 -> 10 | N60: ="SFG-FRBNPK-ET-CVR-"&K60&"X"&L60&"X"&M60 -> SFG-FRBNPK-ET-CVR-75X39X10 | P60: 10 | Q60: =P60=AJ60 -> TRUE | S60: ="Restonic Hotel Motel ET Cover "&K60&"X"&L60&"X"&M60 -> Restonic Hotel Motel ET Cover 75X39X10 | T60: =T59 -> SFG-FRBNPK-ET-CVR-75X39X10 | U60: =T60=N60 -> TRUE | V60: =S60=W60 -> TRUE | W60: =W59 -> Restonic Hotel Motel ET Cover 75X39X10 | X60: Standard | Y60: Production | Z60: TAIL-ET-PT | AA60: NOS | AB60: 1 | AC60: MRP&Rollup | AD60: CBESFG | AE60: 50 | AF60: I | AG60: HW-CTON-THREAD | AH60: COTTON THREAD WHITE 3PLY | AI60: MTR | AJ60: =P60 -> 10 | AK60: CBEWIP | AL60: Backflush | AM60: Active | AN60: =AJ60/5000 -> 0.002 | AO60: =VLOOKUP(AG60,'RM-cost - feb-24'!B:P,15,0) -> 58 | AP60: =AO60*AN60 -> 0.116 | AS60: =AS59 -> 137
A62: 1 | B62: 11 | C62: ET-COVER | D62: =MID(E62,9,2) -> PT | E62: RTHTMTBNPT75X45X10 | F62: =LEFT(E62,MIN(FIND({0,1,2,3,4,5,6,7,8,9},E62&"0123456789"))-1) -> RTHTMTBNPT | G62: =SUBSTITUTE(E62,F62,"") -> 75X45X10 | H62: =IFERROR(LEFT(G62,FIND("-",G62)-1),G62) -> 75X45X10 | I62: =SEARCH("X",H62) -> 3 | J62: =SEARCH("X",H62,I62+1) -> 6 | K62: =LEFT(G62,SEARCH("x",G62)-1) -> 75 | L62: =MID(H62,I62+1,J62-I62-1) -> 45 | M62: =MID(H62,J62+1,20) -> 10 | N62: ="SFG-FRBNPK-ET-CVR-"&K62&"X"&L62&"X"&M62 -> SFG-FRBNPK-ET-CVR-75X45X10 | P62: =ROUND(((((K62+L62+K62+L62)+3)*0.0254)*5.3196),3) -> 32.834 | Q62: 0 | R62: =P62+Q62 -> 32.834 | S62: ="Restonic Hotel Motel ET Cover "&K62&"X"&L62&"X"&M62 -> Restonic Hotel Motel ET Cover 75X45X10 | T62: =N62 -> SFG-FRBNPK-ET-CVR-75X45X10 | U62: =T62=N62 -> TRUE | V62: =S62=W62 -> TRUE | W62: =S62 -> Restonic Hotel Motel ET Cover 75X45X10 | X62: Standard | Y62: Production | Z62: TAIL-ET-PT | AA62: NOS | AB62: 1 | AC62: MRP&Rollup | AD62: CBESFG | AE62: 10 | AF62: I | AG62: RM-THRD-QS-TKT40 | AH62: THREAD TKT40 210D/3 PLY 10000MTS | AI62: MTR | AJ62: =R62 -> 32.834 | AK62: CBEWIP | AL62: Backflush | AM62: Active | AN62: =AJ62/10000 -> 0.0032834 | AO62: =VLOOKUP(AG62,'RM-cost - feb-24'!B:P,15,0) -> 231.1423 | AP62: =AO62*AN62 -> 0.75893263 | AQ62: =SUM(AP62:AP66) -> 146.42979 | AR62: =ROUND(AQ62,0) -> 146 | AS62: =AR62 -> 146 | AT62: =+AS62+AY62 -> 164.06735 | AU62: =+SUM(((AS62*3%*18%))) -> 0.7884 | AV62: =+SUM(((AS62*14.33%*53%))) -> 11.088554 | AW62: =+SUM(((AS62*5.92%*53%))) -> 4.580896 | AX62: =+SUM(((AS62*2.08%*53%))) -> 1.609504 | AY62: =SUM(AU62:AX66) -> 18.067354 | AZ62: =ROUNDUP(AT62,0) -> 165 | BA62: =AZ62 -> 165
A63: 2 | B63: =B62 -> 11 | C63: =C62 -> ET-COVER | D63: =MID(E63,9,2) -> PT | E63: =E62 -> RTHTMTBNPT75X45X10 | F63: =F62 -> RTHTMTBNPT | G63: =G62 -> 75X45X10 | H63: =H62 -> 75X45X10 | I63: =I62 -> 3 | J63: =J62 -> 6 | K63: =K62 -> 75 | L63: =L62 -> 45 | M63: =M62 -> 10 | N63: ="SFG-FRBNPK-ET-CVR-"&K63&"X"&L63&"X"&M63 -> SFG-FRBNPK-ET-CVR-75X45X10 | O63: =K63*L63/144 -> 23.4375 | P63: =ROUNDUP((((K63*L63/144)*0.003)),3) -> 0.071 | S63: ="Restonic Hotel Motel ET Cover "&K63&"X"&L63&"X"&M63 -> Restonic Hotel Motel ET Cover 75X45X10 | T63: =T62 -> SFG-FRBNPK-ET-CVR-75X45X10 | U63: =T63=N63 -> TRUE | V63: =S63=W63 -> TRUE | W63: =W62 -> Restonic Hotel Motel ET Cover 75X45X10 | X63: Standard | Y63: Production | Z63: TAIL-ET-PT | AA63: NOS | AB63: 1 | AC63: MRP&Rollup | AD63: CBESFG | AE63: 20 | AF63: I | AG63: RM-NWN-70GSMX6INCH | AH63: NON WOVEN FABRIC 70GSMX6" | AI63: KGS | AJ63: 0.06 | AK63: CBEWIP | AL63: Backflush | AM63: Active | AN63: =AJ63 -> 0.06 | AO63: =VLOOKUP(AG63,'RM-cost - feb-24'!B:P,15,0) -> 113.786 | AP63: =AO63*AN63 -> 6.82716 | AS63: =AS62 -> 146
A64: 3 | B64: =B63 -> 11 | C64: =C63 -> ET-COVER | D64: =MID(E64,9,2) -> PT | E64: =E63 -> RTHTMTBNPT75X45X10 | F64: =F63 -> RTHTMTBNPT | G64: =G63 -> 75X45X10 | H64: =H63 -> 75X45X10 | I64: =I63 -> 3 | J64: =J63 -> 6 | K64: =K63 -> 75 | L64: =L63 -> 45 | M64: =M63 -> 10 | N64: ="SFG-FRBNPK-ET-CVR-"&K64&"X"&L64&"X"&M64 -> SFG-FRBNPK-ET-CVR-75X45X10 | P64: =ROUNDUP((((K64*L64/144)*0.00692)),3) -> 0.163 | Q64: =P64=AJ64 -> FALSE | S64: ="Restonic Hotel Motel ET Cover "&K64&"X"&L64&"X"&M64 -> Restonic Hotel Motel ET Cover 75X45X10 | T64: =T63 -> SFG-FRBNPK-ET-CVR-75X45X10 | U64: =T64=N64 -> TRUE | V64: =S64=W64 -> TRUE | W64: =W63 -> Restonic Hotel Motel ET Cover 75X45X10 | X64: Standard | Y64: Production | Z64: TAIL-ET-PT | AA64: NOS | AB64: 1 | AC64: MRP&Rollup | AD64: CBESFG | AE64: 30 | AF64: I | AG64: RML-NWN-70GSMX76" | AH64: NON WOVEN FABRIC WHITE 70 GSM 76 INCH | AI64: KGS | AJ64: 0.157 | AK64: CBEWIP | AL64: Backflush | AM64: Active | AN64: =AJ64 -> 0.157 | AO64: =VLOOKUP(AG64,'RM-cost - feb-24'!B:P,15,0) -> 112.8872 | AP64: =AO64*AN64 -> 17.72329 | AS64: =AS63 -> 146
A65: 4 | B65: =B64 -> 11 | C65: =C64 -> ET-COVER | D65: =MID(E65,9,2) -> PT | E65: =E64 -> RTHTMTBNPT75X45X10 | F65: =F64 -> RTHTMTBNPT | G65: =G64 -> 75X45X10 | H65: =H64 -> 75X45X10 | I65: =I64 -> 3 | J65: =J64 -> 6 | K65: =K64 -> 75 | L65: =L64 -> 45 | M65: =M64 -> 10 | N65: ="SFG-FRBNPK-ET-CVR-"&K65&"X"&L65&"X"&M65 -> SFG-FRBNPK-ET-CVR-75X45X10 | P65: =ROUND(((((K65+L65+K65+L65)+3))*0.0254),3) -> 6.172 | Q65: =P65=AJ65 -> TRUE | S65: ="Restonic Hotel Motel ET Cover "&K65&"X"&L65&"X"&M65 -> Restonic Hotel Motel ET Cover 75X45X10 | T65: =T64 -> SFG-FRBNPK-ET-CVR-75X45X10 | U65: =T65=N65 -> TRUE | V65: =S65=W65 -> TRUE | W65: =W64 -> Restonic Hotel Motel ET Cover 75X45X10 | X65: Standard | Y65: Production | Z65: TAIL-ET-PT | AA65: NOS | AB65: 1 | AC65: MRP&Rollup | AD65: CBESFG | AE65: 40 | AF65: I | AG65: SFG-RTHTMT-BNPK-ETBOR-11CM | AH65: Hotel Motel Poc ET-10 & 12 8MM/16D Pre Foam Border 11 CM Height | AI65: MTR | AJ65: =P65 -> 6.172 | AK65: CBESFG | AL65: Backflush | AM65: Active | AN65: =AJ65 -> 6.172 | AO65: =VLOOKUP(AG65,'SFG-rate rm - feb-24'!A:B,2,0) -> 19.60538 | AP65: =AO65*AN65 -> 121.00441 | AS65: =AS64 -> 146
A66: 5 | B66: =B65 -> 11 | C66: =C65 -> ET-COVER | D66: =MID(E66,9,2) -> PT | E66: =E65 -> RTHTMTBNPT75X45X10 | F66: =F65 -> RTHTMTBNPT | G66: =G65 -> 75X45X10 | H66: =H65 -> 75X45X10 | I66: =I65 -> 3 | J66: =J65 -> 6 | K66: =K65 -> 75 | L66: =L65 -> 45 | M66: =M65 -> 10 | N66: ="SFG-FRBNPK-ET-CVR-"&K66&"X"&L66&"X"&M66 -> SFG-FRBNPK-ET-CVR-75X45X10 | P66: 10 | Q66: =P66=AJ66 -> TRUE | S66: ="Restonic Hotel Motel ET Cover "&K66&"X"&L66&"X"&M66 -> Restonic Hotel Motel ET Cover 75X45X10 | T66: =T65 -> SFG-FRBNPK-ET-CVR-75X45X10 | U66: =T66=N66 -> TRUE | V66: =S66=W66 -> TRUE | W66: =W65 -> Restonic Hotel Motel ET Cover 75X45X10 | X66: Standard | Y66: Production | Z66: TAIL-ET-PT | AA66: NOS | AB66: 1 | AC66: MRP&Rollup | AD66: CBESFG | AE66: 50 | AF66: I | AG66: HW-CTON-THREAD | AH66: COTTON THREAD WHITE 3PLY | AI66: MTR | AJ66: =P66 -> 10 | AK66: CBEWIP | AL66: Backflush | AM66: Active | AN66: =AJ66/5000 -> 0.002 | AO66: =VLOOKUP(AG66,'RM-cost - feb-24'!B:P,15,0) -> 58 | AP66: =AO66*AN66 -> 0.116 | AS66: =AS65 -> 146
A68: 1 | B68: 12 | C68: ET-COVER | D68: =MID(E68,9,2) -> PT | E68: RTHTMTBNPT75X51X10 | F68: =LEFT(E68,MIN(FIND({0,1,2,3,4,5,6,7,8,9},E68&"0123456789"))-1) -> RTHTMTBNPT | G68: =SUBSTITUTE(E68,F68,"") -> 75X51X10 | H68: =IFERROR(LEFT(G68,FIND("-",G68)-1),G68) -> 75X51X10 | I68: =SEARCH("X",H68) -> 3 | J68: =SEARCH("X",H68,I68+1) -> 6 | K68: =LEFT(G68,SEARCH("x",G68)-1) -> 75 | L68: =MID(H68,I68+1,J68-I68-1) -> 51 | M68: =MID(H68,J68+1,20) -> 10 | N68: ="SFG-FRBNPK-ET-CVR-"&K68&"X"&L68&"X"&M68 -> SFG-FRBNPK-ET-CVR-75X51X10 | P68: =ROUND(((((K68+L68+K68+L68)+3)*0.0254)*5.3196),3) -> 34.455 | Q68: 0 | R68: =P68+Q68 -> 34.455 | S68: ="Restonic Hotel Motel ET Cover "&K68&"X"&L68&"X"&M68 -> Restonic Hotel Motel ET Cover 75X51X10 | T68: =N68 -> SFG-FRBNPK-ET-CVR-75X51X10 | U68: =T68=N68 -> TRUE | V68: =S68=W68 -> TRUE | W68: =S68 -> Restonic Hotel Motel ET Cover 75X51X10 | X68: Standard | Y68: Production | Z68: TAIL-ET-PT | AA68: NOS | AB68: 1 | AC68: MRP&Rollup | AD68: CBESFG | AE68: 10 | AF68: I | AG68: RM-THRD-QS-TKT40 | AH68: THREAD TKT40 210D/3 PLY 10000MTS | AI68: MTR | AJ68: =R68 -> 34.455 | AK68: CBEWIP | AL68: Backflush | AM68: Active | AN68: =AJ68/10000 -> 0.0034455 | AO68: =VLOOKUP(AG68,'RM-cost - feb-24'!B:P,15,0) -> 231.1423 | AP68: =AO68*AN68 -> 0.79640079 | AQ68: =SUM(AP68:AP72) -> 154.59445 | AR68: =ROUND(AQ68,0) -> 155 | AS68: =AR68 -> 155 | AT68: =+AS68+AY68 -> 174.18109 | AU68: =+SUM(((AS68*3%*18%))) -> 0.837 | AV68: =+SUM(((AS68*14.33%*53%))) -> 11.772095 | AW68: =+SUM(((AS68*5.92%*53%))) -> 4.86328 | AX68: =+SUM(((AS68*2.08%*53%))) -> 1.70872 | AY68: =SUM(AU68:AX72) -> 19.181095 | AZ68: =ROUNDUP(AT68,0) -> 175 | BA68: =AZ68 -> 175
A69: 2 | B69: =B68 -> 12 | C69: =C68 -> ET-COVER | D69: =MID(E69,9,2) -> PT | E69: =E68 -> RTHTMTBNPT75X51X10 | F69: =F68 -> RTHTMTBNPT | G69: =G68 -> 75X51X10 | H69: =H68 -> 75X51X10 | I69: =I68 -> 3 | J69: =J68 -> 6 | K69: =K68 -> 75 | L69: =L68 -> 51 | M69: =M68 -> 10 | N69: ="SFG-FRBNPK-ET-CVR-"&K69&"X"&L69&"X"&M69 -> SFG-FRBNPK-ET-CVR-75X51X10 | O69: =K69*L69/144 -> 26.5625 | P69: =ROUNDUP((((K69*L69/144)*0.003)),3) -> 0.08 | S69: ="Restonic Hotel Motel ET Cover "&K69&"X"&L69&"X"&M69 -> Restonic Hotel Motel ET Cover 75X51X10 | T69: =T68 -> SFG-FRBNPK-ET-CVR-75X51X10 | U69: =T69=N69 -> TRUE | V69: =S69=W69 -> TRUE | W69: =W68 -> Restonic Hotel Motel ET Cover 75X51X10 | X69: Standard | Y69: Production | Z69: TAIL-ET-PT | AA69: NOS | AB69: 1 | AC69: MRP&Rollup | AD69: CBESFG | AE69: 20 | AF69: I | AG69: RM-NWN-70GSMX6INCH | AH69: NON WOVEN FABRIC 70GSMX6" | AI69: KGS | AJ69: 0.063 | AK69: CBEWIP | AL69: Backflush | AM69: Active | AN69: =AJ69 -> 0.063 | AO69: =VLOOKUP(AG69,'RM-cost - feb-24'!B:P,15,0) -> 113.786 | AP69: =AO69*AN69 -> 7.168518 | AS69: =AS68 -> 155
A70: 3 | B70: =B69 -> 12 | C70: =C69 -> ET-COVER | D70: =MID(E70,9,2) -> PT | E70: =E69 -> RTHTMTBNPT75X51X10 | F70: =F69 -> RTHTMTBNPT | G70: =G69 -> 75X51X10 | H70: =H69 -> 75X51X10 | I70: =I69 -> 3 | J70: =J69 -> 6 | K70: =K69 -> 75 | L70: =L69 -> 51 | M70: =M69 -> 10 | N70: ="SFG-FRBNPK-ET-CVR-"&K70&"X"&L70&"X"&M70 -> SFG-FRBNPK-ET-CVR-75X51X10 | P70: =ROUNDUP((((K70*L70/144)*0.00692)),3) -> 0.184 | Q70: =P70=AJ70 -> FALSE | S70: ="Restonic Hotel Motel ET Cover "&K70&"X"&L70&"X"&M70 -> Restonic Hotel Motel ET Cover 75X51X10 | T70: =T69 -> SFG-FRBNPK-ET-CVR-75X51X10 | U70: =T70=N70 -> TRUE | V70: =S70=W70 -> TRUE | W70: =W69 -> Restonic Hotel Motel ET Cover 75X51X10 | X70: Standard | Y70: Production | Z70: TAIL-ET-PT | AA70: NOS | AB70: 1 | AC70: MRP&Rollup | AD70: CBESFG | AE70: 30 | AF70: I | AG70: RML-NWN-70GSMX76" | AH70: NON WOVEN FABRIC WHITE 70 GSM 76 INCH | AI70: KGS | AJ70: 0.173 | AK70: CBEWIP | AL70: Backflush | AM70: Active | AN70: =AJ70 -> 0.173 | AO70: =VLOOKUP(AG70,'RM-cost - feb-24'!B:P,15,0) -> 112.8872 | AP70: =AO70*AN70 -> 19.529486 | AS70: =AS69 -> 155
A71: 4 | B71: =B70 -> 12 | C71: =C70 -> ET-COVER | D71: =MID(E71,9,2) -> PT | E71: =E70 -> RTHTMTBNPT75X51X10 | F71: =F70 -> RTHTMTBNPT | G71: =G70 -> 75X51X10 | H71: =H70 -> 75X51X10 | I71: =I70 -> 3 | J71: =J70 -> 6 | K71: =K70 -> 75 | L71: =L70 -> 51 | M71: =M70 -> 10 | N71: ="SFG-FRBNPK-ET-CVR-"&K71&"X"&L71&"X"&M71 -> SFG-FRBNPK-ET-CVR-75X51X10 | P71: =ROUND(((((K71+L71+K71+L71)+3))*0.0254),3) -> 6.477 | Q71: =P71=AJ71 -> TRUE | S71: ="Restonic Hotel Motel ET Cover "&K71&"X"&L71&"X"&M71 -> Restonic Hotel Motel ET Cover 75X51X10 | T71: =T70 -> SFG-FRBNPK-ET-CVR-75X51X10 | U71: =T71=N71 -> TRUE | V71: =S71=W71 -> TRUE | W71: =W70 -> Restonic Hotel Motel ET Cover 75X51X10 | X71: Standard | Y71: Production | Z71: TAIL-ET-PT | AA71: NOS | AB71: 1 | AC71: MRP&Rollup | AD71: CBESFG | AE71: 40 | AF71: I | AG71: SFG-RTHTMT-BNPK-ETBOR-11CM | AH71: Hotel Motel Poc ET-10 & 12 8MM/16D Pre Foam Border 11 CM Height | AI71: MTR | AJ71: =P71 -> 6.477 | AK71: CBESFG | AL71: Backflush | AM71: Active | AN71: =AJ71 -> 6.477 | AO71: =VLOOKUP(AG71,'SFG-rate rm - feb-24'!A:B,2,0) -> 19.60538 | AP71: =AO71*AN71 -> 126.98405 | AS71: =AS70 -> 155
A72: 5 | B72: =B71 -> 12 | C72: =C71 -> ET-COVER | D72: =MID(E72,9,2) -> PT | E72: =E71 -> RTHTMTBNPT75X51X10 | F72: =F71 -> RTHTMTBNPT | G72: =G71 -> 75X51X10 | H72: =H71 -> 75X51X10 | I72: =I71 -> 3 | J72: =J71 -> 6 | K72: =K71 -> 75 | L72: =L71 -> 51 | M72: =M71 -> 10 | N72: ="SFG-FRBNPK-ET-CVR-"&K72&"X"&L72&"X"&M72 -> SFG-FRBNPK-ET-CVR-75X51X10 | P72: 10 | Q72: =P72=AJ72 -> TRUE | S72: ="Restonic Hotel Motel ET Cover "&K72&"X"&L72&"X"&M72 -> Restonic Hotel Motel ET Cover 75X51X10 | T72: =T71 -> SFG-FRBNPK-ET-CVR-75X51X10 | U72: =T72=N72 -> TRUE | V72: =S72=W72 -> TRUE | W72: =W71 -> Restonic Hotel Motel ET Cover 75X51X10 | X72: Standard | Y72: Production | Z72: TAIL-ET-PT | AA72: NOS | AB72: 1 | AC72: MRP&Rollup | AD72: CBESFG | AE72: 50 | AF72: I | AG72: HW-CTON-THREAD | AH72: COTTON THREAD WHITE 3PLY | AI72: MTR | AJ72: =P72 -> 10 | AK72: CBEWIP | AL72: Backflush | AM72: Active | AN72: =AJ72/5000 -> 0.002 | AO72: =VLOOKUP(AG72,'RM-cost - feb-24'!B:P,15,0) -> 58 | AP72: =AO72*AN72 -> 0.116 | AS72: =AS71 -> 155
A74: 1 | B74: 13 | C74: ET-COVER | D74: =MID(E74,9,2) -> PT | E74: RTHTMTBNPT75X54X10 | F74: =LEFT(E74,MIN(FIND({0,1,2,3,4,5,6,7,8,9},E74&"0123456789"))-1) -> RTHTMTBNPT | G74: =SUBSTITUTE(E74,F74,"") -> 75X54X10 | H74: =IFERROR(LEFT(G74,FIND("-",G74)-1),G74) -> 75X54X10 | I74: =SEARCH("X",H74) -> 3 | J74: =SEARCH("X",H74,I74+1) -> 6 | K74: =LEFT(G74,SEARCH("x",G74)-1) -> 75 | L74: =MID(H74,I74+1,J74-I74-1) -> 54 | M74: =MID(H74,J74+1,20) -> 10 | N74: ="SFG-FRBNPK-ET-CVR-"&K74&"X"&L74&"X"&M74 -> SFG-FRBNPK-ET-CVR-75X54X10 | P74: =ROUND(((((K74+L74+K74+L74)+3)*0.0254)*5.3196),3) -> 35.266 | Q74: 0 | R74: =P74+Q74 -> 35.266 | S74: ="Restonic Hotel Motel ET Cover "&K74&"X"&L74&"X"&M74 -> Restonic Hotel Motel ET Cover 75X54X10 | T74: =N74 -> SFG-FRBNPK-ET-CVR-75X54X10 | U74: =T74=N74 -> TRUE | V74: =S74=W74 -> TRUE | W74: =S74 -> Restonic Hotel Motel ET Cover 75X54X10 | X74: Standard | Y74: Production | Z74: TAIL-ET-PT | AA74: NOS | AB74: 1 | AC74: MRP&Rollup | AD74: CBESFG | AE74: 10 | AF74: I | AG74: RM-THRD-QS-TKT40 | AH74: THREAD TKT40 210D/3 PLY 10000MTS | AI74: MTR | AJ74: =R74 -> 35.266 | AK74: CBEWIP | AL74: Backflush | AM74: Active | AN74: =AJ74/10000 -> 0.0035266 | AO74: =VLOOKUP(AG74,'RM-cost - feb-24'!B:P,15,0) -> 231.1423 | AP74: =AO74*AN74 -> 0.81514644 | AQ74: =SUM(AP74:AP78) -> 159.06165 | AR74: =ROUND(AQ74,0) -> 159 | AS74: =AR74 -> 159 | AT74: =+AS74+AY74 -> 178.67609 | AU74: =+SUM(((AS74*3%*18%))) -> 0.8586 | AV74: =+SUM(((AS74*14.33%*53%))) -> 12.075891 | AW74: =+SUM(((AS74*5.92%*53%))) -> 4.988784 | AX74: =+SUM(((AS74*2.08%*53%))) -> 1.752816 | AY74: =SUM(AU74:AX78) -> 19.676091 | AZ74: =ROUNDUP(AT74,0) -> 179 | BA74: =AZ74 -> 179
A75: 2 | B75: =B74 -> 13 | C75: =C74 -> ET-COVER | D75: =MID(E75,9,2) -> PT | E75: =E74 -> RTHTMTBNPT75X54X10 | F75: =F74 -> RTHTMTBNPT | G75: =G74 -> 75X54X10 | H75: =H74 -> 75X54X10 | I75: =I74 -> 3 | J75: =J74 -> 6 | K75: =K74 -> 75 | L75: =L74 -> 54 | M75: =M74 -> 10 | N75: ="SFG-FRBNPK-ET-CVR-"&K75&"X"&L75&"X"&M75 -> SFG-FRBNPK-ET-CVR-75X54X10 | O75: =K75*L75/144 -> 28.125 | P75: =ROUNDUP((((K75*L75/144)*0.003)),3) -> 0.085 | S75: ="Restonic Hotel Motel ET Cover "&K75&"X"&L75&"X"&M75 -> Restonic Hotel Motel ET Cover 75X54X10 | T75: =T74 -> SFG-FRBNPK-ET-CVR-75X54X10 | U75: =T75=N75 -> TRUE | V75: =S75=W75 -> TRUE | W75: =W74 -> Restonic Hotel Motel ET Cover 75X54X10 | X75: Standard | Y75: Production | Z75: TAIL-ET-PT | AA75: NOS | AB75: 1 | AC75: MRP&Rollup | AD75: CBESFG | AE75: 20 | AF75: I | AG75: RM-NWN-70GSMX6INCH | AH75: NON WOVEN FABRIC 70GSMX6" | AI75: KGS | AJ75: 0.064 | AK75: CBEWIP | AL75: Backflush | AM75: Active | AN75: =AJ75 -> 0.064 | AO75: =VLOOKUP(AG75,'RM-cost - feb-24'!B:P,15,0) -> 113.786 | AP75: =AO75*AN75 -> 7.282304 | AS75: =AS74 -> 159
A76: 3 | B76: =B75 -> 13 | C76: =C75 -> ET-COVER | D76: =MID(E76,9,2) -> PT | E76: =E75 -> RTHTMTBNPT75X54X10 | F76: =F75 -> RTHTMTBNPT | G76: =G75 -> 75X54X10 | H76: =H75 -> 75X54X10 | I76: =I75 -> 3 | J76: =J75 -> 6 | K76: =K75 -> 75 | L76: =L75 -> 54 | M76: =M75 -> 10 | N76: ="SFG-FRBNPK-ET-CVR-"&K76&"X"&L76&"X"&M76 -> SFG-FRBNPK-ET-CVR-75X54X10 | P76: =ROUNDUP((((K76*L76/144)*0.00692)),3) -> 0.195 | Q76: =P76=AJ76 -> FALSE | S76: ="Restonic Hotel Motel ET Cover "&K76&"X"&L76&"X"&M76 -> Restonic Hotel Motel ET Cover 75X54X10 | T76: =T75 -> SFG-FRBNPK-ET-CVR-75X54X10 | U76: =T76=N76 -> TRUE | V76: =S76=W76 -> TRUE | W76: =W75 -> Restonic Hotel Motel ET Cover 75X54X10 | X76: Standard | Y76: Production | Z76: TAIL-ET-PT | AA76: NOS | AB76: 1 | AC76: MRP&Rollup | AD76: CBESFG | AE76: 30 | AF76: I | AG76: RML-NWN-70GSMX76" | AH76: NON WOVEN FABRIC WHITE 70 GSM 76 INCH | AI76: KGS | AJ76: 0.185 | AK76: CBEWIP | AL76: Backflush | AM76: Active | AN76: =AJ76 -> 0.185 | AO76: =VLOOKUP(AG76,'RM-cost - feb-24'!B:P,15,0) -> 112.8872 | AP76: =AO76*AN76 -> 20.884132 | AS76: =AS75 -> 159
A77: 4 | B77: =B76 -> 13 | C77: =C76 -> ET-COVER | D77: =MID(E77,9,2) -> PT | E77: =E76 -> RTHTMTBNPT75X54X10 | F77: =F76 -> RTHTMTBNPT | G77: =G76 -> 75X54X10 | H77: =H76 -> 75X54X10 | I77: =I76 -> 3 | J77: =J76 -> 6 | K77: =K76 -> 75 | L77: =L76 -> 54 | M77: =M76 -> 10 | N77: ="SFG-FRBNPK-ET-CVR-"&K77&"X"&L77&"X"&M77 -> SFG-FRBNPK-ET-CVR-75X54X10 | P77: =ROUND(((((K77+L77+K77+L77)+3))*0.0254),3) -> 6.629 | Q77: =P77=AJ77 -> TRUE | S77: ="Restonic Hotel Motel ET Cover "&K77&"X"&L77&"X"&M77 -> Restonic Hotel Motel ET Cover 75X54X10 | T77: =T76 -> SFG-FRBNPK-ET-CVR-75X54X10 | U77: =T77=N77 -> TRUE | V77: =S77=W77 -> TRUE | W77: =W76 -> Restonic Hotel Motel ET Cover 75X54X10 | X77: Standard | Y77: Production | Z77: TAIL-ET-PT | AA77: NOS | AB77: 1 | AC77: MRP&Rollup | AD77: CBESFG | AE77: 40 | AF77: I | AG77: SFG-RTHTMT-BNPK-ETBOR-11CM | AH77: Hotel Motel Poc ET-10 & 12 8MM/16D Pre Foam Border 11 CM Height | AI77: MTR | AJ77: =P77 -> 6.629 | AK77: CBESFG | AL77: Backflush | AM77: Active | AN77: =AJ77 -> 6.629 | AO77: =VLOOKUP(AG77,'SFG-rate rm - feb-24'!A:B,2,0) -> 19.60538 | AP77: =AO77*AN77 -> 129.96407 | AS77: =AS76 -> 159
A78: 5 | B78: =B77 -> 13 | C78: =C77 -> ET-COVER | D78: =MID(E78,9,2) -> PT | E78: =E77 -> RTHTMTBNPT75X54X10 | F78: =F77 -> RTHTMTBNPT | G78: =G77 -> 75X54X10 | H78: =H77 -> 75X54X10 | I78: =I77 -> 3 | J78: =J77 -> 6 | K78: =K77 -> 75 | L78: =L77 -> 54 | M78: =M77 -> 10 | N78: ="SFG-FRBNPK-ET-CVR-"&K78&"X"&L78&"X"&M78 -> SFG-FRBNPK-ET-CVR-75X54X10 | P78: 10 | Q78: =P78=AJ78 -> TRUE | S78: ="Restonic Hotel Motel ET Cover "&K78&"X"&L78&"X"&M78 -> Restonic Hotel Motel ET Cover 75X54X10 | T78: =T77 -> SFG-FRBNPK-ET-CVR-75X54X10 | U78: =T78=N78 -> TRUE | V78: =S78=W78 -> TRUE | W78: =W77 -> Restonic Hotel Motel ET Cover 75X54X10 | X78: Standard | Y78: Production | Z78: TAIL-ET-PT | AA78: NOS | AB78: 1 | AC78: MRP&Rollup | AD78: CBESFG | AE78: 50 | AF78: I | AG78: HW-CTON-THREAD | AH78: COTTON THREAD WHITE 3PLY | AI78: MTR | AJ78: =P78 -> 10 | AK78: CBEWIP | AL78: Backflush | AM78: Active | AN78: =AJ78/5000 -> 0.002 | AO78: =VLOOKUP(AG78,'RM-cost - feb-24'!B:P,15,0) -> 58 | AP78: =AO78*AN78 -> 0.116 | AS78: =AS77 -> 159
A80: 1 | B80: 14 | C80: ET-COVER | D80: =MID(E80,9,2) -> PT | E80: RTHTMTBNPT75X57X10 | F80: =LEFT(E80,MIN(FIND({0,1,2,3,4,5,6,7,8,9},E80&"0123456789"))-1) -> RTHTMTBNPT | G80: =SUBSTITUTE(E80,F80,"") -> 75X57X10 | H80: =IFERROR(LEFT(G80,FIND("-",G80)-1),G80) -> 75X57X10 | I80: =SEARCH("X",H80) -> 3 | J80: =SEARCH("X",H80,I80+1) -> 6 | K80: =LEFT(G80,SEARCH("x",G80)-1) -> 75 | L80: =MID(H80,I80+1,J80-I80-1) -> 57 | M80: =MID(H80,J80+1,20) -> 10 | N80: ="SFG-FRBNPK-ET-CVR-"&K80&"X"&L80&"X"&M80 -> SFG-FRBNPK-ET-CVR-75X57X10 | P80: =ROUND(((((K80+L80+K80+L80)+3)*0.0254)*5.3196),3) -> 36.076 | Q80: 0 | R80: =P80+Q80 -> 36.076 | S80: ="Restonic Hotel Motel ET Cover "&K80&"X"&L80&"X"&M80 -> Restonic Hotel Motel ET Cover 75X57X10 | T80: =N80 -> SFG-FRBNPK-ET-CVR-75X57X10 | U80: =T80=N80 -> TRUE | V80: =S80=W80 -> TRUE | W80: =S80 -> Restonic Hotel Motel ET Cover 75X57X10 | X80: Standard | Y80: Production | Z80: TAIL-ET-PT | AA80: NOS | AB80: 1 | AC80: MRP&Rollup | AD80: CBESFG | AE80: 10 | AF80: I | AG80: RM-THRD-QS-TKT40 | AH80: THREAD TKT40 210D/3 PLY 10000MTS | AI80: MTR | AJ80: =R80 -> 36.076 | AK80: CBEWIP | AL80: Backflush | AM80: Active | AN80: =AJ80/10000 -> 0.0036076 | AO80: =VLOOKUP(AG80,'RM-cost - feb-24'!B:P,15,0) -> 231.1423 | AP80: =AO80*AN80 -> 0.83386896 | AQ80: =SUM(AP80:AP84) -> 163.54933 | AR80: =ROUND(AQ80,0) -> 164 | AS80: =AR80 -> 164 | AT80: =+AS80+AY80 -> 184.29484 | AU80: =+SUM(((AS80*3%*18%))) -> 0.8856 | AV80: =+SUM(((AS80*14.33%*53%))) -> 12.455636 | AW80: =+SUM(((AS80*5.92%*53%))) -> 5.145664 | AX80: =+SUM(((AS80*2.08%*53%))) -> 1.807936 | AY80: =SUM(AU80:AX84) -> 20.294836 | AZ80: =ROUNDUP(AT80,0) -> 185 | BA80: =AZ80 -> 185
A81: 2 | B81: =B80 -> 14 | C81: =C80 -> ET-COVER | D81: =MID(E81,9,2) -> PT | E81: =E80 -> RTHTMTBNPT75X57X10 | F81: =F80 -> RTHTMTBNPT | G81: =G80 -> 75X57X10 | H81: =H80 -> 75X57X10 | I81: =I80 -> 3 | J81: =J80 -> 6 | K81: =K80 -> 75 | L81: =L80 -> 57 | M81: =M80 -> 10 | N81: ="SFG-FRBNPK-ET-CVR-"&K81&"X"&L81&"X"&M81 -> SFG-FRBNPK-ET-CVR-75X57X10 | O81: =K81*L81/144 -> 29.6875 | P81: =ROUNDUP((((K81*L81/144)*0.003)),3) -> 0.09 | S81: ="Restonic Hotel Motel ET Cover "&K81&"X"&L81&"X"&M81 -> Restonic Hotel Motel ET Cover 75X57X10 | T81: =T80 -> SFG-FRBNPK-ET-CVR-75X57X10 | U81: =T81=N81 -> TRUE | V81: =S81=W81 -> TRUE | W81: =W80 -> Restonic Hotel Motel ET Cover 75X57X10 | X81: Standard | Y81: Production | Z81: TAIL-ET-PT | AA81: NOS | AB81: 1 | AC81: MRP&Rollup | AD81: CBESFG | AE81: 20 | AF81: I | AG81: RM-NWN-70GSMX6INCH | AH81: NON WOVEN FABRIC 70GSMX6" | AI81: KGS | AJ81: 0.066 | AK81: CBEWIP | AL81: Backflush | AM81: Active | AN81: =AJ81 -> 0.066 | AO81: =VLOOKUP(AG81,'RM-cost - feb-24'!B:P,15,0) -> 113.786 | AP81: =AO81*AN81 -> 7.509876 | AS81: =AS80 -> 164
A82: 3 | B82: =B81 -> 14 | C82: =C81 -> ET-COVER | D82: =MID(E82,9,2) -> PT | E82: =E81 -> RTHTMTBNPT75X57X10 | F82: =F81 -> RTHTMTBNPT | G82: =G81 -> 75X57X10 | H82: =H81 -> 75X57X10 | I82: =I81 -> 3 | J82: =J81 -> 6 | K82: =K81 -> 75 | L82: =L81 -> 57 | M82: =M81 -> 10 | N82: ="SFG-FRBNPK-ET-CVR-"&K82&"X"&L82&"X"&M82 -> SFG-FRBNPK-ET-CVR-75X57X10 | P82: =ROUNDUP((((K82*L82/144)*0.00692)),3) -> 0.206 | Q82: =P82=AJ82 -> FALSE | S82: ="Restonic Hotel Motel ET Cover "&K82&"X"&L82&"X"&M82 -> Restonic Hotel Motel ET Cover 75X57X10 | T82: =T81 -> SFG-FRBNPK-ET-CVR-75X57X10 | U82: =T82=N82 -> TRUE | V82: =S82=W82 -> TRUE | W82: =W81 -> Restonic Hotel Motel ET Cover 75X57X10 | X82: Standard | Y82: Production | Z82: TAIL-ET-PT | AA82: NOS | AB82: 1 | AC82: MRP&Rollup | AD82: CBESFG | AE82: 30 | AF82: I | AG82: RML-NWN-70GSMX76" | AH82: NON WOVEN FABRIC WHITE 70 GSM 76 INCH | AI82: KGS | AJ82: 0.196 | AK82: CBEWIP | AL82: Backflush | AM82: Active | AN82: =AJ82 -> 0.196 | AO82: =VLOOKUP(AG82,'RM-cost - feb-24'!B:P,15,0) -> 112.8872 | AP82: =AO82*AN82 -> 22.125891 | AS82: =AS81 -> 164
A83: 4 | B83: =B82 -> 14 | C83: =C82 -> ET-COVER | D83: =MID(E83,9,2) -> PT | E83: =E82 -> RTHTMTBNPT75X57X10 | F83: =F82 -> RTHTMTBNPT | G83: =G82 -> 75X57X10 | H83: =H82 -> 75X57X10 | I83: =I82 -> 3 | J83: =J82 -> 6 | K83: =K82 -> 75 | L83: =L82 -> 57 | M83: =M82 -> 10 | N83: ="SFG-FRBNPK-ET-CVR-"&K83&"X"&L83&"X"&M83 -> SFG-FRBNPK-ET-CVR-75X57X10 | P83: =ROUND(((((K83+L83+K83+L83)+3))*0.0254),3) -> 6.782 | Q83: =P83=AJ83 -> TRUE | S83: ="Restonic Hotel Motel ET Cover "&K83&"X"&L83&"X"&M83 -> Restonic Hotel Motel ET Cover 75X57X10 | T83: =T82 -> SFG-FRBNPK-ET-CVR-75X57X10 | U83: =T83=N83 -> TRUE | V83: =S83=W83 -> TRUE | W83: =W82 -> Restonic Hotel Motel ET Cover 75X57X10 | X83: Standard | Y83: Production | Z83: TAIL-ET-PT | AA83: NOS | AB83: 1 | AC83: MRP&Rollup | AD83: CBESFG | AE83: 40 | AF83: I | AG83: SFG-RTHTMT-BNPK-ETBOR-11CM | AH83: Hotel Motel Poc ET-10 & 12 8MM/16D Pre Foam Border 11 CM Height | AI83: MTR | AJ83: =P83 -> 6.782 | AK83: CBESFG | AL83: Backflush | AM83: Active | AN83: =AJ83 -> 6.782 | AO83: =VLOOKUP(AG83,'SFG-rate rm - feb-24'!A:B,2,0) -> 19.60538 | AP83: =AO83*AN83 -> 132.96369 | AS83: =AS82 -> 164
A84: 5 | B84: =B83 -> 14 | C84: =C83 -> ET-COVER | D84: =MID(E84,9,2) -> PT | E84: =E83 -> RTHTMTBNPT75X57X10 | F84: =F83 -> RTHTMTBNPT | G84: =G83 -> 75X57X10 | H84: =H83 -> 75X57X10 | I84: =I83 -> 3 | J84: =J83 -> 6 | K84: =K83 -> 75 | L84: =L83 -> 57 | M84: =M83 -> 10 | N84: ="SFG-FRBNPK-ET-CVR-"&K84&"X"&L84&"X"&M84 -> SFG-FRBNPK-ET-CVR-75X57X10 | P84: 10 | Q84: =P84=AJ84 -> TRUE | S84: ="Restonic Hotel Motel ET Cover "&K84&"X"&L84&"X"&M84 -> Restonic Hotel Motel ET Cover 75X57X10 | T84: =T83 -> SFG-FRBNPK-ET-CVR-75X57X10 | U84: =T84=N84 -> TRUE | V84: =S84=W84 -> TRUE | W84: =W83 -> Restonic Hotel Motel ET Cover 75X57X10 | X84: Standard | Y84: Production | Z84: TAIL-ET-PT | AA84: NOS | AB84: 1 | AC84: MRP&Rollup | AD84: CBESFG | AE84: 50 | AF84: I | AG84: HW-CTON-THREAD | AH84: COTTON THREAD WHITE 3PLY | AI84: MTR | AJ84: =P84 -> 10 | AK84: CBEWIP | AL84: Backflush | AM84: Active | AN84: =AJ84/5000 -> 0.002 | AO84: =VLOOKUP(AG84,'RM-cost - feb-24'!B:P,15,0) -> 58 | AP84: =AO84*AN84 -> 0.116 | AS84: =AS83 -> 164
A86: 1 | B86: 15 | C86: ET-COVER | D86: =MID(E86,9,2) -> PT | E86: RTHTMTBNPT75X63X10 | F86: =LEFT(E86,MIN(FIND({0,1,2,3,4,5,6,7,8,9},E86&"0123456789"))-1) -> RTHTMTBNPT | G86: =SUBSTITUTE(E86,F86,"") -> 75X63X10 | H86: =IFERROR(LEFT(G86,FIND("-",G86)-1),G86) -> 75X63X10 | I86: =SEARCH("X",H86) -> 3 | J86: =SEARCH("X",H86,I86+1) -> 6 | K86: =LEFT(G86,SEARCH("x",G86)-1) -> 75 | L86: =MID(H86,I86+1,J86-I86-1) -> 63 | M86: =MID(H86,J86+1,20) -> 10 | N86: ="SFG-FRBNPK-ET-CVR-"&K86&"X"&L86&"X"&M86 -> SFG-FRBNPK-ET-CVR-75X63X10 | P86: =ROUND(((((K86+L86+K86+L86)+3)*0.0254)*5.3196),3) -> 37.698 | Q86: 0 | R86: =P86+Q86 -> 37.698 | S86: ="Restonic Hotel Motel ET Cover "&K86&"X"&L86&"X"&M86 -> Restonic Hotel Motel ET Cover 75X63X10 | T86: =N86 -> SFG-FRBNPK-ET-CVR-75X63X10 | U86: =T86=N86 -> TRUE | V86: =S86=W86 -> TRUE | W86: =S86 -> Restonic Hotel Motel ET Cover 75X63X10 | X86: Standard | Y86: Production | Z86: TAIL-ET-PT | AA86: NOS | AB86: 1 | AC86: MRP&Rollup | AD86: CBESFG | AE86: 10 | AF86: I | AG86: RM-THRD-QS-TKT40 | AH86: THREAD TKT40 210D/3 PLY 10000MTS | AI86: MTR | AJ86: =R86 -> 37.698 | AK86: CBEWIP | AL86: Backflush | AM86: Active | AN86: =AJ86/10000 -> 0.0037698 | AO86: =VLOOKUP(AG86,'RM-cost - feb-24'!B:P,15,0) -> 231.1423 | AP86: =AO86*AN86 -> 0.87136024 | AQ86: =SUM(AP86:AP90) -> 172.50422 | AR86: =ROUND(AQ86,0) -> 173 | AS86: =AR86 -> 173 | AT86: =+AS86+AY86 -> 194.40858 | AU86: =+SUM(((AS86*3%*18%))) -> 0.9342 | AV86: =+SUM(((AS86*14.33%*53%))) -> 13.139177 | AW86: =+SUM(((AS86*5.92%*53%))) -> 5.428048 | AX86: =+SUM(((AS86*2.08%*53%))) -> 1.907152 | AY86: =SUM(AU86:AX90) -> 21.408577 | AZ86: =ROUNDUP(AT86,0) -> 195 | BA86: =AZ86 -> 195
A87: 2 | B87: =B86 -> 15 | C87: =C86 -> ET-COVER | D87: =MID(E87,9,2) -> PT | E87: =E86 -> RTHTMTBNPT75X63X10 | F87: =F86 -> RTHTMTBNPT | G87: =G86 -> 75X63X10 | H87: =H86 -> 75X63X10 | I87: =I86 -> 3 | J87: =J86 -> 6 | K87: =K86 -> 75 | L87: =L86 -> 63 | M87: =M86 -> 10 | N87: ="SFG-FRBNPK-ET-CVR-"&K87&"X"&L87&"X"&M87 -> SFG-FRBNPK-ET-CVR-75X63X10 | O87: =K87*L87/144 -> 32.8125 | P87: =ROUNDUP((((K87*L87/144)*0.003)),3) -> 0.099 | S87: ="Restonic Hotel Motel ET Cover "&K87&"X"&L87&"X"&M87 -> Restonic Hotel Motel ET Cover 75X63X10 | T87: =T86 -> SFG-FRBNPK-ET-CVR-75X63X10 | U87: =T87=N87 -> TRUE | V87: =S87=W87 -> TRUE | W87: =W86 -> Restonic Hotel Motel ET Cover 75X63X10 | X87: Standard | Y87: Production | Z87: TAIL-ET-PT | AA87: NOS | AB87: 1 | AC87: MRP&Rollup | AD87: CBESFG | AE87: 20 | AF87: I | AG87: RM-NWN-70GSMX6INCH | AH87: NON WOVEN FABRIC 70GSMX6" | AI87: KGS | AJ87: 0.069 | AK87: CBEWIP | AL87: Backflush | AM87: Active | AN87: =AJ87 -> 0.069 | AO87: =VLOOKUP(AG87,'RM-cost - feb-24'!B:P,15,0) -> 113.786 | AP87: =AO87*AN87 -> 7.851234 | AS87: =AS86 -> 173
A88: 3 | B88: =B87 -> 15 | C88: =C87 -> ET-COVER | D88: =MID(E88,9,2) -> PT | E88: =E87 -> RTHTMTBNPT75X63X10 | F88: =F87 -> RTHTMTBNPT | G88: =G87 -> 75X63X10 | H88: =H87 -> 75X63X10 | I88: =I87 -> 3 | J88: =J87 -> 6 | K88: =K87 -> 75 | L88: =L87 -> 63 | M88: =M87 -> 10 | N88: ="SFG-FRBNPK-ET-CVR-"&K88&"X"&L88&"X"&M88 -> SFG-FRBNPK-ET-CVR-75X63X10 | P88: =ROUNDUP((((K88*L88/144)*0.00692)),3) -> 0.228 | Q88: =P88=AJ88 -> FALSE | S88: ="Restonic Hotel Motel ET Cover "&K88&"X"&L88&"X"&M88 -> Restonic Hotel Motel ET Cover 75X63X10 | T88: =T87 -> SFG-FRBNPK-ET-CVR-75X63X10 | U88: =T88=N88 -> TRUE | V88: =S88=W88 -> TRUE | W88: =W87 -> Restonic Hotel Motel ET Cover 75X63X10 | X88: Standard | Y88: Production | Z88: TAIL-ET-PT | AA88: NOS | AB88: 1 | AC88: MRP&Rollup | AD88: CBESFG | AE88: 30 | AF88: I | AG88: RML-NWN-70GSMX76" | AH88: NON WOVEN FABRIC WHITE 70 GSM 76 INCH | AI88: KGS | AJ88: 0.219 | AK88: CBEWIP | AL88: Backflush | AM88: Active | AN88: =AJ88 -> 0.219 | AO88: =VLOOKUP(AG88,'RM-cost - feb-24'!B:P,15,0) -> 112.8872 | AP88: =AO88*AN88 -> 24.722297 | AS88: =AS87 -> 173
A89: 4 | B89: =B88 -> 15 | C89: =C88 -> ET-COVER | D89: =MID(E89,9,2) -> PT | E89: =E88 -> RTHTMTBNPT75X63X10 | F89: =F88 -> RTHTMTBNPT | G89: =G88 -> 75X63X10 | H89: =H88 -> 75X63X10 | I89: =I88 -> 3 | J89: =J88 -> 6 | K89: =K88 -> 75 | L89: =L88 -> 63 | M89: =M88 -> 10 | N89: ="SFG-FRBNPK-ET-CVR-"&K89&"X"&L89&"X"&M89 -> SFG-FRBNPK-ET-CVR-75X63X10 | P89: =ROUND(((((K89+L89+K89+L89)+3))*0.0254),3) -> 7.087 | Q89: =P89=AJ89 -> TRUE | S89: ="Restonic Hotel Motel ET Cover "&K89&"X"&L89&"X"&M89 -> Restonic Hotel Motel ET Cover 75X63X10 | T89: =T88 -> SFG-FRBNPK-ET-CVR-75X63X10 | U89: =T89=N89 -> TRUE | V89: =S89=W89 -> TRUE | W89: =W88 -> Restonic Hotel Motel ET Cover 75X63X10 | X89: Standard | Y89: Production | Z89: TAIL-ET-PT | AA89: NOS | AB89: 1 | AC89: MRP&Rollup | AD89: CBESFG | AE89: 40 | AF89: I | AG89: SFG-RTHTMT-BNPK-ETBOR-11CM | AH89: Hotel Motel Poc ET-10 & 12 8MM/16D Pre Foam Border 11 CM Height | AI89: MTR | AJ89: =P89 -> 7.087 | AK89: CBESFG | AL89: Backflush | AM89: Active | AN89: =AJ89 -> 7.087 | AO89: =VLOOKUP(AG89,'SFG-rate rm - feb-24'!A:B,2,0) -> 19.60538 | AP89: =AO89*AN89 -> 138.94333 | AS89: =AS88 -> 173
A90: 5 | B90: =B89 -> 15 | C90: =C89 -> ET-COVER | D90: =MID(E90,9,2) -> PT | E90: =E89 -> RTHTMTBNPT75X63X10 | F90: =F89 -> RTHTMTBNPT | G90: =G89 -> 75X63X10 | H90: =H89 -> 75X63X10 | I90: =I89 -> 3 | J90: =J89 -> 6 | K90: =K89 -> 75 | L90: =L89 -> 63 | M90: =M89 -> 10 | N90: ="SFG-FRBNPK-ET-CVR-"&K90&"X"&L90&"X"&M90 -> SFG-FRBNPK-ET-CVR-75X63X10 | P90: 10 | Q90: =P90=AJ90 -> TRUE | S90: ="Restonic Hotel Motel ET Cover "&K90&"X"&L90&"X"&M90 -> Restonic Hotel Motel ET Cover 75X63X10 | T90: =T89 -> SFG-FRBNPK-ET-CVR-75X63X10 | U90: =T90=N90 -> TRUE | V90: =S90=W90 -> TRUE | W90: =W89 -> Restonic Hotel Motel ET Cover 75X63X10 | X90: Standard | Y90: Production | Z90: TAIL-ET-PT | AA90: NOS | AB90: 1 | AC90: MRP&Rollup | AD90: CBESFG | AE90: 50 | AF90: I | AG90: HW-CTON-THREAD | AH90: COTTON THREAD WHITE 3PLY | AI90: MTR | AJ90: =P90 -> 10 | AK90: CBEWIP | AL90: Backflush | AM90: Active | AN90: =AJ90/5000 -> 0.002 | AO90: =VLOOKUP(AG90,'RM-cost - feb-24'!B:P,15,0) -> 58 | AP90: =AO90*AN90 -> 0.116 | AS90: =AS89 -> 173
A92: 1 | B92: 16 | C92: ET-COVER | D92: =MID(E92,9,2) -> PT | E92: RTHTMTBNPT75X69X10 | F92: =LEFT(E92,MIN(FIND({0,1,2,3,4,5,6,7,8,9},E92&"0123456789"))-1) -> RTHTMTBNPT | G92: =SUBSTITUTE(E92,F92,"") -> 75X69X10 | H92: =IFERROR(LEFT(G92,FIND("-",G92)-1),G92) -> 75X69X10 | I92: =SEARCH("X",H92) -> 3 | J92: =SEARCH("X",H92,I92+1) -> 6 | K92: =LEFT(G92,SEARCH("x",G92)-1) -> 75 | L92: =MID(H92,I92+1,J92-I92-1) -> 69 | M92: =MID(H92,J92+1,20) -> 10 | N92: ="SFG-FRBNPK-ET-CVR-"&K92&"X"&L92&"X"&M92 -> SFG-FRBNPK-ET-CVR-75X69X10 | P92: =ROUND(((((K92+L92+K92+L92)+3)*0.0254)*5.3196),3) -> 39.319 | Q92: 0 | R92: =P92+Q92 -> 39.319 | S92: ="Restonic Hotel Motel ET Cover "&K92&"X"&L92&"X"&M92 -> Restonic Hotel Motel ET Cover 75X69X10 | T92: =N92 -> SFG-FRBNPK-ET-CVR-75X69X10 | U92: =T92=N92 -> TRUE | V92: =S92=W92 -> TRUE | W92: =S92 -> Restonic Hotel Motel ET Cover 75X69X10 | X92: Standard | Y92: Production | Z92: TAIL-ET-PT | AA92: NOS | AB92: 1 | AC92: MRP&Rollup | AD92: CBESFG | AE92: 10 | AF92: I | AG92: RM-THRD-QS-TKT40 | AH92: THREAD TKT40 210D/3 PLY 10000MTS | AI92: MTR | AJ92: =R92 -> 39.319 | AK92: CBEWIP | AL92: Backflush | AM92: Active | AN92: =AJ92/10000 -> 0.0039319 | AO92: =VLOOKUP(AG92,'RM-cost - feb-24'!B:P,15,0) -> 231.1423 | AP92: =AO92*AN92 -> 0.90882841 | AQ92: =SUM(AP92:AP96) -> 180.98794 | AR92: =ROUND(AQ92,0) -> 181 | AS92: =AR92 -> 181 | AT92: =+AS92+AY92 -> 203.39857 | AU92: =+SUM(((AS92*3%*18%))) -> 0.9774 | AV92: =+SUM(((AS92*14.33%*53%))) -> 13.746769 | AW92: =+SUM(((AS92*5.92%*53%))) -> 5.679056 | AX92: =+SUM(((AS92*2.08%*53%))) -> 1.995344 | AY92: =SUM(AU92:AX96) -> 22.398569 | AZ92: =ROUNDUP(AT92,0) -> 204 | BA92: =AZ92 -> 204
A93: 2 | B93: =B92 -> 16 | C93: =C92 -> ET-COVER | D93: =MID(E93,9,2) -> PT | E93: =E92 -> RTHTMTBNPT75X69X10 | F93: =F92 -> RTHTMTBNPT | G93: =G92 -> 75X69X10 | H93: =H92 -> 75X69X10 | I93: =I92 -> 3 | J93: =J92 -> 6 | K93: =K92 -> 75 | L93: =L92 -> 69 | M93: =M92 -> 10 | N93: ="SFG-FRBNPK-ET-CVR-"&K93&"X"&L93&"X"&M93 -> SFG-FRBNPK-ET-CVR-75X69X10 | O93: =K93*L93/144 -> 35.9375 | P93: =ROUNDUP((((K93*L93/144)*0.003)),3) -> 0.108 | S93: ="Restonic Hotel Motel ET Cover "&K93&"X"&L93&"X"&M93 -> Restonic Hotel Motel ET Cover 75X69X10 | T93: =T92 -> SFG-FRBNPK-ET-CVR-75X69X10 | U93: =T93=N93 -> TRUE | V93: =S93=W93 -> TRUE | W93: =W92 -> Restonic Hotel Motel ET Cover 75X69X10 | X93: Standard | Y93: Production | Z93: TAIL-ET-PT | AA93: NOS | AB93: 1 | AC93: MRP&Rollup | AD93: CBESFG | AE93: 20 | AF93: I | AG93: RM-NWN-70GSMX6INCH | AH93: NON WOVEN FABRIC 70GSMX6" | AI93: KGS | AJ93: 0.072 | AK93: CBEWIP | AL93: Backflush | AM93: Active | AN93: =AJ93 -> 0.072 | AO93: =VLOOKUP(AG93,'RM-cost - feb-24'!B:P,15,0) -> 113.786 | AP93: =AO93*AN93 -> 8.192592 | AS93: =AS92 -> 181
A94: 3 | B94: =B93 -> 16 | C94: =C93 -> ET-COVER | D94: =MID(E94,9,2) -> PT | E94: =E93 -> RTHTMTBNPT75X69X10 | F94: =F93 -> RTHTMTBNPT | G94: =G93 -> 75X69X10 | H94: =H93 -> 75X69X10 | I94: =I93 -> 3 | J94: =J93 -> 6 | K94: =K93 -> 75 | L94: =L93 -> 69 | M94: =M93 -> 10 | N94: ="SFG-FRBNPK-ET-CVR-"&K94&"X"&L94&"X"&M94 -> SFG-FRBNPK-ET-CVR-75X69X10 | P94: =ROUNDUP((((K94*L94/144)*0.00692)),3) -> 0.249 | Q94: =P94=AJ94 -> FALSE | S94: ="Restonic Hotel Motel ET Cover "&K94&"X"&L94&"X"&M94 -> Restonic Hotel Motel ET Cover 75X69X10 | T94: =T93 -> SFG-FRBNPK-ET-CVR-75X69X10 | U94: =T94=N94 -> TRUE | V94: =S94=W94 -> TRUE | W94: =W93 -> Restonic Hotel Motel ET Cover 75X69X10 | X94: Standard | Y94: Production | Z94: TAIL-ET-PT | AA94: NOS | AB94: 1 | AC94: MRP&Rollup | AD94: CBESFG | AE94: 30 | AF94: I | AG94: RML-NWN-70GSMX76" | AH94: NON WOVEN FABRIC WHITE 70 GSM 76 INCH | AI94: KGS | AJ94: 0.238 | AK94: CBEWIP | AL94: Backflush | AM94: Active | AN94: =AJ94 -> 0.238 | AO94: =VLOOKUP(AG94,'RM-cost - feb-24'!B:P,15,0) -> 112.8872 | AP94: =AO94*AN94 -> 26.867154 | AS94: =AS93 -> 181
A95: 4 | B95: =B94 -> 16 | C95: =C94 -> ET-COVER | D95: =MID(E95,9,2) -> PT | E95: =E94 -> RTHTMTBNPT75X69X10 | F95: =F94 -> RTHTMTBNPT | G95: =G94 -> 75X69X10 | H95: =H94 -> 75X69X10 | I95: =I94 -> 3 | J95: =J94 -> 6 | K95: =K94 -> 75 | L95: =L94 -> 69 | M95: =M94 -> 10 | N95: ="SFG-FRBNPK-ET-CVR-"&K95&"X"&L95&"X"&M95 -> SFG-FRBNPK-ET-CVR-75X69X10 | P95: =ROUND(((((K95+L95+K95+L95)+3))*0.0254),3) -> 7.391 | Q95: =P95=AJ95 -> TRUE | S95: ="Restonic Hotel Motel ET Cover "&K95&"X"&L95&"X"&M95 -> Restonic Hotel Motel ET Cover 75X69X10 | T95: =T94 -> SFG-FRBNPK-ET-CVR-75X69X10 | U95: =T95=N95 -> TRUE | V95: =S95=W95 -> TRUE | W95: =W94 -> Restonic Hotel Motel ET Cover 75X69X10 | X95: Standard | Y95: Production | Z95: TAIL-ET-PT | AA95: NOS | AB95: 1 | AC95: MRP&Rollup | AD95: CBESFG | AE95: 40 | AF95: I | AG95: SFG-RTHTMT-BNPK-ETBOR-11CM | AH95: Hotel Motel Poc ET-10 & 12 8MM/16D Pre Foam Border 11 CM Height | AI95: MTR | AJ95: =P95 -> 7.391 | AK95: CBESFG | AL95: Backflush | AM95: Active | AN95: =AJ95 -> 7.391 | AO95: =VLOOKUP(AG95,'SFG-rate rm - feb-24'!A:B,2,0) -> 19.60538 | AP95: =AO95*AN95 -> 144.90337 | AS95: =AS94 -> 181
A96: 5 | B96: =B95 -> 16 | C96: =C95 -> ET-COVER | D96: =MID(E96,9,2) -> PT | E96: =E95 -> RTHTMTBNPT75X69X10 | F96: =F95 -> RTHTMTBNPT | G96: =G95 -> 75X69X10 | H96: =H95 -> 75X69X10 | I96: =I95 -> 3 | J96: =J95 -> 6 | K96: =K95 -> 75 | L96: =L95 -> 69 | M96: =M95 -> 10 | N96: ="SFG-FRBNPK-ET-CVR-"&K96&"X"&L96&"X"&M96 -> SFG-FRBNPK-ET-CVR-75X69X10 | P96: 10 | Q96: =P96=AJ96 -> TRUE | S96: ="Restonic Hotel Motel ET Cover "&K96&"X"&L96&"X"&M96 -> Restonic Hotel Motel ET Cover 75X69X10 | T96: =T95 -> SFG-FRBNPK-ET-CVR-75X69X10 | U96: =T96=N96 -> TRUE | V96: =S96=W96 -> TRUE | W96: =W95 -> Restonic Hotel Motel ET Cover 75X69X10 | X96: Standard | Y96: Production | Z96: TAIL-ET-PT | AA96: NOS | AB96: 1 | AC96: MRP&Rollup | AD96: CBESFG | AE96: 50 | AF96: I | AG96: HW-CTON-THREAD | AH96: COTTON THREAD WHITE 3PLY | AI96: MTR | AJ96: =P96 -> 10 | AK96: CBEWIP | AL96: Backflush | AM96: Active | AN96: =AJ96/5000 -> 0.002 | AO96: =VLOOKUP(AG96,'RM-cost - feb-24'!B:P,15,0) -> 58 | AP96: =AO96*AN96 -> 0.116 | AS96: =AS95 -> 181
A98: 1 | B98: 17 | C98: ET-COVER | D98: =MID(E98,9,2) -> PT | E98: RTHTMTBNPT78X33X10 | F98: =LEFT(E98,MIN(FIND({0,1,2,3,4,5,6,7,8,9},E98&"0123456789"))-1) -> RTHTMTBNPT | G98: =SUBSTITUTE(E98,F98,"") -> 78X33X10 | H98: =IFERROR(LEFT(G98,FIND("-",G98)-1),G98) -> 78X33X10 | I98: =SEARCH("X",H98) -> 3 | J98: =SEARCH("X",H98,I98+1) -> 6 | K98: =LEFT(G98,SEARCH("x",G98)-1) -> 78 | L98: =MID(H98,I98+1,J98-I98-1) -> 33 | M98: =MID(H98,J98+1,20) -> 10 | N98: ="SFG-FRBNPK-ET-CVR-"&K98&"X"&L98&"X"&M98 -> SFG-FRBNPK-ET-CVR-78X33X10 | P98: =ROUND(((((K98+L98+K98+L98)+3)*0.0254)*5.3196),3) -> 30.402 | Q98: 0 | R98: =P98+Q98 -> 30.402 | S98: ="Restonic Hotel Motel ET Cover "&K98&"X"&L98&"X"&M98 -> Restonic Hotel Motel ET Cover 78X33X10 | T98: =N98 -> SFG-FRBNPK-ET-CVR-78X33X10 | U98: =T98=N98 -> TRUE | V98: =S98=W98 -> TRUE | W98: =S98 -> Restonic Hotel Motel ET Cover 78X33X10 | X98: Standard | Y98: Production | Z98: TAIL-ET-PT | AA98: NOS | AB98: 1 | AC98: MRP&Rollup | AD98: CBESFG | AE98: 10 | AF98: I | AG98: RM-THRD-QS-TKT40 | AH98: THREAD TKT40 210D/3 PLY 10000MTS | AI98: MTR | AJ98: =R98 -> 30.402 | AK98: CBEWIP | AL98: Backflush | AM98: Active | AN98: =AJ98/10000 -> 0.0030402 | AO98: =VLOOKUP(AG98,'RM-cost - feb-24'!B:P,15,0) -> 231.1423 | AP98: =AO98*AN98 -> 0.70271882 | AQ98: =SUM(AP98:AP102) -> 132.68585 | AR98: =ROUND(AQ98,0) -> 133 | AS98: =AR98 -> 133 | AT98: =+AS98+AY98 -> 149.45862 | AU98: =+SUM(((AS98*3%*18%))) -> 0.7182 | AV98: =+SUM(((AS98*14.33%*53%))) -> 10.101217 | AW98: =+SUM(((AS98*5.92%*53%))) -> 4.173008 | AX98: =+SUM(((AS98*2.08%*53%))) -> 1.466192 | AY98: =SUM(AU98:AX102) -> 16.458617 | AZ98: =ROUNDUP(AT98,0) -> 150 | BA98: =AZ98 -> 150
A99: 2 | B99: =B98 -> 17 | C99: =C98 -> ET-COVER | D99: =MID(E99,9,2) -> PT | E99: =E98 -> RTHTMTBNPT78X33X10 | F99: =F98 -> RTHTMTBNPT | G99: =G98 -> 78X33X10 | H99: =H98 -> 78X33X10 | I99: =I98 -> 3 | J99: =J98 -> 6 | K99: =K98 -> 78 | L99: =L98 -> 33 | M99: =M98 -> 10 | N99: ="SFG-FRBNPK-ET-CVR-"&K99&"X"&L99&"X"&M99 -> SFG-FRBNPK-ET-CVR-78X33X10 | O99: =K99*L99/144 -> 17.875 | P99: =ROUNDUP((((K99*L99/144)*0.003)),3) -> 0.054 | S99: ="Restonic Hotel Motel ET Cover "&K99&"X"&L99&"X"&M99 -> Restonic Hotel Motel ET Cover 78X33X10 | T99: =T98 -> SFG-FRBNPK-ET-CVR-78X33X10 | U99: =T99=N99 -> TRUE | V99: =S99=W99 -> TRUE | W99: =W98 -> Restonic Hotel Motel ET Cover 78X33X10 | X99: Standard | Y99: Production | Z99: TAIL-ET-PT | AA99: NOS | AB99: 1 | AC99: MRP&Rollup | AD99: CBESFG | AE99: 20 | AF99: I | AG99: RM-NWN-70GSMX6INCH | AH99: NON WOVEN FABRIC 70GSMX6" | AI99: KGS | AJ99: 0.055 | AK99: CBEWIP | AL99: Backflush | AM99: Active | AN99: =AJ99 -> 0.055 | AO99: =VLOOKUP(AG99,'RM-cost - feb-24'!B:P,15,0) -> 113.786 | AP99: =AO99*AN99 -> 6.25823 | AS99: =AS98 -> 133
A100: 3 | B100: =B99 -> 17 | C100: =C99 -> ET-COVER | D100: =MID(E100,9,2) -> PT | E100: =E99 -> RTHTMTBNPT78X33X10 | F100: =F99 -> RTHTMTBNPT | G100: =G99 -> 78X33X10 | H100: =H99 -> 78X33X10 | I100: =I99 -> 3 | J100: =J99 -> 6 | K100: =K99 -> 78 | L100: =L99 -> 33 | M100: =M99 -> 10 | N100: ="SFG-FRBNPK-ET-CVR-"&K100&"X"&L100&"X"&M100 -> SFG-FRBNPK-ET-CVR-78X33X10 | P100: =ROUNDUP((((K100*L100/144)*0.00692)),3) -> 0.124 | Q100: =P100=AJ100 -> FALSE | S100: ="Restonic Hotel Motel ET Cover "&K100&"X"&L100&"X"&M100 -> Restonic Hotel Motel ET Cover 78X33X10 | T100: =T99 -> SFG-FRBNPK-ET-CVR-78X33X10 | U100: =T100=N100 -> TRUE | V100: =S100=W100 -> TRUE | W100: =W99 -> Restonic Hotel Motel ET Cover 78X33X10 | X100: Standard | Y100: Production | Z100: TAIL-ET-PT | AA100: NOS | AB100: 1 | AC100: MRP&Rollup | AD100: CBESFG | AE100: 30 | AF100: I | AG100: RML-NWN-70GSMX79" | AH100: NON WOVEN FABRIC WHITE 70 GSM 79 INCH | AI100: KGS | AJ100: 0.119 | AK100: CBEWIP | AL100: Backflush | AM100: Active | AN100: =AJ100 -> 0.119 | AO100: =VLOOKUP(AG100,'RM-cost - feb-24'!B:P,15,0) -> 113.9845 | AP100: =AO100*AN100 -> 13.564155 | AS100: =AS99 -> 133
A101: 4 | B101: =B100 -> 17 | C101: =C100 -> ET-COVER | D101: =MID(E101,9,2) -> PT | E101: =E100 -> RTHTMTBNPT78X33X10 | F101: =F100 -> RTHTMTBNPT | G101: =G100 -> 78X33X10 | H101: =H100 -> 78X33X10 | I101: =I100 -> 3 | J101: =J100 -> 6 | K101: =K100 -> 78 | L101: =L100 -> 33 | M101: =M100 -> 10 | N101: ="SFG-FRBNPK-ET-CVR-"&K101&"X"&L101&"X"&M101 -> SFG-FRBNPK-ET-CVR-78X33X10 | P101: =ROUND(((((K101+L101+K101+L101)+3))*0.0254),3) -> 5.715 | Q101: =P101=AJ101 -> TRUE | S101: ="Restonic Hotel Motel ET Cover "&K101&"X"&L101&"X"&M101 -> Restonic Hotel Motel ET Cover 78X33X10 | T101: =T100 -> SFG-FRBNPK-ET-CVR-78X33X10 | U101: =T101=N101 -> TRUE | V101: =S101=W101 -> TRUE | W101: =W100 -> Restonic Hotel Motel ET Cover 78X33X10 | X101: Standard | Y101: Production | Z101: TAIL-ET-PT | AA101: NOS | AB101: 1 | AC101: MRP&Rollup | AD101: CBESFG | AE101: 40 | AF101: I | AG101: SFG-RTHTMT-BNPK-ETBOR-11CM | AH101: Hotel Motel Poc ET-10 & 12 8MM/16D Pre Foam Border 11 CM Height | AI101: MTR | AJ101: =P101 -> 5.715 | AK101: CBESFG | AL101: Backflush | AM101: Active | AN101: =AJ101 -> 5.715 | AO101: =VLOOKUP(AG101,'SFG-rate rm - feb-24'!A:B,2,0) -> 19.60538 | AP101: =AO101*AN101 -> 112.04475 | AS101: =AS100 -> 133
A102: 5 | B102: =B101 -> 17 | C102: =C101 -> ET-COVER | D102: =MID(E102,9,2) -> PT | E102: =E101 -> RTHTMTBNPT78X33X10 | F102: =F101 -> RTHTMTBNPT | G102: =G101 -> 78X33X10 | H102: =H101 -> 78X33X10 | I102: =I101 -> 3 | J102: =J101 -> 6 | K102: =K101 -> 78 | L102: =L101 -> 33 | M102: =M101 -> 10 | N102: ="SFG-FRBNPK-ET-CVR-"&K102&"X"&L102&"X"&M102 -> SFG-FRBNPK-ET-CVR-78X33X10 | P102: 10 | Q102: =P102=AJ102 -> TRUE | S102: ="Restonic Hotel Motel ET Cover "&K102&"X"&L102&"X"&M102 -> Restonic Hotel Motel ET Cover 78X33X10 | T102: =T101 -> SFG-FRBNPK-ET-CVR-78X33X10 | U102: =T102=N102 -> TRUE | V102: =S102=W102 -> TRUE | W102: =W101 -> Restonic Hotel Motel ET Cover 78X33X10 | X102: Standard | Y102: Production | Z102: TAIL-ET-PT | AA102: NOS | AB102: 1 | AC102: MRP&Rollup | AD102: CBESFG | AE102: 50 | AF102: I | AG102: HW-CTON-THREAD | AH102: COTTON THREAD WHITE 3PLY | AI102: MTR | AJ102: =P102 -> 10 | AK102: CBEWIP | AL102: Backflush | AM102: Active | AN102: =AJ102/5000 -> 0.002 | AO102: =VLOOKUP(AG102,'RM-cost - feb-24'!B:P,15,0) -> 58 | AP102: =AO102*AN102 -> 0.116 | AS102: =AS101 -> 133
A104: 1 | B104: 18 | C104: ET-COVER | D104: =MID(E104,9,2) -> PT | E104: RTHTMTBNPT78X39X10 | F104: =LEFT(E104,MIN(FIND({0,1,2,3,4,5,6,7,8,9},E104&"0123456789"))-1) -> RTHTMTBNPT | G104: =SUBSTITUTE(E104,F104,"") -> 78X39X10 | H104: =IFERROR(LEFT(G104,FIND("-",G104)-1),G104) -> 78X39X10 | I104: =SEARCH("X",H104) -> 3 | J104: =SEARCH("X",H104,I104+1) -> 6 | K104: =LEFT(G104,SEARCH("x",G104)-1) -> 78 | L104: =MID(H104,I104+1,J104-I104-1) -> 39 | M104: =MID(H104,J104+1,20) -> 10 | N104: ="SFG-FRBNPK-ET-CVR-"&K104&"X"&L104&"X"&M104 -> SFG-FRBNPK-ET-CVR-78X39X10 | P104: =ROUND(((((K104+L104+K104+L104)+3)*0.0254)*5.3196),3) -> 32.023 | Q104: 0 | R104: =P104+Q104 -> 32.023 | S104: ="Restonic Hotel Motel ET Cover "&K104&"X"&L104&"X"&M104 -> Restonic Hotel Motel ET Cover 78X39X10 | T104: =N104 -> SFG-FRBNPK-ET-CVR-78X39X10 | U104: =T104=N104 -> TRUE | V104: =S104=W104 -> TRUE | W104: =S104 -> Restonic Hotel Motel ET Cover 78X39X10 | X104: Standard | Y104: Production | Z104: TAIL-ET-PT | AA104: NOS | AB104: 1 | AC104: MRP&Rollup | AD104: CBESFG | AE104: 10 | AF104: I | AG104: RM-THRD-QS-TKT40 | AH104: THREAD TKT40 210D/3 PLY 10000MTS | AI104: MTR | AJ104: =R104 -> 32.023 | AK104: CBEWIP | AL104: Backflush | AM104: Active | AN104: =AJ104/10000 -> 0.0032023 | AO104: =VLOOKUP(AG104,'RM-cost - feb-24'!B:P,15,0) -> 231.1423 | AP104: =AO104*AN104 -> 0.74018699 | AQ104: =SUM(AP104:AP108) -> 141.66596 | AR104: =ROUND(AQ104,0) -> 142 | AS104: =AR104 -> 142 | AT104: =+AS104+AY104 -> 159.57236 | AU104: =+SUM(((AS104*3%*18%))) -> 0.7668 | AV104: =+SUM(((AS104*14.33%*53%))) -> 10.784758 | AW104: =+SUM(((AS104*5.92%*53%))) -> 4.455392 | AX104: =+SUM(((AS104*2.08%*53%))) -> 1.565408 | AY104: =SUM(AU104:AX108) -> 17.572358 | AZ104: =ROUNDUP(AT104,0) -> 160 | BA104: =AZ104 -> 160
A105: 2 | B105: =B104 -> 18 | C105: =C104 -> ET-COVER | D105: =MID(E105,9,2) -> PT | E105: =E104 -> RTHTMTBNPT78X39X10 | F105: =F104 -> RTHTMTBNPT | G105: =G104 -> 78X39X10 | H105: =H104 -> 78X39X10 | I105: =I104 -> 3 | J105: =J104 -> 6 | K105: =K104 -> 78 | L105: =L104 -> 39 | M105: =M104 -> 10 | N105: ="SFG-FRBNPK-ET-CVR-"&K105&"X"&L105&"X"&M105 -> SFG-FRBNPK-ET-CVR-78X39X10 | O105: =K105*L105/144 -> 21.125 | P105: =ROUNDUP((((K105*L105/144)*0.003)),3) -> 0.064 | S105: ="Restonic Hotel Motel ET Cover "&K105&"X"&L105&"X"&M105 -> Restonic Hotel Motel ET Cover 78X39X10 | T105: =T104 -> SFG-FRBNPK-ET-CVR-78X39X10 | U105: =T105=N105 -> TRUE | V105: =S105=W105 -> TRUE | W105: =W104 -> Restonic Hotel Motel ET Cover 78X39X10 | X105: Standard | Y105: Production | Z105: TAIL-ET-PT | AA105: NOS | AB105: 1 | AC105: MRP&Rollup | AD105: CBESFG | AE105: 20 | AF105: I | AG105: RM-NWN-70GSMX6INCH | AH105: NON WOVEN FABRIC 70GSMX6" | AI105: KGS | AJ105: 0.058 | AK105: CBEWIP | AL105: Backflush | AM105: Active | AN105: =AJ105 -> 0.058 | AO105: =VLOOKUP(AG105,'RM-cost - feb-24'!B:P,15,0) -> 113.786 | AP105: =AO105*AN105 -> 6.599588 | AS105: =AS104 -> 142
A106: 3 | B106: =B105 -> 18 | C106: =C105 -> ET-COVER | D106: =MID(E106,9,2) -> PT | E106: =E105 -> RTHTMTBNPT78X39X10 | F106: =F105 -> RTHTMTBNPT | G106: =G105 -> 78X39X10 | H106: =H105 -> 78X39X10 | I106: =I105 -> 3 | J106: =J105 -> 6 | K106: =K105 -> 78 | L106: =L105 -> 39 | M106: =M105 -> 10 | N106: ="SFG-FRBNPK-ET-CVR-"&K106&"X"&L106&"X"&M106 -> SFG-FRBNPK-ET-CVR-78X39X10 | P106: =ROUNDUP((((K106*L106/144)*0.00692)),3) -> 0.147 | Q106: =P106=AJ106 -> FALSE | S106: ="Restonic Hotel Motel ET Cover "&K106&"X"&L106&"X"&M106 -> Restonic Hotel Motel ET Cover 78X39X10 | T106: =T105 -> SFG-FRBNPK-ET-CVR-78X39X10 | U106: =T106=N106 -> TRUE | V106: =S106=W106 -> TRUE | W106: =W105 -> Restonic Hotel Motel ET Cover 78X39X10 | X106: Standard | Y106: Production | Z106: TAIL-ET-PT | AA106: NOS | AB106: 1 | AC106: MRP&Rollup | AD106: CBESFG | AE106: 30 | AF106: I | AG106: RML-NWN-70GSMX79" | AH106: NON WOVEN FABRIC WHITE 70 GSM 79 INCH | AI106: KGS | AJ106: 0.142 | AK106: CBEWIP | AL106: Backflush | AM106: Active | AN106: =AJ106 -> 0.142 | AO106: =VLOOKUP(AG106,'RM-cost - feb-24'!B:P,15,0) -> 113.9845 | AP106: =AO106*AN106 -> 16.185799 | AS106: =AS105 -> 142
A107: 4 | B107: =B106 -> 18 | C107: =C106 -> ET-COVER | D107: =MID(E107,9,2) -> PT | E107: =E106 -> RTHTMTBNPT78X39X10 | F107: =F106 -> RTHTMTBNPT | G107: =G106 -> 78X39X10 | H107: =H106 -> 78X39X10 | I107: =I106 -> 3 | J107: =J106 -> 6 | K107: =K106 -> 78 | L107: =L106 -> 39 | M107: =M106 -> 10 | N107: ="SFG-FRBNPK-ET-CVR-"&K107&"X"&L107&"X"&M107 -> SFG-FRBNPK-ET-CVR-78X39X10 | P107: =ROUND(((((K107+L107+K107+L107)+3))*0.0254),3) -> 6.02 | Q107: =P107=AJ107 -> TRUE | S107: ="Restonic Hotel Motel ET Cover "&K107&"X"&L107&"X"&M107 -> Restonic Hotel Motel ET Cover 78X39X10 | T107: =T106 -> SFG-FRBNPK-ET-CVR-78X39X10 | U107: =T107=N107 -> TRUE | V107: =S107=W107 -> TRUE | W107: =W106 -> Restonic Hotel Motel ET Cover 78X39X10 | X107: Standard | Y107: Production | Z107: TAIL-ET-PT | AA107: NOS | AB107: 1 | AC107: MRP&Rollup | AD107: CBESFG | AE107: 40 | AF107: I | AG107: SFG-RTHTMT-BNPK-ETBOR-11CM | AH107: Hotel Motel Poc ET-10 & 12 8MM/16D Pre Foam Border 11 CM Height | AI107: MTR | AJ107: =P107 -> 6.02 | AK107: CBESFG | AL107: Backflush | AM107: Active | AN107: =AJ107 -> 6.02 | AO107: =VLOOKUP(AG107,'SFG-rate rm - feb-24'!A:B,2,0) -> 19.60538 | AP107: =AO107*AN107 -> 118.02439 | AS107: =AS106 -> 142
A108: 5 | B108: =B107 -> 18 | C108: =C107 -> ET-COVER | D108: =MID(E108,9,2) -> PT | E108: =E107 -> RTHTMTBNPT78X39X10 | F108: =F107 -> RTHTMTBNPT | G108: =G107 -> 78X39X10 | H108: =H107 -> 78X39X10 | I108: =I107 -> 3 | J108: =J107 -> 6 | K108: =K107 -> 78 | L108: =L107 -> 39 | M108: =M107 -> 10 | N108: ="SFG-FRBNPK-ET-CVR-"&K108&"X"&L108&"X"&M108 -> SFG-FRBNPK-ET-CVR-78X39X10 | P108: 10 | Q108: =P108=AJ108 -> TRUE | S108: ="Restonic Hotel Motel ET Cover "&K108&"X"&L108&"X"&M108 -> Restonic Hotel Motel ET Cover 78X39X10 | T108: =T107 -> SFG-FRBNPK-ET-CVR-78X39X10 | U108: =T108=N108 -> TRUE | V108: =S108=W108 -> TRUE | W108: =W107 -> Restonic Hotel Motel ET Cover 78X39X10 | X108: Standard | Y108: Production | Z108: TAIL-ET-PT | AA108: NOS | AB108: 1 | AC108: MRP&Rollup | AD108: CBESFG | AE108: 50 | AF108: I | AG108: HW-CTON-THREAD | AH108: COTTON THREAD WHITE 3PLY | AI108: MTR | AJ108: =P108 -> 10 | AK108: CBEWIP | AL108: Backflush | AM108: Active | AN108: =AJ108/5000 -> 0.002 | AO108: =VLOOKUP(AG108,'RM-cost - feb-24'!B:P,15,0) -> 58 | AP108: =AO108*AN108 -> 0.116 | AS108: =AS107 -> 142
A110: 1 | B110: 19 | C110: ET-COVER | D110: =MID(E110,9,2) -> PT | E110: RTHTMTBNPT78X45X10 | F110: =LEFT(E110,MIN(FIND({0,1,2,3,4,5,6,7,8,9},E110&"0123456789"))-1) -> RTHTMTBNPT | G110: =SUBSTITUTE(E110,F110,"") -> 78X45X10 | H110: =IFERROR(LEFT(G110,FIND("-",G110)-1),G110) -> 78X45X10 | I110: =SEARCH("X",H110) -> 3 | J110: =SEARCH("X",H110,I110+1) -> 6 | K110: =LEFT(G110,SEARCH("x",G110)-1) -> 78 | L110: =MID(H110,I110+1,J110-I110-1) -> 45 | M110: =MID(H110,J110+1,20) -> 10 | N110: ="SFG-FRBNPK-ET-CVR-"&K110&"X"&L110&"X"&M110 -> SFG-FRBNPK-ET-CVR-78X45X10 | P110: =ROUND(((((K110+L110+K110+L110)+3)*0.0254)*5.3196),3) -> 33.644 | Q110: 0 | R110: =P110+Q110 -> 33.644 | S110: ="Restonic Hotel Motel ET Cover "&K110&"X"&L110&"X"&M110 -> Restonic Hotel Motel ET Cover 78X45X10 | T110: =N110 -> SFG-FRBNPK-ET-CVR-78X45X10 | U110: =T110=N110 -> TRUE | V110: =S110=W110 -> TRUE | W110: =S110 -> Restonic Hotel Motel ET Cover 78X45X10 | X110: Standard | Y110: Production | Z110: TAIL-ET-PT | AA110: NOS | AB110: 1 | AC110: MRP&Rollup | AD110: CBESFG | AE110: 10 | AF110: I | AG110: RM-THRD-QS-TKT40 | AH110: THREAD TKT40 210D/3 PLY 10000MTS | AI110: MTR | AJ110: =R110 -> 33.644 | AK110: CBEWIP | AL110: Backflush | AM110: Active | AN110: =AJ110/10000 -> 0.0033644 | AO110: =VLOOKUP(AG110,'RM-cost - feb-24'!B:P,15,0) -> 231.1423 | AP110: =AO110*AN110 -> 0.77765515 | AQ110: =SUM(AP110:AP114) -> 150.98783 | AR110: =ROUND(AQ110,0) -> 151 | AS110: =AR110 -> 151 | AT110: =+AS110+AY110 -> 169.6861 | AU110: =+SUM(((AS110*3%*18%))) -> 0.8154 | AV110: =+SUM(((AS110*14.33%*53%))) -> 11.468299 | AW110: =+SUM(((AS110*5.92%*53%))) -> 4.737776 | AX110: =+SUM(((AS110*2.08%*53%))) -> 1.664624 | AY110: =SUM(AU110:AX114) -> 18.686099 | AZ110: =ROUNDUP(AT110,0) -> 170 | BA110: =AZ110 -> 170
A111: 2 | B111: =B110 -> 19 | C111: =C110 -> ET-COVER | D111: =MID(E111,9,2) -> PT | E111: =E110 -> RTHTMTBNPT78X45X10 | F111: =F110 -> RTHTMTBNPT | G111: =G110 -> 78X45X10 | H111: =H110 -> 78X45X10 | I111: =I110 -> 3 | J111: =J110 -> 6 | K111: =K110 -> 78 | L111: =L110 -> 45 | M111: =M110 -> 10 | N111: ="SFG-FRBNPK-ET-CVR-"&K111&"X"&L111&"X"&M111 -> SFG-FRBNPK-ET-CVR-78X45X10 | O111: =K111*L111/144 -> 24.375 | P111: =ROUNDUP((((K111*L111/144)*0.003)),3) -> 0.074 | S111: ="Restonic Hotel Motel ET Cover "&K111&"X"&L111&"X"&M111 -> Restonic Hotel Motel ET Cover 78X45X10 | T111: =T110 -> SFG-FRBNPK-ET-CVR-78X45X10 | U111: =T111=N111 -> TRUE | V111: =S111=W111 -> TRUE | W111: =W110 -> Restonic Hotel Motel ET Cover 78X45X10 | X111: Standard | Y111: Production | Z111: TAIL-ET-PT | AA111: NOS | AB111: 1 | AC111: MRP&Rollup | AD111: CBESFG | AE111: 20 | AF111: I | AG111: RM-NWN-70GSMX6INCH | AH111: NON WOVEN FABRIC 70GSMX6" | AI111: KGS | AJ111: 0.062 | AK111: CBEWIP | AL111: Backflush | AM111: Active | AN111: =AJ111 -> 0.062 | AO111: =VLOOKUP(AG111,'RM-cost - feb-24'!B:P,15,0) -> 113.786 | AP111: =AO111*AN111 -> 7.054732 | AS111: =AS110 -> 151
A112: 3 | B112: =B111 -> 19 | C112: =C111 -> ET-COVER | D112: =MID(E112,9,2) -> PT | E112: =E111 -> RTHTMTBNPT78X45X10 | F112: =F111 -> RTHTMTBNPT | G112: =G111 -> 78X45X10 | H112: =H111 -> 78X45X10 | I112: =I111 -> 3 | J112: =J111 -> 6 | K112: =K111 -> 78 | L112: =L111 -> 45 | M112: =M111 -> 10 | N112: ="SFG-FRBNPK-ET-CVR-"&K112&"X"&L112&"X"&M112 -> SFG-FRBNPK-ET-CVR-78X45X10 | P112: =ROUNDUP((((K112*L112/144)*0.00692)),3) -> 0.169 | Q112: =P112=AJ112 -> FALSE | S112: ="Restonic Hotel Motel ET Cover "&K112&"X"&L112&"X"&M112 -> Restonic Hotel Motel ET Cover 78X45X10 | T112: =T111 -> SFG-FRBNPK-ET-CVR-78X45X10 | U112: =T112=N112 -> TRUE | V112: =S112=W112 -> TRUE | W112: =W111 -> Restonic Hotel Motel ET Cover 78X45X10 | X112: Standard | Y112: Production | Z112: TAIL-ET-PT | AA112: NOS | AB112: 1 | AC112: MRP&Rollup | AD112: CBESFG | AE112: 30 | AF112: I | AG112: RML-NWN-70GSMX79" | AH112: NON WOVEN FABRIC WHITE 70 GSM 79 INCH | AI112: KGS | AJ112: 0.167 | AK112: CBEWIP | AL112: Backflush | AM112: Active | AN112: =AJ112 -> 0.167 | AO112: =VLOOKUP(AG112,'RM-cost - feb-24'!B:P,15,0) -> 113.9845 | AP112: =AO112*AN112 -> 19.035412 | AS112: =AS111 -> 151
A113: 4 | B113: =B112 -> 19 | C113: =C112 -> ET-COVER | D113: =MID(E113,9,2) -> PT | E113: =E112 -> RTHTMTBNPT78X45X10 | F113: =F112 -> RTHTMTBNPT | G113: =G112 -> 78X45X10 | H113: =H112 -> 78X45X10 | I113: =I112 -> 3 | J113: =J112 -> 6 | K113: =K112 -> 78 | L113: =L112 -> 45 | M113: =M112 -> 10 | N113: ="SFG-FRBNPK-ET-CVR-"&K113&"X"&L113&"X"&M113 -> SFG-FRBNPK-ET-CVR-78X45X10 | P113: =ROUND(((((K113+L113+K113+L113)+3))*0.0254),3) -> 6.325 | Q113: =P113=AJ113 -> TRUE | S113: ="Restonic Hotel Motel ET Cover "&K113&"X"&L113&"X"&M113 -> Restonic Hotel Motel ET Cover 78X45X10 | T113: =T112 -> SFG-FRBNPK-ET-CVR-78X45X10 | U113: =T113=N113 -> TRUE | V113: =S113=W113 -> TRUE | W113: =W112 -> Restonic Hotel Motel ET Cover 78X45X10 | X113: Standard | Y113: Production | Z113: TAIL-ET-PT | AA113: NOS | AB113: 1 | AC113: MRP&Rollup | AD113: CBESFG | AE113: 40 | AF113: I | AG113: SFG-RTHTMT-BNPK-ETBOR-11CM | AH113: Hotel Motel Poc ET-10 & 12 8MM/16D Pre Foam Border 11 CM Height | AI113: MTR | AJ113: =P113 -> 6.325 | AK113: CBESFG | AL113: Backflush | AM113: Active | AN113: =AJ113 -> 6.325 | AO113: =VLOOKUP(AG113,'SFG-rate rm - feb-24'!A:B,2,0) -> 19.60538 | AP113: =AO113*AN113 -> 124.00403 | AS113: =AS112 -> 151
A114: 5 | B114: =B113 -> 19 | C114: =C113 -> ET-COVER | D114: =MID(E114,9,2) -> PT | E114: =E113 -> RTHTMTBNPT78X45X10 | F114: =F113 -> RTHTMTBNPT | G114: =G113 -> 78X45X10 | H114: =H113 -> 78X45X10 | I114: =I113 -> 3 | J114: =J113 -> 6 | K114: =K113 -> 78 | L114: =L113 -> 45 | M114: =M113 -> 10 | N114: ="SFG-FRBNPK-ET-CVR-"&K114&"X"&L114&"X"&M114 -> SFG-FRBNPK-ET-CVR-78X45X10 | P114: 10 | Q114: =P114=AJ114 -> TRUE | S114: ="Restonic Hotel Motel ET Cover "&K114&"X"&L114&"X"&M114 -> Restonic Hotel Motel ET Cover 78X45X10 | T114: =T113 -> SFG-FRBNPK-ET-CVR-78X45X10 | U114: =T114=N114 -> TRUE | V114: =S114=W114 -> TRUE | W114: =W113 -> Restonic Hotel Motel ET Cover 78X45X10 | X114: Standard | Y114: Production | Z114: TAIL-ET-PT | AA114: NOS | AB114: 1 | AC114: MRP&Rollup | AD114: CBESFG | AE114: 50 | AF114: I | AG114: HW-CTON-THREAD | AH114: COTTON THREAD WHITE 3PLY | AI114: MTR | AJ114: =P114 -> 10 | AK114: CBEWIP | AL114: Backflush | AM114: Active | AN114: =AJ114/5000 -> 0.002 | AO114: =VLOOKUP(AG114,'RM-cost - feb-24'!B:P,15,0) -> 58 | AP114: =AO114*AN114 -> 0.116 | AS114: =AS113 -> 151
A116: 1 | B116: 20 | C116: ET-COVER | D116: =MID(E116,9,2) -> PT | E116: RTHTMTBNPT78X51X10 | F116: =LEFT(E116,MIN(FIND({0,1,2,3,4,5,6,7,8,9},E116&"0123456789"))-1) -> RTHTMTBNPT | G116: =SUBSTITUTE(E116,F116,"") -> 78X51X10 | H116: =IFERROR(LEFT(G116,FIND("-",G116)-1),G116) -> 78X51X10 | I116: =SEARCH("X",H116) -> 3 | J116: =SEARCH("X",H116,I116+1) -> 6 | K116: =LEFT(G116,SEARCH("x",G116)-1) -> 78 | L116: =MID(H116,I116+1,J116-I116-1) -> 51 | M116: =MID(H116,J116+1,20) -> 10 | N116: ="SFG-FRBNPK-ET-CVR-"&K116&"X"&L116&"X"&M116 -> SFG-FRBNPK-ET-CVR-78X51X10 | P116: =ROUND(((((K116+L116+K116+L116)+3)*0.0254)*5.3196),3) -> 35.266 | Q116: 0 | R116: =P116+Q116 -> 35.266 | S116: ="Restonic Hotel Motel ET Cover "&K116&"X"&L116&"X"&M116 -> Restonic Hotel Motel ET Cover 78X51X10 | T116: =N116 -> SFG-FRBNPK-ET-CVR-78X51X10 | U116: =T116=N116 -> TRUE | V116: =S116=W116 -> TRUE | W116: =S116 -> Restonic Hotel Motel ET Cover 78X51X10 | X116: Standard | Y116: Production | Z116: TAIL-ET-PT | AA116: NOS | AB116: 1 | AC116: MRP&Rollup | AD116: CBESFG | AE116: 10 | AF116: I | AG116: RM-THRD-QS-TKT40 | AH116: THREAD TKT40 210D/3 PLY 10000MTS | AI116: MTR | AJ116: =R116 -> 35.266 | AK116: CBEWIP | AL116: Backflush | AM116: Active | AN116: =AJ116/10000 -> 0.0035266 | AO116: =VLOOKUP(AG116,'RM-cost - feb-24'!B:P,15,0) -> 231.1423 | AP116: =AO116*AN116 -> 0.81514644 | AQ116: =SUM(AP116:AP120) -> 158.9225 | AR116: =ROUND(AQ116,0) -> 159 | AS116: =AR116 -> 159 | AT116: =+AS116+AY116 -> 178.67609 | AU116: =+SUM(((AS116*3%*18%))) -> 0.8586 | AV116: =+SUM(((AS116*14.33%*53%))) -> 12.075891 | AW116: =+SUM(((AS116*5.92%*53%))) -> 4.988784 | AX116: =+SUM(((AS116*2.08%*53%))) -> 1.752816 | AY116: =SUM(AU116:AX120) -> 19.676091 | AZ116: =ROUNDUP(AT116,0) -> 179 | BA116: =AZ116 -> 179
A117: 2 | B117: =B116 -> 20 | C117: =C116 -> ET-COVER | D117: =MID(E117,9,2) -> PT | E117: =E116 -> RTHTMTBNPT78X51X10 | F117: =F116 -> RTHTMTBNPT | G117: =G116 -> 78X51X10 | H117: =H116 -> 78X51X10 | I117: =I116 -> 3 | J117: =J116 -> 6 | K117: =K116 -> 78 | L117: =L116 -> 51 | M117: =M116 -> 10 | N117: ="SFG-FRBNPK-ET-CVR-"&K117&"X"&L117&"X"&M117 -> SFG-FRBNPK-ET-CVR-78X51X10 | O117: =K117*L117/144 -> 27.625 | P117: =ROUNDUP((((K117*L117/144)*0.003)),3) -> 0.083 | S117: ="Restonic Hotel Motel ET Cover "&K117&"X"&L117&"X"&M117 -> Restonic Hotel Motel ET Cover 78X51X10 | T117: =T116 -> SFG-FRBNPK-ET-CVR-78X51X10 | U117: =T117=N117 -> TRUE | V117: =S117=W117 -> TRUE | W117: =W116 -> Restonic Hotel Motel ET Cover 78X51X10 | X117: Standard | Y117: Production | Z117: TAIL-ET-PT | AA117: NOS | AB117: 1 | AC117: MRP&Rollup | AD117: CBESFG | AE117: 20 | AF117: I | AG117: RM-NWN-70GSMX6INCH | AH117: NON WOVEN FABRIC 70GSMX6" | AI117: KGS | AJ117: 0.065 | AK117: CBEWIP | AL117: Backflush | AM117: Active | AN117: =AJ117 -> 0.065 | AO117: =VLOOKUP(AG117,'RM-cost - feb-24'!B:P,15,0) -> 113.786 | AP117: =AO117*AN117 -> 7.39609 | AS117: =AS116 -> 159
A118: 3 | B118: =B117 -> 20 | C118: =C117 -> ET-COVER | D118: =MID(E118,9,2) -> PT | E118: =E117 -> RTHTMTBNPT78X51X10 | F118: =F117 -> RTHTMTBNPT | G118: =G117 -> 78X51X10 | H118: =H117 -> 78X51X10 | I118: =I117 -> 3 | J118: =J117 -> 6 | K118: =K117 -> 78 | L118: =L117 -> 51 | M118: =M117 -> 10 | N118: ="SFG-FRBNPK-ET-CVR-"&K118&"X"&L118&"X"&M118 -> SFG-FRBNPK-ET-CVR-78X51X10 | P118: =ROUNDUP((((K118*L118/144)*0.00692)),3) -> 0.192 | Q118: =P118=AJ118 -> FALSE | S118: ="Restonic Hotel Motel ET Cover "&K118&"X"&L118&"X"&M118 -> Restonic Hotel Motel ET Cover 78X51X10 | T118: =T117 -> SFG-FRBNPK-ET-CVR-78X51X10 | U118: =T118=N118 -> TRUE | V118: =S118=W118 -> TRUE | W118: =W117 -> Restonic Hotel Motel ET Cover 78X51X10 | X118: Standard | Y118: Production | Z118: TAIL-ET-PT | AA118: NOS | AB118: 1 | AC118: MRP&Rollup | AD118: CBESFG | AE118: 30 | AF118: I | AG118: RML-NWN-70GSMX79" | AH118: NON WOVEN FABRIC WHITE 70 GSM 79 INCH | AI118: KGS | AJ118: 0.181 | AK118: CBEWIP | AL118: Backflush | AM118: Active | AN118: =AJ118 -> 0.181 | AO118: =VLOOKUP(AG118,'RM-cost - feb-24'!B:P,15,0) -> 113.9845 | AP118: =AO118*AN118 -> 20.631194 | AS118: =AS117 -> 159
A119: 4 | B119: =B118 -> 20 | C119: =C118 -> ET-COVER | D119: =MID(E119,9,2) -> PT | E119: =E118 -> RTHTMTBNPT78X51X10 | F119: =F118 -> RTHTMTBNPT | G119: =G118 -> 78X51X10 | H119: =H118 -> 78X51X10 | I119: =I118 -> 3 | J119: =J118 -> 6 | K119: =K118 -> 78 | L119: =L118 -> 51 | M119: =M118 -> 10 | N119: ="SFG-FRBNPK-ET-CVR-"&K119&"X"&L119&"X"&M119 -> SFG-FRBNPK-ET-CVR-78X51X10 | P119: =ROUND(((((K119+L119+K119+L119)+3))*0.0254),3) -> 6.629 | Q119: =P119=AJ119 -> TRUE | S119: ="Restonic Hotel Motel ET Cover "&K119&"X"&L119&"X"&M119 -> Restonic Hotel Motel ET Cover 78X51X10 | T119: =T118 -> SFG-FRBNPK-ET-CVR-78X51X10 | U119: =T119=N119 -> TRUE | V119: =S119=W119 -> TRUE | W119: =W118 -> Restonic Hotel Motel ET Cover 78X51X10 | X119: Standard | Y119: Production | Z119: TAIL-ET-PT | AA119: NOS | AB119: 1 | AC119: MRP&Rollup | AD119: CBESFG | AE119: 40 | AF119: I | AG119: SFG-RTHTMT-BNPK-ETBOR-11CM | AH119: Hotel Motel Poc ET-10 & 12 8MM/16D Pre Foam Border 11 CM Height | AI119: MTR | AJ119: =P119 -> 6.629 | AK119: CBESFG | AL119: Backflush | AM119: Active | AN119: =AJ119 -> 6.629 | AO119: =VLOOKUP(AG119,'SFG-rate rm - feb-24'!A:B,2,0) -> 19.60538 | AP119: =AO119*AN119 -> 129.96407 | AS119: =AS118 -> 159
...

Sheet Item creat
A1: S.no | B1: R.no | C1: Item | D1: Item Desc | E1: PS Usage | F1: PS Category | G1: Process Plan | H1: Uom | I1: Qty | J1: Default For | K1: Wh Code | L1: Rm-cost | M1: PRO-RATE
A2: 1 | B2: 1 | C2: SFG-FRBNPK-ET-CVR-72X33X10 | D2: Restonic Hotel Motel ET Cover 72X33X10 | E2: Standard | F2: Production | G2: TAIL-ET-PT | H2: NOS | I2: 1 | J2: MRP&Rollup | K2: CBESFG | L2: 126 | M2: 142
A3: 2 | B3: 2 | C3: SFG-FRBNPK-ET-CVR-72X39X10 | D3: Restonic Hotel Motel ET Cover 72X39X10 | E3: Standard | F3: Production | G3: TAIL-ET-PT | H3: NOS | I3: 1 | J3: MRP&Rollup | K3: CBESFG | L3: 134 | M3: 151
A4: 3 | B4: 3 | C4: SFG-FRBNPK-ET-CVR-72X45X10 | D4: Restonic Hotel Motel ET Cover 72X45X10 | E4: Standard | F4: Production | G4: TAIL-ET-PT | H4: NOS | I4: 1 | J4: MRP&Rollup | K4: CBESFG | L4: 143 | M4: 161
A5: 4 | B5: 4 | C5: SFG-FRBNPK-ET-CVR-72X51X10 | D5: Restonic Hotel Motel ET Cover 72X51X10 | E5: Standard | F5: Production | G5: TAIL-ET-PT | H5: NOS | I5: 1 | J5: MRP&Rollup | K5: CBESFG | L5: 151 | M5: 170
A6: 5 | B6: 5 | C6: SFG-FRBNPK-ET-CVR-72X54X10 | D6: Restonic Hotel Motel ET Cover 72X54X10 | E6: Standard | F6: Production | G6: TAIL-ET-PT | H6: NOS | I6: 1 | J6: MRP&Rollup | K6: CBESFG | L6: 156 | M6: 176
A7: 6 | B7: 6 | C7: SFG-FRBNPK-ET-CVR-72X57X10 | D7: Restonic Hotel Motel ET Cover 72X57X10 | E7: Standard | F7: Production | G7: TAIL-ET-PT | H7: NOS | I7: 1 | J7: MRP&Rollup | K7: CBESFG | L7: 160 | M7: 180
A8: 7 | B8: 7 | C8: SFG-FRBNPK-ET-CVR-72X63X10 | D8: Restonic Hotel Motel ET Cover 72X63X10 | E8: Standard | F8: Production | G8: TAIL-ET-PT | H8: NOS | I8: 1 | J8: MRP&Rollup | K8: CBESFG | L8: 169 | M8: 190
A9: 8 | B9: 8 | C9: SFG-FRBNPK-ET-CVR-72X69X10 | D9: Restonic Hotel Motel ET Cover 72X69X10 | E9: Standard | F9: Production | G9: TAIL-ET-PT | H9: NOS | I9: 1 | J9: MRP&Rollup | K9: CBESFG | L9: 178 | M9: 201
A10: 9 | B10: 9 | C10: SFG-FRBNPK-ET-CVR-75X33X10 | D10: Restonic Hotel Motel ET Cover 75X33X10 | E10: Standard | F10: Production | G10: TAIL-ET-PT | H10: NOS | I10: 1 | J10: MRP&Rollup | K10: CBESFG | L10: 129 | M10: 145
A11: 10 | B11: 10 | C11: SFG-FRBNPK-ET-CVR-75X39X10 | D11: Restonic Hotel Motel ET Cover 75X39X10 | E11: Standard | F11: Production | G11: TAIL-ET-PT | H11: NOS | I11: 1 | J11: MRP&Rollup | K11: CBESFG | L11: 137 | M11: 154
A12: 11 | B12: 11 | C12: SFG-FRBNPK-ET-CVR-75X45X10 | D12: Restonic Hotel Motel ET Cover 75X45X10 | E12: Standard | F12: Production | G12: TAIL-ET-PT | H12: NOS | I12: 1 | J12: MRP&Rollup | K12: CBESFG | L12: 146 | M12: 165
A13: 12 | B13: 12 | C13: SFG-FRBNPK-ET-CVR-75X51X10 | D13: Restonic Hotel Motel ET Cover 75X51X10 | E13: Standard | F13: Production | G13: TAIL-ET-PT | H13: NOS | I13: 1 | J13: MRP&Rollup | K13: CBESFG | L13: 155 | M13: 175
... A41: 40 | B41: 40 | C41: SFG-FRBNPK-ET-CVR-84X69X10 | D41: Restonic Hotel Motel ET Cover 84X69X10 | E41: Standard | F41: Production | G41: TAIL-ET-PT | H41: NOS | I41: 1 | J41: MRP&Rollup | K41: CBESFG | L41: 198 | M41: 223

Sheet ps creat & upload
A1: S.no | B1: R.no | C1: Bom Code/PS.No | D1: PS Desc. | E1: Item | F1: Item Desc | G1: PS Usage | H1: PS Category | I1: Process Plan | J1: Uom | K1: Qty | L1: Default For | M1: Wh Code | N1: PS Seq | O1: I/O Flag | P1: Issue Item | Q1: Item Desc | R1: Uom | S1: Qty | T1: Std Wh Code | U1: Backflush | V1: Status
A2: 1 | B2: 1 | C2: SFG-FRBNPK-ET-CVR-72X33X10 | D2: Restonic Hotel Motel ET Cover 72X33X10 | E2: SFG-FRBNPK-ET-CVR-72X33X10 | F2: Restonic Hotel Motel ET Cover 72X33X10 | G2: Standard | H2: Production | I2: TAIL-ET-PT | J2: NOS | K2: 1 | L2: MRP&Rollup | M2: CBESFG | N2: 10 | O2: I | P2: RM-THRD-QS-TKT40 | Q2: THREAD TKT40 210D/3 PLY 10000MTS | R2: MTR | S2: 28.78 | T2: CBEWIP | U2: Backflush | V2: Active
A3: 2 | B3: 1 | C3: SFG-FRBNPK-ET-CVR-72X33X10 | D3: Restonic Hotel Motel ET Cover 72X33X10 | E3: SFG-FRBNPK-ET-CVR-72X33X10 | F3: Restonic Hotel Motel ET Cover 72X33X10 | G3: Standard | H3: Production | I3: TAIL-ET-PT | J3: NOS | K3: 1 | L3: MRP&Rollup | M3: CBESFG | N3: 20 | O3: I | P3: RM-NWN-70GSMX6INCH | Q3: NON WOVEN FABRIC 70GSMX6" | R3: KGS | S3: 0.052 | T3: CBEWIP | U3: Backflush | V3: Active
A4: 3 | B4: 1 | C4: SFG-FRBNPK-ET-CVR-72X33X10 | D4: Restonic Hotel Motel ET Cover 72X33X10 | E4: SFG-FRBNPK-ET-CVR-72X33X10 | F4: Restonic Hotel Motel ET Cover 72X33X10 | G4: Standard | H4: Production | I4: TAIL-ET-PT | J4: NOS | K4: 1 | L4: MRP&Rollup | M4: CBESFG | N4: 30 | O4: I | P4: RML-NWN-70GSMX76" | Q4: NON WOVEN FABRIC WHITE 70 GSM 76 INCH | R4: KGS | S4: 0.113 | T4: CBEWIP | U4: Backflush | V4: Active
A5: 4 | B5: 1 | C5: SFG-FRBNPK-ET-CVR-72X33X10 | D5: Restonic Hotel Motel ET Cover 72X33X10 | E5: SFG-FRBNPK-ET-CVR-72X33X10 | F5: Restonic Hotel Motel ET Cover 72X33X10 | G5: Standard | H5: Production | I5: TAIL-ET-PT | J5: NOS | K5: 1 | L5: MRP&Rollup | M5: CBESFG | N5: 40 | O5: I | P5: SFG-RTHTMT-BNPK-ETBOR-11CM | Q5: Hotel Motel Poc ET-10 & 12 8MM/16D Pre Foam Border 11 CM Height | R5: MTR | S5: 5.41 | T5: CBESFG | U5: Backflush | V5: Active
A6: 5 | B6: 1 | C6: SFG-FRBNPK-ET-CVR-72X33X10 | D6: Restonic Hotel Motel ET Cover 72X33X10 | E6: SFG-FRBNPK-ET-CVR-72X33X10 | F6: Restonic Hotel Motel ET Cover 72X33X10 | G6: Standard | H6: Production | I6: TAIL-ET-PT | J6: NOS | K6: 1 | L6: MRP&Rollup | M6: CBESFG | N6: 50 | O6: I | P6: HW-CTON-THREAD | Q6: COTTON THREAD WHITE 3PLY | R6: MTR | S6: 10 | T6: CBEWIP | U6: Backflush | V6: Active
A7: 6 | B7: 2 | C7: SFG-FRBNPK-ET-CVR-72X39X10 | D7: Restonic Hotel Motel ET Cover 72X39X10 | E7: SFG-FRBNPK-ET-CVR-72X39X10 | F7: Restonic Hotel Motel ET Cover 72X39X10 | G7: Standard | H7: Production | I7: TAIL-ET-PT | J7: NOS | K7: 1 | L7: MRP&Rollup | M7: CBESFG | N7: 10 | O7: I | P7: RM-THRD-QS-TKT40 | Q7: THREAD TKT40 210D/3 PLY 10000MTS | R7: MTR | S7: 30.402 | T7: CBEWIP | U7: Backflush | V7: Active
A8: 7 | B8: 2 | C8: SFG-FRBNPK-ET-CVR-72X39X10 | D8: Restonic Hotel Motel ET Cover 72X39X10 | E8: SFG-FRBNPK-ET-CVR-72X39X10 | F8: Restonic Hotel Motel ET Cover 72X39X10 | G8: Standard | H8: Production | I8: TAIL-ET-PT | J8: NOS | K8: 1 | L8: MRP&Rollup | M8: CBESFG | N8: 20 | O8: I | P8: RM-NWN-70GSMX6INCH | Q8: NON WOVEN FABRIC 70GSMX6" | R8: KGS | S8: 0.056 | T8: CBEWIP | U8: Backflush | V8: Active
A9: 8 | B9: 2 | C9: SFG-FRBNPK-ET-CVR-72X39X10 | D9: Restonic Hotel Motel ET Cover 72X39X10 | E9: SFG-FRBNPK-ET-CVR-72X39X10 | F9: Restonic Hotel Motel ET Cover 72X39X10 | G9: Standard | H9: Production | I9: TAIL-ET-PT | J9: NOS | K9: 1 | L9: MRP&Rollup | M9: CBESFG | N9: 30 | O9: I | P9: RML-NWN-70GSMX76" | Q9: NON WOVEN FABRIC WHITE 70 GSM 76 INCH | R9: KGS | S9: 0.133 | T9: CBEWIP | U9: Backflush | V9: Active
A10: 9 | B10: 2 | C10: SFG-FRBNPK-ET-CVR-72X39X10 | D10: Restonic Hotel Motel ET Cover 72X39X10 | E10: SFG-FRBNPK-ET-CVR-72X39X10 | F10: Restonic Hotel Motel ET Cover 72X39X10 | G10: Standard | H10: Production | I10: TAIL-ET-PT | J10: NOS | K10: 1 | L10: MRP&Rollup | M10: CBESFG | N10: 40 | O10: I | P10: SFG-RTHTMT-BNPK-ETBOR-11CM | Q10: Hotel Motel Poc ET-10 & 12 8MM/16D Pre Foam Border 11 CM Height | R10: MTR | S10: 5.715 | T10: CBESFG | U10: Backflush | V10: Active
A11: 10 | B11: 2 | C11: SFG-FRBNPK-ET-CVR-72X39X10 | D11: Restonic Hotel Motel ET Cover 72X39X10 | E11: SFG-FRBNPK-ET-CVR-72X39X10 | F11: Restonic Hotel Motel ET Cover 72X39X10 | G11: Standard | H11: Production | I11: TAIL-ET-PT | J11: NOS | K11: 1 | L11: MRP&Rollup | M11: CBESFG | N11: 50 | O11: I | P11: HW-CTON-THREAD | Q11: COTTON THREAD WHITE 3PLY | R11: MTR | S11: 10 | T11: CBEWIP | U11: Backflush | V11: Active
A12: 11 | B12: 3 | C12: SFG-FRBNPK-ET-CVR-72X45X10 | D12: Restonic Hotel Motel ET Cover 72X45X10 | E12: SFG-FRBNPK-ET-CVR-72X45X10 | F12: Restonic Hotel Motel ET Cover 72X45X10 | G12: Standard | H12: Production | I12: TAIL-ET-PT | J12: NOS | K12: 1 | L12: MRP&Rollup | M12: CBESFG | N12: 10 | O12: I | P12: RM-THRD-QS-TKT40 | Q12: THREAD TKT40 210D/3 PLY 10000MTS | R12: MTR | S12: 32.023 | T12: CBEWIP | U12: Backflush | V12: Active
A13: 12 | B13: 3 | C13: SFG-FRBNPK-ET-CVR-72X45X10 | D13: Restonic Hotel Motel ET Cover 72X45X10 | E13: SFG-FRBNPK-ET-CVR-72X45X10 | F13: Restonic Hotel Motel ET Cover 72X45X10 | G13: Standard | H13: Production | I13: TAIL-ET-PT | J13: NOS | K13: 1 | L13: MRP&Rollup | M13: CBESFG | N13: 20 | O13: I | P13: RM-NWN-70GSMX6INCH | Q13: NON WOVEN FABRIC 70GSMX6" | R13: KGS | S13: 0.058 | T13: CBEWIP | U13: Backflush | V13: Active
... A201: 200 | B201: 40 | C201: SFG-FRBNPK-ET-CVR-84X69X10 | D201: Restonic Hotel Motel ET Cover 84X69X10 | E201: SFG-FRBNPK-ET-CVR-84X69X10 | F201: Restonic Hotel Motel ET Cover 84X69X10 | G201: Standard | H201: Production | I201: TAIL-ET-PT | J201: NOS | K201: 1 | L201: MRP&Rollup | M201: CBESFG | N201: 50 | O201: I | P201: HW-CTON-THREAD | Q201: COTTON THREAD WHITE 3PLY | R201: MTR | S201: 10 | T201: CBEWIP | U201: Backflush | V201: Active

Sheet RM-cost - feb-24
A1: SI.No | B1: Item Code | C1: Item Desc | D1: UOM | E1: Warehouse | F1: Opening Stock Qty | G1: Opening Stock Rate | H1: Opening Stock Value | I1: Stock In Qty | J1: Stock In Rate | K1: Stock In Value | L1: Stock Out Qty | M1: Stock Out Rate | N1: Stock Out Value | O1: Closing Stock Qty | P1: Closing Stock Rate | Q1: Closing Stock Value | R1: Item Account Group | S1: Item Account Group Desc | T1: Item Category
A2: 33 | B2: RML-CS-RTC-PLUSH-7.5 | C2: CORNER SHOES RESTONIC PLUSH - 7.5" | D2: NOS | E2: CBERM | F2: 900 | G2: 10.2033 | H2: 9182.97 | I2: 600 | J2: 10 | K2: 6000 | L2: 300 | M2: 10.1452 | N2: 3043.57 | O2: 1200 | P2: 10.1162 | Q2: 12139.4 | R2: LCE | S2: Label,CnrShoe,CentreBand,EdgeTape-10195 | T2: MATRESS
A3: 35 | B3: RML-CS-RTC-PLUSH-9.5 | C3: CORNER SHOES RESTONIC PLUSH - 9.5" | D3: NOS | E3: CBERM | F3: 1000 | G3: 10.3332 | H3: 10333.16 | I3: 500 | J3: 12.3 | K3: 6150 | L3: 200 | M3: 10.9888 | N3: 2197.76 | O3: 1300 | P3: 10.9888 | Q3: 14285.4 | R3: LCE | S3: Label,CnrShoe,CentreBand,EdgeTape-10195 | T3: MATRESS
A4: 37 | B4: RML-CS-SPG-6.5" | C4: CORNER SHOES. SPINE GUARD - 6.5" | D4: NOS | E4: CBERM | F4: 1200 | G4: 10.7018 | H4: 12842.19 | I4: 0 | K4: 0 | L4: 200 | M4: 10.7018 | N4: 2140.36 | O4: 1000 | P4: 10.7018 | Q4: 10701.83 | R4: LCE | S4: Label,CnrShoe,CentreBand,EdgeTape-10195 | T4: MATRESS
A5: 42 | B5: RML-CS-SPG-7.5" | C5: CORNER SHOES. SPINE GUARD - 7.5" | D5: NOS | E5: CBERM | F5: 1300 | G5: 10 | H5: 13000 | I5: 4800 | J5: 10 | K5: 48000 | L5: 3300 | M5: 10 | N5: 33000 | O5: 2800 | P5: 10 | Q5: 28000 | R5: LCE | S5: Label,CnrShoe,CentreBand,EdgeTape-10195 | T5: MATRESS
A6: 48 | B6: RML-CS-SPG-9.5" | C6: CORNER SHOES. SPINE GUARD - 9.5" | D6: NOS | E6: CBERM | F6: 1100 | G6: 10.48 | H6: 11528 | I6: 1000 | J6: 10.48 | K6: 10480 | L6: 1600 | M6: 10.48 | N6: 16768 | O6: 500 | P6: 10.48 | Q6: 5240 | R6: LCE | S6: Label,CnrShoe,CentreBand,EdgeTape-10195 | T6: MATRESS
A7: 56 | B7: RML-CS-SPK-10.5" | C7: CORNER SHOES. SPK - 10.5" | D7: NOS | E7: CBERM | F7: 1389 | G7: 9.7779 | H7: 13581.54 | I7: 0 | K7: 0 | L7: 0 | N7: 0 | O7: 1389 | P7: 9.7779 | Q7: 13581.54 | R7: LCE | S7: Label,CnrShoe,CentreBand,EdgeTape-10195 | T7: MATRESS
A8: 59 | B8: RML-CS-SPK-8.5" | C8: CORNER SHOES. SPK - 8.5" | D8: NOS | E8: CBERM | F8: 1000 | G8: 10.3146 | H8: 10314.55 | I8: 0 | K8: 0 | L8: 0 | N8: 0 | O8: 1000 | P8: 10.3146 | Q8: 10314.55 | R8: LCE | S8: Label,CnrShoe,CentreBand,EdgeTape-10195 | T8: MATRESS
A9: 63 | B9: RML-CS-SPK-BG-10.5 | C9: CORNER SHOES SPRINGKOIL BEIGE -10.5" | D9: NOS | E9: CBERM | F9: 400 | G9: 12.5 | H9: 5000 | I9: 0 | K9: 0 | L9: 0 | N9: 0 | O9: 400 | P9: 12.5 | Q9: 5000 | R9: LCE | S9: Label,CnrShoe,CentreBand,EdgeTape-10195 | T9: MATRESS
A10: 66 | B10: RML-CS-SPK-BG-7 | C10: CORNER SHOES SPRINGKOIL BEIGE -7" | D10: NOS | E10: CBERM | F10: 6500 | G10: 10 | H10: 65000 | I10: 0 | K10: 0 | L10: 400 | M10: 10 | N10: 4000 | O10: 6100 | P10: 10 | Q10: 61000 | R10: LCE | S10: Label,CnrShoe,CentreBand,EdgeTape-10195 | T10: MATRESS
A11: 67 | B11: RML-CS-SPK-BG-8.5 | C11: CORNER SHOES SPRINGKOIL BEIGE -8.5" | D11: NOS | E11: CBERM | F11: 3300 | G11: 10 | H11: 33000 | I11: 0 | K11: 0 | L11: 0 | N11: 0 | O11: 3300 | P11: 10 | Q11: 33000 | R11: LCE | S11: Label,CnrShoe,CentreBand,EdgeTape-10195 | T11: MATRESS
A12: 69 | B12: RML-CS-SPK-BL-10.5 | C12: CORNER SHOES SPRINGKOIL BLUE -10.5" | D12: NOS | E12: CBERM | F12: 500 | G12: 11.5625 | H12: 5781.25 | I12: 0 | K12: 0 | L12: 0 | N12: 0 | O12: 500 | P12: 11.5625 | Q12: 5781.25 | R12: LCE | S12: Label,CnrShoe,CentreBand,EdgeTape-10195 | T12: MATRESS
A13: 71 | B13: RML-CS-SPK-BL-6 | C13: CORNER SHOES SPRINGKOIL BLUE -6" | D13: NOS | E13: CBERM | F13: 2900 | G13: 10 | H13: 29000 | I13: 0 | K13: 0 | L13: 200 | M13: 10 | N13: 2000 | O13: 2700 | P13: 10 | Q13: 27000 | R13: LCE | S13: Label,CnrShoe,CentreBand,EdgeTape-10195 | T13: MATRESS
A14: 73 | B14: RML-CS-SPK-BL-7 | C14: CORNER SHOES SPRINGKOIL BLUE -7" | D14: NOS | E14: CBERM | F14: 21800 | G14: 8.6732 | H14: 189076.19 | I14: 50 | J14: 8.6732 | K14: 433.66 | L14: 6600 | M14: 8.6732 | N14: 57243.12 | O14: 15250 | P14: 8.6732 | Q14: 132266.73 | R14: LCE | S14: Label,CnrShoe,CentreBand,EdgeTape-10195 | T14: MATRESS
A15: 75 | B15: RML-CS-SPK-BL-7.5 | C15: CORNER SHOES SPRINGKOIL BLUE -7.5" | D15: NOS | E15: CBERM | F15: 1065 | G15: 10 | H15: 10650 | I15: 0 | K15: 0 | L15: 0 | N15: 0 | O15: 1065 | P15: 10 | Q15: 10650 | R15: LCE | S15: Label,CnrShoe,CentreBand,EdgeTape-10195 | T15: MATRESS
A16: 77 | B16: RML-CS-SPK-BL-8.5 | C16: CORNER SHOES SPRINGKOIL BLUE -8.5" | D16: NOS | E16: CBERM | F16: 4000 | G16: 10.2861 | H16: 41144.42 | I16: 100 | J16: 10.2861 | K16: 1028.61 | L16: 300 | M16: 10.2861 | N16: 3085.83 | O16: 3800 | P16: 10.2861 | Q16: 39087.2 | R16: LCE | S16: Label,CnrShoe,CentreBand,EdgeTape-10195 | T16: MATRESS
A17: 78 | B17: RML-CS-SPK-BW-10.5 | C17: CORNER SHOES SPRINGKOIL BROWN -10.5" | D17: NOS | E17: CBERM | F17: 800 | G17: 11.5625 | H17: 9250 | I17: 0 | K17: 0 | L17: 0 | N17: 0 | O17: 800 | P17: 11.5625 | Q17: 9250 | R17: LCE | S17: Label,CnrShoe,CentreBand,EdgeTape-10195 | T17: MATRESS
A18: 81 | B18: RML-CS-SPK-BW-6 | C18: CORNER SHOES SPRINGKOIL BROWN -6" | D18: NOS | E18: CBERM | F18: 500 | G18: 10 | H18: 5000 | I18: 0 | K18: 0 | L18: 100 | M18: 10 | N18: 1000 | O18: 400 | P18: 10 | Q18: 4000 | R18: LCE | S18: Label,CnrShoe,CentreBand,EdgeTape-10195 | T18: MATRESS
A19: 82 | B19: RML-CS-SPK-BW-7 | C19: CORNER SHOES SPRINGKOIL BROWN -7" | D19: NOS | E19: CBERM | F19: 4400 | G19: 10 | H19: 44000 | I19: 1000 | J19: 10 | K19: 10000 | L19: 2700 | M19: 10 | N19: 27000 | O19: 2700 | P19: 10 | Q19: 27000 | R19: LCE | S19: Label,CnrShoe,CentreBand,EdgeTape-10195 | T19: MATRESS
A20: 84 | B20: RML-CS-SPK-BW-7.5 | C20: CORNER SHOES SPRINGKOIL BROWN -7.5" | D20: NOS | E20: CBERM | F20: 555 | G20: 10 | H20: 5550 | I20: 0 | K20: 0 | L20: 0 | N20: 0 | O20: 555 | P20: 10 | Q20: 5550 | R20: LCE | S20: Label,CnrShoe,CentreBand,EdgeTape-10195 | T20: MATRESS
A21: 85 | B21: RML-CS-SPK-BW-8.5 | C21: CORNER SHOES SPRINGKOIL BROWN -8.5" | D21: NOS | E21: CBERM | F21: 3348 | G21: 10 | H21: 33480 | I21: 0 | K21: 0 | L21: 0 | N21: 0 | O21: 3348 | P21: 10 | Q21: 33480 | R21: LCE | S21: Label,CnrShoe,CentreBand,EdgeTape-10195 | T21: MATRESS
A22: 87 | B22: RML-CS-SPK-CR-10.5 | C22: CORNER SHOES SPRINGKOIL CREAM -10.5" | D22: NOS | E22: CBERM | F22: 800 | G22: 11.3889 | H22: 9111.11 | I22: 0 | K22: 0 | L22: 0 | N22: 0 | O22: 800 | P22: 11.3889 | Q22: 9111.11 | R22: LCE | S22: Label,CnrShoe,CentreBand,EdgeTape-10195 | T22: MATRESS
A23: 89 | B23: RML-CS-SPK-CR-6 | C23: CORNER SHOES SPRINGKOIL CREAM -6" | D23: NOS | E23: CBERM | F23: 400 | G23: 10 | H23: 4000 | I23: 0 | K23: 0 | L23: 100 | M23: 10 | N23: 1000 | O23: 300 | P23: 10 | Q23: 3000 | R23: LCE | S23: Label,CnrShoe,CentreBand,EdgeTape-10195 | T23: MATRESS
A24: 92 | B24: RML-CS-SPK-CR-7 | C24: CORNER SHOES SPRINGKOIL CREAM -7" | D24: NOS | E24: CBERM | F24: 4600 | G24: 10 | H24: 46000 | I24: 0 | K24: 0 | L24: 500 | M24: 10 | N24: 5000 | O24: 4100 | P24: 10 | Q24: 41000 | R24: LCE | S24: Label,CnrShoe,CentreBand,EdgeTape-10195 | T24: MATRESS
A25: 93 | B25: RML-CS-SPK-CR-7.5 | C25: CORNER SHOES SPRINGKOIL CREAM -7.5" | D25: NOS | E25: CBERM | F25: 280 | G25: 10 | H25: 2800 | I25: 0 | K25: 0 | L25: 0 | N25: 0 | O25: 280 | P25: 10 | Q25: 2800 | R25: LCE | S25: Label,CnrShoe,CentreBand,EdgeTape-10195 | T25: MATRESS
A26: 94 | B26: RML-CS-SPK-CR-8.5 | C26: CORNER SHOES SPRINGKOIL CREAM -8.5" | D26: NOS | E26: CBERM | F26: 2900 | G26: 10 | H26: 29000 | I26: 0 | K26: 0 | L26: 0 | N26: 0 | O26: 2900 | P26: 10 | Q26: 29000 | R26: LCE | S26: Label,CnrShoe,CentreBand,EdgeTape-10195 | T26: MATRESS
A27: 97 | B27: RML-CS-SPK-CT-6 | C27: PEPS SPRINGKOIL CROWN TOP CORNER SHOES 6" | D27: NOS | E27: CBERM | F27: 2000 | G27: 8.65 | H27: 17300 | I27: 14000 | J27: 8.65 | K27: 121100 | L27: 2400 | M27: 8.65 | N27: 20760 | O27: 13600 | P27: 8.65 | Q27: 117640 | R27: LCE | S27: Label,CnrShoe,CentreBand,EdgeTape-10195 | T27: MATRESS
A28: 102 | B28: RML-CS-SPK-CT-7.5 | C28: PEPS SPRINGKOIL CROWN TOP CORNER SHOES 7.5" | D28: NOS | E28: CBERM | F28: 1400 | G28: 9.9 | H28: 13860 | I28: 0 | K28: 0 | L28: 200 | M28: 9.9 | N28: 1980 | O28: 1200 | P28: 9.9 | Q28: 11880 | R28: LCE | S28: Label,CnrShoe,CentreBand,EdgeTape-10195 | T28: MATRESS
A29: 108 | B29: RML-CS-SPK-CT-9.25 | C29: PEPS SPRINGKOIL CROWN TOP CORNER SHOES 9.25" | D29: NOS | E29: CBERM | F29: 850 | G29: 15.3 | H29: 13005 | I29: 0 | K29: 0 | L29: 100 | M29: 15.3 | N29: 1530 | O29: 750 | P29: 15.3 | Q29: 11475 | R29: LCE | S29: Label,CnrShoe,CentreBand,EdgeTape-10195 | T29: MATRESS
A30: 110 | B30: RML-CS-SPK-GR-10.5 | C30: CORNER SHOES SPRINGKOIL GREY -10.5" | D30: NOS | E30: CBERM | F30: 400 | G30: 12.5 | H30: 5000 | I30: 0 | K30: 0 | L30: 0 | N30: 0 | O30: 400 | P30: 12.5 | Q30: 5000 | R30: LCE | S30: Label,CnrShoe,CentreBand,EdgeTape-10195 | T30: MATRESS
A31: 113 | B31: RML-CS-SPK-GR-7 | C31: CORNER SHOES SPRINGKOIL GREY -7" | D31: NOS | E31: CBERM | F31: 6600 | G31: 10 | H31: 66000 | I31: 0 | K31: 0 | L31: 1700 | M31: 10 | N31: 17000 | O31: 4900 | P31: 10 | Q31: 49000 | R31: LCE | S31: Label,CnrShoe,CentreBand,EdgeTape-10195 | T31: MATRESS
A32: 115 | B32: RML-CS-SPK-GR-8.5 | C32: CORNER SHOES SPRINGKOIL GREY -8.5" | D32: NOS | E32: CBERM | F32: 4400 | G32: 10 | H32: 44000 | I32: 0 | K32: 0 | L32: 100 | M32: 10 | N32: 1000 | O32: 4300 | P32: 10 | Q32: 43000 | R32: LCE | S32: Label,CnrShoe,CentreBand,EdgeTape-10195 | T32: MATRESS
A33: 116 | B33: RML-CS-SPK-MR-10.5 | C33: CORNER SHOES SPRINGKOIL MAROON -10.5" | D33: NOS | E33: CBERM | F33: 1100 | G33: 11.5385 | H33: 12692.3 | I33: 0 | K33: 0 | L33: 200 | M33: 11.5385 | N33: 2307.7 | O33: 900 | P33: 11.5384 | Q33: 10384.6 | R33: LCE | S33: Label,CnrShoe,CentreBand,EdgeTape-10195 | T33: MATRESS
A34: 118 | B34: RML-CS-SPK-MR-6 | C34: CORNER SHOES SPRINGKOIL MAROON -6" | D34: NOS | E34: CBERM | F34: 4100 | G34: 10 | H34: 41000 | I34: 0 | K34: 0 | L34: 300 | M34: 10 | N34: 3000 | O34: 3800 | P34: 10 | Q34: 38000 | R34: LCE | S34: Label,CnrShoe,CentreBand,EdgeTape-10195 | T34: MATRESS
A35: 120 | B35: RML-CS-SPK-MR-7 | C35: CORNER SHOES SPRINGKOIL MAROON -7" | D35: NOS | E35: CBERM | F35: 16500 | G35: 8.6704 | H35: 143061.16 | I35: 0 | K35: 0 | L35: 7500 | M35: 8.6704 | N35: 65028 | O35: 9000 | P35: 8.6704 | Q35: 78033.16 | R35: LCE | S35: Label,CnrShoe,CentreBand,EdgeTape-10195 | T35: MATRESS
A36: 122 | B36: RML-CS-SPK-MR-7.5 | C36: CORNER SHOES SPRINGKOIL MAROON -7.5" | D36: NOS | E36: CBERM | F36: 1145 | G36: 10 | H36: 11450 | I36: 0 | K36: 0 | L36: 0 | N36: 0 | O36: 1145 | P36: 10 | Q36: 11450 | R36: LCE | S36: Label,CnrShoe,CentreBand,EdgeTape-10195 | T36: MATRESS
A37: 124 | B37: RML-CS-SPK-MR-8.5 | C37: CORNER SHOES SPRINGKOIL MAROON -8.5" | D37: NOS | E37: CBERM | F37: 3160 | G37: 10.3345 | H37: 32657.08 | I37: 600 | J37: 10.0477 | K37: 6028.62 | L37: 560 | M37: 10.3034 | N37: 5769.93 | O37: 3200 | P37: 10.2862 | Q37: 32915.77 | R37: LCE | S37: Label,CnrShoe,CentreBand,EdgeTape-10195 | T37: MATRESS
A38: 126 | B38: RML-CS-TRT-7 | C38: CORNER SHOES. TARTANIA-7" | D38: NOS | E38: CBERM | F38: 3500 | G38: 10.2299 | H38: 35804.78 | I38: 0 | K38: 0 | L38: 300 | M38: 10.2299 | N38: 3068.97 | O38: 3200 | P38: 10.2299 | Q38: 32735.81 | R38: LCE | S38: Label,CnrShoe,CentreBand,EdgeTape-10195 | T38: MATRESS
A39: 253 | B39: 100D-RB-FOAM-77X71X25MM | C39: 100D-Rebonded Foam Sheet-77X71X25mm | D39: KGS | E39: CBERM | F39: 0 | H39: 0 | I39: 865.5 | J39: 92 | K39: 79626 | L39: 865.5 | M39: 92 | N39: 79626 | O39: 0 | Q39: 0 | R39: FMREBOND | S39: FOAM REBONDED -10181 | T39: FOAM
A40: 627 | B40: SBLGPS | C40: Knurling Bush | D40: NOS | E40: CBERM | F40: 1220 | G40: 25 | H40: 30500 | I40: 80 | J40: 25 | K40: 2000 | L40: 900 | M40: 25 | N40: 22500 | O40: 400 | P40: 25 | Q40: 10000 | R40: LCE | S40: Label,CnrShoe,CentreBand,EdgeTape-10195 | T40: MATRESS
A41: 629 | B41: SCRAP-COIR-BLOCK | C41: Coir Block Waste Scrop | D41: KGS | E41: CBERM | F41: 0 | H41: 0 | I41: 80.3 | J41: 28 | K41: 2248.4 | L41: 80.3 | M41: 28 | N41: 2248.4 | O41: 0 | Q41: 0 | R41: SEMIQUILT | S41: SEMI FINISHED QUILT SECTION -10198 | T41: MATRESS
A42: 701 | B42: RML-FTD-SHT-75X60 | C42: PEPS FITTED SHEET 75X60 | D42: NOS | E42: CBERM | F42: 42 | G42: 627 | H42: 26334 | I42: 0 | K42: 0 | L42: 0 | N42: 0 | O42: 42 | P42: 627 | Q42: 26334 | R42: ALIPROD | S42: Allied Products-13015 | T42: MATRESS
A43: 709 | B43: RML-FTD-SHT-75X72 | C43: PEPS FITTED SHEET 75X72 | D43: NOS | E43: CBERM | F43: 20 | G43: 752 | H43: 15040 | I43: 0 | K43: 0 | L43: 0 | N43: 0 | O43: 20 | P43: 752 | Q43: 15040 | R43: ALIPROD | S43: Allied Products-13015 | T43: MATRESS
A44: 721 | B44: RML-FTD-SHT-78X60 | C44: PEPS FITTED SHEET 78X60 | D44: NOS | E44: CBERM | F44: 22 | G44: 652 | H44: 14344 | I44: 0 | K44: 0 | L44: 0 | N44: 0 | O44: 22 | P44: 652 | Q44: 14344 | R44: ALIPROD | S44: Allied Products-13015 | T44: MATRESS
A45: 743 | B45: RML-FTD-SHT-78X72 | C45: PEPS FITTED SHEET 78X72 | D45: NOS | E45: CBERM | F45: 21 | G45: 782 | H45: 16422 | I45: 0 | K45: 0 | L45: 0 | N45: 0 | O45: 21 | P45: 782 | Q45: 16422 | R45: ALIPROD | S45: Allied Products-13015 | T45: MATRESS
A46: 795 | B46: RML-HNDL-ALLURA-BLUE | C46: PEPS ALLURA BLUE HANDLE | D46: NOS | E46: CBERM | F46: 600 | G46: 5.5 | H46: 3300 | I46: 0 | K46: 0 | L46: 0 | N46: 0 | O46: 600 | P46: 5.5 | Q46: 3300 | R46: LCE | S46: Label,CnrShoe,CentreBand,EdgeTape-10195 | T46: MATRESS
A47: 796 | B47: RML-HNDL-ALLURA-OR | C47: PEPS ALLURA ORANGE HANDLE | D47: NOS | E47: CBERM | F47: 1465 | G47: 5.5 | H47: 8057.5 | I47: 0 | K47: 0 | L47: 0 | N47: 0 | O47: 1465 | P47: 5.5 | Q47: 8057.5 | R47: LCE | S47: Label,CnrShoe,CentreBand,EdgeTape-10195 | T47: MATRESS
A48: 801 | B48: RML-HNDL-ARD-BRN | C48: RESTONIC ARDENE BROWN HANDLE | D48: NOS | E48: CBERM | F48: 2150 | G48: 12.2002 | H48: 26230.46 | I48: 1875 | J48: 12.2 | K48: 22875 | L48: 350 | M48: 12.2001 | N48: 4270.05 | O48: 3675 | P48: 12.2001 | Q48: 44835.41 | R48: LCE | S48: Label,CnrShoe,CentreBand,EdgeTape-10195 | T48: MATRESS
A49: 805 | B49: RML-HNDL-ARD-GREY | C49: RESTONIC ARDENE GREY HANDLE | D49: NOS | E49: CBERM | F49: 700 | G49: 9.3642 | H49: 6554.91 | I49: 0 | K49: 0 | L49: 150 | M49: 9.3642 | N49: 1404.63 | O49: 550 | P49: 9.3641 | Q49: 5150.28 | R49: LCE | S49: Label,CnrShoe,CentreBand,EdgeTape-10195 | T49: MATRESS
A50: 810 | B50: RML-HNDL-CAR-BLUE | C50: RESTONIC CAROUSEL BLUE HANDLE | D50: NOS | E50: CBERM | F50: 13036 | G50: 6.115 | H50: 79714.67 | I50: 0 | K50: 0 | L50: 1100 | M50: 6.1149 | N50: 6726.39 | O50: 11936 | P50: 6.115 | Q50: 72988.28 | R50: LCE | S50: Label,CnrShoe,CentreBand,EdgeTape-10195 | T50: MATRESS
A51: 814 | B51: RML-HNDL-CAR-CRM | C51: RESTONIC CAROUSEL CREAM HANDLE | D51: NOS | E51: CBERM | F51: 2300 | G51: 6.25 | H51: 14375.05 | I51: 2500 | J51: 6.25 | K51: 15625 | L51: 1800 | M51: 6.25 | N51: 11250 | O51: 3000 | P51: 6.25 | Q51: 18750.05 | R51: LCE | S51: Label,CnrShoe,CentreBand,EdgeTape-10195 | T51: MATRESS
A52: 820 | B52: RML-HNDL-CAR-PL-CRM | C52: RESTONIC CAROUSEL PLUSH CREAM HANDLE | D52: NOS | E52: CBERM | F52: 1725 | G52: 6.7498 | H52: 11643.36 | I52: 500 | J52: 6.75 | K52: 3375 | L52: 675 | M52: 6.7498 | N52: 4556.12 | O52: 1550 | P52: 6.7498 | Q52: 10462.24 | R52: LCE | S52: Label,CnrShoe,CentreBand,EdgeTape-10195 | T52: MATRESS
A53: 882 | B53: RML-KOM-COM-MRP-LBL | C53: KOMFFY FEATHER SOFT COMFORTER MRP LABEL | D53: NOS | E53: CBERM | F53: 190 | G53: 2.9247 | H53: 555.7 | I53: 0 | K53: 0 | L53: 0 | N53: 0 | O53: 190 | P53: 2.9247 | Q53: 555.7 | R53: LCE | S53: Label,CnrShoe,CentreBand,EdgeTape-10195 | T53: MATRESS
A54: 883 | B54: RML-KOM-COM-PVC-CVR | C54: KOMFFY COMFORTER PVC COVER (12MIC PET+75MIC LDPE N ,750MMX490MM) | D54: NOS | E54: CBERM | F54: 4515 | G54: 18 | H54: 81270 | I54: 10408 | J54: 18 | K54: 187344 | L54: 500 | M54: 18 | N54: 9000 | O54: 14423 | P54: 18 | Q54: 259614 | R54: PML | S54: Packing Material-10195 | T54: MATRESS
A55: 884 | B55: RML-KOM-GRIP-INS | C55: KOMFFY GRIPSTER INSERTER | D55: NOS | E55: CBERM | F55: 1000 | G55: 19.1 | H55: 19100 | I55: 0 | K55: 0 | L55: 0 | N55: 0 | O55: 1000 | P55: 19.1 | Q55: 19100 | R55: LCE | S55: Label,CnrShoe,CentreBand,EdgeTape-10195 | T55: MATRESS
A56: 924 | B56: RML-KOM-PL-BED-SHT-105X120 | C56: KOMFFY PLUS BED SHEET SUPER KING- 105"X120" (RTC) | D56: NOS | E56: CBERM | F56: 5396 | G56: 429 | H56: 2314884 | I56: 0 | K56: 0 | L56: 192 | M56: 429 | N56: 82368 | O56: 5204 | P56: 429 | Q56: 2232516 | R56: SCHEME | S56: Scheme Materials-13015 | T56: MATRESS
A57: 992 | B57: RML-CUT-RES-GLS | C57: CUTTING RESISTANCE GLOVES | D57: PRS | E57: CBERM | F57: 26 | G57: 175 | H57: 4550 | I57: 25 | J57: 175 | K57: 4375 | L57: 25 | M57: 175 | N57: 4375 | O57: 26 | P57: 175 | Q57: 4550 | R57: PML | S57: Packing Material-10195 | T57: MATRESS
A58: 999 | B58: RML-DDR-SDE-LBL | C58: DOUBLE DECKER SIDE LABEL (RUBBER PATCH) | D58: NOS | E58: CBERM | F58: 1343 | G58: 115.9205 | H58: 155681.17 | I58: 0 | K58: 0 | L58: 2 | M58: 115.92 | N58: 231.84 | O58: 1341 | P58: 115.9205 | Q58: 155449.33 | R58: LCE | S58: Label,CnrShoe,CentreBand,EdgeTape-10195 | T58: MATRESS
A59: 1000 | B59: RML-DD-WCRD | C59: PEPS DOUBLE DECKER WARRANTY CARD | D59: NOS | E59: CBERM | F59: 1095 | G59: 13.8549 | H59: 15171.17 | I59: 5 | J59: 13.854 | K59: 69.27 | L59: 0 | N59: 0 | O59: 1100 | P59: 13.8549 | Q59: 15240.44 | R59: LCE | S59: Label,CnrShoe,CentreBand,EdgeTape-10195 | T59: MATRESS
A60: 1005 | B60: RM-LDPE-50"TUBE-PLAIN | C60: LDPE TUBE 58"X50.MIC | D60: KGS | E60: CBERM | F60: 519.4 | G60: 127.0259 | H60: 65977.26 | I60: 211.9 | J60: 130 | K60: 27547 | L60: 312.1 | M60: 127.4226 | N60: 39768.6 | O60: 419.2 | P60: 128.2339 | Q60: 53755.66 | R60: PML | S60: Packing Material-10195 | T60: MATRESS
A61: 1096 | B61: RML-FIT-SHT-INS-DOUBLE | C61: PEPS POLAR FLEECE BLANKET INSERTER- DOUBLE | D61: NOS | E61: CBERM | F61: 515 | G61: 17.9391 | H61: 9238.64 | I61: 0 | K61: 0 | L61: 13 | M61: 17.9392 | N61: 233.21 | O61: 502 | P61: 17.9391 | Q61: 9005.43 | R61: LCE | S61: Label,CnrShoe,CentreBand,EdgeTape-10195 | T61: FOAM
A62: 1098 | B62: RML-FIT-SHT-INS-SINGLE | C62: PEPS POLAR FLEECE BLANKET INSERTER- SINGLE | D62: NOS | E62: CBERM | F62: 286 | G62: 16.4821 | H62: 4713.88 | I62: 0 | K62: 0 | L62: 15 | M62: 16.482 | N62: 247.23 | O62: 271 | P62: 16.4821 | Q62: 4466.65 | R62: LCE | S62: Label,CnrShoe,CentreBand,EdgeTape-10195 | T62: FOAM
A63: 1099 | B63: RML-FIX-BRACKET | C63: BASE AND HB FIXING BRACKET | D63: SET | E63: CBERM | F63: 708 | G63: 76.5997 | H63: 54232.56 | I63: 0 | K63: 0 | L63: 60 | M63: 76.5997 | N63: 4595.98 | O63: 648 | P63: 76.5997 | Q63: 49636.58 | R63: BASHB | S63: Base and Head Board -10181 | T63: FOAM
A64: 1101 | B64: RML-FLN-BLNK-60X85 | C64: PEPS Flano Printed blanket Single- Size:60x85 Inch | D64: NOS | E64: CBERM | F64: 64 | G64: 255 | H64: 16320 | I64: 0 | K64: 0 | L64: 0 | N64: 0 | O64: 64 | P64: 255 | Q64: 16320 | R64: ALIPROD | S64: Allied Products-13015 | T64: MATRESS
A65: 1103 | B65: RML-FLN-BLNK-85X95 | C65: PEPS FLANO PRINTED BLANKET DOUBLE- SIZE:85X95 INCH | D65: NOS | E65: CBERM | F65: 58 | G65: 265 | H65: 15370 | I65: 0 | K65: 0 | L65: 0 | N65: 0 | O65: 58 | P65: 265 | Q65: 15370 | R65: ALIPROD | S65: Allied Products-13015 | T65: MATRESS
A66: 1107 | B66: RML-FLXI-NECK-PLW-CTN-ROPE | C66: FLEXI NECK PILLOW COTTON ROPE - 2.5MM | D66: KGS | E66: CBERM | F66: 16.98 | G66: 185 | H66: 3141.3 | I66: 0 | K66: 0 | L66: 5.92 | M66: 185 | N66: 1095.2 | O66: 11.06 | P66: 185 | Q66: 2046.1 | R66: LCE | S66: Label,CnrShoe,CentreBand,EdgeTape-10195 | T66: MATRESS
A67: 1109 | B67: RML-FLXI-NECK-PLW-MRP-LBL | C67: FLEXI NECK PILLOW MRP LABEL | D67: NOS | E67: CBERM | F67: 100 | G67: 11 | H67: 1100 | I67: 700 | J67: 11 | K67: 7700 | L67: 200 | M67: 11 | N67: 2200 | O67: 600 | P67: 11 | Q67: 6600 | R67: LCE | S67: Label,CnrShoe,CentreBand,EdgeTape-10195 | T67: MATRESS
A68: 1111 | B68: RML-FLXI-NECK-PLW-PVC-BAG | C68: FLEXI NECK PILLOW PVC BAG 11.25" Wx11.5" Hx4" G | D68: NOS | E68: CBERM | F68: 1325 | G68: 27 | H68: 35775 | I68: 575 | J68: 27 | K68: 15525 | L68: 50 | M68: 27 | N68: 1350 | O68: 1850 | P68: 27 | Q68: 49950 | R68: PML | S68: Packing Material-10195 | T68: MATRESS
A69: 1113 | B69: RML-FLXI-NECK-PLW-WSCR-LBL | C69: FLEXI NECK PILLOW WASH CARE LABEL | D69: NOS | E69: CBERM | F69: 500 | G69: 0.8 | H69: 400 | I69: 0 | K69: 0 | L69: 0 | N69: 0 | O69: 500 | P69: 0.8 | Q69: 400 | R69: LCE | S69: Label,CnrShoe,CentreBand,EdgeTape-10195 | T69: MATRESS
A70: 1115 | B70: RML-FLXI-SPN-LDPE-7X30+4FX75MIC | C70: FLEXI SPINE LDPE PLAIN SEAL KING BAG 7"X 30"+ 4"F X 75MIC | D70: NOS | E70: CBERM | F70: 1500 | G70: 2.4 | H70: 3600 | I70: 0 | K70: 0 | L70: 0 | N70: 0 | O70: 1500 | P70: 2.4 | Q70: 3600 | R70: PML | S70: Packing Material-10195 | T70: MATRESS
A71: 1116 | B71: RML-FLXI-SPN-PLW-BOX | C71: FLEXI SPINE PILLOW BOX 27"x5"x4" - 3 Ply | D71: NOS | E71: CBERM | F71: 600 | G71: 44 | H71: 26400 | I71: 500 | J71: 44 | K71: 22000 | L71: 75 | M71: 44 | N71: 3300 | O71: 1025 | P71: 44 | Q71: 45100 | R71: PML | S71: Packing Material-10195 | T71: MATRESS
A72: 1119 | B72: RML-FLXI-SPN-PLW-WSCR-LBL | C72: FLEXI SPINE PILLOW WASH CARE LABEL | D72: NOS | E72: CBERM | F72: 750 | G72: 0.8 | H72: 600 | I72: 0 | K72: 0 | L72: 0 | N72: 0 | O72: 750 | P72: 0.8 | Q72: 600 | R72: LCE | S72: Label,CnrShoe,CentreBand,EdgeTape-10195 | T72: MATRESS
A73: 1121 | B73: RML-FLXI-SPN-PVC-HOSE | C73: FLEXI SPINE PVC HOSE 1/2" X 26" | D73: NOS | E73: CBERM | F73: 689 | G73: 164.5714 | H73: 113389.71 | I73: 0 | K73: 0 | L73: 0 | N73: 0 | O73: 689 | P73: 164.5714 | Q73: 113389.71 | R73: CPG | S73: Clips, Polygel & Glue-10195 | T73: MATRESS
A74: 1122 | B74: RML-FLX-STRAP-GRY | C74: FLEXI SPINE PILLOW STRAP GREY-12MM | D74: MTR | E74: CBERM | F74: 60 | G74: 33.33 | H74: 1999.8 | I74: 0 | K74: 0 | L74: 0 | N74: 0 | O74: 60 | P74: 33.33 | Q74: 1999.8 | R74: PML | S74: Packing Material-10195 | T74: MATRESS
A75: 1123 | B75: RML-FLX-STRAP-NVBL | C75: FLEXI SPINE PILLOW STRAP NAVY BLUE-12MM | D75: MTR | E75: CBERM | F75: 60 | G75: 33.33 | H75: 1999.8 | I75: 0 | K75: 0 | L75: 0 | N75: 0 | O75: 60 | P75: 33.33 | Q75: 1999.8 | R75: PML | S75: Packing Material-10195 | T75: MATRESS
A76: 1124 | B76: RML-FM-WHT-HANDLE | C76: FOAM MATTRESS WHITE WITH CREAM HANDLE | D76: NOS | E76: CBERM | F76: 2150 | G76: 5.2502 | H76: 11287.86 | I76: 250 | J76: 5.25 | K76: 1312.5 | L76: 325 | M76: 5.2502 | N76: 1706.32 | O76: 2075 | P76: 5.2501 | Q76: 10894.04 | R76: LCE | S76: Label,CnrShoe,CentreBand,EdgeTape-10195 | T76: MATRESS
A77: 1130 | B77: RML-FOAMERA-WCRD | C77: FOAMERA 7 YEARS WARRANTY CARD | D77: NOS | E77: CBERM | F77: 1250 | G77: 5.4498 | H77: 6812.23 | I77: 0 | K77: 0 | L77: 0 | N77: 0 | O77: 1250 | P77: 5.4498 | Q77: 6812.23 | R77: LCE | S77: Label,CnrShoe,CentreBand,EdgeTape-10195 | T77: MATRESS
A78: 1142 | B78: RML-FOL-ROLWAY-COT | C78: FOLDING ROLLWAY COT 72"X36" | D78: NOS | E78: CBERM | F78: 8 | G78: 6963.7175 | H78: 55709.74 | I78: 0 | K78: 0 | L78: 6 | M78: 6963.72 | N78: 41782.32 | O78: 2 | P78: 6963.71 | Q78: 13927.42 | R78: SPARE | S78: SPARES Inventory - 10698 | T78: MATRESS
A79: 1681 | B79: RML-KOM-PTR-78X30 | C79: KOMFFY MATTRESSES PROTECTOR 78X30 | D79: NOS | E79: CBERM | F79: 5 | G79: 416 | H79: 2080 | I79: 0 | K79: 0 | L79: 0 | N79: 0 | O79: 5 | P79: 416 | Q79: 2080 | R79: SCHEME | S79: Scheme Materials-13015 | T79: MATRESS
A80: 1685 | B80: RML-KOM-PTR-78X36 | C80: KOMFFY MATTRESSES PROTECTOR 78X36 | D80: NOS | E80: CBERM | F80: 123 | G80: 498 | H80: 61254 | I80: 0 | K80: 0 | L80: 0 | N80: 0 | O80: 123 | P80: 498 | Q80: 61254 | R80: SCHEME | S80: Scheme Materials-13015 | T80: MATRESS
A81: 1692 | B81: RML-KOM-PTR-78X48 | C81: KOMFFY MATTRESSES PROTECTOR 78X48 | D81: NOS | E81: CBERM | F81: 308 | G81: 590 | H81: 181720 | I81: 0 | K81: 0 | L81: 0 | N81: 0 | O81: 308 | P81: 590 | Q81: 181720 | R81: SCHEME | S81: Scheme Materials-13015 | T81: MATRESS
A82: 1703 | B82: RML-KOM-PTR-78X60 | C82: KOMFFY MATTRESSES PROTECTOR 78X60 | D82: NOS | E82: CBERM | F82: 691 | G82: 592 | H82: 409072 | I82: 2 | J82: 592 | K82: 1184 | L82: 0 | N82: 0 | O82: 693 | P82: 592 | Q82: 410256 | R82: SCHEME | S82: Scheme Materials-13015 | T82: MATRESS
A83: 1731 | B83: RML-KOM-PTR-84X72 | C83: KOMFFY MATTRESSES PROTECTOR 84X72 | D83: NOS | E83: CBERM | F83: 13 | G83: 1030 | H83: 13390 | I83: 0 | K83: 0 | L83: 0 | N83: 0 | O83: 13 | P83: 1030 | Q83: 13390 | R83: SCHEME | S83: Scheme Materials-13015 | T83: MATRESS
A84: 1734 | B84: RML-KOM-PTR-INS | C84: KOMFFY PROTECTOR INSERTER | D84: NOS | E84: CBERM | F84: 3950 | G84: 7.2601 | H84: 28677.42 | I84: 0 | K84: 0 | L84: 0 | N84: 0 | O84: 3950 | P84: 7.2601 | Q84: 28677.42 | R84: LCE | S84: Label,CnrShoe,CentreBand,EdgeTape-10195 | T84: FOAM
A85: 1737 | B85: RML-KOM-PTR-MRP-LBL | C85: KOMFFY PROTECTOR MRP LABEL | D85: NOS | E85: CBERM | F85: 11400 | G85: 0.9693 | H85: 11049.86 | I85: 0 | K85: 0 | L85: 0 | N85: 0 | O85: 11400 | P85: 0.9693 | Q85: 11049.86 | R85: LCE | S85: Label,CnrShoe,CentreBand,EdgeTape-10195 | T85: FOAM
A86: 1784 | B86: RML-KOM-WSCR-LBL-CNTR-PLW | C86: KOMFFY MEMORY CONTOUR PILLOW WASH CARE LABEL | D86: NOS | E86: CBERM | F86: 7500 | G86: 0.5995 | H86: 4496.6 | I86: 0 | K86: 0 | L86: 0 | N86: 0 | O86: 7500 | P86: 0.5995 | Q86: 4496.6 | R86: LCE | S86: Label,CnrShoe,CentreBand,EdgeTape-10195 | T86: FOAM
A87: 1785 | B87: RML-KOZBRE-SDE-LBL | C87: KOZYBREEZ SIDE LABEL | D87: NOS | E87: CBERM | F87: 3100 | G87: 8.8006 | H87: 27281.9 | I87: 0 | K87: 0 | L87: 100 | M87: 8.8006 | N87: 880.06 | O87: 3000 | P87: 8.8006 | Q87: 26401.84 | R87: LCE | S87: Label,CnrShoe,CentreBand,EdgeTape-10195 | T87: MATRESS
A88: 1789 | B88: RML-KOZBRE-WCRD | C88: KOZYBREEZ WARRANTY CARD | D88: NOS | E88: CBERM | F88: 1973 | G88: 3.2768 | H88: 6465.22 | I88: 300 | J88: 11 | K88: 3300 | L88: 0 | N88: 0 | O88: 2273 | P88: 4.2962 | Q88: 9765.22 | R88: LCE | S88: Label,CnrShoe,CentreBand,EdgeTape-10195 | T88: MATRESS
A89: 1792 | B89: RML-LAT-MAS-PIL-BOX | C89: LATEX MASSAGE PILLOW BOX | D89: NOS | E89: CBERM | F89: 240 | G89: 103.3256 | H89: 24798.15 | I89: 0 | K89: 0 | L89: 56 | M89: 103.3257 | N89: 5786.24 | O89: 184 | P89: 103.3256 | Q89: 19011.91 | R89: PML | S89: Packing Material-10195 | T89: MATRESS
A90: 1796 | B90: RML-LCORNER-PAD-15 | C90: 15X15 INCH L CORNER PAD | D90: NOS | E90: CBERM | F90: 2350 | G90: 12.4986 | H90: 29371.76 | I90: 0 | K90: 0 | L90: 1550 | M90: 12.4986 | N90: 19372.83 | O90: 800 | P90: 12.4987 | Q90: 9998.93 | R90: PML | S90: Packing Material-10195 | T90: MATRESS
A91: 1831 | B91: RML-NET-PADDING | C91: HDPE KNITTED FABRIC ( MOSQUITO NET) | D91: MTR | E91: CBERM | F91: 81374 | G91: 6.4828 | H91: 527533.33 | I91: 71387 | J91: 6.4889 | K91: 463225.54 | L91: 72551 | M91: 6.4852 | N91: 470508.36 | O91: 80210 | P91: 6.4861 | Q91: 520250.51 | R91: NET | S91: Net-10195 | T91: MATRESS
A92: 1836 | B92: RML-NET-PADDING-TNDR | C92: TNDR - HDPE KNITTED FABRIC ( MOSQUITO NET) | D92: MTR | E92: CBERM | F92: 45928 | G92: 6 | H92: 275568 | I92: 0 | K92: 0 | L92: 45928 | M92: 6 | N92: 275568 | O92: 0 | Q92: 0 | R92: NET | S92: Net-10195 | T92: MATRESS
A93: 1838 | B93: RML-NET-PADDING-WHT | C93: HDPE KNITTED FABRIC - WHITE (MOSQUITO NET) | D93: MTR | E93: CBERM | F93: 1425 | G93: 8.5 | H93: 12112.5 | I93: 1920 | J93: 8.5 | K93: 16320 | L93: 1425 | M93: 8.5 | N93: 12112.5 | O93: 1920 | P93: 8.5 | Q93: 16320 | R93: LCE | S93: Label,CnrShoe,CentreBand,EdgeTape-10195 | T93: MATRESS
A94: 1839 | B94: RML-NONSTANDARD-SKR | C94: NON STANDARD STICKER | D94: NOS | E94: CBERM | F94: 950 | G94: 0.51 | H94: 484.51 | I94: 1000 | J94: 0.8 | K94: 800 | L94: 700 | M94: 0.6197 | N94: 433.8 | O94: 1250 | P94: 0.6806 | Q94: 850.71 | R94: LCE | S94: Label,CnrShoe,CentreBand,EdgeTape-10195 | T94: MATRESS
A95: 1841 | B95: RML-NWN-70GSMX76" | C95: NON WOVEN FABRIC 70 GSM x 76 INCH - WHITE | D95: KGS | E95: CBERM | F95: 607.8 | G95: 112.8872 | H95: 68612.82 | I95: 0 | K95: 0 | L95: 191 | M95: 112.8872 | N95: 21561.45 | O95: 416.8 | P95: 112.8872 | Q95: 47051.37 | R95: NW | S95: Non Woven Fabric-10195 | T95: MATRESS
A96: 1846 | B96: RML-NWN-70GSMX79" | C96: NON WOVEN FABRIC 70 GSM x 79 INCH - WHITE | D96: KGS | E96: CBERM | F96: 715.4 | G96: 113.6458 | H96: 81302.17 | I96: 3985.4 | J96: 114 | K96: 454335.43 | L96: 2965 | M96: 113.9235 | N96: 337783.29 | O96: 1735.8 | P96: 113.9845 | Q96: 197854.31 | R96: NW | S96: Non Woven Fabric-10195 | T96: MATRESS
A97: 1850 | B97: RML-NWN-80GSMX8" | C97: NON WOVEN FABRIC 80 GSM x 8 INCH - WHITE | D97: KGS | E97: CBERM | F97: 285.8 | G97: 111.0368 | H97: 31734.32 | I97: 0 | K97: 0 | L97: 0 | N97: 0 | O97: 285.8 | P97: 111.0368 | Q97: 31734.32 | R97: NW | S97: Non Woven Fabric-10195 | T97: MATRESS
A98: 1851 | B98: RML-NWN-80GSMX82BLK | C98: NON WOVEN FABRIC 80 GSM x 82 INCH - BLACK | D98: KGS | E98: CBERM | F98: 441.6 | G98: 123.9498 | H98: 54736.25 | I98: 0 | K98: 0 | L98: 81.8 | M98: 123.95 | N98: 10139.11 | O98: 359.8 | P98: 123.9498 | Q98: 44597.14 | R98: NW | S98: Non Woven Fabric-10195 | T98: MATRESS
A99: 1854 | B99: RML-NYLONBUSH-50X100 | C99: NYLON BUSH WHITE COLOR | D99: NOS | E99: CBERM | F99: 1047 | G99: 17.7208 | H99: 18553.71 | I99: 0 | K99: 0 | L99: 2 | M99: 17.72 | N99: 35.44 | O99: 1045 | P99: 17.7208 | Q99: 18518.27 | R99: CPG | S99: Clips, Polygel & Glue-10195 | T99: MATRESS
A100: 1858 | B100: RML-OGA-WCRD | C100: PEPS ORGANICA WARRANTY CARD | D100: NOS | E100: CBERM | F100: 7630 | G100: 9.4147 | H100: 71834.51 | I100: 0 | K100: 0 | L100: 160 | M100: 9.4148 | N100: 1506.37 | O100: 7470 | P100: 9.4147 | Q100: 70328.14 | R100: LCE | S100: Label,CnrShoe,CentreBand,EdgeTape-10195 | T100: MATRESS
...

Sheet SFG-rate rm - feb-24
A1: Row Labels | B1: Sum of Feb-24-Total
A2: BNAS-106X72X130 | B2: 1650.0082
A3: BNAS-13X13X100 | B3: 27.727734
A4: BNAS-13X13X130 | B4: 32.182134
A5: BNAS-13X13X150 | B5: 36.559734
A6: BNAS-13X13X90 | B6: 27.113334
A7: BNAS-18X18X100 | B7: 47.467619
A8: BNAS-18X18X130 | B8: 54.891619
A9: BNAS-20X18X100 | B9: 55.968766
A10: BNAS-20X18X130 | B10: 64.877566
A11: BNAS-20X18X150 | B11: 73.632766
A12: BNAS-20X18X90 | B12: 54.739966
A13: BNAS-24X60X130 | B13: 273.74261
... A29219: Grand Total | B29219: 18179053
